/*     */ package com.intellij.ml.llm.matterhorn.ej.ui.login;
/*     */ 
/*     */ import androidx.compose.runtime.Composable;
/*     */ import androidx.compose.runtime.ComposableTarget;
/*     */ import androidx.compose.runtime.Composer;
/*     */ import androidx.compose.runtime.RecomposeScopeImplKt;
/*     */ import androidx.compose.runtime.State;
/*     */ import com.intellij.ml.llm.matterhorn.ej.ui.login.states.GrazieActivationState;
/*     */ import com.intellij.ml.llm.matterhorn.ej.ui.login.states.JbaUnauthenticated;
/*     */ import com.intellij.ml.llm.matterhorn.ej.ui.login.states.MissingAIPLicense;
/*     */ import kotlin.Metadata;
/*     */ import kotlin.Unit;
/*     */ import kotlin.jvm.functions.Function0;
/*     */ import kotlin.jvm.internal.FunctionReferenceImpl;
/*     */ import kotlin.jvm.internal.SourceDebugExtension;
/*     */ import kotlin.reflect.KProperty;
/*     */ import org.jetbrains.annotations.NotNull;
/*     */ import org.jetbrains.annotations.Nullable;
/*     */ 
/*     */ 
/*     */ 
/*     */ 
/*     */ 
/*     */ 
/*     */ 
/*     */ 
/*     */ 
/*     */ 
/*     */ 
/*     */ 
/*     */ 
/*     */ 
/*     */ 
/*     */ 
/*     */ 
/*     */ 
/*     */ 
/*     */ 
/*     */ 
/*     */ 
/*     */ 
/*     */ 
/*     */ 
/*     */ 
/*     */ 
/*     */ 
/*     */ @Metadata(mv = {2, 1, 0}, k = 2, xi = 48, d1 = {"\000&\n\000\n\002\020\002\n\000\n\002\030\002\n\000\n\002\020\016\n\002\b\003\n\002\030\002\n\000\n\002\030\002\n\000\n\002\030\002\032\037\020\000\032\0020\0012\006\020\002\032\0020\0032\b\020\004\032\004\030\0010\005H\001¢\006\002\020\006¨\006\007²\006\n\020\b\032\0020\tX\002²\006\n\020\n\032\0020\013X\002²\006\n\020\f\032\0020\rX\002"}, d2 = {"GrazieActivationPageComponent", "", "state", "Lcom/intellij/ml/llm/matterhorn/ej/ui/login/states/GrazieActivationState;", "username", "", "(Lcom/intellij/ml/llm/matterhorn/ej/ui/login/states/GrazieActivationState;Ljava/lang/String;Landroidx/compose/runtime/Composer;I)V", "ej-ui", "phase", "Lcom/intellij/ml/llm/matterhorn/ej/ui/login/states/JbaUnauthenticated$LoginPhase;", "trialRequestState", "Lcom/intellij/ml/llm/matterhorn/ej/ui/login/states/MissingAIPLicense$TrialRequestState;", "refreshState", "Lcom/intellij/ml/llm/matterhorn/ej/ui/login/states/MissingAIPLicense$RefreshState;"})
/*     */ @SourceDebugExtension({"SMAP\nGrazieActivationPageComponent.kt\nKotlin\n*S Kotlin\n*F\n+ 1 GrazieActivationPageComponent.kt\ncom/intellij/ml/llm/matterhorn/ej/ui/login/GrazieActivationPageComponentKt\n+ 2 Composer.kt\nandroidx/compose/runtime/ComposerKt\n+ 3 SnapshotState.kt\nandroidx/compose/runtime/SnapshotStateKt__SnapshotStateKt\n*L\n1#1,190:1\n1225#2,6:191\n1225#2,6:197\n1225#2,6:203\n1225#2,6:209\n1225#2,6:215\n1225#2,6:221\n1225#2,6:227\n1225#2,6:233\n1225#2,6:239\n1225#2,6:245\n1225#2,6:251\n1225#2,6:257\n1225#2,6:263\n1225#2,6:269\n1225#2,6:275\n1225#2,6:281\n1225#2,6:287\n1225#2,6:293\n1225#2,6:299\n1225#2,6:305\n1225#2,6:311\n1225#2,6:317\n81#3:323\n81#3:324\n81#3:325\n*S KotlinDebug\n*F\n+ 1 GrazieActivationPageComponent.kt\ncom/intellij/ml/llm/matterhorn/ej/ui/login/GrazieActivationPageComponentKt\n*L\n99#1:191,6\n100#1:197,6\n101#1:203,6\n102#1:209,6\n117#1:215,6\n118#1:221,6\n119#1:227,6\n120#1:233,6\n130#1:239,6\n131#1:245,6\n132#1:251,6\n133#1:257,6\n143#1:263,6\n144#1:269,6\n152#1:275,6\n153#1:281,6\n161#1:287,6\n162#1:293,6\n170#1:299,6\n171#1:305,6\n178#1:311,6\n179#1:317,6\n58#1:323\n94#1:324\n95#1:325\n*E\n"})
/*     */ public final class GrazieActivationPageComponentKt
/*     */ {
/*     */   @Composable
/*     */   @ComposableTarget(applier = "androidx.compose.ui.UiComposable")
/*     */   public static final void GrazieActivationPageComponent(@NotNull GrazieActivationState state, @Nullable String username, @Nullable Composer $composer, int $changed) {
/*     */     // Byte code:
/*     */     //   0: aload_0
/*     */     //   1: ldc 'state'
/*     */     //   3: invokestatic checkNotNullParameter : (Ljava/lang/Object;Ljava/lang/String;)V
/*     */     //   6: aload_2
/*     */     //   7: ldc 198688888
/*     */     //   9: invokeinterface startRestartGroup : (I)Landroidx/compose/runtime/Composer;
/*     */     //   14: astore_2
/*     */     //   15: iload_3
/*     */     //   16: istore #4
/*     */     //   18: iload_3
/*     */     //   19: bipush #6
/*     */     //   21: iand
/*     */     //   22: ifne -> 62
/*     */     //   25: iload #4
/*     */     //   27: iload_3
/*     */     //   28: bipush #8
/*     */     //   30: iand
/*     */     //   31: ifne -> 44
/*     */     //   34: aload_2
/*     */     //   35: aload_0
/*     */     //   36: invokeinterface changed : (Ljava/lang/Object;)Z
/*     */     //   41: goto -> 51
/*     */     //   44: aload_2
/*     */     //   45: aload_0
/*     */     //   46: invokeinterface changedInstance : (Ljava/lang/Object;)Z
/*     */     //   51: ifeq -> 58
/*     */     //   54: iconst_4
/*     */     //   55: goto -> 59
/*     */     //   58: iconst_2
/*     */     //   59: ior
/*     */     //   60: istore #4
/*     */     //   62: iload_3
/*     */     //   63: bipush #48
/*     */     //   65: iand
/*     */     //   66: ifne -> 91
/*     */     //   69: iload #4
/*     */     //   71: aload_2
/*     */     //   72: aload_1
/*     */     //   73: invokeinterface changed : (Ljava/lang/Object;)Z
/*     */     //   78: ifeq -> 86
/*     */     //   81: bipush #32
/*     */     //   83: goto -> 88
/*     */     //   86: bipush #16
/*     */     //   88: ior
/*     */     //   89: istore #4
/*     */     //   91: iload #4
/*     */     //   93: bipush #19
/*     */     //   95: iand
/*     */     //   96: bipush #18
/*     */     //   98: if_icmpne -> 110
/*     */     //   101: aload_2
/*     */     //   102: invokeinterface getSkipping : ()Z
/*     */     //   107: ifne -> 3844
/*     */     //   110: invokestatic isTraceInProgress : ()Z
/*     */     //   113: ifeq -> 126
/*     */     //   116: ldc 198688888
/*     */     //   118: iload #4
/*     */     //   120: iconst_m1
/*     */     //   121: ldc 'com.intellij.ml.llm.matterhorn.ej.ui.login.GrazieActivationPageComponent (GrazieActivationPageComponent.kt:32)'
/*     */     //   123: invokestatic traceEventStart : (IIILjava/lang/String;)V
/*     */     //   126: aload_0
/*     */     //   127: astore #5
/*     */     //   129: aload #5
/*     */     //   131: instanceof com/intellij/ml/llm/matterhorn/ej/ui/login/states/GrazieActivationState$Progressing
/*     */     //   134: ifeq -> 159
/*     */     //   137: aload_2
/*     */     //   138: ldc 1201305612
/*     */     //   140: invokeinterface startReplaceGroup : (I)V
/*     */     //   145: aload_2
/*     */     //   146: iconst_0
/*     */     //   147: invokestatic GrazieActivationInProgress : (Landroidx/compose/runtime/Composer;I)V
/*     */     //   150: aload_2
/*     */     //   151: invokeinterface endReplaceGroup : ()V
/*     */     //   156: goto -> 3832
/*     */     //   159: aload #5
/*     */     //   161: instanceof com/intellij/ml/llm/matterhorn/ej/ui/login/states/StepFail
/*     */     //   164: ifeq -> 193
/*     */     //   167: aload_2
/*     */     //   168: ldc 1201446042
/*     */     //   170: invokeinterface startReplaceGroup : (I)V
/*     */     //   175: aload_0
/*     */     //   176: checkcast com/intellij/ml/llm/matterhorn/ej/ui/login/states/StepFail
/*     */     //   179: aload_2
/*     */     //   180: iconst_0
/*     */     //   181: invokestatic GrazieActivationStepFail : (Lcom/intellij/ml/llm/matterhorn/ej/ui/login/states/StepFail;Landroidx/compose/runtime/Composer;I)V
/*     */     //   184: aload_2
/*     */     //   185: invokeinterface endReplaceGroup : ()V
/*     */     //   190: goto -> 3832
/*     */     //   193: aload #5
/*     */     //   195: instanceof com/intellij/ml/llm/matterhorn/ej/ui/login/states/LicenseAgreement
/*     */     //   198: ifeq -> 227
/*     */     //   201: aload_2
/*     */     //   202: ldc 1201610559
/*     */     //   204: invokeinterface startReplaceGroup : (I)V
/*     */     //   209: aload_0
/*     */     //   210: checkcast com/intellij/ml/llm/matterhorn/ej/ui/login/states/LicenseAgreement
/*     */     //   213: aload_2
/*     */     //   214: iconst_0
/*     */     //   215: invokestatic RequireLicenseAcceptance : (Lcom/intellij/ml/llm/matterhorn/ej/ui/login/states/LicenseAgreement;Landroidx/compose/runtime/Composer;I)V
/*     */     //   218: aload_2
/*     */     //   219: invokeinterface endReplaceGroup : ()V
/*     */     //   224: goto -> 3832
/*     */     //   227: aload #5
/*     */     //   229: getstatic com/intellij/ml/llm/matterhorn/ej/ui/login/states/GrazieActivationState$Ready.INSTANCE : Lcom/intellij/ml/llm/matterhorn/ej/ui/login/states/GrazieActivationState$Ready;
/*     */     //   232: invokestatic areEqual : (Ljava/lang/Object;Ljava/lang/Object;)Z
/*     */     //   235: ifeq -> 281
/*     */     //   238: aload_2
/*     */     //   239: ldc 1201748819
/*     */     //   241: invokeinterface startReplaceGroup : (I)V
/*     */     //   246: ldc 'Ready'
/*     */     //   248: aconst_null
/*     */     //   249: lconst_0
/*     */     //   250: lconst_0
/*     */     //   251: aconst_null
/*     */     //   252: aconst_null
/*     */     //   253: aconst_null
/*     */     //   254: lconst_0
/*     */     //   255: aconst_null
/*     */     //   256: iconst_0
/*     */     //   257: lconst_0
/*     */     //   258: iconst_0
/*     */     //   259: iconst_0
/*     */     //   260: iconst_0
/*     */     //   261: aconst_null
/*     */     //   262: aconst_null
/*     */     //   263: aload_2
/*     */     //   264: bipush #6
/*     */     //   266: iconst_0
/*     */     //   267: ldc 65534
/*     */     //   269: invokestatic Text-bAzTDeA : (Ljava/lang/String;Landroidx/compose/ui/Modifier;JJLandroidx/compose/ui/text/font/FontStyle;Landroidx/compose/ui/text/font/FontWeight;Landroidx/compose/ui/text/font/FontFamily;JLandroidx/compose/ui/text/style/TextDecoration;IJIZILkotlin/jvm/functions/Function1;Landroidx/compose/ui/text/TextStyle;Landroidx/compose/runtime/Composer;III)V
/*     */     //   272: aload_2
/*     */     //   273: invokeinterface endReplaceGroup : ()V
/*     */     //   278: goto -> 3832
/*     */     //   281: aload #5
/*     */     //   283: instanceof com/intellij/ml/llm/matterhorn/ej/ui/login/states/JbaUnauthenticated
/*     */     //   286: ifeq -> 534
/*     */     //   289: aload_2
/*     */     //   290: ldc 1201948304
/*     */     //   292: invokeinterface startReplaceGroup : (I)V
/*     */     //   297: aload_0
/*     */     //   298: checkcast com/intellij/ml/llm/matterhorn/ej/ui/login/states/JbaUnauthenticated
/*     */     //   301: invokevirtual getPhase : ()Lkotlinx/coroutines/flow/StateFlow;
/*     */     //   304: aconst_null
/*     */     //   305: aload_2
/*     */     //   306: iconst_0
/*     */     //   307: iconst_1
/*     */     //   308: invokestatic collectAsState : (Lkotlinx/coroutines/flow/StateFlow;Lkotlin/coroutines/CoroutineContext;Landroidx/compose/runtime/Composer;II)Landroidx/compose/runtime/State;
/*     */     //   311: astore #6
/*     */     //   313: aload #6
/*     */     //   315: invokestatic GrazieActivationPageComponent$lambda$0 : (Landroidx/compose/runtime/State;)Lcom/intellij/ml/llm/matterhorn/ej/ui/login/states/JbaUnauthenticated$LoginPhase;
/*     */     //   318: astore #7
/*     */     //   320: aload #7
/*     */     //   322: instanceof com/intellij/ml/llm/matterhorn/ej/ui/login/states/JbaUnauthenticated$LoginPhase$Error
/*     */     //   325: ifeq -> 358
/*     */     //   328: aload_2
/*     */     //   329: ldc 1202043133
/*     */     //   331: invokeinterface startReplaceGroup : (I)V
/*     */     //   336: aload_0
/*     */     //   337: checkcast com/intellij/ml/llm/matterhorn/ej/ui/login/states/JbaUnauthenticated
/*     */     //   340: ldc 'Failed to login, please try again.'
/*     */     //   342: aload_2
/*     */     //   343: bipush #48
/*     */     //   345: iconst_0
/*     */     //   346: invokestatic JBALoginInitial : (Lcom/intellij/ml/llm/matterhorn/ej/ui/login/states/JbaUnauthenticated;Ljava/lang/String;Landroidx/compose/runtime/Composer;II)V
/*     */     //   349: aload_2
/*     */     //   350: invokeinterface endReplaceGroup : ()V
/*     */     //   355: goto -> 525
/*     */     //   358: aload #7
/*     */     //   360: getstatic com/intellij/ml/llm/matterhorn/ej/ui/login/states/JbaUnauthenticated$LoginPhase$COMPLETED.INSTANCE : Lcom/intellij/ml/llm/matterhorn/ej/ui/login/states/JbaUnauthenticated$LoginPhase$COMPLETED;
/*     */     //   363: invokestatic areEqual : (Ljava/lang/Object;Ljava/lang/Object;)Z
/*     */     //   366: ifeq -> 412
/*     */     //   369: aload_2
/*     */     //   370: ldc 1202230590
/*     */     //   372: invokeinterface startReplaceGroup : (I)V
/*     */     //   377: ldc 'Succeeded.'
/*     */     //   379: aconst_null
/*     */     //   380: lconst_0
/*     */     //   381: lconst_0
/*     */     //   382: aconst_null
/*     */     //   383: aconst_null
/*     */     //   384: aconst_null
/*     */     //   385: lconst_0
/*     */     //   386: aconst_null
/*     */     //   387: iconst_0
/*     */     //   388: lconst_0
/*     */     //   389: iconst_0
/*     */     //   390: iconst_0
/*     */     //   391: iconst_0
/*     */     //   392: aconst_null
/*     */     //   393: aconst_null
/*     */     //   394: aload_2
/*     */     //   395: bipush #6
/*     */     //   397: iconst_0
/*     */     //   398: ldc 65534
/*     */     //   400: invokestatic Text-bAzTDeA : (Ljava/lang/String;Landroidx/compose/ui/Modifier;JJLandroidx/compose/ui/text/font/FontStyle;Landroidx/compose/ui/text/font/FontWeight;Landroidx/compose/ui/text/font/FontFamily;JLandroidx/compose/ui/text/style/TextDecoration;IJIZILkotlin/jvm/functions/Function1;Landroidx/compose/ui/text/TextStyle;Landroidx/compose/runtime/Composer;III)V
/*     */     //   403: aload_2
/*     */     //   404: invokeinterface endReplaceGroup : ()V
/*     */     //   409: goto -> 525
/*     */     //   412: aload #7
/*     */     //   414: getstatic com/intellij/ml/llm/matterhorn/ej/ui/login/states/JbaUnauthenticated$LoginPhase$INITIAL.INSTANCE : Lcom/intellij/ml/llm/matterhorn/ej/ui/login/states/JbaUnauthenticated$LoginPhase$INITIAL;
/*     */     //   417: invokestatic areEqual : (Ljava/lang/Object;Ljava/lang/Object;)Z
/*     */     //   420: ifeq -> 466
/*     */     //   423: aload_2
/*     */     //   424: ldc 1202446660
/*     */     //   426: invokeinterface startReplaceGroup : (I)V
/*     */     //   431: aload_0
/*     */     //   432: checkcast com/intellij/ml/llm/matterhorn/ej/ui/login/states/JbaUnauthenticated
/*     */     //   435: aload_0
/*     */     //   436: checkcast com/intellij/ml/llm/matterhorn/ej/ui/login/states/JbaUnauthenticated
/*     */     //   439: invokevirtual getRejected : ()Z
/*     */     //   442: ifeq -> 450
/*     */     //   445: ldc 'Failed to login, please try again.'
/*     */     //   447: goto -> 451
/*     */     //   450: aconst_null
/*     */     //   451: aload_2
/*     */     //   452: iconst_0
/*     */     //   453: iconst_0
/*     */     //   454: invokestatic JBALoginInitial : (Lcom/intellij/ml/llm/matterhorn/ej/ui/login/states/JbaUnauthenticated;Ljava/lang/String;Landroidx/compose/runtime/Composer;II)V
/*     */     //   457: aload_2
/*     */     //   458: invokeinterface endReplaceGroup : ()V
/*     */     //   463: goto -> 525
/*     */     //   466: aload #7
/*     */     //   468: getstatic com/intellij/ml/llm/matterhorn/ej/ui/login/states/JbaUnauthenticated$LoginPhase$PROGRESS.INSTANCE : Lcom/intellij/ml/llm/matterhorn/ej/ui/login/states/JbaUnauthenticated$LoginPhase$PROGRESS;
/*     */     //   471: invokestatic areEqual : (Ljava/lang/Object;Ljava/lang/Object;)Z
/*     */     //   474: ifeq -> 503
/*     */     //   477: aload_2
/*     */     //   478: ldc 1202688801
/*     */     //   480: invokeinterface startReplaceGroup : (I)V
/*     */     //   485: aload_0
/*     */     //   486: checkcast com/intellij/ml/llm/matterhorn/ej/ui/login/states/JbaUnauthenticated
/*     */     //   489: aload_2
/*     */     //   490: iconst_0
/*     */     //   491: invokestatic JBALoginProgress : (Lcom/intellij/ml/llm/matterhorn/ej/ui/login/states/JbaUnauthenticated;Landroidx/compose/runtime/Composer;I)V
/*     */     //   494: aload_2
/*     */     //   495: invokeinterface endReplaceGroup : ()V
/*     */     //   500: goto -> 525
/*     */     //   503: aload_2
/*     */     //   504: ldc 177321588
/*     */     //   506: invokeinterface startReplaceGroup : (I)V
/*     */     //   511: aload_2
/*     */     //   512: invokeinterface endReplaceGroup : ()V
/*     */     //   517: new kotlin/NoWhenBranchMatchedException
/*     */     //   520: dup
/*     */     //   521: invokespecial <init> : ()V
/*     */     //   524: athrow
/*     */     //   525: aload_2
/*     */     //   526: invokeinterface endReplaceGroup : ()V
/*     */     //   531: goto -> 3832
/*     */     //   534: aload #5
/*     */     //   536: instanceof com/intellij/ml/llm/matterhorn/ej/ui/login/states/AIEBlocked
/*     */     //   539: ifeq -> 573
/*     */     //   542: aload_2
/*     */     //   543: ldc 1202886240
/*     */     //   545: invokeinterface startReplaceGroup : (I)V
/*     */     //   550: aload_0
/*     */     //   551: checkcast com/intellij/ml/llm/matterhorn/ej/ui/login/states/AIEBlocked
/*     */     //   554: invokevirtual getReasonText : ()Ljava/lang/String;
/*     */     //   557: aconst_null
/*     */     //   558: aload_2
/*     */     //   559: bipush #48
/*     */     //   561: invokestatic JunieUnavailable : (Ljava/lang/String;Lkotlin/jvm/functions/Function0;Landroidx/compose/runtime/Composer;I)V
/*     */     //   564: aload_2
/*     */     //   565: invokeinterface endReplaceGroup : ()V
/*     */     //   570: goto -> 3832
/*     */     //   573: aload #5
/*     */     //   575: instanceof com/intellij/ml/llm/matterhorn/ej/ui/login/states/AIPBlocked
/*     */     //   578: ifeq -> 617
/*     */     //   581: aload_2
/*     */     //   582: ldc 1203040000
/*     */     //   584: invokeinterface startReplaceGroup : (I)V
/*     */     //   589: aload_0
/*     */     //   590: checkcast com/intellij/ml/llm/matterhorn/ej/ui/login/states/AIPBlocked
/*     */     //   593: invokevirtual getReasonText : ()Ljava/lang/String;
/*     */     //   596: aload_0
/*     */     //   597: checkcast com/intellij/ml/llm/matterhorn/ej/ui/login/states/AIPBlocked
/*     */     //   600: invokevirtual getOnRefresh : ()Lkotlin/jvm/functions/Function0;
/*     */     //   603: aload_2
/*     */     //   604: iconst_0
/*     */     //   605: invokestatic JunieUnavailable : (Ljava/lang/String;Lkotlin/jvm/functions/Function0;Landroidx/compose/runtime/Composer;I)V
/*     */     //   608: aload_2
/*     */     //   609: invokeinterface endReplaceGroup : ()V
/*     */     //   614: goto -> 3832
/*     */     //   617: aload #5
/*     */     //   619: instanceof com/intellij/ml/llm/matterhorn/ej/ui/login/states/MissingAIPLicense
/*     */     //   622: ifeq -> 3809
/*     */     //   625: aload_2
/*     */     //   626: ldc 1203319186
/*     */     //   628: invokeinterface startReplaceGroup : (I)V
/*     */     //   633: aload_0
/*     */     //   634: checkcast com/intellij/ml/llm/matterhorn/ej/ui/login/states/MissingAIPLicense
/*     */     //   637: invokevirtual getTrialRequestState : ()Lkotlinx/coroutines/flow/StateFlow;
/*     */     //   640: aconst_null
/*     */     //   641: aload_2
/*     */     //   642: iconst_0
/*     */     //   643: iconst_1
/*     */     //   644: invokestatic collectAsState : (Lkotlinx/coroutines/flow/StateFlow;Lkotlin/coroutines/CoroutineContext;Landroidx/compose/runtime/Composer;II)Landroidx/compose/runtime/State;
/*     */     //   647: astore #6
/*     */     //   649: aload_0
/*     */     //   650: checkcast com/intellij/ml/llm/matterhorn/ej/ui/login/states/MissingAIPLicense
/*     */     //   653: invokevirtual getRefreshState : ()Lkotlinx/coroutines/flow/StateFlow;
/*     */     //   656: aconst_null
/*     */     //   657: aload_2
/*     */     //   658: iconst_0
/*     */     //   659: iconst_1
/*     */     //   660: invokestatic collectAsState : (Lkotlinx/coroutines/flow/StateFlow;Lkotlin/coroutines/CoroutineContext;Landroidx/compose/runtime/Composer;II)Landroidx/compose/runtime/State;
/*     */     //   663: astore #7
/*     */     //   665: aload #6
/*     */     //   667: invokestatic GrazieActivationPageComponent$lambda$1 : (Landroidx/compose/runtime/State;)Lcom/intellij/ml/llm/matterhorn/ej/ui/login/states/MissingAIPLicense$TrialRequestState;
/*     */     //   670: astore #8
/*     */     //   672: aload #8
/*     */     //   674: getstatic com/intellij/ml/llm/matterhorn/ej/ui/login/states/MissingAIPLicense$TrialRequestState$NotRequested.INSTANCE : Lcom/intellij/ml/llm/matterhorn/ej/ui/login/states/MissingAIPLicense$TrialRequestState$NotRequested;
/*     */     //   677: invokestatic areEqual : (Ljava/lang/Object;Ljava/lang/Object;)Z
/*     */     //   680: ifeq -> 1194
/*     */     //   683: aload_2
/*     */     //   684: ldc 1203451587
/*     */     //   686: invokeinterface startReplaceGroup : (I)V
/*     */     //   691: aload_0
/*     */     //   692: checkcast com/intellij/ml/llm/matterhorn/ej/ui/login/states/MissingAIPLicense
/*     */     //   695: astore #9
/*     */     //   697: aload_2
/*     */     //   698: ldc 177370001
/*     */     //   700: invokeinterface startReplaceGroup : (I)V
/*     */     //   705: aload_2
/*     */     //   706: astore #11
/*     */     //   708: aload_2
/*     */     //   709: aload #9
/*     */     //   711: invokeinterface changedInstance : (Ljava/lang/Object;)Z
/*     */     //   716: istore #12
/*     */     //   718: iconst_0
/*     */     //   719: istore #13
/*     */     //   721: aload #11
/*     */     //   723: invokeinterface rememberedValue : ()Ljava/lang/Object;
/*     */     //   728: astore #14
/*     */     //   730: iconst_0
/*     */     //   731: istore #15
/*     */     //   733: iload #12
/*     */     //   735: ifne -> 749
/*     */     //   738: aload #14
/*     */     //   740: getstatic androidx/compose/runtime/Composer.Companion : Landroidx/compose/runtime/Composer$Companion;
/*     */     //   743: invokevirtual getEmpty : ()Ljava/lang/Object;
/*     */     //   746: if_acmpne -> 780
/*     */     //   749: iconst_0
/*     */     //   750: istore #16
/*     */     //   752: new com/intellij/ml/llm/matterhorn/ej/ui/login/GrazieActivationPageComponentKt$GrazieActivationPageComponent$1$1
/*     */     //   755: dup
/*     */     //   756: aload #9
/*     */     //   758: invokespecial <init> : (Ljava/lang/Object;)V
/*     */     //   761: checkcast kotlin/reflect/KFunction
/*     */     //   764: astore #17
/*     */     //   766: aload #11
/*     */     //   768: aload #17
/*     */     //   770: invokeinterface updateRememberedValue : (Ljava/lang/Object;)V
/*     */     //   775: aload #17
/*     */     //   777: goto -> 782
/*     */     //   780: aload #14
/*     */     //   782: nop
/*     */     //   783: nop
/*     */     //   784: nop
/*     */     //   785: checkcast kotlin/reflect/KFunction
/*     */     //   788: astore #10
/*     */     //   790: aload_2
/*     */     //   791: invokeinterface endReplaceGroup : ()V
/*     */     //   796: aload #10
/*     */     //   798: checkcast kotlin/jvm/functions/Function0
/*     */     //   801: aload_0
/*     */     //   802: checkcast com/intellij/ml/llm/matterhorn/ej/ui/login/states/MissingAIPLicense
/*     */     //   805: astore #9
/*     */     //   807: aload_2
/*     */     //   808: ldc 177371803
/*     */     //   810: invokeinterface startReplaceGroup : (I)V
/*     */     //   815: aload_2
/*     */     //   816: astore #11
/*     */     //   818: aload_2
/*     */     //   819: aload #9
/*     */     //   821: invokeinterface changedInstance : (Ljava/lang/Object;)Z
/*     */     //   826: istore #12
/*     */     //   828: iconst_0
/*     */     //   829: istore #13
/*     */     //   831: aload #11
/*     */     //   833: invokeinterface rememberedValue : ()Ljava/lang/Object;
/*     */     //   838: astore #14
/*     */     //   840: iconst_0
/*     */     //   841: istore #15
/*     */     //   843: iload #12
/*     */     //   845: ifne -> 859
/*     */     //   848: aload #14
/*     */     //   850: getstatic androidx/compose/runtime/Composer.Companion : Landroidx/compose/runtime/Composer$Companion;
/*     */     //   853: invokevirtual getEmpty : ()Ljava/lang/Object;
/*     */     //   856: if_acmpne -> 895
/*     */     //   859: astore #23
/*     */     //   861: iconst_0
/*     */     //   862: istore #16
/*     */     //   864: new com/intellij/ml/llm/matterhorn/ej/ui/login/GrazieActivationPageComponentKt$GrazieActivationPageComponent$2$1
/*     */     //   867: dup
/*     */     //   868: aload #9
/*     */     //   870: invokespecial <init> : (Ljava/lang/Object;)V
/*     */     //   873: checkcast kotlin/reflect/KFunction
/*     */     //   876: aload #23
/*     */     //   878: swap
/*     */     //   879: astore #17
/*     */     //   881: aload #11
/*     */     //   883: aload #17
/*     */     //   885: invokeinterface updateRememberedValue : (Ljava/lang/Object;)V
/*     */     //   890: aload #17
/*     */     //   892: goto -> 897
/*     */     //   895: aload #14
/*     */     //   897: nop
/*     */     //   898: nop
/*     */     //   899: nop
/*     */     //   900: checkcast kotlin/reflect/KFunction
/*     */     //   903: astore #10
/*     */     //   905: aload_2
/*     */     //   906: invokeinterface endReplaceGroup : ()V
/*     */     //   911: aload #10
/*     */     //   913: checkcast kotlin/jvm/functions/Function0
/*     */     //   916: aload_0
/*     */     //   917: checkcast com/intellij/ml/llm/matterhorn/ej/ui/login/states/MissingAIPLicense
/*     */     //   920: astore #9
/*     */     //   922: aload_2
/*     */     //   923: ldc 177373655
/*     */     //   925: invokeinterface startReplaceGroup : (I)V
/*     */     //   930: aload_2
/*     */     //   931: astore #11
/*     */     //   933: aload_2
/*     */     //   934: aload #9
/*     */     //   936: invokeinterface changedInstance : (Ljava/lang/Object;)Z
/*     */     //   941: istore #12
/*     */     //   943: iconst_0
/*     */     //   944: istore #13
/*     */     //   946: aload #11
/*     */     //   948: invokeinterface rememberedValue : ()Ljava/lang/Object;
/*     */     //   953: astore #14
/*     */     //   955: iconst_0
/*     */     //   956: istore #15
/*     */     //   958: iload #12
/*     */     //   960: ifne -> 974
/*     */     //   963: aload #14
/*     */     //   965: getstatic androidx/compose/runtime/Composer.Companion : Landroidx/compose/runtime/Composer$Companion;
/*     */     //   968: invokevirtual getEmpty : ()Ljava/lang/Object;
/*     */     //   971: if_acmpne -> 1017
/*     */     //   974: astore #24
/*     */     //   976: astore #23
/*     */     //   978: iconst_0
/*     */     //   979: istore #16
/*     */     //   981: new com/intellij/ml/llm/matterhorn/ej/ui/login/GrazieActivationPageComponentKt$GrazieActivationPageComponent$3$1
/*     */     //   984: dup
/*     */     //   985: aload #9
/*     */     //   987: invokespecial <init> : (Ljava/lang/Object;)V
/*     */     //   990: checkcast kotlin/reflect/KFunction
/*     */     //   993: astore #25
/*     */     //   995: aload #23
/*     */     //   997: aload #24
/*     */     //   999: aload #25
/*     */     //   1001: astore #17
/*     */     //   1003: aload #11
/*     */     //   1005: aload #17
/*     */     //   1007: invokeinterface updateRememberedValue : (Ljava/lang/Object;)V
/*     */     //   1012: aload #17
/*     */     //   1014: goto -> 1019
/*     */     //   1017: aload #14
/*     */     //   1019: nop
/*     */     //   1020: nop
/*     */     //   1021: nop
/*     */     //   1022: checkcast kotlin/reflect/KFunction
/*     */     //   1025: astore #10
/*     */     //   1027: aload_2
/*     */     //   1028: invokeinterface endReplaceGroup : ()V
/*     */     //   1033: aload #10
/*     */     //   1035: checkcast kotlin/jvm/functions/Function0
/*     */     //   1038: aload_0
/*     */     //   1039: checkcast com/intellij/ml/llm/matterhorn/ej/ui/login/states/MissingAIPLicense
/*     */     //   1042: astore #9
/*     */     //   1044: aload_2
/*     */     //   1045: ldc 177375223
/*     */     //   1047: invokeinterface startReplaceGroup : (I)V
/*     */     //   1052: aload_2
/*     */     //   1053: astore #11
/*     */     //   1055: aload_2
/*     */     //   1056: aload #9
/*     */     //   1058: invokeinterface changedInstance : (Ljava/lang/Object;)Z
/*     */     //   1063: istore #12
/*     */     //   1065: iconst_0
/*     */     //   1066: istore #13
/*     */     //   1068: aload #11
/*     */     //   1070: invokeinterface rememberedValue : ()Ljava/lang/Object;
/*     */     //   1075: astore #14
/*     */     //   1077: iconst_0
/*     */     //   1078: istore #15
/*     */     //   1080: iload #12
/*     */     //   1082: ifne -> 1096
/*     */     //   1085: aload #14
/*     */     //   1087: getstatic androidx/compose/runtime/Composer.Companion : Landroidx/compose/runtime/Composer$Companion;
/*     */     //   1090: invokevirtual getEmpty : ()Ljava/lang/Object;
/*     */     //   1093: if_acmpne -> 1143
/*     */     //   1096: astore #25
/*     */     //   1098: astore #24
/*     */     //   1100: astore #23
/*     */     //   1102: iconst_0
/*     */     //   1103: istore #16
/*     */     //   1105: new com/intellij/ml/llm/matterhorn/ej/ui/login/GrazieActivationPageComponentKt$GrazieActivationPageComponent$4$1
/*     */     //   1108: dup
/*     */     //   1109: aload #9
/*     */     //   1111: invokespecial <init> : (Ljava/lang/Object;)V
/*     */     //   1114: checkcast kotlin/reflect/KFunction
/*     */     //   1117: astore #26
/*     */     //   1119: aload #23
/*     */     //   1121: aload #24
/*     */     //   1123: aload #25
/*     */     //   1125: aload #26
/*     */     //   1127: astore #17
/*     */     //   1129: aload #11
/*     */     //   1131: aload #17
/*     */     //   1133: invokeinterface updateRememberedValue : (Ljava/lang/Object;)V
/*     */     //   1138: aload #17
/*     */     //   1140: goto -> 1145
/*     */     //   1143: aload #14
/*     */     //   1145: nop
/*     */     //   1146: nop
/*     */     //   1147: nop
/*     */     //   1148: checkcast kotlin/reflect/KFunction
/*     */     //   1151: astore #10
/*     */     //   1153: aload_2
/*     */     //   1154: invokeinterface endReplaceGroup : ()V
/*     */     //   1159: aload #10
/*     */     //   1161: checkcast kotlin/jvm/functions/Function0
/*     */     //   1164: aload_1
/*     */     //   1165: dup
/*     */     //   1166: ifnonnull -> 1172
/*     */     //   1169: pop
/*     */     //   1170: ldc ''
/*     */     //   1172: aconst_null
/*     */     //   1173: aload #7
/*     */     //   1175: invokestatic GrazieActivationPageComponent$lambda$2 : (Landroidx/compose/runtime/State;)Lcom/intellij/ml/llm/matterhorn/ej/ui/login/states/MissingAIPLicense$RefreshState;
/*     */     //   1178: aload_2
/*     */     //   1179: iconst_0
/*     */     //   1180: bipush #32
/*     */     //   1182: invokestatic RequestTrial : (Lkotlin/jvm/functions/Function0;Lkotlin/jvm/functions/Function0;Lkotlin/jvm/functions/Function0;Lkotlin/jvm/functions/Function0;Ljava/lang/String;Ljava/lang/String;Lcom/intellij/ml/llm/matterhorn/ej/ui/login/states/MissingAIPLicense$RefreshState;Landroidx/compose/runtime/Composer;II)V
/*     */     //   1185: aload_2
/*     */     //   1186: invokeinterface endReplaceGroup : ()V
/*     */     //   1191: goto -> 3800
/*     */     //   1194: aload #8
/*     */     //   1196: getstatic com/intellij/ml/llm/matterhorn/ej/ui/login/states/MissingAIPLicense$TrialRequestState$Progress.INSTANCE : Lcom/intellij/ml/llm/matterhorn/ej/ui/login/states/MissingAIPLicense$TrialRequestState$Progress;
/*     */     //   1199: invokestatic areEqual : (Ljava/lang/Object;Ljava/lang/Object;)Z
/*     */     //   1202: ifeq -> 1228
/*     */     //   1205: aload_2
/*     */     //   1206: ldc_w 1203852231
/*     */     //   1209: invokeinterface startReplaceGroup : (I)V
/*     */     //   1214: aload_2
/*     */     //   1215: iconst_0
/*     */     //   1216: invokestatic GrazieActivationInProgress : (Landroidx/compose/runtime/Composer;I)V
/*     */     //   1219: aload_2
/*     */     //   1220: invokeinterface endReplaceGroup : ()V
/*     */     //   1225: goto -> 3800
/*     */     //   1228: aload #8
/*     */     //   1230: instanceof com/intellij/ml/llm/matterhorn/ej/ui/login/states/MissingAIPLicense$TrialRequestState$Error
/*     */     //   1233: ifeq -> 1753
/*     */     //   1236: aload_2
/*     */     //   1237: ldc_w 1204044338
/*     */     //   1240: invokeinterface startReplaceGroup : (I)V
/*     */     //   1245: aload_1
/*     */     //   1246: dup
/*     */     //   1247: ifnonnull -> 1253
/*     */     //   1250: pop
/*     */     //   1251: ldc ''
/*     */     //   1253: astore #9
/*     */     //   1255: aload_0
/*     */     //   1256: checkcast com/intellij/ml/llm/matterhorn/ej/ui/login/states/MissingAIPLicense
/*     */     //   1259: astore #11
/*     */     //   1261: aload_2
/*     */     //   1262: ldc_w 177392625
/*     */     //   1265: invokeinterface startReplaceGroup : (I)V
/*     */     //   1270: aload_2
/*     */     //   1271: astore #13
/*     */     //   1273: aload_2
/*     */     //   1274: aload #11
/*     */     //   1276: invokeinterface changedInstance : (Ljava/lang/Object;)Z
/*     */     //   1281: istore #14
/*     */     //   1283: iconst_0
/*     */     //   1284: istore #15
/*     */     //   1286: aload #13
/*     */     //   1288: invokeinterface rememberedValue : ()Ljava/lang/Object;
/*     */     //   1293: astore #16
/*     */     //   1295: iconst_0
/*     */     //   1296: istore #17
/*     */     //   1298: iload #14
/*     */     //   1300: ifne -> 1314
/*     */     //   1303: aload #16
/*     */     //   1305: getstatic androidx/compose/runtime/Composer.Companion : Landroidx/compose/runtime/Composer$Companion;
/*     */     //   1308: invokevirtual getEmpty : ()Ljava/lang/Object;
/*     */     //   1311: if_acmpne -> 1345
/*     */     //   1314: iconst_0
/*     */     //   1315: istore #18
/*     */     //   1317: new com/intellij/ml/llm/matterhorn/ej/ui/login/GrazieActivationPageComponentKt$GrazieActivationPageComponent$5$1
/*     */     //   1320: dup
/*     */     //   1321: aload #11
/*     */     //   1323: invokespecial <init> : (Ljava/lang/Object;)V
/*     */     //   1326: checkcast kotlin/reflect/KFunction
/*     */     //   1329: astore #19
/*     */     //   1331: aload #13
/*     */     //   1333: aload #19
/*     */     //   1335: invokeinterface updateRememberedValue : (Ljava/lang/Object;)V
/*     */     //   1340: aload #19
/*     */     //   1342: goto -> 1347
/*     */     //   1345: aload #16
/*     */     //   1347: nop
/*     */     //   1348: nop
/*     */     //   1349: nop
/*     */     //   1350: checkcast kotlin/reflect/KFunction
/*     */     //   1353: astore #12
/*     */     //   1355: aload_2
/*     */     //   1356: invokeinterface endReplaceGroup : ()V
/*     */     //   1361: aload #12
/*     */     //   1363: astore #10
/*     */     //   1365: aload_0
/*     */     //   1366: checkcast com/intellij/ml/llm/matterhorn/ej/ui/login/states/MissingAIPLicense
/*     */     //   1369: astore #12
/*     */     //   1371: aload_2
/*     */     //   1372: ldc_w 177394427
/*     */     //   1375: invokeinterface startReplaceGroup : (I)V
/*     */     //   1380: aload_2
/*     */     //   1381: astore #14
/*     */     //   1383: aload_2
/*     */     //   1384: aload #12
/*     */     //   1386: invokeinterface changedInstance : (Ljava/lang/Object;)Z
/*     */     //   1391: istore #15
/*     */     //   1393: iconst_0
/*     */     //   1394: istore #16
/*     */     //   1396: aload #14
/*     */     //   1398: invokeinterface rememberedValue : ()Ljava/lang/Object;
/*     */     //   1403: astore #17
/*     */     //   1405: iconst_0
/*     */     //   1406: istore #18
/*     */     //   1408: iload #15
/*     */     //   1410: ifne -> 1424
/*     */     //   1413: aload #17
/*     */     //   1415: getstatic androidx/compose/runtime/Composer.Companion : Landroidx/compose/runtime/Composer$Companion;
/*     */     //   1418: invokevirtual getEmpty : ()Ljava/lang/Object;
/*     */     //   1421: if_acmpne -> 1455
/*     */     //   1424: iconst_0
/*     */     //   1425: istore #19
/*     */     //   1427: new com/intellij/ml/llm/matterhorn/ej/ui/login/GrazieActivationPageComponentKt$GrazieActivationPageComponent$6$1
/*     */     //   1430: dup
/*     */     //   1431: aload #12
/*     */     //   1433: invokespecial <init> : (Ljava/lang/Object;)V
/*     */     //   1436: checkcast kotlin/reflect/KFunction
/*     */     //   1439: astore #20
/*     */     //   1441: aload #14
/*     */     //   1443: aload #20
/*     */     //   1445: invokeinterface updateRememberedValue : (Ljava/lang/Object;)V
/*     */     //   1450: aload #20
/*     */     //   1452: goto -> 1457
/*     */     //   1455: aload #17
/*     */     //   1457: nop
/*     */     //   1458: nop
/*     */     //   1459: nop
/*     */     //   1460: checkcast kotlin/reflect/KFunction
/*     */     //   1463: astore #13
/*     */     //   1465: aload_2
/*     */     //   1466: invokeinterface endReplaceGroup : ()V
/*     */     //   1471: aload #13
/*     */     //   1473: astore #11
/*     */     //   1475: aload_0
/*     */     //   1476: checkcast com/intellij/ml/llm/matterhorn/ej/ui/login/states/MissingAIPLicense
/*     */     //   1479: astore #13
/*     */     //   1481: aload_2
/*     */     //   1482: ldc_w 177396279
/*     */     //   1485: invokeinterface startReplaceGroup : (I)V
/*     */     //   1490: aload_2
/*     */     //   1491: astore #15
/*     */     //   1493: aload_2
/*     */     //   1494: aload #13
/*     */     //   1496: invokeinterface changedInstance : (Ljava/lang/Object;)Z
/*     */     //   1501: istore #16
/*     */     //   1503: iconst_0
/*     */     //   1504: istore #17
/*     */     //   1506: aload #15
/*     */     //   1508: invokeinterface rememberedValue : ()Ljava/lang/Object;
/*     */     //   1513: astore #18
/*     */     //   1515: iconst_0
/*     */     //   1516: istore #19
/*     */     //   1518: iload #16
/*     */     //   1520: ifne -> 1534
/*     */     //   1523: aload #18
/*     */     //   1525: getstatic androidx/compose/runtime/Composer.Companion : Landroidx/compose/runtime/Composer$Companion;
/*     */     //   1528: invokevirtual getEmpty : ()Ljava/lang/Object;
/*     */     //   1531: if_acmpne -> 1565
/*     */     //   1534: iconst_0
/*     */     //   1535: istore #20
/*     */     //   1537: new com/intellij/ml/llm/matterhorn/ej/ui/login/GrazieActivationPageComponentKt$GrazieActivationPageComponent$7$1
/*     */     //   1540: dup
/*     */     //   1541: aload #13
/*     */     //   1543: invokespecial <init> : (Ljava/lang/Object;)V
/*     */     //   1546: checkcast kotlin/reflect/KFunction
/*     */     //   1549: astore #21
/*     */     //   1551: aload #15
/*     */     //   1553: aload #21
/*     */     //   1555: invokeinterface updateRememberedValue : (Ljava/lang/Object;)V
/*     */     //   1560: aload #21
/*     */     //   1562: goto -> 1567
/*     */     //   1565: aload #18
/*     */     //   1567: nop
/*     */     //   1568: nop
/*     */     //   1569: nop
/*     */     //   1570: checkcast kotlin/reflect/KFunction
/*     */     //   1573: astore #14
/*     */     //   1575: aload_2
/*     */     //   1576: invokeinterface endReplaceGroup : ()V
/*     */     //   1581: aload #14
/*     */     //   1583: astore #12
/*     */     //   1585: aload_0
/*     */     //   1586: checkcast com/intellij/ml/llm/matterhorn/ej/ui/login/states/MissingAIPLicense
/*     */     //   1589: astore #14
/*     */     //   1591: aload_2
/*     */     //   1592: ldc_w 177397847
/*     */     //   1595: invokeinterface startReplaceGroup : (I)V
/*     */     //   1600: aload_2
/*     */     //   1601: astore #16
/*     */     //   1603: aload_2
/*     */     //   1604: aload #14
/*     */     //   1606: invokeinterface changedInstance : (Ljava/lang/Object;)Z
/*     */     //   1611: istore #17
/*     */     //   1613: iconst_0
/*     */     //   1614: istore #18
/*     */     //   1616: aload #16
/*     */     //   1618: invokeinterface rememberedValue : ()Ljava/lang/Object;
/*     */     //   1623: astore #19
/*     */     //   1625: iconst_0
/*     */     //   1626: istore #20
/*     */     //   1628: iload #17
/*     */     //   1630: ifne -> 1644
/*     */     //   1633: aload #19
/*     */     //   1635: getstatic androidx/compose/runtime/Composer.Companion : Landroidx/compose/runtime/Composer$Companion;
/*     */     //   1638: invokevirtual getEmpty : ()Ljava/lang/Object;
/*     */     //   1641: if_acmpne -> 1675
/*     */     //   1644: iconst_0
/*     */     //   1645: istore #21
/*     */     //   1647: new com/intellij/ml/llm/matterhorn/ej/ui/login/GrazieActivationPageComponentKt$GrazieActivationPageComponent$8$1
/*     */     //   1650: dup
/*     */     //   1651: aload #14
/*     */     //   1653: invokespecial <init> : (Ljava/lang/Object;)V
/*     */     //   1656: checkcast kotlin/reflect/KFunction
/*     */     //   1659: astore #22
/*     */     //   1661: aload #16
/*     */     //   1663: aload #22
/*     */     //   1665: invokeinterface updateRememberedValue : (Ljava/lang/Object;)V
/*     */     //   1670: aload #22
/*     */     //   1672: goto -> 1677
/*     */     //   1675: aload #19
/*     */     //   1677: nop
/*     */     //   1678: nop
/*     */     //   1679: nop
/*     */     //   1680: checkcast kotlin/reflect/KFunction
/*     */     //   1683: astore #15
/*     */     //   1685: aload_2
/*     */     //   1686: invokeinterface endReplaceGroup : ()V
/*     */     //   1691: aload #15
/*     */     //   1693: astore #13
/*     */     //   1695: aload #8
/*     */     //   1697: checkcast com/intellij/ml/llm/matterhorn/ej/ui/login/states/MissingAIPLicense$TrialRequestState$Error
/*     */     //   1700: invokevirtual getMessage : ()Ljava/lang/String;
/*     */     //   1703: astore #14
/*     */     //   1705: aload #7
/*     */     //   1707: invokestatic GrazieActivationPageComponent$lambda$2 : (Landroidx/compose/runtime/State;)Lcom/intellij/ml/llm/matterhorn/ej/ui/login/states/MissingAIPLicense$RefreshState;
/*     */     //   1710: astore #15
/*     */     //   1712: aload #10
/*     */     //   1714: checkcast kotlin/jvm/functions/Function0
/*     */     //   1717: aload #11
/*     */     //   1719: checkcast kotlin/jvm/functions/Function0
/*     */     //   1722: aload #12
/*     */     //   1724: checkcast kotlin/jvm/functions/Function0
/*     */     //   1727: aload #13
/*     */     //   1729: checkcast kotlin/jvm/functions/Function0
/*     */     //   1732: aload #9
/*     */     //   1734: aload #14
/*     */     //   1736: aload #15
/*     */     //   1738: aload_2
/*     */     //   1739: iconst_0
/*     */     //   1740: iconst_0
/*     */     //   1741: invokestatic RequestTrial : (Lkotlin/jvm/functions/Function0;Lkotlin/jvm/functions/Function0;Lkotlin/jvm/functions/Function0;Lkotlin/jvm/functions/Function0;Ljava/lang/String;Ljava/lang/String;Lcom/intellij/ml/llm/matterhorn/ej/ui/login/states/MissingAIPLicense$RefreshState;Landroidx/compose/runtime/Composer;II)V
/*     */     //   1744: aload_2
/*     */     //   1745: invokeinterface endReplaceGroup : ()V
/*     */     //   1750: goto -> 3800
/*     */     //   1753: aload #8
/*     */     //   1755: instanceof com/intellij/ml/llm/matterhorn/ej/ui/login/states/MissingAIPLicense$TrialRequestState$RequestFailedAndCanTryAgain
/*     */     //   1758: ifeq -> 2278
/*     */     //   1761: aload_2
/*     */     //   1762: ldc_w 1204586187
/*     */     //   1765: invokeinterface startReplaceGroup : (I)V
/*     */     //   1770: aload_1
/*     */     //   1771: dup
/*     */     //   1772: ifnonnull -> 1778
/*     */     //   1775: pop
/*     */     //   1776: ldc ''
/*     */     //   1778: astore #9
/*     */     //   1780: aload_0
/*     */     //   1781: checkcast com/intellij/ml/llm/matterhorn/ej/ui/login/states/MissingAIPLicense
/*     */     //   1784: astore #11
/*     */     //   1786: aload_2
/*     */     //   1787: ldc_w 177410353
/*     */     //   1790: invokeinterface startReplaceGroup : (I)V
/*     */     //   1795: aload_2
/*     */     //   1796: astore #13
/*     */     //   1798: aload_2
/*     */     //   1799: aload #11
/*     */     //   1801: invokeinterface changedInstance : (Ljava/lang/Object;)Z
/*     */     //   1806: istore #14
/*     */     //   1808: iconst_0
/*     */     //   1809: istore #15
/*     */     //   1811: aload #13
/*     */     //   1813: invokeinterface rememberedValue : ()Ljava/lang/Object;
/*     */     //   1818: astore #16
/*     */     //   1820: iconst_0
/*     */     //   1821: istore #17
/*     */     //   1823: iload #14
/*     */     //   1825: ifne -> 1839
/*     */     //   1828: aload #16
/*     */     //   1830: getstatic androidx/compose/runtime/Composer.Companion : Landroidx/compose/runtime/Composer$Companion;
/*     */     //   1833: invokevirtual getEmpty : ()Ljava/lang/Object;
/*     */     //   1836: if_acmpne -> 1870
/*     */     //   1839: iconst_0
/*     */     //   1840: istore #18
/*     */     //   1842: new com/intellij/ml/llm/matterhorn/ej/ui/login/GrazieActivationPageComponentKt$GrazieActivationPageComponent$9$1
/*     */     //   1845: dup
/*     */     //   1846: aload #11
/*     */     //   1848: invokespecial <init> : (Ljava/lang/Object;)V
/*     */     //   1851: checkcast kotlin/reflect/KFunction
/*     */     //   1854: astore #19
/*     */     //   1856: aload #13
/*     */     //   1858: aload #19
/*     */     //   1860: invokeinterface updateRememberedValue : (Ljava/lang/Object;)V
/*     */     //   1865: aload #19
/*     */     //   1867: goto -> 1872
/*     */     //   1870: aload #16
/*     */     //   1872: nop
/*     */     //   1873: nop
/*     */     //   1874: nop
/*     */     //   1875: checkcast kotlin/reflect/KFunction
/*     */     //   1878: astore #12
/*     */     //   1880: aload_2
/*     */     //   1881: invokeinterface endReplaceGroup : ()V
/*     */     //   1886: aload #12
/*     */     //   1888: astore #10
/*     */     //   1890: aload_0
/*     */     //   1891: checkcast com/intellij/ml/llm/matterhorn/ej/ui/login/states/MissingAIPLicense
/*     */     //   1894: astore #12
/*     */     //   1896: aload_2
/*     */     //   1897: ldc_w 177412155
/*     */     //   1900: invokeinterface startReplaceGroup : (I)V
/*     */     //   1905: aload_2
/*     */     //   1906: astore #14
/*     */     //   1908: aload_2
/*     */     //   1909: aload #12
/*     */     //   1911: invokeinterface changedInstance : (Ljava/lang/Object;)Z
/*     */     //   1916: istore #15
/*     */     //   1918: iconst_0
/*     */     //   1919: istore #16
/*     */     //   1921: aload #14
/*     */     //   1923: invokeinterface rememberedValue : ()Ljava/lang/Object;
/*     */     //   1928: astore #17
/*     */     //   1930: iconst_0
/*     */     //   1931: istore #18
/*     */     //   1933: iload #15
/*     */     //   1935: ifne -> 1949
/*     */     //   1938: aload #17
/*     */     //   1940: getstatic androidx/compose/runtime/Composer.Companion : Landroidx/compose/runtime/Composer$Companion;
/*     */     //   1943: invokevirtual getEmpty : ()Ljava/lang/Object;
/*     */     //   1946: if_acmpne -> 1980
/*     */     //   1949: iconst_0
/*     */     //   1950: istore #19
/*     */     //   1952: new com/intellij/ml/llm/matterhorn/ej/ui/login/GrazieActivationPageComponentKt$GrazieActivationPageComponent$10$1
/*     */     //   1955: dup
/*     */     //   1956: aload #12
/*     */     //   1958: invokespecial <init> : (Ljava/lang/Object;)V
/*     */     //   1961: checkcast kotlin/reflect/KFunction
/*     */     //   1964: astore #20
/*     */     //   1966: aload #14
/*     */     //   1968: aload #20
/*     */     //   1970: invokeinterface updateRememberedValue : (Ljava/lang/Object;)V
/*     */     //   1975: aload #20
/*     */     //   1977: goto -> 1982
/*     */     //   1980: aload #17
/*     */     //   1982: nop
/*     */     //   1983: nop
/*     */     //   1984: nop
/*     */     //   1985: checkcast kotlin/reflect/KFunction
/*     */     //   1988: astore #13
/*     */     //   1990: aload_2
/*     */     //   1991: invokeinterface endReplaceGroup : ()V
/*     */     //   1996: aload #13
/*     */     //   1998: astore #11
/*     */     //   2000: aload_0
/*     */     //   2001: checkcast com/intellij/ml/llm/matterhorn/ej/ui/login/states/MissingAIPLicense
/*     */     //   2004: astore #13
/*     */     //   2006: aload_2
/*     */     //   2007: ldc_w 177414007
/*     */     //   2010: invokeinterface startReplaceGroup : (I)V
/*     */     //   2015: aload_2
/*     */     //   2016: astore #15
/*     */     //   2018: aload_2
/*     */     //   2019: aload #13
/*     */     //   2021: invokeinterface changedInstance : (Ljava/lang/Object;)Z
/*     */     //   2026: istore #16
/*     */     //   2028: iconst_0
/*     */     //   2029: istore #17
/*     */     //   2031: aload #15
/*     */     //   2033: invokeinterface rememberedValue : ()Ljava/lang/Object;
/*     */     //   2038: astore #18
/*     */     //   2040: iconst_0
/*     */     //   2041: istore #19
/*     */     //   2043: iload #16
/*     */     //   2045: ifne -> 2059
/*     */     //   2048: aload #18
/*     */     //   2050: getstatic androidx/compose/runtime/Composer.Companion : Landroidx/compose/runtime/Composer$Companion;
/*     */     //   2053: invokevirtual getEmpty : ()Ljava/lang/Object;
/*     */     //   2056: if_acmpne -> 2090
/*     */     //   2059: iconst_0
/*     */     //   2060: istore #20
/*     */     //   2062: new com/intellij/ml/llm/matterhorn/ej/ui/login/GrazieActivationPageComponentKt$GrazieActivationPageComponent$11$1
/*     */     //   2065: dup
/*     */     //   2066: aload #13
/*     */     //   2068: invokespecial <init> : (Ljava/lang/Object;)V
/*     */     //   2071: checkcast kotlin/reflect/KFunction
/*     */     //   2074: astore #21
/*     */     //   2076: aload #15
/*     */     //   2078: aload #21
/*     */     //   2080: invokeinterface updateRememberedValue : (Ljava/lang/Object;)V
/*     */     //   2085: aload #21
/*     */     //   2087: goto -> 2092
/*     */     //   2090: aload #18
/*     */     //   2092: nop
/*     */     //   2093: nop
/*     */     //   2094: nop
/*     */     //   2095: checkcast kotlin/reflect/KFunction
/*     */     //   2098: astore #14
/*     */     //   2100: aload_2
/*     */     //   2101: invokeinterface endReplaceGroup : ()V
/*     */     //   2106: aload #14
/*     */     //   2108: astore #12
/*     */     //   2110: aload_0
/*     */     //   2111: checkcast com/intellij/ml/llm/matterhorn/ej/ui/login/states/MissingAIPLicense
/*     */     //   2114: astore #14
/*     */     //   2116: aload_2
/*     */     //   2117: ldc_w 177415575
/*     */     //   2120: invokeinterface startReplaceGroup : (I)V
/*     */     //   2125: aload_2
/*     */     //   2126: astore #16
/*     */     //   2128: aload_2
/*     */     //   2129: aload #14
/*     */     //   2131: invokeinterface changedInstance : (Ljava/lang/Object;)Z
/*     */     //   2136: istore #17
/*     */     //   2138: iconst_0
/*     */     //   2139: istore #18
/*     */     //   2141: aload #16
/*     */     //   2143: invokeinterface rememberedValue : ()Ljava/lang/Object;
/*     */     //   2148: astore #19
/*     */     //   2150: iconst_0
/*     */     //   2151: istore #20
/*     */     //   2153: iload #17
/*     */     //   2155: ifne -> 2169
/*     */     //   2158: aload #19
/*     */     //   2160: getstatic androidx/compose/runtime/Composer.Companion : Landroidx/compose/runtime/Composer$Companion;
/*     */     //   2163: invokevirtual getEmpty : ()Ljava/lang/Object;
/*     */     //   2166: if_acmpne -> 2200
/*     */     //   2169: iconst_0
/*     */     //   2170: istore #21
/*     */     //   2172: new com/intellij/ml/llm/matterhorn/ej/ui/login/GrazieActivationPageComponentKt$GrazieActivationPageComponent$12$1
/*     */     //   2175: dup
/*     */     //   2176: aload #14
/*     */     //   2178: invokespecial <init> : (Ljava/lang/Object;)V
/*     */     //   2181: checkcast kotlin/reflect/KFunction
/*     */     //   2184: astore #22
/*     */     //   2186: aload #16
/*     */     //   2188: aload #22
/*     */     //   2190: invokeinterface updateRememberedValue : (Ljava/lang/Object;)V
/*     */     //   2195: aload #22
/*     */     //   2197: goto -> 2202
/*     */     //   2200: aload #19
/*     */     //   2202: nop
/*     */     //   2203: nop
/*     */     //   2204: nop
/*     */     //   2205: checkcast kotlin/reflect/KFunction
/*     */     //   2208: astore #15
/*     */     //   2210: aload_2
/*     */     //   2211: invokeinterface endReplaceGroup : ()V
/*     */     //   2216: aload #15
/*     */     //   2218: astore #13
/*     */     //   2220: aload #8
/*     */     //   2222: checkcast com/intellij/ml/llm/matterhorn/ej/ui/login/states/MissingAIPLicense$TrialRequestState$RequestFailedAndCanTryAgain
/*     */     //   2225: invokevirtual getReason : ()Ljava/lang/String;
/*     */     //   2228: astore #14
/*     */     //   2230: aload #7
/*     */     //   2232: invokestatic GrazieActivationPageComponent$lambda$2 : (Landroidx/compose/runtime/State;)Lcom/intellij/ml/llm/matterhorn/ej/ui/login/states/MissingAIPLicense$RefreshState;
/*     */     //   2235: astore #15
/*     */     //   2237: aload #10
/*     */     //   2239: checkcast kotlin/jvm/functions/Function0
/*     */     //   2242: aload #11
/*     */     //   2244: checkcast kotlin/jvm/functions/Function0
/*     */     //   2247: aload #12
/*     */     //   2249: checkcast kotlin/jvm/functions/Function0
/*     */     //   2252: aload #13
/*     */     //   2254: checkcast kotlin/jvm/functions/Function0
/*     */     //   2257: aload #9
/*     */     //   2259: aload #14
/*     */     //   2261: aload #15
/*     */     //   2263: aload_2
/*     */     //   2264: iconst_0
/*     */     //   2265: iconst_0
/*     */     //   2266: invokestatic RequestTrial : (Lkotlin/jvm/functions/Function0;Lkotlin/jvm/functions/Function0;Lkotlin/jvm/functions/Function0;Lkotlin/jvm/functions/Function0;Ljava/lang/String;Ljava/lang/String;Lcom/intellij/ml/llm/matterhorn/ej/ui/login/states/MissingAIPLicense$RefreshState;Landroidx/compose/runtime/Composer;II)V
/*     */     //   2269: aload_2
/*     */     //   2270: invokeinterface endReplaceGroup : ()V
/*     */     //   2275: goto -> 3800
/*     */     //   2278: aload #8
/*     */     //   2280: instanceof com/intellij/ml/llm/matterhorn/ej/ui/login/states/MissingAIPLicense$TrialRequestState$TrialDenied
/*     */     //   2283: ifeq -> 2581
/*     */     //   2286: aload_2
/*     */     //   2287: ldc_w 1205113342
/*     */     //   2290: invokeinterface startReplaceGroup : (I)V
/*     */     //   2295: aload #8
/*     */     //   2297: checkcast com/intellij/ml/llm/matterhorn/ej/ui/login/states/MissingAIPLicense$TrialRequestState$TrialDenied
/*     */     //   2300: invokevirtual getReason : ()Ljava/lang/String;
/*     */     //   2303: ldc_w 'Upgrade your License'
/*     */     //   2306: aload_0
/*     */     //   2307: checkcast com/intellij/ml/llm/matterhorn/ej/ui/login/states/MissingAIPLicense
/*     */     //   2310: astore #9
/*     */     //   2312: aload_2
/*     */     //   2313: ldc_w 177427959
/*     */     //   2316: invokeinterface startReplaceGroup : (I)V
/*     */     //   2321: aload_2
/*     */     //   2322: astore #11
/*     */     //   2324: aload_2
/*     */     //   2325: aload #9
/*     */     //   2327: invokeinterface changedInstance : (Ljava/lang/Object;)Z
/*     */     //   2332: istore #12
/*     */     //   2334: iconst_0
/*     */     //   2335: istore #13
/*     */     //   2337: aload #11
/*     */     //   2339: invokeinterface rememberedValue : ()Ljava/lang/Object;
/*     */     //   2344: astore #14
/*     */     //   2346: iconst_0
/*     */     //   2347: istore #15
/*     */     //   2349: iload #12
/*     */     //   2351: ifne -> 2365
/*     */     //   2354: aload #14
/*     */     //   2356: getstatic androidx/compose/runtime/Composer.Companion : Landroidx/compose/runtime/Composer$Companion;
/*     */     //   2359: invokevirtual getEmpty : ()Ljava/lang/Object;
/*     */     //   2362: if_acmpne -> 2408
/*     */     //   2365: astore #26
/*     */     //   2367: astore #23
/*     */     //   2369: iconst_0
/*     */     //   2370: istore #16
/*     */     //   2372: new com/intellij/ml/llm/matterhorn/ej/ui/login/GrazieActivationPageComponentKt$GrazieActivationPageComponent$13$1
/*     */     //   2375: dup
/*     */     //   2376: aload #9
/*     */     //   2378: invokespecial <init> : (Ljava/lang/Object;)V
/*     */     //   2381: checkcast kotlin/reflect/KFunction
/*     */     //   2384: astore #27
/*     */     //   2386: aload #23
/*     */     //   2388: aload #26
/*     */     //   2390: aload #27
/*     */     //   2392: astore #17
/*     */     //   2394: aload #11
/*     */     //   2396: aload #17
/*     */     //   2398: invokeinterface updateRememberedValue : (Ljava/lang/Object;)V
/*     */     //   2403: aload #17
/*     */     //   2405: goto -> 2410
/*     */     //   2408: aload #14
/*     */     //   2410: nop
/*     */     //   2411: nop
/*     */     //   2412: nop
/*     */     //   2413: checkcast kotlin/reflect/KFunction
/*     */     //   2416: astore #10
/*     */     //   2418: aload_2
/*     */     //   2419: invokeinterface endReplaceGroup : ()V
/*     */     //   2424: aload #10
/*     */     //   2426: checkcast kotlin/jvm/functions/Function0
/*     */     //   2429: astore #28
/*     */     //   2431: astore #29
/*     */     //   2433: new com/intellij/ml/llm/matterhorn/ej/ui/tasks/chain/header/Action
/*     */     //   2436: dup
/*     */     //   2437: aload #29
/*     */     //   2439: aload #28
/*     */     //   2441: invokespecial <init> : (Ljava/lang/String;Lkotlin/jvm/functions/Function0;)V
/*     */     //   2444: aload_0
/*     */     //   2445: checkcast com/intellij/ml/llm/matterhorn/ej/ui/login/states/MissingAIPLicense
/*     */     //   2448: astore #9
/*     */     //   2450: aload_2
/*     */     //   2451: ldc_w 177429559
/*     */     //   2454: invokeinterface startReplaceGroup : (I)V
/*     */     //   2459: aload_2
/*     */     //   2460: astore #11
/*     */     //   2462: aload_2
/*     */     //   2463: aload #9
/*     */     //   2465: invokeinterface changedInstance : (Ljava/lang/Object;)Z
/*     */     //   2470: istore #12
/*     */     //   2472: iconst_0
/*     */     //   2473: istore #13
/*     */     //   2475: aload #11
/*     */     //   2477: invokeinterface rememberedValue : ()Ljava/lang/Object;
/*     */     //   2482: astore #14
/*     */     //   2484: iconst_0
/*     */     //   2485: istore #15
/*     */     //   2487: iload #12
/*     */     //   2489: ifne -> 2503
/*     */     //   2492: aload #14
/*     */     //   2494: getstatic androidx/compose/runtime/Composer.Companion : Landroidx/compose/runtime/Composer$Companion;
/*     */     //   2497: invokevirtual getEmpty : ()Ljava/lang/Object;
/*     */     //   2500: if_acmpne -> 2546
/*     */     //   2503: astore #24
/*     */     //   2505: astore #23
/*     */     //   2507: iconst_0
/*     */     //   2508: istore #16
/*     */     //   2510: new com/intellij/ml/llm/matterhorn/ej/ui/login/GrazieActivationPageComponentKt$GrazieActivationPageComponent$14$1
/*     */     //   2513: dup
/*     */     //   2514: aload #9
/*     */     //   2516: invokespecial <init> : (Ljava/lang/Object;)V
/*     */     //   2519: checkcast kotlin/reflect/KFunction
/*     */     //   2522: astore #25
/*     */     //   2524: aload #23
/*     */     //   2526: aload #24
/*     */     //   2528: aload #25
/*     */     //   2530: astore #17
/*     */     //   2532: aload #11
/*     */     //   2534: aload #17
/*     */     //   2536: invokeinterface updateRememberedValue : (Ljava/lang/Object;)V
/*     */     //   2541: aload #17
/*     */     //   2543: goto -> 2548
/*     */     //   2546: aload #14
/*     */     //   2548: nop
/*     */     //   2549: nop
/*     */     //   2550: nop
/*     */     //   2551: checkcast kotlin/reflect/KFunction
/*     */     //   2554: astore #10
/*     */     //   2556: aload_2
/*     */     //   2557: invokeinterface endReplaceGroup : ()V
/*     */     //   2562: aload #10
/*     */     //   2564: checkcast kotlin/jvm/functions/Function0
/*     */     //   2567: aload_2
/*     */     //   2568: iconst_0
/*     */     //   2569: invokestatic TrialUnavailable : (Ljava/lang/String;Lcom/intellij/ml/llm/matterhorn/ej/ui/tasks/chain/header/Action;Lkotlin/jvm/functions/Function0;Landroidx/compose/runtime/Composer;I)V
/*     */     //   2572: aload_2
/*     */     //   2573: invokeinterface endReplaceGroup : ()V
/*     */     //   2578: goto -> 3800
/*     */     //   2581: aload #8
/*     */     //   2583: instanceof com/intellij/ml/llm/matterhorn/ej/ui/login/states/MissingAIPLicense$TrialRequestState$TrialMaxCountExceeded
/*     */     //   2586: ifeq -> 2880
/*     */     //   2589: aload_2
/*     */     //   2590: ldc_w 1205480413
/*     */     //   2593: invokeinterface startReplaceGroup : (I)V
/*     */     //   2598: ldc_w 'Your trial may have ended or your balance needs a top-up. Head to AI Hub for details.'
/*     */     //   2601: ldc_w 'Review'
/*     */     //   2604: aload_0
/*     */     //   2605: checkcast com/intellij/ml/llm/matterhorn/ej/ui/login/states/MissingAIPLicense
/*     */     //   2608: astore #9
/*     */     //   2610: aload_2
/*     */     //   2611: ldc_w 177441815
/*     */     //   2614: invokeinterface startReplaceGroup : (I)V
/*     */     //   2619: aload_2
/*     */     //   2620: astore #11
/*     */     //   2622: aload_2
/*     */     //   2623: aload #9
/*     */     //   2625: invokeinterface changedInstance : (Ljava/lang/Object;)Z
/*     */     //   2630: istore #12
/*     */     //   2632: iconst_0
/*     */     //   2633: istore #13
/*     */     //   2635: aload #11
/*     */     //   2637: invokeinterface rememberedValue : ()Ljava/lang/Object;
/*     */     //   2642: astore #14
/*     */     //   2644: iconst_0
/*     */     //   2645: istore #15
/*     */     //   2647: iload #12
/*     */     //   2649: ifne -> 2663
/*     */     //   2652: aload #14
/*     */     //   2654: getstatic androidx/compose/runtime/Composer.Companion : Landroidx/compose/runtime/Composer$Companion;
/*     */     //   2657: invokevirtual getEmpty : ()Ljava/lang/Object;
/*     */     //   2660: if_acmpne -> 2706
/*     */     //   2663: astore #26
/*     */     //   2665: astore #23
/*     */     //   2667: iconst_0
/*     */     //   2668: istore #16
/*     */     //   2670: new com/intellij/ml/llm/matterhorn/ej/ui/login/GrazieActivationPageComponentKt$GrazieActivationPageComponent$15$1
/*     */     //   2673: dup
/*     */     //   2674: aload #9
/*     */     //   2676: invokespecial <init> : (Ljava/lang/Object;)V
/*     */     //   2679: checkcast kotlin/reflect/KFunction
/*     */     //   2682: astore #27
/*     */     //   2684: aload #23
/*     */     //   2686: aload #26
/*     */     //   2688: aload #27
/*     */     //   2690: astore #17
/*     */     //   2692: aload #11
/*     */     //   2694: aload #17
/*     */     //   2696: invokeinterface updateRememberedValue : (Ljava/lang/Object;)V
/*     */     //   2701: aload #17
/*     */     //   2703: goto -> 2708
/*     */     //   2706: aload #14
/*     */     //   2708: nop
/*     */     //   2709: nop
/*     */     //   2710: nop
/*     */     //   2711: checkcast kotlin/reflect/KFunction
/*     */     //   2714: astore #10
/*     */     //   2716: aload_2
/*     */     //   2717: invokeinterface endReplaceGroup : ()V
/*     */     //   2722: aload #10
/*     */     //   2724: checkcast kotlin/jvm/functions/Function0
/*     */     //   2727: astore #30
/*     */     //   2729: astore #31
/*     */     //   2731: new com/intellij/ml/llm/matterhorn/ej/ui/tasks/chain/header/Action
/*     */     //   2734: dup
/*     */     //   2735: aload #31
/*     */     //   2737: aload #30
/*     */     //   2739: invokespecial <init> : (Ljava/lang/String;Lkotlin/jvm/functions/Function0;)V
/*     */     //   2742: aload_0
/*     */     //   2743: checkcast com/intellij/ml/llm/matterhorn/ej/ui/login/states/MissingAIPLicense
/*     */     //   2746: astore #9
/*     */     //   2748: aload_2
/*     */     //   2749: ldc_w 177443415
/*     */     //   2752: invokeinterface startReplaceGroup : (I)V
/*     */     //   2757: aload_2
/*     */     //   2758: astore #11
/*     */     //   2760: aload_2
/*     */     //   2761: aload #9
/*     */     //   2763: invokeinterface changedInstance : (Ljava/lang/Object;)Z
/*     */     //   2768: istore #12
/*     */     //   2770: iconst_0
/*     */     //   2771: istore #13
/*     */     //   2773: aload #11
/*     */     //   2775: invokeinterface rememberedValue : ()Ljava/lang/Object;
/*     */     //   2780: astore #14
/*     */     //   2782: iconst_0
/*     */     //   2783: istore #15
/*     */     //   2785: iload #12
/*     */     //   2787: ifne -> 2801
/*     */     //   2790: aload #14
/*     */     //   2792: getstatic androidx/compose/runtime/Composer.Companion : Landroidx/compose/runtime/Composer$Companion;
/*     */     //   2795: invokevirtual getEmpty : ()Ljava/lang/Object;
/*     */     //   2798: if_acmpne -> 2844
/*     */     //   2801: astore #24
/*     */     //   2803: astore #23
/*     */     //   2805: iconst_0
/*     */     //   2806: istore #16
/*     */     //   2808: new com/intellij/ml/llm/matterhorn/ej/ui/login/GrazieActivationPageComponentKt$GrazieActivationPageComponent$16$1
/*     */     //   2811: dup
/*     */     //   2812: aload #9
/*     */     //   2814: invokespecial <init> : (Ljava/lang/Object;)V
/*     */     //   2817: checkcast kotlin/reflect/KFunction
/*     */     //   2820: astore #25
/*     */     //   2822: aload #23
/*     */     //   2824: aload #24
/*     */     //   2826: aload #25
/*     */     //   2828: astore #17
/*     */     //   2830: aload #11
/*     */     //   2832: aload #17
/*     */     //   2834: invokeinterface updateRememberedValue : (Ljava/lang/Object;)V
/*     */     //   2839: aload #17
/*     */     //   2841: goto -> 2846
/*     */     //   2844: aload #14
/*     */     //   2846: nop
/*     */     //   2847: nop
/*     */     //   2848: nop
/*     */     //   2849: checkcast kotlin/reflect/KFunction
/*     */     //   2852: astore #10
/*     */     //   2854: aload_2
/*     */     //   2855: invokeinterface endReplaceGroup : ()V
/*     */     //   2860: aload #10
/*     */     //   2862: checkcast kotlin/jvm/functions/Function0
/*     */     //   2865: aload_2
/*     */     //   2866: bipush #6
/*     */     //   2868: invokestatic TrialUnavailable : (Ljava/lang/String;Lcom/intellij/ml/llm/matterhorn/ej/ui/tasks/chain/header/Action;Lkotlin/jvm/functions/Function0;Landroidx/compose/runtime/Composer;I)V
/*     */     //   2871: aload_2
/*     */     //   2872: invokeinterface endReplaceGroup : ()V
/*     */     //   2877: goto -> 3800
/*     */     //   2880: aload #8
/*     */     //   2882: instanceof com/intellij/ml/llm/matterhorn/ej/ui/login/states/MissingAIPLicense$TrialRequestState$TrialNoLinkedPaymentMethod
/*     */     //   2885: ifeq -> 3179
/*     */     //   2888: aload_2
/*     */     //   2889: ldc_w 1205914754
/*     */     //   2892: invokeinterface startReplaceGroup : (I)V
/*     */     //   2897: ldc_w 'Trial is not available because no payment method is linked.'
/*     */     //   2900: ldc_w 'Review Payment Method'
/*     */     //   2903: aload_0
/*     */     //   2904: checkcast com/intellij/ml/llm/matterhorn/ej/ui/login/states/MissingAIPLicense
/*     */     //   2907: astore #9
/*     */     //   2909: aload_2
/*     */     //   2910: ldc_w 177455516
/*     */     //   2913: invokeinterface startReplaceGroup : (I)V
/*     */     //   2918: aload_2
/*     */     //   2919: astore #11
/*     */     //   2921: aload_2
/*     */     //   2922: aload #9
/*     */     //   2924: invokeinterface changedInstance : (Ljava/lang/Object;)Z
/*     */     //   2929: istore #12
/*     */     //   2931: iconst_0
/*     */     //   2932: istore #13
/*     */     //   2934: aload #11
/*     */     //   2936: invokeinterface rememberedValue : ()Ljava/lang/Object;
/*     */     //   2941: astore #14
/*     */     //   2943: iconst_0
/*     */     //   2944: istore #15
/*     */     //   2946: iload #12
/*     */     //   2948: ifne -> 2962
/*     */     //   2951: aload #14
/*     */     //   2953: getstatic androidx/compose/runtime/Composer.Companion : Landroidx/compose/runtime/Composer$Companion;
/*     */     //   2956: invokevirtual getEmpty : ()Ljava/lang/Object;
/*     */     //   2959: if_acmpne -> 3005
/*     */     //   2962: astore #26
/*     */     //   2964: astore #23
/*     */     //   2966: iconst_0
/*     */     //   2967: istore #16
/*     */     //   2969: new com/intellij/ml/llm/matterhorn/ej/ui/login/GrazieActivationPageComponentKt$GrazieActivationPageComponent$17$1
/*     */     //   2972: dup
/*     */     //   2973: aload #9
/*     */     //   2975: invokespecial <init> : (Ljava/lang/Object;)V
/*     */     //   2978: checkcast kotlin/reflect/KFunction
/*     */     //   2981: astore #27
/*     */     //   2983: aload #23
/*     */     //   2985: aload #26
/*     */     //   2987: aload #27
/*     */     //   2989: astore #17
/*     */     //   2991: aload #11
/*     */     //   2993: aload #17
/*     */     //   2995: invokeinterface updateRememberedValue : (Ljava/lang/Object;)V
/*     */     //   3000: aload #17
/*     */     //   3002: goto -> 3007
/*     */     //   3005: aload #14
/*     */     //   3007: nop
/*     */     //   3008: nop
/*     */     //   3009: nop
/*     */     //   3010: checkcast kotlin/reflect/KFunction
/*     */     //   3013: astore #10
/*     */     //   3015: aload_2
/*     */     //   3016: invokeinterface endReplaceGroup : ()V
/*     */     //   3021: aload #10
/*     */     //   3023: checkcast kotlin/jvm/functions/Function0
/*     */     //   3026: astore #32
/*     */     //   3028: astore #33
/*     */     //   3030: new com/intellij/ml/llm/matterhorn/ej/ui/tasks/chain/header/Action
/*     */     //   3033: dup
/*     */     //   3034: aload #33
/*     */     //   3036: aload #32
/*     */     //   3038: invokespecial <init> : (Ljava/lang/String;Lkotlin/jvm/functions/Function0;)V
/*     */     //   3041: aload_0
/*     */     //   3042: checkcast com/intellij/ml/llm/matterhorn/ej/ui/login/states/MissingAIPLicense
/*     */     //   3045: astore #9
/*     */     //   3047: aload_2
/*     */     //   3048: ldc_w 177457271
/*     */     //   3051: invokeinterface startReplaceGroup : (I)V
/*     */     //   3056: aload_2
/*     */     //   3057: astore #11
/*     */     //   3059: aload_2
/*     */     //   3060: aload #9
/*     */     //   3062: invokeinterface changedInstance : (Ljava/lang/Object;)Z
/*     */     //   3067: istore #12
/*     */     //   3069: iconst_0
/*     */     //   3070: istore #13
/*     */     //   3072: aload #11
/*     */     //   3074: invokeinterface rememberedValue : ()Ljava/lang/Object;
/*     */     //   3079: astore #14
/*     */     //   3081: iconst_0
/*     */     //   3082: istore #15
/*     */     //   3084: iload #12
/*     */     //   3086: ifne -> 3100
/*     */     //   3089: aload #14
/*     */     //   3091: getstatic androidx/compose/runtime/Composer.Companion : Landroidx/compose/runtime/Composer$Companion;
/*     */     //   3094: invokevirtual getEmpty : ()Ljava/lang/Object;
/*     */     //   3097: if_acmpne -> 3143
/*     */     //   3100: astore #24
/*     */     //   3102: astore #23
/*     */     //   3104: iconst_0
/*     */     //   3105: istore #16
/*     */     //   3107: new com/intellij/ml/llm/matterhorn/ej/ui/login/GrazieActivationPageComponentKt$GrazieActivationPageComponent$18$1
/*     */     //   3110: dup
/*     */     //   3111: aload #9
/*     */     //   3113: invokespecial <init> : (Ljava/lang/Object;)V
/*     */     //   3116: checkcast kotlin/reflect/KFunction
/*     */     //   3119: astore #25
/*     */     //   3121: aload #23
/*     */     //   3123: aload #24
/*     */     //   3125: aload #25
/*     */     //   3127: astore #17
/*     */     //   3129: aload #11
/*     */     //   3131: aload #17
/*     */     //   3133: invokeinterface updateRememberedValue : (Ljava/lang/Object;)V
/*     */     //   3138: aload #17
/*     */     //   3140: goto -> 3145
/*     */     //   3143: aload #14
/*     */     //   3145: nop
/*     */     //   3146: nop
/*     */     //   3147: nop
/*     */     //   3148: checkcast kotlin/reflect/KFunction
/*     */     //   3151: astore #10
/*     */     //   3153: aload_2
/*     */     //   3154: invokeinterface endReplaceGroup : ()V
/*     */     //   3159: aload #10
/*     */     //   3161: checkcast kotlin/jvm/functions/Function0
/*     */     //   3164: aload_2
/*     */     //   3165: bipush #6
/*     */     //   3167: invokestatic TrialUnavailable : (Ljava/lang/String;Lcom/intellij/ml/llm/matterhorn/ej/ui/tasks/chain/header/Action;Lkotlin/jvm/functions/Function0;Landroidx/compose/runtime/Composer;I)V
/*     */     //   3170: aload_2
/*     */     //   3171: invokeinterface endReplaceGroup : ()V
/*     */     //   3176: goto -> 3800
/*     */     //   3179: aload #8
/*     */     //   3181: instanceof com/intellij/ml/llm/matterhorn/ej/ui/login/states/MissingAIPLicense$TrialRequestState$CountryUnknown
/*     */     //   3184: ifeq -> 3478
/*     */     //   3187: aload_2
/*     */     //   3188: ldc_w 1206334184
/*     */     //   3191: invokeinterface startReplaceGroup : (I)V
/*     */     //   3196: ldc_w 'The country/region field in your JetBrains Account is empty. To start a trial, add this information in your account.'
/*     */     //   3199: ldc_w 'Review Region Settings'
/*     */     //   3202: aload_0
/*     */     //   3203: checkcast com/intellij/ml/llm/matterhorn/ej/ui/login/states/MissingAIPLicense
/*     */     //   3206: astore #9
/*     */     //   3208: aload_2
/*     */     //   3209: ldc_w 177470813
/*     */     //   3212: invokeinterface startReplaceGroup : (I)V
/*     */     //   3217: aload_2
/*     */     //   3218: astore #11
/*     */     //   3220: aload_2
/*     */     //   3221: aload #9
/*     */     //   3223: invokeinterface changedInstance : (Ljava/lang/Object;)Z
/*     */     //   3228: istore #12
/*     */     //   3230: iconst_0
/*     */     //   3231: istore #13
/*     */     //   3233: aload #11
/*     */     //   3235: invokeinterface rememberedValue : ()Ljava/lang/Object;
/*     */     //   3240: astore #14
/*     */     //   3242: iconst_0
/*     */     //   3243: istore #15
/*     */     //   3245: iload #12
/*     */     //   3247: ifne -> 3261
/*     */     //   3250: aload #14
/*     */     //   3252: getstatic androidx/compose/runtime/Composer.Companion : Landroidx/compose/runtime/Composer$Companion;
/*     */     //   3255: invokevirtual getEmpty : ()Ljava/lang/Object;
/*     */     //   3258: if_acmpne -> 3304
/*     */     //   3261: astore #26
/*     */     //   3263: astore #23
/*     */     //   3265: iconst_0
/*     */     //   3266: istore #16
/*     */     //   3268: new com/intellij/ml/llm/matterhorn/ej/ui/login/GrazieActivationPageComponentKt$GrazieActivationPageComponent$19$1
/*     */     //   3271: dup
/*     */     //   3272: aload #9
/*     */     //   3274: invokespecial <init> : (Ljava/lang/Object;)V
/*     */     //   3277: checkcast kotlin/reflect/KFunction
/*     */     //   3280: astore #27
/*     */     //   3282: aload #23
/*     */     //   3284: aload #26
/*     */     //   3286: aload #27
/*     */     //   3288: astore #17
/*     */     //   3290: aload #11
/*     */     //   3292: aload #17
/*     */     //   3294: invokeinterface updateRememberedValue : (Ljava/lang/Object;)V
/*     */     //   3299: aload #17
/*     */     //   3301: goto -> 3306
/*     */     //   3304: aload #14
/*     */     //   3306: nop
/*     */     //   3307: nop
/*     */     //   3308: nop
/*     */     //   3309: checkcast kotlin/reflect/KFunction
/*     */     //   3312: astore #10
/*     */     //   3314: aload_2
/*     */     //   3315: invokeinterface endReplaceGroup : ()V
/*     */     //   3320: aload #10
/*     */     //   3322: checkcast kotlin/jvm/functions/Function0
/*     */     //   3325: astore #34
/*     */     //   3327: astore #35
/*     */     //   3329: new com/intellij/ml/llm/matterhorn/ej/ui/tasks/chain/header/Action
/*     */     //   3332: dup
/*     */     //   3333: aload #35
/*     */     //   3335: aload #34
/*     */     //   3337: invokespecial <init> : (Ljava/lang/String;Lkotlin/jvm/functions/Function0;)V
/*     */     //   3340: aload_0
/*     */     //   3341: checkcast com/intellij/ml/llm/matterhorn/ej/ui/login/states/MissingAIPLicense
/*     */     //   3344: astore #9
/*     */     //   3346: aload_2
/*     */     //   3347: ldc_w 177472599
/*     */     //   3350: invokeinterface startReplaceGroup : (I)V
/*     */     //   3355: aload_2
/*     */     //   3356: astore #11
/*     */     //   3358: aload_2
/*     */     //   3359: aload #9
/*     */     //   3361: invokeinterface changedInstance : (Ljava/lang/Object;)Z
/*     */     //   3366: istore #12
/*     */     //   3368: iconst_0
/*     */     //   3369: istore #13
/*     */     //   3371: aload #11
/*     */     //   3373: invokeinterface rememberedValue : ()Ljava/lang/Object;
/*     */     //   3378: astore #14
/*     */     //   3380: iconst_0
/*     */     //   3381: istore #15
/*     */     //   3383: iload #12
/*     */     //   3385: ifne -> 3399
/*     */     //   3388: aload #14
/*     */     //   3390: getstatic androidx/compose/runtime/Composer.Companion : Landroidx/compose/runtime/Composer$Companion;
/*     */     //   3393: invokevirtual getEmpty : ()Ljava/lang/Object;
/*     */     //   3396: if_acmpne -> 3442
/*     */     //   3399: astore #24
/*     */     //   3401: astore #23
/*     */     //   3403: iconst_0
/*     */     //   3404: istore #16
/*     */     //   3406: new com/intellij/ml/llm/matterhorn/ej/ui/login/GrazieActivationPageComponentKt$GrazieActivationPageComponent$20$1
/*     */     //   3409: dup
/*     */     //   3410: aload #9
/*     */     //   3412: invokespecial <init> : (Ljava/lang/Object;)V
/*     */     //   3415: checkcast kotlin/reflect/KFunction
/*     */     //   3418: astore #25
/*     */     //   3420: aload #23
/*     */     //   3422: aload #24
/*     */     //   3424: aload #25
/*     */     //   3426: astore #17
/*     */     //   3428: aload #11
/*     */     //   3430: aload #17
/*     */     //   3432: invokeinterface updateRememberedValue : (Ljava/lang/Object;)V
/*     */     //   3437: aload #17
/*     */     //   3439: goto -> 3444
/*     */     //   3442: aload #14
/*     */     //   3444: nop
/*     */     //   3445: nop
/*     */     //   3446: nop
/*     */     //   3447: checkcast kotlin/reflect/KFunction
/*     */     //   3450: astore #10
/*     */     //   3452: aload_2
/*     */     //   3453: invokeinterface endReplaceGroup : ()V
/*     */     //   3458: aload #10
/*     */     //   3460: checkcast kotlin/jvm/functions/Function0
/*     */     //   3463: aload_2
/*     */     //   3464: bipush #6
/*     */     //   3466: invokestatic TrialUnavailable : (Ljava/lang/String;Lcom/intellij/ml/llm/matterhorn/ej/ui/tasks/chain/header/Action;Lkotlin/jvm/functions/Function0;Landroidx/compose/runtime/Composer;I)V
/*     */     //   3469: aload_2
/*     */     //   3470: invokeinterface endReplaceGroup : ()V
/*     */     //   3475: goto -> 3800
/*     */     //   3478: aload #8
/*     */     //   3480: instanceof com/intellij/ml/llm/matterhorn/ej/ui/login/states/MissingAIPLicense$TrialRequestState$CountryRestricted
/*     */     //   3483: ifeq -> 3777
/*     */     //   3486: aload_2
/*     */     //   3487: ldc_w 1206809073
/*     */     //   3490: invokeinterface startReplaceGroup : (I)V
/*     */     //   3495: ldc_w 'Due to export control regulations, we currently cannot provide services in your region.'
/*     */     //   3498: ldc_w 'Review Region Settings'
/*     */     //   3501: aload_0
/*     */     //   3502: checkcast com/intellij/ml/llm/matterhorn/ej/ui/login/states/MissingAIPLicense
/*     */     //   3505: astore #9
/*     */     //   3507: aload_2
/*     */     //   3508: ldc_w 177482877
/*     */     //   3511: invokeinterface startReplaceGroup : (I)V
/*     */     //   3516: aload_2
/*     */     //   3517: astore #11
/*     */     //   3519: aload_2
/*     */     //   3520: aload #9
/*     */     //   3522: invokeinterface changedInstance : (Ljava/lang/Object;)Z
/*     */     //   3527: istore #12
/*     */     //   3529: iconst_0
/*     */     //   3530: istore #13
/*     */     //   3532: aload #11
/*     */     //   3534: invokeinterface rememberedValue : ()Ljava/lang/Object;
/*     */     //   3539: astore #14
/*     */     //   3541: iconst_0
/*     */     //   3542: istore #15
/*     */     //   3544: iload #12
/*     */     //   3546: ifne -> 3560
/*     */     //   3549: aload #14
/*     */     //   3551: getstatic androidx/compose/runtime/Composer.Companion : Landroidx/compose/runtime/Composer$Companion;
/*     */     //   3554: invokevirtual getEmpty : ()Ljava/lang/Object;
/*     */     //   3557: if_acmpne -> 3603
/*     */     //   3560: astore #26
/*     */     //   3562: astore #23
/*     */     //   3564: iconst_0
/*     */     //   3565: istore #16
/*     */     //   3567: new com/intellij/ml/llm/matterhorn/ej/ui/login/GrazieActivationPageComponentKt$GrazieActivationPageComponent$21$1
/*     */     //   3570: dup
/*     */     //   3571: aload #9
/*     */     //   3573: invokespecial <init> : (Ljava/lang/Object;)V
/*     */     //   3576: checkcast kotlin/reflect/KFunction
/*     */     //   3579: astore #27
/*     */     //   3581: aload #23
/*     */     //   3583: aload #26
/*     */     //   3585: aload #27
/*     */     //   3587: astore #17
/*     */     //   3589: aload #11
/*     */     //   3591: aload #17
/*     */     //   3593: invokeinterface updateRememberedValue : (Ljava/lang/Object;)V
/*     */     //   3598: aload #17
/*     */     //   3600: goto -> 3605
/*     */     //   3603: aload #14
/*     */     //   3605: nop
/*     */     //   3606: nop
/*     */     //   3607: nop
/*     */     //   3608: checkcast kotlin/reflect/KFunction
/*     */     //   3611: astore #10
/*     */     //   3613: aload_2
/*     */     //   3614: invokeinterface endReplaceGroup : ()V
/*     */     //   3619: aload #10
/*     */     //   3621: checkcast kotlin/jvm/functions/Function0
/*     */     //   3624: astore #36
/*     */     //   3626: astore #37
/*     */     //   3628: new com/intellij/ml/llm/matterhorn/ej/ui/tasks/chain/header/Action
/*     */     //   3631: dup
/*     */     //   3632: aload #37
/*     */     //   3634: aload #36
/*     */     //   3636: invokespecial <init> : (Ljava/lang/String;Lkotlin/jvm/functions/Function0;)V
/*     */     //   3639: aload_0
/*     */     //   3640: checkcast com/intellij/ml/llm/matterhorn/ej/ui/login/states/MissingAIPLicense
/*     */     //   3643: astore #9
/*     */     //   3645: aload_2
/*     */     //   3646: ldc_w 177484663
/*     */     //   3649: invokeinterface startReplaceGroup : (I)V
/*     */     //   3654: aload_2
/*     */     //   3655: astore #11
/*     */     //   3657: aload_2
/*     */     //   3658: aload #9
/*     */     //   3660: invokeinterface changedInstance : (Ljava/lang/Object;)Z
/*     */     //   3665: istore #12
/*     */     //   3667: iconst_0
/*     */     //   3668: istore #13
/*     */     //   3670: aload #11
/*     */     //   3672: invokeinterface rememberedValue : ()Ljava/lang/Object;
/*     */     //   3677: astore #14
/*     */     //   3679: iconst_0
/*     */     //   3680: istore #15
/*     */     //   3682: iload #12
/*     */     //   3684: ifne -> 3698
/*     */     //   3687: aload #14
/*     */     //   3689: getstatic androidx/compose/runtime/Composer.Companion : Landroidx/compose/runtime/Composer$Companion;
/*     */     //   3692: invokevirtual getEmpty : ()Ljava/lang/Object;
/*     */     //   3695: if_acmpne -> 3741
/*     */     //   3698: astore #24
/*     */     //   3700: astore #23
/*     */     //   3702: iconst_0
/*     */     //   3703: istore #16
/*     */     //   3705: new com/intellij/ml/llm/matterhorn/ej/ui/login/GrazieActivationPageComponentKt$GrazieActivationPageComponent$22$1
/*     */     //   3708: dup
/*     */     //   3709: aload #9
/*     */     //   3711: invokespecial <init> : (Ljava/lang/Object;)V
/*     */     //   3714: checkcast kotlin/reflect/KFunction
/*     */     //   3717: astore #25
/*     */     //   3719: aload #23
/*     */     //   3721: aload #24
/*     */     //   3723: aload #25
/*     */     //   3725: astore #17
/*     */     //   3727: aload #11
/*     */     //   3729: aload #17
/*     */     //   3731: invokeinterface updateRememberedValue : (Ljava/lang/Object;)V
/*     */     //   3736: aload #17
/*     */     //   3738: goto -> 3743
/*     */     //   3741: aload #14
/*     */     //   3743: nop
/*     */     //   3744: nop
/*     */     //   3745: nop
/*     */     //   3746: checkcast kotlin/reflect/KFunction
/*     */     //   3749: astore #10
/*     */     //   3751: aload_2
/*     */     //   3752: invokeinterface endReplaceGroup : ()V
/*     */     //   3757: aload #10
/*     */     //   3759: checkcast kotlin/jvm/functions/Function0
/*     */     //   3762: aload_2
/*     */     //   3763: bipush #6
/*     */     //   3765: invokestatic TrialUnavailable : (Ljava/lang/String;Lcom/intellij/ml/llm/matterhorn/ej/ui/tasks/chain/header/Action;Lkotlin/jvm/functions/Function0;Landroidx/compose/runtime/Composer;I)V
/*     */     //   3768: aload_2
/*     */     //   3769: invokeinterface endReplaceGroup : ()V
/*     */     //   3774: goto -> 3800
/*     */     //   3777: aload_2
/*     */     //   3778: ldc_w 177368475
/*     */     //   3781: invokeinterface startReplaceGroup : (I)V
/*     */     //   3786: aload_2
/*     */     //   3787: invokeinterface endReplaceGroup : ()V
/*     */     //   3792: new kotlin/NoWhenBranchMatchedException
/*     */     //   3795: dup
/*     */     //   3796: invokespecial <init> : ()V
/*     */     //   3799: athrow
/*     */     //   3800: aload_2
/*     */     //   3801: invokeinterface endReplaceGroup : ()V
/*     */     //   3806: goto -> 3832
/*     */     //   3809: aload_2
/*     */     //   3810: ldc_w 177303045
/*     */     //   3813: invokeinterface startReplaceGroup : (I)V
/*     */     //   3818: aload_2
/*     */     //   3819: invokeinterface endReplaceGroup : ()V
/*     */     //   3824: new kotlin/NoWhenBranchMatchedException
/*     */     //   3827: dup
/*     */     //   3828: invokespecial <init> : ()V
/*     */     //   3831: athrow
/*     */     //   3832: invokestatic isTraceInProgress : ()Z
/*     */     //   3835: ifeq -> 3850
/*     */     //   3838: invokestatic traceEventEnd : ()V
/*     */     //   3841: goto -> 3850
/*     */     //   3844: aload_2
/*     */     //   3845: invokeinterface skipToGroupEnd : ()V
/*     */     //   3850: aload_2
/*     */     //   3851: invokeinterface endRestartGroup : ()Landroidx/compose/runtime/ScopeUpdateScope;
/*     */     //   3856: dup
/*     */     //   3857: ifnull -> 3876
/*     */     //   3860: aload_0
/*     */     //   3861: aload_1
/*     */     //   3862: iload_3
/*     */     //   3863: <illegal opcode> invoke : (Lcom/intellij/ml/llm/matterhorn/ej/ui/login/states/GrazieActivationState;Ljava/lang/String;I)Lkotlin/jvm/functions/Function2;
/*     */     //   3868: invokeinterface updateScope : (Lkotlin/jvm/functions/Function2;)V
/*     */     //   3873: goto -> 3877
/*     */     //   3876: pop
/*     */     //   3877: return
/*     */     // Line number table:
/*     */     //   Java source line number -> byte code offset
/*     */     //   #33	-> 6
/*     */     //   #34	-> 126
/*     */     //   #35	-> 129
/*     */     //   #37	-> 147
/*     */     //   #35	-> 150
/*     */     //   #40	-> 159
/*     */     //   #42	-> 175
/*     */     //   #40	-> 184
/*     */     //   #45	-> 193
/*     */     //   #48	-> 209
/*     */     //   #45	-> 218
/*     */     //   #52	-> 227
/*     */     //   #54	-> 246
/*     */     //   #52	-> 272
/*     */     //   #57	-> 281
/*     */     //   #58	-> 297
/*     */     //   #59	-> 313
/*     */     //   #60	-> 320
/*     */     //   #62	-> 336
/*     */     //   #60	-> 349
/*     */     //   #65	-> 358
/*     */     //   #67	-> 377
/*     */     //   #65	-> 403
/*     */     //   #70	-> 412
/*     */     //   #72	-> 431
/*     */     //   #70	-> 457
/*     */     //   #76	-> 466
/*     */     //   #78	-> 485
/*     */     //   #76	-> 494
/*     */     //   #59	-> 503
/*     */     //   #57	-> 525
/*     */     //   #83	-> 534
/*     */     //   #85	-> 550
/*     */     //   #83	-> 564
/*     */     //   #88	-> 573
/*     */     //   #90	-> 589
/*     */     //   #88	-> 608
/*     */     //   #93	-> 617
/*     */     //   #94	-> 633
/*     */     //   #95	-> 649
/*     */     //   #96	-> 665
/*     */     //   #97	-> 672
/*     */     //   #99	-> 691
/*     */     //   #191	-> 721
/*     */     //   #192	-> 733
/*     */     //   #193	-> 749
/*     */     //   #99	-> 752
/*     */     //   #193	-> 764
/*     */     //   #194	-> 766
/*     */     //   #195	-> 775
/*     */     //   #196	-> 780
/*     */     //   #192	-> 782
/*     */     //   #191	-> 783
/*     */     //   #191	-> 784
/*     */     //   #99	-> 785
/*     */     //   #100	-> 801
/*     */     //   #197	-> 831
/*     */     //   #198	-> 843
/*     */     //   #199	-> 859
/*     */     //   #100	-> 864
/*     */     //   #199	-> 879
/*     */     //   #200	-> 881
/*     */     //   #201	-> 890
/*     */     //   #202	-> 895
/*     */     //   #198	-> 897
/*     */     //   #197	-> 898
/*     */     //   #197	-> 899
/*     */     //   #100	-> 900
/*     */     //   #101	-> 916
/*     */     //   #203	-> 946
/*     */     //   #204	-> 958
/*     */     //   #205	-> 974
/*     */     //   #101	-> 981
/*     */     //   #205	-> 1001
/*     */     //   #206	-> 1003
/*     */     //   #207	-> 1012
/*     */     //   #208	-> 1017
/*     */     //   #204	-> 1019
/*     */     //   #203	-> 1020
/*     */     //   #203	-> 1021
/*     */     //   #101	-> 1022
/*     */     //   #102	-> 1038
/*     */     //   #209	-> 1068
/*     */     //   #210	-> 1080
/*     */     //   #211	-> 1096
/*     */     //   #102	-> 1105
/*     */     //   #211	-> 1127
/*     */     //   #212	-> 1129
/*     */     //   #213	-> 1138
/*     */     //   #214	-> 1143
/*     */     //   #210	-> 1145
/*     */     //   #209	-> 1146
/*     */     //   #209	-> 1147
/*     */     //   #102	-> 1148
/*     */     //   #103	-> 1164
/*     */     //   #104	-> 1173
/*     */     //   #98	-> 1182
/*     */     //   #97	-> 1185
/*     */     //   #108	-> 1194
/*     */     //   #110	-> 1216
/*     */     //   #108	-> 1219
/*     */     //   #113	-> 1228
/*     */     //   #116	-> 1245
/*     */     //   #117	-> 1255
/*     */     //   #215	-> 1286
/*     */     //   #216	-> 1298
/*     */     //   #217	-> 1314
/*     */     //   #117	-> 1317
/*     */     //   #217	-> 1329
/*     */     //   #218	-> 1331
/*     */     //   #219	-> 1340
/*     */     //   #220	-> 1345
/*     */     //   #216	-> 1347
/*     */     //   #215	-> 1348
/*     */     //   #215	-> 1349
/*     */     //   #117	-> 1350
/*     */     //   #118	-> 1365
/*     */     //   #221	-> 1396
/*     */     //   #222	-> 1408
/*     */     //   #223	-> 1424
/*     */     //   #118	-> 1427
/*     */     //   #223	-> 1439
/*     */     //   #224	-> 1441
/*     */     //   #225	-> 1450
/*     */     //   #226	-> 1455
/*     */     //   #222	-> 1457
/*     */     //   #221	-> 1458
/*     */     //   #221	-> 1459
/*     */     //   #118	-> 1460
/*     */     //   #119	-> 1475
/*     */     //   #227	-> 1506
/*     */     //   #228	-> 1518
/*     */     //   #229	-> 1534
/*     */     //   #119	-> 1537
/*     */     //   #229	-> 1549
/*     */     //   #230	-> 1551
/*     */     //   #231	-> 1560
/*     */     //   #232	-> 1565
/*     */     //   #228	-> 1567
/*     */     //   #227	-> 1568
/*     */     //   #227	-> 1569
/*     */     //   #119	-> 1570
/*     */     //   #120	-> 1585
/*     */     //   #233	-> 1616
/*     */     //   #234	-> 1628
/*     */     //   #235	-> 1644
/*     */     //   #120	-> 1647
/*     */     //   #235	-> 1659
/*     */     //   #236	-> 1661
/*     */     //   #237	-> 1670
/*     */     //   #238	-> 1675
/*     */     //   #234	-> 1677
/*     */     //   #233	-> 1678
/*     */     //   #233	-> 1679
/*     */     //   #120	-> 1680
/*     */     //   #121	-> 1695
/*     */     //   #122	-> 1705
/*     */     //   #117	-> 1712
/*     */     //   #118	-> 1717
/*     */     //   #119	-> 1722
/*     */     //   #120	-> 1727
/*     */     //   #116	-> 1732
/*     */     //   #121	-> 1734
/*     */     //   #122	-> 1736
/*     */     //   #115	-> 1741
/*     */     //   #113	-> 1744
/*     */     //   #126	-> 1753
/*     */     //   #129	-> 1770
/*     */     //   #130	-> 1780
/*     */     //   #239	-> 1811
/*     */     //   #240	-> 1823
/*     */     //   #241	-> 1839
/*     */     //   #130	-> 1842
/*     */     //   #241	-> 1854
/*     */     //   #242	-> 1856
/*     */     //   #243	-> 1865
/*     */     //   #244	-> 1870
/*     */     //   #240	-> 1872
/*     */     //   #239	-> 1873
/*     */     //   #239	-> 1874
/*     */     //   #130	-> 1875
/*     */     //   #131	-> 1890
/*     */     //   #245	-> 1921
/*     */     //   #246	-> 1933
/*     */     //   #247	-> 1949
/*     */     //   #131	-> 1952
/*     */     //   #247	-> 1964
/*     */     //   #248	-> 1966
/*     */     //   #249	-> 1975
/*     */     //   #250	-> 1980
/*     */     //   #246	-> 1982
/*     */     //   #245	-> 1983
/*     */     //   #245	-> 1984
/*     */     //   #131	-> 1985
/*     */     //   #132	-> 2000
/*     */     //   #251	-> 2031
/*     */     //   #252	-> 2043
/*     */     //   #253	-> 2059
/*     */     //   #132	-> 2062
/*     */     //   #253	-> 2074
/*     */     //   #254	-> 2076
/*     */     //   #255	-> 2085
/*     */     //   #256	-> 2090
/*     */     //   #252	-> 2092
/*     */     //   #251	-> 2093
/*     */     //   #251	-> 2094
/*     */     //   #132	-> 2095
/*     */     //   #133	-> 2110
/*     */     //   #257	-> 2141
/*     */     //   #258	-> 2153
/*     */     //   #259	-> 2169
/*     */     //   #133	-> 2172
/*     */     //   #259	-> 2184
/*     */     //   #260	-> 2186
/*     */     //   #261	-> 2195
/*     */     //   #262	-> 2200
/*     */     //   #258	-> 2202
/*     */     //   #257	-> 2203
/*     */     //   #257	-> 2204
/*     */     //   #133	-> 2205
/*     */     //   #134	-> 2220
/*     */     //   #135	-> 2230
/*     */     //   #130	-> 2237
/*     */     //   #131	-> 2242
/*     */     //   #132	-> 2247
/*     */     //   #133	-> 2252
/*     */     //   #129	-> 2257
/*     */     //   #134	-> 2259
/*     */     //   #135	-> 2261
/*     */     //   #128	-> 2266
/*     */     //   #126	-> 2269
/*     */     //   #139	-> 2278
/*     */     //   #142	-> 2295
/*     */     //   #143	-> 2303
/*     */     //   #263	-> 2337
/*     */     //   #264	-> 2349
/*     */     //   #265	-> 2365
/*     */     //   #143	-> 2372
/*     */     //   #265	-> 2392
/*     */     //   #266	-> 2394
/*     */     //   #267	-> 2403
/*     */     //   #268	-> 2408
/*     */     //   #264	-> 2410
/*     */     //   #263	-> 2411
/*     */     //   #263	-> 2412
/*     */     //   #143	-> 2413
/*     */     //   #144	-> 2444
/*     */     //   #269	-> 2475
/*     */     //   #270	-> 2487
/*     */     //   #271	-> 2503
/*     */     //   #144	-> 2510
/*     */     //   #271	-> 2530
/*     */     //   #272	-> 2532
/*     */     //   #273	-> 2541
/*     */     //   #274	-> 2546
/*     */     //   #270	-> 2548
/*     */     //   #269	-> 2549
/*     */     //   #269	-> 2550
/*     */     //   #144	-> 2551
/*     */     //   #141	-> 2569
/*     */     //   #139	-> 2572
/*     */     //   #148	-> 2581
/*     */     //   #151	-> 2598
/*     */     //   #152	-> 2601
/*     */     //   #275	-> 2635
/*     */     //   #276	-> 2647
/*     */     //   #277	-> 2663
/*     */     //   #152	-> 2670
/*     */     //   #277	-> 2690
/*     */     //   #278	-> 2692
/*     */     //   #279	-> 2701
/*     */     //   #280	-> 2706
/*     */     //   #276	-> 2708
/*     */     //   #275	-> 2709
/*     */     //   #275	-> 2710
/*     */     //   #152	-> 2711
/*     */     //   #153	-> 2742
/*     */     //   #281	-> 2773
/*     */     //   #282	-> 2785
/*     */     //   #283	-> 2801
/*     */     //   #153	-> 2808
/*     */     //   #283	-> 2828
/*     */     //   #284	-> 2830
/*     */     //   #285	-> 2839
/*     */     //   #286	-> 2844
/*     */     //   #282	-> 2846
/*     */     //   #281	-> 2847
/*     */     //   #281	-> 2848
/*     */     //   #153	-> 2849
/*     */     //   #150	-> 2868
/*     */     //   #148	-> 2871
/*     */     //   #157	-> 2880
/*     */     //   #160	-> 2897
/*     */     //   #161	-> 2900
/*     */     //   #287	-> 2934
/*     */     //   #288	-> 2946
/*     */     //   #289	-> 2962
/*     */     //   #161	-> 2969
/*     */     //   #289	-> 2989
/*     */     //   #290	-> 2991
/*     */     //   #291	-> 3000
/*     */     //   #292	-> 3005
/*     */     //   #288	-> 3007
/*     */     //   #287	-> 3008
/*     */     //   #287	-> 3009
/*     */     //   #161	-> 3010
/*     */     //   #162	-> 3041
/*     */     //   #293	-> 3072
/*     */     //   #294	-> 3084
/*     */     //   #295	-> 3100
/*     */     //   #162	-> 3107
/*     */     //   #295	-> 3127
/*     */     //   #296	-> 3129
/*     */     //   #297	-> 3138
/*     */     //   #298	-> 3143
/*     */     //   #294	-> 3145
/*     */     //   #293	-> 3146
/*     */     //   #293	-> 3147
/*     */     //   #162	-> 3148
/*     */     //   #159	-> 3167
/*     */     //   #157	-> 3170
/*     */     //   #166	-> 3179
/*     */     //   #169	-> 3196
/*     */     //   #170	-> 3199
/*     */     //   #299	-> 3233
/*     */     //   #300	-> 3245
/*     */     //   #301	-> 3261
/*     */     //   #170	-> 3268
/*     */     //   #301	-> 3288
/*     */     //   #302	-> 3290
/*     */     //   #303	-> 3299
/*     */     //   #304	-> 3304
/*     */     //   #300	-> 3306
/*     */     //   #299	-> 3307
/*     */     //   #299	-> 3308
/*     */     //   #170	-> 3309
/*     */     //   #171	-> 3340
/*     */     //   #305	-> 3371
/*     */     //   #306	-> 3383
/*     */     //   #307	-> 3399
/*     */     //   #171	-> 3406
/*     */     //   #307	-> 3426
/*     */     //   #308	-> 3428
/*     */     //   #309	-> 3437
/*     */     //   #310	-> 3442
/*     */     //   #306	-> 3444
/*     */     //   #305	-> 3445
/*     */     //   #305	-> 3446
/*     */     //   #171	-> 3447
/*     */     //   #168	-> 3466
/*     */     //   #166	-> 3469
/*     */     //   #175	-> 3478
/*     */     //   #177	-> 3495
/*     */     //   #178	-> 3498
/*     */     //   #311	-> 3532
/*     */     //   #312	-> 3544
/*     */     //   #313	-> 3560
/*     */     //   #178	-> 3567
/*     */     //   #313	-> 3587
/*     */     //   #314	-> 3589
/*     */     //   #315	-> 3598
/*     */     //   #316	-> 3603
/*     */     //   #312	-> 3605
/*     */     //   #311	-> 3606
/*     */     //   #311	-> 3607
/*     */     //   #178	-> 3608
/*     */     //   #179	-> 3639
/*     */     //   #317	-> 3670
/*     */     //   #318	-> 3682
/*     */     //   #319	-> 3698
/*     */     //   #179	-> 3705
/*     */     //   #319	-> 3725
/*     */     //   #320	-> 3727
/*     */     //   #321	-> 3736
/*     */     //   #322	-> 3741
/*     */     //   #318	-> 3743
/*     */     //   #317	-> 3744
/*     */     //   #317	-> 3745
/*     */     //   #179	-> 3746
/*     */     //   #176	-> 3765
/*     */     //   #175	-> 3768
/*     */     //   #96	-> 3777
/*     */     //   #93	-> 3800
/*     */     //   #34	-> 3809
/*     */     //   #186	-> 3844
/*     */     // Local variable table:
/*     */     //   start	length	slot	name	descriptor
/*     */     //   313	212	6	phase$delegate	Landroidx/compose/runtime/State;
/*     */     //   752	12	16	$i$a$-cache-GrazieActivationPageComponentKt$GrazieActivationPageComponent$1	I
/*     */     //   766	11	17	value$iv	Ljava/lang/Object;
/*     */     //   733	50	15	$i$a$-let-ComposerKt$cache$1$iv	I
/*     */     //   730	53	14	it$iv	Ljava/lang/Object;
/*     */     //   721	64	13	$i$f$cache	I
/*     */     //   718	67	11	$this$cache$iv	Landroidx/compose/runtime/Composer;
/*     */     //   718	67	12	invalid$iv	Z
/*     */     //   864	12	16	$i$a$-cache-GrazieActivationPageComponentKt$GrazieActivationPageComponent$2	I
/*     */     //   881	11	17	value$iv	Ljava/lang/Object;
/*     */     //   843	55	15	$i$a$-let-ComposerKt$cache$1$iv	I
/*     */     //   840	58	14	it$iv	Ljava/lang/Object;
/*     */     //   831	69	13	$i$f$cache	I
/*     */     //   828	72	11	$this$cache$iv	Landroidx/compose/runtime/Composer;
/*     */     //   828	72	12	invalid$iv	Z
/*     */     //   981	12	16	$i$a$-cache-GrazieActivationPageComponentKt$GrazieActivationPageComponent$3	I
/*     */     //   1003	11	17	value$iv	Ljava/lang/Object;
/*     */     //   958	62	15	$i$a$-let-ComposerKt$cache$1$iv	I
/*     */     //   955	65	14	it$iv	Ljava/lang/Object;
/*     */     //   946	76	13	$i$f$cache	I
/*     */     //   943	79	11	$this$cache$iv	Landroidx/compose/runtime/Composer;
/*     */     //   943	79	12	invalid$iv	Z
/*     */     //   1105	12	16	$i$a$-cache-GrazieActivationPageComponentKt$GrazieActivationPageComponent$4	I
/*     */     //   1129	11	17	value$iv	Ljava/lang/Object;
/*     */     //   1080	66	15	$i$a$-let-ComposerKt$cache$1$iv	I
/*     */     //   1077	69	14	it$iv	Ljava/lang/Object;
/*     */     //   1068	80	13	$i$f$cache	I
/*     */     //   1065	83	11	$this$cache$iv	Landroidx/compose/runtime/Composer;
/*     */     //   1065	83	12	invalid$iv	Z
/*     */     //   1317	12	18	$i$a$-cache-GrazieActivationPageComponentKt$GrazieActivationPageComponent$5	I
/*     */     //   1331	11	19	value$iv	Ljava/lang/Object;
/*     */     //   1298	50	17	$i$a$-let-ComposerKt$cache$1$iv	I
/*     */     //   1295	53	16	it$iv	Ljava/lang/Object;
/*     */     //   1286	64	15	$i$f$cache	I
/*     */     //   1283	67	13	$this$cache$iv	Landroidx/compose/runtime/Composer;
/*     */     //   1283	67	14	invalid$iv	Z
/*     */     //   1427	12	19	$i$a$-cache-GrazieActivationPageComponentKt$GrazieActivationPageComponent$6	I
/*     */     //   1441	11	20	value$iv	Ljava/lang/Object;
/*     */     //   1408	50	18	$i$a$-let-ComposerKt$cache$1$iv	I
/*     */     //   1405	53	17	it$iv	Ljava/lang/Object;
/*     */     //   1396	64	16	$i$f$cache	I
/*     */     //   1393	67	14	$this$cache$iv	Landroidx/compose/runtime/Composer;
/*     */     //   1393	67	15	invalid$iv	Z
/*     */     //   1537	12	20	$i$a$-cache-GrazieActivationPageComponentKt$GrazieActivationPageComponent$7	I
/*     */     //   1551	11	21	value$iv	Ljava/lang/Object;
/*     */     //   1518	50	19	$i$a$-let-ComposerKt$cache$1$iv	I
/*     */     //   1515	53	18	it$iv	Ljava/lang/Object;
/*     */     //   1506	64	17	$i$f$cache	I
/*     */     //   1503	67	15	$this$cache$iv	Landroidx/compose/runtime/Composer;
/*     */     //   1503	67	16	invalid$iv	Z
/*     */     //   1647	12	21	$i$a$-cache-GrazieActivationPageComponentKt$GrazieActivationPageComponent$8	I
/*     */     //   1661	11	22	value$iv	Ljava/lang/Object;
/*     */     //   1628	50	20	$i$a$-let-ComposerKt$cache$1$iv	I
/*     */     //   1625	53	19	it$iv	Ljava/lang/Object;
/*     */     //   1616	64	18	$i$f$cache	I
/*     */     //   1613	67	16	$this$cache$iv	Landroidx/compose/runtime/Composer;
/*     */     //   1613	67	17	invalid$iv	Z
/*     */     //   1842	12	18	$i$a$-cache-GrazieActivationPageComponentKt$GrazieActivationPageComponent$9	I
/*     */     //   1856	11	19	value$iv	Ljava/lang/Object;
/*     */     //   1823	50	17	$i$a$-let-ComposerKt$cache$1$iv	I
/*     */     //   1820	53	16	it$iv	Ljava/lang/Object;
/*     */     //   1811	64	15	$i$f$cache	I
/*     */     //   1808	67	13	$this$cache$iv	Landroidx/compose/runtime/Composer;
/*     */     //   1808	67	14	invalid$iv	Z
/*     */     //   1952	12	19	$i$a$-cache-GrazieActivationPageComponentKt$GrazieActivationPageComponent$10	I
/*     */     //   1966	11	20	value$iv	Ljava/lang/Object;
/*     */     //   1933	50	18	$i$a$-let-ComposerKt$cache$1$iv	I
/*     */     //   1930	53	17	it$iv	Ljava/lang/Object;
/*     */     //   1921	64	16	$i$f$cache	I
/*     */     //   1918	67	14	$this$cache$iv	Landroidx/compose/runtime/Composer;
/*     */     //   1918	67	15	invalid$iv	Z
/*     */     //   2062	12	20	$i$a$-cache-GrazieActivationPageComponentKt$GrazieActivationPageComponent$11	I
/*     */     //   2076	11	21	value$iv	Ljava/lang/Object;
/*     */     //   2043	50	19	$i$a$-let-ComposerKt$cache$1$iv	I
/*     */     //   2040	53	18	it$iv	Ljava/lang/Object;
/*     */     //   2031	64	17	$i$f$cache	I
/*     */     //   2028	67	15	$this$cache$iv	Landroidx/compose/runtime/Composer;
/*     */     //   2028	67	16	invalid$iv	Z
/*     */     //   2172	12	21	$i$a$-cache-GrazieActivationPageComponentKt$GrazieActivationPageComponent$12	I
/*     */     //   2186	11	22	value$iv	Ljava/lang/Object;
/*     */     //   2153	50	20	$i$a$-let-ComposerKt$cache$1$iv	I
/*     */     //   2150	53	19	it$iv	Ljava/lang/Object;
/*     */     //   2141	64	18	$i$f$cache	I
/*     */     //   2138	67	16	$this$cache$iv	Landroidx/compose/runtime/Composer;
/*     */     //   2138	67	17	invalid$iv	Z
/*     */     //   2372	12	16	$i$a$-cache-GrazieActivationPageComponentKt$GrazieActivationPageComponent$13	I
/*     */     //   2394	11	17	value$iv	Ljava/lang/Object;
/*     */     //   2349	62	15	$i$a$-let-ComposerKt$cache$1$iv	I
/*     */     //   2346	65	14	it$iv	Ljava/lang/Object;
/*     */     //   2337	76	13	$i$f$cache	I
/*     */     //   2334	79	11	$this$cache$iv	Landroidx/compose/runtime/Composer;
/*     */     //   2334	79	12	invalid$iv	Z
/*     */     //   2510	12	16	$i$a$-cache-GrazieActivationPageComponentKt$GrazieActivationPageComponent$14	I
/*     */     //   2532	11	17	value$iv	Ljava/lang/Object;
/*     */     //   2487	62	15	$i$a$-let-ComposerKt$cache$1$iv	I
/*     */     //   2484	65	14	it$iv	Ljava/lang/Object;
/*     */     //   2475	76	13	$i$f$cache	I
/*     */     //   2472	79	11	$this$cache$iv	Landroidx/compose/runtime/Composer;
/*     */     //   2472	79	12	invalid$iv	Z
/*     */     //   2670	12	16	$i$a$-cache-GrazieActivationPageComponentKt$GrazieActivationPageComponent$15	I
/*     */     //   2692	11	17	value$iv	Ljava/lang/Object;
/*     */     //   2647	62	15	$i$a$-let-ComposerKt$cache$1$iv	I
/*     */     //   2644	65	14	it$iv	Ljava/lang/Object;
/*     */     //   2635	76	13	$i$f$cache	I
/*     */     //   2632	79	11	$this$cache$iv	Landroidx/compose/runtime/Composer;
/*     */     //   2632	79	12	invalid$iv	Z
/*     */     //   2808	12	16	$i$a$-cache-GrazieActivationPageComponentKt$GrazieActivationPageComponent$16	I
/*     */     //   2830	11	17	value$iv	Ljava/lang/Object;
/*     */     //   2785	62	15	$i$a$-let-ComposerKt$cache$1$iv	I
/*     */     //   2782	65	14	it$iv	Ljava/lang/Object;
/*     */     //   2773	76	13	$i$f$cache	I
/*     */     //   2770	79	11	$this$cache$iv	Landroidx/compose/runtime/Composer;
/*     */     //   2770	79	12	invalid$iv	Z
/*     */     //   2969	12	16	$i$a$-cache-GrazieActivationPageComponentKt$GrazieActivationPageComponent$17	I
/*     */     //   2991	11	17	value$iv	Ljava/lang/Object;
/*     */     //   2946	62	15	$i$a$-let-ComposerKt$cache$1$iv	I
/*     */     //   2943	65	14	it$iv	Ljava/lang/Object;
/*     */     //   2934	76	13	$i$f$cache	I
/*     */     //   2931	79	11	$this$cache$iv	Landroidx/compose/runtime/Composer;
/*     */     //   2931	79	12	invalid$iv	Z
/*     */     //   3107	12	16	$i$a$-cache-GrazieActivationPageComponentKt$GrazieActivationPageComponent$18	I
/*     */     //   3129	11	17	value$iv	Ljava/lang/Object;
/*     */     //   3084	62	15	$i$a$-let-ComposerKt$cache$1$iv	I
/*     */     //   3081	65	14	it$iv	Ljava/lang/Object;
/*     */     //   3072	76	13	$i$f$cache	I
/*     */     //   3069	79	11	$this$cache$iv	Landroidx/compose/runtime/Composer;
/*     */     //   3069	79	12	invalid$iv	Z
/*     */     //   3268	12	16	$i$a$-cache-GrazieActivationPageComponentKt$GrazieActivationPageComponent$19	I
/*     */     //   3290	11	17	value$iv	Ljava/lang/Object;
/*     */     //   3245	62	15	$i$a$-let-ComposerKt$cache$1$iv	I
/*     */     //   3242	65	14	it$iv	Ljava/lang/Object;
/*     */     //   3233	76	13	$i$f$cache	I
/*     */     //   3230	79	11	$this$cache$iv	Landroidx/compose/runtime/Composer;
/*     */     //   3230	79	12	invalid$iv	Z
/*     */     //   3406	12	16	$i$a$-cache-GrazieActivationPageComponentKt$GrazieActivationPageComponent$20	I
/*     */     //   3428	11	17	value$iv	Ljava/lang/Object;
/*     */     //   3383	62	15	$i$a$-let-ComposerKt$cache$1$iv	I
/*     */     //   3380	65	14	it$iv	Ljava/lang/Object;
/*     */     //   3371	76	13	$i$f$cache	I
/*     */     //   3368	79	11	$this$cache$iv	Landroidx/compose/runtime/Composer;
/*     */     //   3368	79	12	invalid$iv	Z
/*     */     //   3567	12	16	$i$a$-cache-GrazieActivationPageComponentKt$GrazieActivationPageComponent$21	I
/*     */     //   3589	11	17	value$iv	Ljava/lang/Object;
/*     */     //   3544	62	15	$i$a$-let-ComposerKt$cache$1$iv	I
/*     */     //   3541	65	14	it$iv	Ljava/lang/Object;
/*     */     //   3532	76	13	$i$f$cache	I
/*     */     //   3529	79	11	$this$cache$iv	Landroidx/compose/runtime/Composer;
/*     */     //   3529	79	12	invalid$iv	Z
/*     */     //   3705	12	16	$i$a$-cache-GrazieActivationPageComponentKt$GrazieActivationPageComponent$22	I
/*     */     //   3727	11	17	value$iv	Ljava/lang/Object;
/*     */     //   3682	62	15	$i$a$-let-ComposerKt$cache$1$iv	I
/*     */     //   3679	65	14	it$iv	Ljava/lang/Object;
/*     */     //   3670	76	13	$i$f$cache	I
/*     */     //   3667	79	11	$this$cache$iv	Landroidx/compose/runtime/Composer;
/*     */     //   3667	79	12	invalid$iv	Z
/*     */     //   672	3128	8	innerstate	Lcom/intellij/ml/llm/matterhorn/ej/ui/login/states/MissingAIPLicense$TrialRequestState;
/*     */     //   649	3151	6	trialRequestState$delegate	Landroidx/compose/runtime/State;
/*     */     //   665	3135	7	refreshState$delegate	Landroidx/compose/runtime/State;
/*     */     //   18	3860	4	$dirty	I
/*     */     //   0	3878	0	state	Lcom/intellij/ml/llm/matterhorn/ej/ui/login/states/GrazieActivationState;
/*     */     //   0	3878	1	username	Ljava/lang/String;
/*     */     //   0	3878	2	$composer	Landroidx/compose/runtime/Composer;
/*     */     //   0	3878	3	$changed	I
/*     */   }
/*     */   
/*     */   private static final JbaUnauthenticated.LoginPhase GrazieActivationPageComponent$lambda$0(State $phase$delegate) {
/*  58 */     State state = $phase$delegate; Object object = null; KProperty property$iv = null; int $i$f$getValue = 0; return 
/*     */ 
/*     */ 
/*     */ 
/*     */ 
/*     */ 
/*     */ 
/*     */ 
/*     */ 
/*     */ 
/*     */ 
/*     */ 
/*     */ 
/*     */ 
/*     */ 
/*     */ 
/*     */ 
/*     */ 
/*     */ 
/*     */ 
/*     */ 
/*     */ 
/*     */ 
/*     */ 
/*     */ 
/*     */ 
/*     */ 
/*     */ 
/*     */ 
/*     */ 
/*     */ 
/*     */ 
/*     */ 
/*     */ 
/*     */ 
/*     */ 
/*     */ 
/*     */ 
/*     */ 
/*     */ 
/*     */ 
/*     */ 
/*     */ 
/*     */ 
/*     */ 
/*     */ 
/*     */ 
/*     */ 
/*     */ 
/*     */ 
/*     */ 
/*     */ 
/*     */ 
/*     */ 
/*     */ 
/*     */ 
/*     */ 
/*     */ 
/*     */ 
/*     */ 
/*     */ 
/*     */ 
/*     */ 
/*     */ 
/*     */ 
/*     */ 
/*     */ 
/*     */ 
/*     */ 
/*     */ 
/*     */ 
/*     */ 
/*     */ 
/*     */ 
/*     */ 
/*     */ 
/*     */ 
/*     */ 
/*     */ 
/*     */ 
/*     */ 
/*     */ 
/*     */ 
/*     */ 
/*     */ 
/*     */ 
/*     */ 
/*     */ 
/*     */ 
/*     */ 
/*     */ 
/*     */ 
/*     */ 
/*     */ 
/*     */ 
/*     */ 
/*     */ 
/*     */ 
/*     */ 
/*     */ 
/*     */ 
/*     */ 
/*     */ 
/*     */ 
/*     */ 
/*     */ 
/*     */ 
/*     */ 
/*     */ 
/*     */ 
/*     */ 
/*     */ 
/*     */ 
/*     */ 
/*     */ 
/*     */ 
/*     */ 
/*     */ 
/*     */ 
/*     */ 
/*     */ 
/*     */ 
/*     */ 
/*     */ 
/*     */ 
/*     */ 
/*     */ 
/*     */ 
/*     */ 
/*     */ 
/*     */ 
/*     */ 
/*     */ 
/*     */ 
/*     */ 
/*     */ 
/*     */ 
/*     */ 
/*     */ 
/*     */ 
/*     */ 
/*     */ 
/*     */ 
/*     */ 
/*     */ 
/*     */ 
/*     */ 
/*     */ 
/*     */ 
/*     */ 
/*     */ 
/*     */ 
/*     */ 
/*     */ 
/*     */ 
/*     */ 
/*     */ 
/*     */ 
/*     */ 
/*     */ 
/*     */ 
/*     */ 
/*     */ 
/*     */ 
/*     */ 
/*     */ 
/*     */ 
/*     */ 
/*     */ 
/*     */ 
/*     */ 
/*     */ 
/*     */ 
/*     */ 
/*     */ 
/*     */ 
/*     */ 
/*     */ 
/*     */ 
/*     */ 
/*     */ 
/*     */ 
/*     */ 
/*     */ 
/*     */ 
/*     */ 
/*     */ 
/*     */ 
/*     */ 
/*     */ 
/*     */ 
/*     */ 
/*     */ 
/*     */ 
/*     */ 
/*     */ 
/*     */ 
/*     */ 
/*     */ 
/*     */ 
/*     */ 
/*     */ 
/*     */ 
/*     */ 
/*     */ 
/*     */ 
/*     */ 
/*     */ 
/*     */ 
/*     */ 
/*     */ 
/*     */ 
/*     */ 
/*     */ 
/*     */ 
/*     */ 
/*     */ 
/*     */ 
/*     */ 
/*     */ 
/*     */ 
/*     */ 
/*     */ 
/*     */ 
/*     */ 
/*     */ 
/*     */ 
/*     */ 
/*     */ 
/*     */ 
/*     */ 
/*     */ 
/*     */ 
/*     */ 
/*     */ 
/*     */ 
/*     */ 
/*     */ 
/*     */ 
/*     */ 
/*     */ 
/*     */ 
/*     */ 
/*     */ 
/*     */ 
/*     */ 
/*     */ 
/*     */ 
/*     */ 
/*     */ 
/*     */ 
/*     */ 
/*     */ 
/*     */ 
/*     */ 
/*     */ 
/*     */ 
/*     */ 
/*     */ 
/*     */ 
/*     */ 
/*     */ 
/*     */ 
/*     */ 
/*     */       
/* 323 */       (JbaUnauthenticated.LoginPhase)state.getValue(); } private static final MissingAIPLicense.TrialRequestState GrazieActivationPageComponent$lambda$1(State $trialRequestState$delegate) { State state = $trialRequestState$delegate; Object object = null; KProperty property$iv = null; int $i$f$getValue = 0;
/* 324 */     return (MissingAIPLicense.TrialRequestState)state.getValue(); } private static final MissingAIPLicense.RefreshState GrazieActivationPageComponent$lambda$2(State $refreshState$delegate) { State state = $refreshState$delegate; Object object = null; KProperty property$iv = null; int $i$f$getValue = 0;
/* 325 */     return (MissingAIPLicense.RefreshState)state.getValue(); }
/*     */ 
/*     */   
/*     */   private static final Unit GrazieActivationPageComponent$lambda$25(GrazieActivationState $state, String $username, int $$changed, Composer $composer, int $force) {
/*     */     GrazieActivationPageComponent($state, $username, $composer, RecomposeScopeImplKt.updateChangedFlags($$changed | 0x1));
/*     */     return Unit.INSTANCE;
/*     */   }
/*     */ }


/* Location:              C:\Users\yuzum\Downloads\ej-release-243.132.63.zip!\ej\lib\ej-243.132.63.jar!\com\intellij\ml\llm\matterhorn\e\\ui\login\GrazieActivationPageComponentKt.class
 * Java compiler version: 17 (61.0)
 * JD-Core Version:       1.1.3
 */