/*     */ package com.intellij.ml.llm.matterhorn.ej.ui.login;
/*     */ 
/*     */ import androidx.compose.foundation.layout.Arrangement;
/*     */ import androidx.compose.foundation.layout.RowScope;
/*     */ import androidx.compose.runtime.ComposablesKt;
/*     */ import androidx.compose.runtime.Composer;
/*     */ import androidx.compose.runtime.ComposerKt;
/*     */ import androidx.compose.runtime.CompositionLocalMap;
/*     */ import androidx.compose.runtime.MutableState;
/*     */ import androidx.compose.runtime.State;
/*     */ import androidx.compose.runtime.Updater;
/*     */ import androidx.compose.ui.Alignment;
/*     */ import androidx.compose.ui.Modifier;
/*     */ import androidx.compose.ui.layout.MeasurePolicy;
/*     */ import androidx.compose.ui.node.ComposeUiNode;
/*     */ import androidx.compose.ui.unit.Dp;
/*     */ import com.intellij.ml.llm.matterhorn.activation.data.model.JbaAuthData;
/*     */ import com.intellij.ml.llm.matterhorn.ej.ui.login.states.GrazieActivationState;
/*     */ import com.intellij.ml.llm.matterhorn.ej.ui.login.test.ActivationTestActionService;
/*     */ import com.intellij.openapi.components.ComponentManager;
/*     */ import kotlin.ResultKt;
/*     */ import kotlin.Unit;
/*     */ import kotlin.coroutines.Continuation;
/*     */ import kotlin.coroutines.intrinsics.IntrinsicsKt;
/*     */ import kotlin.jvm.functions.Function0;
/*     */ import kotlin.jvm.functions.Function2;
/*     */ import kotlin.jvm.internal.Intrinsics;
/*     */ import kotlin.reflect.KProperty;
/*     */ import kotlinx.coroutines.CoroutineScope;
/*     */ 
/*     */ @Metadata(mv = {2, 1, 0}, k = 2, xi = 48, d1 = {"\000.\n\000\n\002\020\002\n\000\n\002\030\002\n\002\b\003\n\002\030\002\n\002\b\006\n\002\020\013\n\000\n\002\020\016\n\000\n\002\030\002\n\000\n\002\030\002\032\025\020\000\032\0020\0012\006\020\002\032\0020\003H\007¢\006\002\020\004\032\037\020\005\032\0020\0012\006\020\002\032\0020\0032\006\020\006\032\0020\007H\003¢\006\004\b\b\020\t\032\r\020\n\032\0020\001H\003¢\006\002\020\013¨\006\f²\006\n\020\r\032\0020\016X\002²\006\f\020\017\032\004\030\0010\020X\002²\006\n\020\021\032\0020\022X\002²\006\030\020\023\032\020\022\004\022\0020\020\022\004\022\0020\022\030\0010\024X\002"}, d2 = {"GrazieActivationPage", "", "model", "Lcom/intellij/ml/llm/matterhorn/ej/ui/login/GrazieActivationPageVm;", "(Lcom/intellij/ml/llm/matterhorn/ej/ui/login/GrazieActivationPageVm;Landroidx/compose/runtime/Composer;I)V", "GrazieActivationPageDebugMockControls", "backgroundColor", "Landroidx/compose/ui/graphics/Color;", "GrazieActivationPageDebugMockControls-RPmYEkk", "(Lcom/intellij/ml/llm/matterhorn/ej/ui/login/GrazieActivationPageVm;JLandroidx/compose/runtime/Composer;I)V", "LoginFooter", "(Landroidx/compose/runtime/Composer;I)V", "ej-ui", "showFooter", "", "username", "", "uiState", "Lcom/intellij/ml/llm/matterhorn/ej/ui/login/states/GrazieActivationState;", "debugMock", "Lkotlin/Pair;"})
/*     */ @SourceDebugExtension({"SMAP\nGrazieActivationPage.kt\nKotlin\n*S Kotlin\n*F\n+ 1 GrazieActivationPage.kt\ncom/intellij/ml/llm/matterhorn/ej/ui/login/GrazieActivationPageKt\n+ 2 Composer.kt\nandroidx/compose/runtime/ComposerKt\n+ 3 Dp.kt\nandroidx/compose/ui/unit/DpKt\n+ 4 Column.kt\nandroidx/compose/foundation/layout/ColumnKt\n+ 5 Layout.kt\nandroidx/compose/ui/layout/LayoutKt\n+ 6 Composables.kt\nandroidx/compose/runtime/ComposablesKt\n+ 7 Composer.kt\nandroidx/compose/runtime/Updater\n+ 8 Row.kt\nandroidx/compose/foundation/layout/RowKt\n+ 9 SnapshotState.kt\nandroidx/compose/runtime/SnapshotStateKt__SnapshotStateKt\n+ 10 services.kt\ncom/intellij/openapi/components/ServicesKt\n*L\n1#1,150:1\n1225#2,6:151\n1225#2,6:157\n1225#2,6:163\n1225#2,6:287\n1225#2,6:334\n149#3:169\n149#3:206\n149#3:207\n149#3:249\n149#3:254\n149#3:293\n149#3:344\n149#3:345\n149#3:381\n149#3:423\n149#3:465\n86#4:170\n83#4,6:171\n89#4:205\n86#4:208\n82#4,7:209\n89#4:244\n93#4:248\n93#4:253\n86#4:294\n83#4,6:295\n89#4:329\n93#4:333\n86#4:346\n84#4,5:347\n89#4:380\n93#4:510\n79#5,6:177\n86#5,4:192\n90#5,2:202\n79#5,6:216\n86#5,4:231\n90#5,2:241\n94#5:247\n94#5:252\n79#5,6:258\n86#5,4:273\n90#5,2:283\n79#5,6:301\n86#5,4:316\n90#5,2:326\n94#5:332\n94#5:342\n79#5,6:352\n86#5,4:367\n90#5,2:377\n79#5,6:390\n86#5,4:405\n90#5,2:415\n94#5:421\n79#5,6:432\n86#5,4:447\n90#5,2:457\n94#5:463\n79#5,6:474\n86#5,4:489\n90#5,2:499\n94#5:505\n94#5:509\n368#6,9:183\n377#6:204\n368#6,9:222\n377#6:243\n378#6,2:245\n378#6,2:250\n368#6,9:264\n377#6:285\n368#6,9:307\n377#6:328\n378#6,2:330\n378#6,2:340\n368#6,9:358\n377#6:379\n368#6,9:396\n377#6:417\n378#6,2:419\n368#6,9:438\n377#6:459\n378#6,2:461\n368#6,9:480\n377#6:501\n378#6,2:503\n378#6,2:507\n4034#7,6:196\n4034#7,6:235\n4034#7,6:277\n4034#7,6:320\n4034#7,6:371\n4034#7,6:409\n4034#7,6:451\n4034#7,6:493\n99#8,3:255\n102#8:286\n106#8:343\n99#8:382\n95#8,7:383\n102#8:418\n106#8:422\n99#8:424\n95#8,7:425\n102#8:460\n106#8:464\n99#8:466\n95#8,7:467\n102#8:502\n106#8:506\n81#9:511\n81#9:512\n107#9,2:513\n81#9:515\n81#9:516\n31#10,2:517\n31#10,2:519\n*S KotlinDebug\n*F\n+ 1 GrazieActivationPage.kt\ncom/intellij/ml/llm/matterhorn/ej/ui/login/GrazieActivationPageKt\n*L\n40#1:151,6\n42#1:157,6\n43#1:163,6\n92#1:287,6\n110#1:334,6\n55#1:169\n58#1:206\n60#1:207\n67#1:249\n87#1:254\n100#1:293\n122#1:344\n123#1:345\n132#1:381\n137#1:423\n142#1:465\n52#1:170\n52#1:171,6\n52#1:205\n60#1:208\n60#1:209,7\n60#1:244\n60#1:248\n52#1:253\n97#1:294\n97#1:295,6\n97#1:329\n97#1:333\n121#1:346\n121#1:347,5\n121#1:380\n121#1:510\n52#1:177,6\n52#1:192,4\n52#1:202,2\n60#1:216,6\n60#1:231,4\n60#1:241,2\n60#1:247\n52#1:252\n82#1:258,6\n82#1:273,4\n82#1:283,2\n97#1:301,6\n97#1:316,4\n97#1:326,2\n97#1:332\n82#1:342\n121#1:352,6\n121#1:367,4\n121#1:377,2\n132#1:390,6\n132#1:405,4\n132#1:415,2\n132#1:421\n137#1:432,6\n137#1:447,4\n137#1:457,2\n137#1:463\n142#1:474,6\n142#1:489,4\n142#1:499,2\n142#1:505\n121#1:509\n52#1:183,9\n52#1:204\n60#1:222,9\n60#1:243\n60#1:245,2\n52#1:250,2\n82#1:264,9\n82#1:285\n97#1:307,9\n97#1:328\n97#1:330,2\n82#1:340,2\n121#1:358,9\n121#1:379\n132#1:396,9\n132#1:417\n132#1:419,2\n137#1:438,9\n137#1:459\n137#1:461,2\n142#1:480,9\n142#1:501\n142#1:503,2\n121#1:507,2\n52#1:196,6\n60#1:235,6\n82#1:277,6\n97#1:320,6\n121#1:371,6\n132#1:409,6\n137#1:451,6\n142#1:493,6\n82#1:255,3\n82#1:286\n82#1:343\n132#1:382\n132#1:383,7\n132#1:418\n132#1:422\n137#1:424\n137#1:425,7\n137#1:460\n137#1:464\n142#1:466\n142#1:467,7\n142#1:502\n142#1:506\n40#1:511\n42#1:512\n42#1:513,2\n48#1:515\n80#1:516\n93#1:517,2\n111#1:519,2\n*E\n"})
/*     */ public final class GrazieActivationPageKt {
/*     */   @Composable
/*     */   @ComposableTarget(applier = "androidx.compose.ui.UiComposable")
/*     */   public static final void GrazieActivationPage(@NotNull GrazieActivationPageVm model, @Nullable Composer $composer, int $changed) {
/*     */     // Byte code:
/*     */     //   0: aload_0
/*     */     //   1: ldc 'model'
/*     */     //   3: invokestatic checkNotNullParameter : (Ljava/lang/Object;Ljava/lang/String;)V
/*     */     //   6: aload_1
/*     */     //   7: ldc 884982568
/*     */     //   9: invokeinterface startRestartGroup : (I)Landroidx/compose/runtime/Composer;
/*     */     //   14: astore_1
/*     */     //   15: iload_2
/*     */     //   16: istore_3
/*     */     //   17: iload_2
/*     */     //   18: bipush #6
/*     */     //   20: iand
/*     */     //   21: ifne -> 42
/*     */     //   24: iload_3
/*     */     //   25: aload_1
/*     */     //   26: aload_0
/*     */     //   27: invokeinterface changedInstance : (Ljava/lang/Object;)Z
/*     */     //   32: ifeq -> 39
/*     */     //   35: iconst_4
/*     */     //   36: goto -> 40
/*     */     //   39: iconst_2
/*     */     //   40: ior
/*     */     //   41: istore_3
/*     */     //   42: iload_3
/*     */     //   43: iconst_3
/*     */     //   44: iand
/*     */     //   45: iconst_2
/*     */     //   46: if_icmpne -> 58
/*     */     //   49: aload_1
/*     */     //   50: invokeinterface getSkipping : ()Z
/*     */     //   55: ifne -> 1421
/*     */     //   58: invokestatic isTraceInProgress : ()Z
/*     */     //   61: ifeq -> 73
/*     */     //   64: ldc 884982568
/*     */     //   66: iload_3
/*     */     //   67: iconst_m1
/*     */     //   68: ldc 'com.intellij.ml.llm.matterhorn.ej.ui.login.GrazieActivationPage (GrazieActivationPage.kt:38)'
/*     */     //   70: invokestatic traceEventStart : (IIILjava/lang/String;)V
/*     */     //   73: aload_1
/*     */     //   74: ldc 1142903648
/*     */     //   76: invokeinterface startReplaceGroup : (I)V
/*     */     //   81: aload_1
/*     */     //   82: astore #6
/*     */     //   84: iconst_0
/*     */     //   85: istore #7
/*     */     //   87: nop
/*     */     //   88: iconst_0
/*     */     //   89: istore #8
/*     */     //   91: aload #6
/*     */     //   93: invokeinterface rememberedValue : ()Ljava/lang/Object;
/*     */     //   98: astore #9
/*     */     //   100: iconst_0
/*     */     //   101: istore #10
/*     */     //   103: aload #9
/*     */     //   105: getstatic androidx/compose/runtime/Composer.Companion : Landroidx/compose/runtime/Composer$Companion;
/*     */     //   108: invokevirtual getEmpty : ()Ljava/lang/Object;
/*     */     //   111: if_acmpne -> 143
/*     */     //   114: iconst_0
/*     */     //   115: istore #11
/*     */     //   117: iconst_1
/*     */     //   118: invokestatic valueOf : (Z)Ljava/lang/Boolean;
/*     */     //   121: aconst_null
/*     */     //   122: iconst_2
/*     */     //   123: aconst_null
/*     */     //   124: invokestatic mutableStateOf$default : (Ljava/lang/Object;Landroidx/compose/runtime/SnapshotMutationPolicy;ILjava/lang/Object;)Landroidx/compose/runtime/MutableState;
/*     */     //   127: astore #11
/*     */     //   129: aload #6
/*     */     //   131: aload #11
/*     */     //   133: invokeinterface updateRememberedValue : (Ljava/lang/Object;)V
/*     */     //   138: aload #11
/*     */     //   140: goto -> 145
/*     */     //   143: aload #9
/*     */     //   145: nop
/*     */     //   146: nop
/*     */     //   147: nop
/*     */     //   148: checkcast androidx/compose/runtime/MutableState
/*     */     //   151: astore #5
/*     */     //   153: aload_1
/*     */     //   154: invokeinterface endReplaceGroup : ()V
/*     */     //   159: aload #5
/*     */     //   161: astore #4
/*     */     //   163: aload_1
/*     */     //   164: iconst_0
/*     */     //   165: invokestatic getMatterhornTheme : (Landroidx/compose/runtime/Composer;I)Lcom/intellij/ml/llm/matterhorn/ej/ui/theming/MatterhornThemeData;
/*     */     //   168: invokevirtual getBackgroundColor-0d7_KjU : ()J
/*     */     //   171: lstore #5
/*     */     //   173: aload_1
/*     */     //   174: ldc 1142907392
/*     */     //   176: invokeinterface startReplaceGroup : (I)V
/*     */     //   181: aload_1
/*     */     //   182: astore #9
/*     */     //   184: iconst_0
/*     */     //   185: istore #10
/*     */     //   187: nop
/*     */     //   188: iconst_0
/*     */     //   189: istore #11
/*     */     //   191: aload #9
/*     */     //   193: invokeinterface rememberedValue : ()Ljava/lang/Object;
/*     */     //   198: astore #12
/*     */     //   200: iconst_0
/*     */     //   201: istore #13
/*     */     //   203: aload #12
/*     */     //   205: getstatic androidx/compose/runtime/Composer.Companion : Landroidx/compose/runtime/Composer$Companion;
/*     */     //   208: invokevirtual getEmpty : ()Ljava/lang/Object;
/*     */     //   211: if_acmpne -> 240
/*     */     //   214: iconst_0
/*     */     //   215: istore #14
/*     */     //   217: aconst_null
/*     */     //   218: aconst_null
/*     */     //   219: iconst_2
/*     */     //   220: aconst_null
/*     */     //   221: invokestatic mutableStateOf$default : (Ljava/lang/Object;Landroidx/compose/runtime/SnapshotMutationPolicy;ILjava/lang/Object;)Landroidx/compose/runtime/MutableState;
/*     */     //   224: astore #14
/*     */     //   226: aload #9
/*     */     //   228: aload #14
/*     */     //   230: invokeinterface updateRememberedValue : (Ljava/lang/Object;)V
/*     */     //   235: aload #14
/*     */     //   237: goto -> 242
/*     */     //   240: aload #12
/*     */     //   242: nop
/*     */     //   243: nop
/*     */     //   244: nop
/*     */     //   245: checkcast androidx/compose/runtime/MutableState
/*     */     //   248: astore #8
/*     */     //   250: aload_1
/*     */     //   251: invokeinterface endReplaceGroup : ()V
/*     */     //   256: aload #8
/*     */     //   258: astore #7
/*     */     //   260: getstatic kotlin/Unit.INSTANCE : Lkotlin/Unit;
/*     */     //   263: aload_1
/*     */     //   264: ldc 1142909318
/*     */     //   266: invokeinterface startReplaceGroup : (I)V
/*     */     //   271: aload_1
/*     */     //   272: astore #9
/*     */     //   274: iconst_0
/*     */     //   275: istore #10
/*     */     //   277: iconst_0
/*     */     //   278: istore #11
/*     */     //   280: aload #9
/*     */     //   282: invokeinterface rememberedValue : ()Ljava/lang/Object;
/*     */     //   287: astore #12
/*     */     //   289: iconst_0
/*     */     //   290: istore #13
/*     */     //   292: aload #12
/*     */     //   294: getstatic androidx/compose/runtime/Composer.Companion : Landroidx/compose/runtime/Composer$Companion;
/*     */     //   297: invokevirtual getEmpty : ()Ljava/lang/Object;
/*     */     //   300: if_acmpne -> 340
/*     */     //   303: astore #63
/*     */     //   305: iconst_0
/*     */     //   306: istore #14
/*     */     //   308: new com/intellij/ml/llm/matterhorn/ej/ui/login/GrazieActivationPageKt$GrazieActivationPage$1$1
/*     */     //   311: dup
/*     */     //   312: aload #7
/*     */     //   314: aconst_null
/*     */     //   315: invokespecial <init> : (Landroidx/compose/runtime/MutableState;Lkotlin/coroutines/Continuation;)V
/*     */     //   318: checkcast kotlin/jvm/functions/Function2
/*     */     //   321: aload #63
/*     */     //   323: swap
/*     */     //   324: astore #15
/*     */     //   326: aload #9
/*     */     //   328: aload #15
/*     */     //   330: invokeinterface updateRememberedValue : (Ljava/lang/Object;)V
/*     */     //   335: aload #15
/*     */     //   337: goto -> 342
/*     */     //   340: aload #12
/*     */     //   342: nop
/*     */     //   343: nop
/*     */     //   344: nop
/*     */     //   345: checkcast kotlin/jvm/functions/Function2
/*     */     //   348: astore #8
/*     */     //   350: aload_1
/*     */     //   351: invokeinterface endReplaceGroup : ()V
/*     */     //   356: aload #8
/*     */     //   358: aload_1
/*     */     //   359: bipush #6
/*     */     //   361: invokestatic LaunchedEffect : (Ljava/lang/Object;Lkotlin/jvm/functions/Function2;Landroidx/compose/runtime/Composer;I)V
/*     */     //   364: aload_0
/*     */     //   365: invokevirtual getLoginVm : ()Lcom/intellij/ml/llm/matterhorn/ej/ui/login/GrazieActivationVm;
/*     */     //   368: invokevirtual getState : ()Lkotlinx/coroutines/flow/StateFlow;
/*     */     //   371: aconst_null
/*     */     //   372: aload_1
/*     */     //   373: iconst_0
/*     */     //   374: iconst_1
/*     */     //   375: invokestatic collectAsState : (Lkotlinx/coroutines/flow/StateFlow;Lkotlin/coroutines/CoroutineContext;Landroidx/compose/runtime/Composer;II)Landroidx/compose/runtime/State;
/*     */     //   378: astore #8
/*     */     //   380: aload_0
/*     */     //   381: lload #5
/*     */     //   383: aload_1
/*     */     //   384: bipush #14
/*     */     //   386: iload_3
/*     */     //   387: iand
/*     */     //   388: invokestatic GrazieActivationPageDebugMockControls-RPmYEkk : (Lcom/intellij/ml/llm/matterhorn/ej/ui/login/GrazieActivationPageVm;JLandroidx/compose/runtime/Composer;I)V
/*     */     //   391: getstatic androidx/compose/ui/Modifier.Companion : Landroidx/compose/ui/Modifier$Companion;
/*     */     //   394: checkcast androidx/compose/ui/Modifier
/*     */     //   397: fconst_0
/*     */     //   398: iconst_1
/*     */     //   399: aconst_null
/*     */     //   400: invokestatic fillMaxWidth$default : (Landroidx/compose/ui/Modifier;FILjava/lang/Object;)Landroidx/compose/ui/Modifier;
/*     */     //   403: lload #5
/*     */     //   405: aconst_null
/*     */     //   406: iconst_2
/*     */     //   407: aconst_null
/*     */     //   408: invokestatic background-bw27NRU$default : (Landroidx/compose/ui/Modifier;JLandroidx/compose/ui/graphics/Shape;ILjava/lang/Object;)Landroidx/compose/ui/Modifier;
/*     */     //   411: astore #9
/*     */     //   413: bipush #24
/*     */     //   415: istore #11
/*     */     //   417: iconst_0
/*     */     //   418: istore #12
/*     */     //   420: iload #11
/*     */     //   422: i2f
/*     */     //   423: invokestatic constructor-impl : (F)F
/*     */     //   426: fstore #10
/*     */     //   428: bipush #24
/*     */     //   430: istore #12
/*     */     //   432: iconst_0
/*     */     //   433: istore #13
/*     */     //   435: iload #12
/*     */     //   437: i2f
/*     */     //   438: invokestatic constructor-impl : (F)F
/*     */     //   441: fstore #11
/*     */     //   443: bipush #24
/*     */     //   445: istore #13
/*     */     //   447: iconst_0
/*     */     //   448: istore #14
/*     */     //   450: iload #13
/*     */     //   452: i2f
/*     */     //   453: invokestatic constructor-impl : (F)F
/*     */     //   456: fstore #12
/*     */     //   458: aload #9
/*     */     //   460: fload #10
/*     */     //   462: fload #12
/*     */     //   464: fload #11
/*     */     //   466: fconst_0
/*     */     //   467: bipush #8
/*     */     //   469: aconst_null
/*     */     //   470: invokestatic padding-qDBjuR0$default : (Landroidx/compose/ui/Modifier;FFFFILjava/lang/Object;)Landroidx/compose/ui/Modifier;
/*     */     //   473: astore #9
/*     */     //   475: iconst_0
/*     */     //   476: istore #12
/*     */     //   478: nop
/*     */     //   479: iconst_0
/*     */     //   480: istore #13
/*     */     //   482: aload_1
/*     */     //   483: ldc -483455358
/*     */     //   485: ldc 'CC(Column)P(2,3,1)86@4330L61,87@4396L133:Column.kt#2w3rfo'
/*     */     //   487: invokestatic sourceInformationMarkerStart : (Landroidx/compose/runtime/Composer;ILjava/lang/String;)V
/*     */     //   490: getstatic androidx/compose/foundation/layout/Arrangement.INSTANCE : Landroidx/compose/foundation/layout/Arrangement;
/*     */     //   493: invokevirtual getTop : ()Landroidx/compose/foundation/layout/Arrangement$Vertical;
/*     */     //   496: astore #10
/*     */     //   498: getstatic androidx/compose/ui/Alignment.Companion : Landroidx/compose/ui/Alignment$Companion;
/*     */     //   501: invokevirtual getStart : ()Landroidx/compose/ui/Alignment$Horizontal;
/*     */     //   504: astore #11
/*     */     //   506: aload #10
/*     */     //   508: aload #11
/*     */     //   510: aload_1
/*     */     //   511: bipush #14
/*     */     //   513: iload #12
/*     */     //   515: iconst_3
/*     */     //   516: ishr
/*     */     //   517: iand
/*     */     //   518: bipush #112
/*     */     //   520: iload #12
/*     */     //   522: iconst_3
/*     */     //   523: ishr
/*     */     //   524: iand
/*     */     //   525: ior
/*     */     //   526: invokestatic columnMeasurePolicy : (Landroidx/compose/foundation/layout/Arrangement$Vertical;Landroidx/compose/ui/Alignment$Horizontal;Landroidx/compose/runtime/Composer;I)Landroidx/compose/ui/layout/MeasurePolicy;
/*     */     //   529: astore #14
/*     */     //   531: bipush #112
/*     */     //   533: iload #12
/*     */     //   535: iconst_3
/*     */     //   536: ishl
/*     */     //   537: iand
/*     */     //   538: istore #15
/*     */     //   540: nop
/*     */     //   541: iconst_0
/*     */     //   542: istore #16
/*     */     //   544: aload_1
/*     */     //   545: ldc -1323940314
/*     */     //   547: ldc 'CC(Layout)P(!1,2)79@3208L23,82@3359L411:Layout.kt#80mrfh'
/*     */     //   549: invokestatic sourceInformationMarkerStart : (Landroidx/compose/runtime/Composer;ILjava/lang/String;)V
/*     */     //   552: aload_1
/*     */     //   553: iconst_0
/*     */     //   554: invokestatic getCurrentCompositeKeyHash : (Landroidx/compose/runtime/Composer;I)I
/*     */     //   557: istore #17
/*     */     //   559: aload_1
/*     */     //   560: invokeinterface getCurrentCompositionLocalMap : ()Landroidx/compose/runtime/CompositionLocalMap;
/*     */     //   565: astore #18
/*     */     //   567: aload_1
/*     */     //   568: aload #9
/*     */     //   570: invokestatic materializeModifier : (Landroidx/compose/runtime/Composer;Landroidx/compose/ui/Modifier;)Landroidx/compose/ui/Modifier;
/*     */     //   573: astore #19
/*     */     //   575: getstatic androidx/compose/ui/node/ComposeUiNode.Companion : Landroidx/compose/ui/node/ComposeUiNode$Companion;
/*     */     //   578: invokevirtual getConstructor : ()Lkotlin/jvm/functions/Function0;
/*     */     //   581: astore #20
/*     */     //   583: bipush #6
/*     */     //   585: sipush #896
/*     */     //   588: iload #15
/*     */     //   590: bipush #6
/*     */     //   592: ishl
/*     */     //   593: iand
/*     */     //   594: ior
/*     */     //   595: istore #21
/*     */     //   597: nop
/*     */     //   598: iconst_0
/*     */     //   599: istore #22
/*     */     //   601: aload_1
/*     */     //   602: ldc -692256719
/*     */     //   604: ldc 'CC(ReusableComposeNode)P(1,2)376@14062L9:Composables.kt#9igjgp'
/*     */     //   606: invokestatic sourceInformationMarkerStart : (Landroidx/compose/runtime/Composer;ILjava/lang/String;)V
/*     */     //   609: aload_1
/*     */     //   610: invokeinterface getApplier : ()Landroidx/compose/runtime/Applier;
/*     */     //   615: instanceof androidx/compose/runtime/Applier
/*     */     //   618: ifne -> 624
/*     */     //   621: invokestatic invalidApplier : ()V
/*     */     //   624: aload_1
/*     */     //   625: invokeinterface startReusableNode : ()V
/*     */     //   630: aload_1
/*     */     //   631: invokeinterface getInserting : ()Z
/*     */     //   636: ifeq -> 650
/*     */     //   639: aload_1
/*     */     //   640: aload #20
/*     */     //   642: invokeinterface createNode : (Lkotlin/jvm/functions/Function0;)V
/*     */     //   647: goto -> 656
/*     */     //   650: aload_1
/*     */     //   651: invokeinterface useNode : ()V
/*     */     //   656: aload_1
/*     */     //   657: invokestatic constructor-impl : (Landroidx/compose/runtime/Composer;)Landroidx/compose/runtime/Composer;
/*     */     //   660: astore #23
/*     */     //   662: iconst_0
/*     */     //   663: istore #24
/*     */     //   665: aload #23
/*     */     //   667: aload #14
/*     */     //   669: getstatic androidx/compose/ui/node/ComposeUiNode.Companion : Landroidx/compose/ui/node/ComposeUiNode$Companion;
/*     */     //   672: invokevirtual getSetMeasurePolicy : ()Lkotlin/jvm/functions/Function2;
/*     */     //   675: invokestatic set-impl : (Landroidx/compose/runtime/Composer;Ljava/lang/Object;Lkotlin/jvm/functions/Function2;)V
/*     */     //   678: aload #23
/*     */     //   680: aload #18
/*     */     //   682: getstatic androidx/compose/ui/node/ComposeUiNode.Companion : Landroidx/compose/ui/node/ComposeUiNode$Companion;
/*     */     //   685: invokevirtual getSetResolvedCompositionLocals : ()Lkotlin/jvm/functions/Function2;
/*     */     //   688: invokestatic set-impl : (Landroidx/compose/runtime/Composer;Ljava/lang/Object;Lkotlin/jvm/functions/Function2;)V
/*     */     //   691: getstatic androidx/compose/ui/node/ComposeUiNode.Companion : Landroidx/compose/ui/node/ComposeUiNode$Companion;
/*     */     //   694: invokevirtual getSetCompositeKeyHash : ()Lkotlin/jvm/functions/Function2;
/*     */     //   697: astore #25
/*     */     //   699: iconst_0
/*     */     //   700: istore #26
/*     */     //   702: aload #23
/*     */     //   704: astore #27
/*     */     //   706: iconst_0
/*     */     //   707: istore #28
/*     */     //   709: aload #27
/*     */     //   711: invokeinterface getInserting : ()Z
/*     */     //   716: ifne -> 737
/*     */     //   719: aload #27
/*     */     //   721: invokeinterface rememberedValue : ()Ljava/lang/Object;
/*     */     //   726: iload #17
/*     */     //   728: invokestatic valueOf : (I)Ljava/lang/Integer;
/*     */     //   731: invokestatic areEqual : (Ljava/lang/Object;Ljava/lang/Object;)Z
/*     */     //   734: ifne -> 763
/*     */     //   737: aload #27
/*     */     //   739: iload #17
/*     */     //   741: invokestatic valueOf : (I)Ljava/lang/Integer;
/*     */     //   744: invokeinterface updateRememberedValue : (Ljava/lang/Object;)V
/*     */     //   749: aload #23
/*     */     //   751: iload #17
/*     */     //   753: invokestatic valueOf : (I)Ljava/lang/Integer;
/*     */     //   756: aload #25
/*     */     //   758: invokeinterface apply : (Ljava/lang/Object;Lkotlin/jvm/functions/Function2;)V
/*     */     //   763: nop
/*     */     //   764: nop
/*     */     //   765: nop
/*     */     //   766: aload #23
/*     */     //   768: aload #19
/*     */     //   770: getstatic androidx/compose/ui/node/ComposeUiNode.Companion : Landroidx/compose/ui/node/ComposeUiNode$Companion;
/*     */     //   773: invokevirtual getSetModifier : ()Lkotlin/jvm/functions/Function2;
/*     */     //   776: invokestatic set-impl : (Landroidx/compose/runtime/Composer;Ljava/lang/Object;Lkotlin/jvm/functions/Function2;)V
/*     */     //   779: nop
/*     */     //   780: nop
/*     */     //   781: aload_1
/*     */     //   782: bipush #14
/*     */     //   784: iload #21
/*     */     //   786: bipush #6
/*     */     //   788: ishr
/*     */     //   789: iand
/*     */     //   790: istore #29
/*     */     //   792: astore #30
/*     */     //   794: iconst_0
/*     */     //   795: istore #31
/*     */     //   797: aload #30
/*     */     //   799: ldc_w -384784025
/*     */     //   802: ldc_w 'C88@4444L9:Column.kt#2w3rfo'
/*     */     //   805: invokestatic sourceInformationMarkerStart : (Landroidx/compose/runtime/Composer;ILjava/lang/String;)V
/*     */     //   808: getstatic androidx/compose/foundation/layout/ColumnScopeInstance.INSTANCE : Landroidx/compose/foundation/layout/ColumnScopeInstance;
/*     */     //   811: aload #30
/*     */     //   813: bipush #6
/*     */     //   815: bipush #112
/*     */     //   817: iload #12
/*     */     //   819: bipush #6
/*     */     //   821: ishr
/*     */     //   822: iand
/*     */     //   823: ior
/*     */     //   824: istore #32
/*     */     //   826: astore #33
/*     */     //   828: checkcast androidx/compose/foundation/layout/ColumnScope
/*     */     //   831: astore #34
/*     */     //   833: iconst_0
/*     */     //   834: istore #35
/*     */     //   836: aconst_null
/*     */     //   837: aconst_null
/*     */     //   838: lconst_0
/*     */     //   839: aload #33
/*     */     //   841: bipush #48
/*     */     //   843: iconst_5
/*     */     //   844: invokestatic JunieLogo-FNF3uiM : (Landroidx/compose/ui/Modifier;Ljava/lang/String;JLandroidx/compose/runtime/Composer;II)V
/*     */     //   847: getstatic androidx/compose/ui/Modifier.Companion : Landroidx/compose/ui/Modifier$Companion;
/*     */     //   850: checkcast androidx/compose/ui/Modifier
/*     */     //   853: bipush #40
/*     */     //   855: istore #36
/*     */     //   857: iconst_0
/*     */     //   858: istore #37
/*     */     //   860: iload #36
/*     */     //   862: i2f
/*     */     //   863: invokestatic constructor-impl : (F)F
/*     */     //   866: invokestatic height-3ABfNKs : (Landroidx/compose/ui/Modifier;F)Landroidx/compose/ui/Modifier;
/*     */     //   869: aload #33
/*     */     //   871: bipush #6
/*     */     //   873: invokestatic Spacer : (Landroidx/compose/ui/Modifier;Landroidx/compose/runtime/Composer;I)V
/*     */     //   876: getstatic androidx/compose/foundation/layout/Arrangement.INSTANCE : Landroidx/compose/foundation/layout/Arrangement;
/*     */     //   879: bipush #16
/*     */     //   881: istore #37
/*     */     //   883: iconst_0
/*     */     //   884: istore #38
/*     */     //   886: iload #37
/*     */     //   888: i2f
/*     */     //   889: invokestatic constructor-impl : (F)F
/*     */     //   892: invokevirtual spacedBy-0680j_4 : (F)Landroidx/compose/foundation/layout/Arrangement$HorizontalOrVertical;
/*     */     //   895: checkcast androidx/compose/foundation/layout/Arrangement$Vertical
/*     */     //   898: astore #37
/*     */     //   900: bipush #48
/*     */     //   902: istore #39
/*     */     //   904: iconst_0
/*     */     //   905: istore #40
/*     */     //   907: aload #33
/*     */     //   909: ldc -483455358
/*     */     //   911: ldc 'CC(Column)P(2,3,1)86@4330L61,87@4396L133:Column.kt#2w3rfo'
/*     */     //   913: invokestatic sourceInformationMarkerStart : (Landroidx/compose/runtime/Composer;ILjava/lang/String;)V
/*     */     //   916: getstatic androidx/compose/ui/Modifier.Companion : Landroidx/compose/ui/Modifier$Companion;
/*     */     //   919: checkcast androidx/compose/ui/Modifier
/*     */     //   922: astore #36
/*     */     //   924: getstatic androidx/compose/ui/Alignment.Companion : Landroidx/compose/ui/Alignment$Companion;
/*     */     //   927: invokevirtual getStart : ()Landroidx/compose/ui/Alignment$Horizontal;
/*     */     //   930: astore #38
/*     */     //   932: aload #37
/*     */     //   934: aload #38
/*     */     //   936: aload #33
/*     */     //   938: bipush #14
/*     */     //   940: iload #39
/*     */     //   942: iconst_3
/*     */     //   943: ishr
/*     */     //   944: iand
/*     */     //   945: bipush #112
/*     */     //   947: iload #39
/*     */     //   949: iconst_3
/*     */     //   950: ishr
/*     */     //   951: iand
/*     */     //   952: ior
/*     */     //   953: invokestatic columnMeasurePolicy : (Landroidx/compose/foundation/layout/Arrangement$Vertical;Landroidx/compose/ui/Alignment$Horizontal;Landroidx/compose/runtime/Composer;I)Landroidx/compose/ui/layout/MeasurePolicy;
/*     */     //   956: astore #41
/*     */     //   958: bipush #112
/*     */     //   960: iload #39
/*     */     //   962: iconst_3
/*     */     //   963: ishl
/*     */     //   964: iand
/*     */     //   965: istore #42
/*     */     //   967: nop
/*     */     //   968: iconst_0
/*     */     //   969: istore #43
/*     */     //   971: aload #33
/*     */     //   973: ldc -1323940314
/*     */     //   975: ldc 'CC(Layout)P(!1,2)79@3208L23,82@3359L411:Layout.kt#80mrfh'
/*     */     //   977: invokestatic sourceInformationMarkerStart : (Landroidx/compose/runtime/Composer;ILjava/lang/String;)V
/*     */     //   980: aload #33
/*     */     //   982: iconst_0
/*     */     //   983: invokestatic getCurrentCompositeKeyHash : (Landroidx/compose/runtime/Composer;I)I
/*     */     //   986: istore #44
/*     */     //   988: aload #33
/*     */     //   990: invokeinterface getCurrentCompositionLocalMap : ()Landroidx/compose/runtime/CompositionLocalMap;
/*     */     //   995: astore #45
/*     */     //   997: aload #33
/*     */     //   999: aload #36
/*     */     //   1001: invokestatic materializeModifier : (Landroidx/compose/runtime/Composer;Landroidx/compose/ui/Modifier;)Landroidx/compose/ui/Modifier;
/*     */     //   1004: astore #46
/*     */     //   1006: getstatic androidx/compose/ui/node/ComposeUiNode.Companion : Landroidx/compose/ui/node/ComposeUiNode$Companion;
/*     */     //   1009: invokevirtual getConstructor : ()Lkotlin/jvm/functions/Function0;
/*     */     //   1012: astore #47
/*     */     //   1014: bipush #6
/*     */     //   1016: sipush #896
/*     */     //   1019: iload #42
/*     */     //   1021: bipush #6
/*     */     //   1023: ishl
/*     */     //   1024: iand
/*     */     //   1025: ior
/*     */     //   1026: istore #48
/*     */     //   1028: nop
/*     */     //   1029: iconst_0
/*     */     //   1030: istore #49
/*     */     //   1032: aload #33
/*     */     //   1034: ldc -692256719
/*     */     //   1036: ldc 'CC(ReusableComposeNode)P(1,2)376@14062L9:Composables.kt#9igjgp'
/*     */     //   1038: invokestatic sourceInformationMarkerStart : (Landroidx/compose/runtime/Composer;ILjava/lang/String;)V
/*     */     //   1041: aload #33
/*     */     //   1043: invokeinterface getApplier : ()Landroidx/compose/runtime/Applier;
/*     */     //   1048: instanceof androidx/compose/runtime/Applier
/*     */     //   1051: ifne -> 1057
/*     */     //   1054: invokestatic invalidApplier : ()V
/*     */     //   1057: aload #33
/*     */     //   1059: invokeinterface startReusableNode : ()V
/*     */     //   1064: aload #33
/*     */     //   1066: invokeinterface getInserting : ()Z
/*     */     //   1071: ifeq -> 1086
/*     */     //   1074: aload #33
/*     */     //   1076: aload #47
/*     */     //   1078: invokeinterface createNode : (Lkotlin/jvm/functions/Function0;)V
/*     */     //   1083: goto -> 1093
/*     */     //   1086: aload #33
/*     */     //   1088: invokeinterface useNode : ()V
/*     */     //   1093: aload #33
/*     */     //   1095: invokestatic constructor-impl : (Landroidx/compose/runtime/Composer;)Landroidx/compose/runtime/Composer;
/*     */     //   1098: astore #50
/*     */     //   1100: iconst_0
/*     */     //   1101: istore #51
/*     */     //   1103: aload #50
/*     */     //   1105: aload #41
/*     */     //   1107: getstatic androidx/compose/ui/node/ComposeUiNode.Companion : Landroidx/compose/ui/node/ComposeUiNode$Companion;
/*     */     //   1110: invokevirtual getSetMeasurePolicy : ()Lkotlin/jvm/functions/Function2;
/*     */     //   1113: invokestatic set-impl : (Landroidx/compose/runtime/Composer;Ljava/lang/Object;Lkotlin/jvm/functions/Function2;)V
/*     */     //   1116: aload #50
/*     */     //   1118: aload #45
/*     */     //   1120: getstatic androidx/compose/ui/node/ComposeUiNode.Companion : Landroidx/compose/ui/node/ComposeUiNode$Companion;
/*     */     //   1123: invokevirtual getSetResolvedCompositionLocals : ()Lkotlin/jvm/functions/Function2;
/*     */     //   1126: invokestatic set-impl : (Landroidx/compose/runtime/Composer;Ljava/lang/Object;Lkotlin/jvm/functions/Function2;)V
/*     */     //   1129: getstatic androidx/compose/ui/node/ComposeUiNode.Companion : Landroidx/compose/ui/node/ComposeUiNode$Companion;
/*     */     //   1132: invokevirtual getSetCompositeKeyHash : ()Lkotlin/jvm/functions/Function2;
/*     */     //   1135: astore #52
/*     */     //   1137: iconst_0
/*     */     //   1138: istore #53
/*     */     //   1140: aload #50
/*     */     //   1142: astore #54
/*     */     //   1144: iconst_0
/*     */     //   1145: istore #55
/*     */     //   1147: aload #54
/*     */     //   1149: invokeinterface getInserting : ()Z
/*     */     //   1154: ifne -> 1175
/*     */     //   1157: aload #54
/*     */     //   1159: invokeinterface rememberedValue : ()Ljava/lang/Object;
/*     */     //   1164: iload #44
/*     */     //   1166: invokestatic valueOf : (I)Ljava/lang/Integer;
/*     */     //   1169: invokestatic areEqual : (Ljava/lang/Object;Ljava/lang/Object;)Z
/*     */     //   1172: ifne -> 1201
/*     */     //   1175: aload #54
/*     */     //   1177: iload #44
/*     */     //   1179: invokestatic valueOf : (I)Ljava/lang/Integer;
/*     */     //   1182: invokeinterface updateRememberedValue : (Ljava/lang/Object;)V
/*     */     //   1187: aload #50
/*     */     //   1189: iload #44
/*     */     //   1191: invokestatic valueOf : (I)Ljava/lang/Integer;
/*     */     //   1194: aload #52
/*     */     //   1196: invokeinterface apply : (Ljava/lang/Object;Lkotlin/jvm/functions/Function2;)V
/*     */     //   1201: nop
/*     */     //   1202: nop
/*     */     //   1203: nop
/*     */     //   1204: aload #50
/*     */     //   1206: aload #46
/*     */     //   1208: getstatic androidx/compose/ui/node/ComposeUiNode.Companion : Landroidx/compose/ui/node/ComposeUiNode$Companion;
/*     */     //   1211: invokevirtual getSetModifier : ()Lkotlin/jvm/functions/Function2;
/*     */     //   1214: invokestatic set-impl : (Landroidx/compose/runtime/Composer;Ljava/lang/Object;Lkotlin/jvm/functions/Function2;)V
/*     */     //   1217: nop
/*     */     //   1218: nop
/*     */     //   1219: aload #33
/*     */     //   1221: bipush #14
/*     */     //   1223: iload #48
/*     */     //   1225: bipush #6
/*     */     //   1227: ishr
/*     */     //   1228: iand
/*     */     //   1229: istore #56
/*     */     //   1231: astore #57
/*     */     //   1233: iconst_0
/*     */     //   1234: istore #58
/*     */     //   1236: aload #57
/*     */     //   1238: ldc_w -384784025
/*     */     //   1241: ldc_w 'C88@4444L9:Column.kt#2w3rfo'
/*     */     //   1244: invokestatic sourceInformationMarkerStart : (Landroidx/compose/runtime/Composer;ILjava/lang/String;)V
/*     */     //   1247: getstatic androidx/compose/foundation/layout/ColumnScopeInstance.INSTANCE : Landroidx/compose/foundation/layout/ColumnScopeInstance;
/*     */     //   1250: aload #57
/*     */     //   1252: bipush #6
/*     */     //   1254: bipush #112
/*     */     //   1256: iload #39
/*     */     //   1258: bipush #6
/*     */     //   1260: ishr
/*     */     //   1261: iand
/*     */     //   1262: ior
/*     */     //   1263: istore #59
/*     */     //   1265: astore #60
/*     */     //   1267: checkcast androidx/compose/foundation/layout/ColumnScope
/*     */     //   1270: astore #61
/*     */     //   1272: iconst_0
/*     */     //   1273: istore #62
/*     */     //   1275: aload #8
/*     */     //   1277: invokestatic GrazieActivationPage$lambda$6 : (Landroidx/compose/runtime/State;)Lcom/intellij/ml/llm/matterhorn/ej/ui/login/states/GrazieActivationState;
/*     */     //   1280: aload #7
/*     */     //   1282: invokestatic GrazieActivationPage$lambda$3 : (Landroidx/compose/runtime/MutableState;)Ljava/lang/String;
/*     */     //   1285: aload #60
/*     */     //   1287: iconst_0
/*     */     //   1288: invokestatic GrazieActivationPageComponent : (Lcom/intellij/ml/llm/matterhorn/ej/ui/login/states/GrazieActivationState;Ljava/lang/String;Landroidx/compose/runtime/Composer;I)V
/*     */     //   1291: nop
/*     */     //   1292: aload #57
/*     */     //   1294: invokestatic sourceInformationMarkerEnd : (Landroidx/compose/runtime/Composer;)V
/*     */     //   1297: aload #33
/*     */     //   1299: invokeinterface endNode : ()V
/*     */     //   1304: aload #33
/*     */     //   1306: invokestatic sourceInformationMarkerEnd : (Landroidx/compose/runtime/Composer;)V
/*     */     //   1309: nop
/*     */     //   1310: aload #33
/*     */     //   1312: invokestatic sourceInformationMarkerEnd : (Landroidx/compose/runtime/Composer;)V
/*     */     //   1315: nop
/*     */     //   1316: aload #33
/*     */     //   1318: invokestatic sourceInformationMarkerEnd : (Landroidx/compose/runtime/Composer;)V
/*     */     //   1321: nop
/*     */     //   1322: getstatic androidx/compose/ui/Modifier.Companion : Landroidx/compose/ui/Modifier$Companion;
/*     */     //   1325: checkcast androidx/compose/ui/Modifier
/*     */     //   1328: bipush #40
/*     */     //   1330: istore #36
/*     */     //   1332: iconst_0
/*     */     //   1333: istore #37
/*     */     //   1335: iload #36
/*     */     //   1337: i2f
/*     */     //   1338: invokestatic constructor-impl : (F)F
/*     */     //   1341: invokestatic height-3ABfNKs : (Landroidx/compose/ui/Modifier;F)Landroidx/compose/ui/Modifier;
/*     */     //   1344: aload #33
/*     */     //   1346: bipush #6
/*     */     //   1348: invokestatic Spacer : (Landroidx/compose/ui/Modifier;Landroidx/compose/runtime/Composer;I)V
/*     */     //   1351: aload #33
/*     */     //   1353: ldc_w -1281173591
/*     */     //   1356: invokeinterface startReplaceGroup : (I)V
/*     */     //   1361: aload #4
/*     */     //   1363: invokestatic GrazieActivationPage$lambda$1 : (Landroidx/compose/runtime/MutableState;)Z
/*     */     //   1366: ifeq -> 1375
/*     */     //   1369: aload #33
/*     */     //   1371: iconst_0
/*     */     //   1372: invokestatic LoginFooter : (Landroidx/compose/runtime/Composer;I)V
/*     */     //   1375: aload #33
/*     */     //   1377: invokeinterface endReplaceGroup : ()V
/*     */     //   1382: nop
/*     */     //   1383: aload #30
/*     */     //   1385: invokestatic sourceInformationMarkerEnd : (Landroidx/compose/runtime/Composer;)V
/*     */     //   1388: aload_1
/*     */     //   1389: invokeinterface endNode : ()V
/*     */     //   1394: aload_1
/*     */     //   1395: invokestatic sourceInformationMarkerEnd : (Landroidx/compose/runtime/Composer;)V
/*     */     //   1398: nop
/*     */     //   1399: aload_1
/*     */     //   1400: invokestatic sourceInformationMarkerEnd : (Landroidx/compose/runtime/Composer;)V
/*     */     //   1403: nop
/*     */     //   1404: aload_1
/*     */     //   1405: invokestatic sourceInformationMarkerEnd : (Landroidx/compose/runtime/Composer;)V
/*     */     //   1408: nop
/*     */     //   1409: invokestatic isTraceInProgress : ()Z
/*     */     //   1412: ifeq -> 1427
/*     */     //   1415: invokestatic traceEventEnd : ()V
/*     */     //   1418: goto -> 1427
/*     */     //   1421: aload_1
/*     */     //   1422: invokeinterface skipToGroupEnd : ()V
/*     */     //   1427: aload_1
/*     */     //   1428: invokeinterface endRestartGroup : ()Landroidx/compose/runtime/ScopeUpdateScope;
/*     */     //   1433: dup
/*     */     //   1434: ifnull -> 1452
/*     */     //   1437: aload_0
/*     */     //   1438: iload_2
/*     */     //   1439: <illegal opcode> invoke : (Lcom/intellij/ml/llm/matterhorn/ej/ui/login/GrazieActivationPageVm;I)Lkotlin/jvm/functions/Function2;
/*     */     //   1444: invokeinterface updateScope : (Lkotlin/jvm/functions/Function2;)V
/*     */     //   1449: goto -> 1453
/*     */     //   1452: pop
/*     */     //   1453: return
/*     */     // Line number table:
/*     */     //   Java source line number -> byte code offset
/*     */     //   #39	-> 6
/*     */     //   #40	-> 87
/*     */     //   #151	-> 91
/*     */     //   #152	-> 103
/*     */     //   #153	-> 114
/*     */     //   #40	-> 117
/*     */     //   #153	-> 127
/*     */     //   #154	-> 129
/*     */     //   #155	-> 138
/*     */     //   #156	-> 143
/*     */     //   #152	-> 145
/*     */     //   #151	-> 146
/*     */     //   #151	-> 147
/*     */     //   #40	-> 148
/*     */     //   #41	-> 165
/*     */     //   #42	-> 187
/*     */     //   #157	-> 191
/*     */     //   #158	-> 203
/*     */     //   #159	-> 214
/*     */     //   #42	-> 217
/*     */     //   #159	-> 224
/*     */     //   #160	-> 226
/*     */     //   #161	-> 235
/*     */     //   #162	-> 240
/*     */     //   #158	-> 242
/*     */     //   #157	-> 243
/*     */     //   #157	-> 244
/*     */     //   #42	-> 245
/*     */     //   #43	-> 260
/*     */     //   #163	-> 280
/*     */     //   #164	-> 292
/*     */     //   #165	-> 303
/*     */     //   #43	-> 308
/*     */     //   #165	-> 324
/*     */     //   #166	-> 326
/*     */     //   #167	-> 335
/*     */     //   #168	-> 340
/*     */     //   #164	-> 342
/*     */     //   #163	-> 343
/*     */     //   #163	-> 344
/*     */     //   #43	-> 345
/*     */     //   #48	-> 364
/*     */     //   #50	-> 380
/*     */     //   #53	-> 391
/*     */     //   #54	-> 403
/*     */     //   #55	-> 413
/*     */     //   #169	-> 420
/*     */     //   #55	-> 426
/*     */     //   #169	-> 435
/*     */     //   #55	-> 441
/*     */     //   #169	-> 450
/*     */     //   #55	-> 456
/*     */     //   #54	-> 458
/*     */     //   #55	-> 460
/*     */     //   #52	-> 478
/*     */     //   #170	-> 487
/*     */     //   #171	-> 490
/*     */     //   #172	-> 498
/*     */     //   #175	-> 506
/*     */     //   #176	-> 540
/*     */     //   #177	-> 549
/*     */     //   #178	-> 554
/*     */     //   #179	-> 560
/*     */     //   #180	-> 568
/*     */     //   #182	-> 575
/*     */     //   #181	-> 597
/*     */     //   #183	-> 606
/*     */     //   #184	-> 609
/*     */     //   #185	-> 625
/*     */     //   #186	-> 630
/*     */     //   #187	-> 640
/*     */     //   #189	-> 651
/*     */     //   #191	-> 656
/*     */     //   #192	-> 665
/*     */     //   #193	-> 678
/*     */     //   #195	-> 691
/*     */     //   #196	-> 702
/*     */     //   #197	-> 709
/*     */     //   #198	-> 737
/*     */     //   #199	-> 749
/*     */     //   #201	-> 763
/*     */     //   #196	-> 764
/*     */     //   #201	-> 765
/*     */     //   #202	-> 766
/*     */     //   #203	-> 779
/*     */     //   #191	-> 780
/*     */     //   #204	-> 781
/*     */     //   #205	-> 805
/*     */     //   #57	-> 837
/*     */     //   #58	-> 847
/*     */     //   #206	-> 860
/*     */     //   #58	-> 866
/*     */     //   #60	-> 876
/*     */     //   #207	-> 886
/*     */     //   #60	-> 892
/*     */     //   #208	-> 913
/*     */     //   #209	-> 916
/*     */     //   #211	-> 924
/*     */     //   #214	-> 932
/*     */     //   #215	-> 967
/*     */     //   #216	-> 977
/*     */     //   #217	-> 983
/*     */     //   #218	-> 990
/*     */     //   #219	-> 999
/*     */     //   #221	-> 1006
/*     */     //   #220	-> 1028
/*     */     //   #222	-> 1038
/*     */     //   #223	-> 1041
/*     */     //   #224	-> 1059
/*     */     //   #225	-> 1064
/*     */     //   #226	-> 1076
/*     */     //   #228	-> 1088
/*     */     //   #230	-> 1093
/*     */     //   #231	-> 1103
/*     */     //   #232	-> 1116
/*     */     //   #234	-> 1129
/*     */     //   #235	-> 1140
/*     */     //   #236	-> 1147
/*     */     //   #237	-> 1175
/*     */     //   #238	-> 1187
/*     */     //   #240	-> 1201
/*     */     //   #235	-> 1202
/*     */     //   #240	-> 1203
/*     */     //   #241	-> 1204
/*     */     //   #242	-> 1217
/*     */     //   #230	-> 1218
/*     */     //   #243	-> 1219
/*     */     //   #244	-> 1244
/*     */     //   #62	-> 1275
/*     */     //   #63	-> 1280
/*     */     //   #61	-> 1288
/*     */     //   #65	-> 1291
/*     */     //   #244	-> 1292
/*     */     //   #243	-> 1297
/*     */     //   #245	-> 1299
/*     */     //   #222	-> 1306
/*     */     //   #246	-> 1309
/*     */     //   #216	-> 1312
/*     */     //   #247	-> 1315
/*     */     //   #208	-> 1318
/*     */     //   #248	-> 1321
/*     */     //   #67	-> 1322
/*     */     //   #249	-> 1335
/*     */     //   #67	-> 1341
/*     */     //   #68	-> 1361
/*     */     //   #69	-> 1372
/*     */     //   #72	-> 1382
/*     */     //   #205	-> 1383
/*     */     //   #204	-> 1388
/*     */     //   #250	-> 1389
/*     */     //   #183	-> 1395
/*     */     //   #251	-> 1398
/*     */     //   #177	-> 1400
/*     */     //   #252	-> 1403
/*     */     //   #170	-> 1405
/*     */     //   #253	-> 1408
/*     */     //   #73	-> 1421
/*     */     // Local variable table:
/*     */     //   start	length	slot	name	descriptor
/*     */     //   117	10	11	$i$a$-cache-GrazieActivationPageKt$GrazieActivationPage$showFooter$2	I
/*     */     //   129	11	11	value$iv	Ljava/lang/Object;
/*     */     //   103	43	10	$i$a$-let-ComposerKt$cache$1$iv	I
/*     */     //   100	46	9	it$iv	Ljava/lang/Object;
/*     */     //   91	57	8	$i$f$cache	I
/*     */     //   88	60	6	$this$cache$iv	Landroidx/compose/runtime/Composer;
/*     */     //   88	60	7	invalid$iv	Z
/*     */     //   217	7	14	$i$a$-cache-GrazieActivationPageKt$GrazieActivationPage$username$2	I
/*     */     //   226	11	14	value$iv	Ljava/lang/Object;
/*     */     //   203	40	13	$i$a$-let-ComposerKt$cache$1$iv	I
/*     */     //   200	43	12	it$iv	Ljava/lang/Object;
/*     */     //   191	54	11	$i$f$cache	I
/*     */     //   188	57	9	$this$cache$iv	Landroidx/compose/runtime/Composer;
/*     */     //   188	57	10	invalid$iv	Z
/*     */     //   308	13	14	$i$a$-cache-GrazieActivationPageKt$GrazieActivationPage$1	I
/*     */     //   326	11	15	value$iv	Ljava/lang/Object;
/*     */     //   292	51	13	$i$a$-let-ComposerKt$cache$1$iv	I
/*     */     //   289	54	12	it$iv	Ljava/lang/Object;
/*     */     //   280	65	11	$i$f$cache	I
/*     */     //   277	68	9	$this$cache$iv	Landroidx/compose/runtime/Composer;
/*     */     //   277	68	10	invalid$iv	Z
/*     */     //   420	6	12	$i$f$getDp	I
/*     */     //   417	9	11	$this$dp$iv	I
/*     */     //   435	6	13	$i$f$getDp	I
/*     */     //   432	9	12	$this$dp$iv	I
/*     */     //   450	6	14	$i$f$getDp	I
/*     */     //   447	9	13	$this$dp$iv	I
/*     */     //   860	6	37	$i$f$getDp	I
/*     */     //   857	9	36	$this$dp$iv	I
/*     */     //   886	6	38	$i$f$getDp	I
/*     */     //   883	9	37	$this$dp$iv	I
/*     */     //   1275	17	62	$i$a$-Column-GrazieActivationPageKt$GrazieActivationPage$2$1	I
/*     */     //   1272	20	61	$this$GrazieActivationPage_u24lambda_u248_u24lambda_u247	Landroidx/compose/foundation/layout/ColumnScope;
/*     */     //   1272	20	60	$composer	Landroidx/compose/runtime/Composer;
/*     */     //   1272	20	59	$changed	I
/*     */     //   1236	61	58	$i$a$-Layout-ColumnKt$Column$1$iv	I
/*     */     //   1233	64	57	$composer$iv	Landroidx/compose/runtime/Composer;
/*     */     //   1233	64	56	$changed$iv	I
/*     */     //   1147	55	55	$i$a$-with-Updater$set$1$iv$iv$iv	I
/*     */     //   1144	58	54	$this$set_impl_u24lambda_u240$iv$iv$iv	Landroidx/compose/runtime/Composer;
/*     */     //   1140	64	53	$i$f$set-impl	I
/*     */     //   1137	67	52	block$iv$iv$iv	Lkotlin/jvm/functions/Function2;
/*     */     //   1103	115	51	$i$a$-ReusableComposeNode-LayoutKt$Layout$1$iv$iv	I
/*     */     //   1100	118	50	$this$Layout_u24lambda_u240$iv$iv	Landroidx/compose/runtime/Composer;
/*     */     //   1032	278	49	$i$f$ReusableComposeNode	I
/*     */     //   1029	281	47	factory$iv$iv$iv	Lkotlin/jvm/functions/Function0;
/*     */     //   1029	281	48	$changed$iv$iv$iv	I
/*     */     //   971	345	43	$i$f$Layout	I
/*     */     //   988	328	44	compositeKeyHash$iv$iv	I
/*     */     //   997	319	45	localMap$iv$iv	Landroidx/compose/runtime/CompositionLocalMap;
/*     */     //   1006	310	46	materialized$iv$iv	Landroidx/compose/ui/Modifier;
/*     */     //   968	348	42	$changed$iv$iv	I
/*     */     //   907	415	40	$i$f$Column	I
/*     */     //   958	364	41	measurePolicy$iv	Landroidx/compose/ui/layout/MeasurePolicy;
/*     */     //   924	398	36	modifier$iv	Landroidx/compose/ui/Modifier;
/*     */     //   904	418	37	verticalArrangement$iv	Landroidx/compose/foundation/layout/Arrangement$Vertical;
/*     */     //   932	390	38	horizontalAlignment$iv	Landroidx/compose/ui/Alignment$Horizontal;
/*     */     //   904	418	39	$changed$iv	I
/*     */     //   1335	6	37	$i$f$getDp	I
/*     */     //   1332	9	36	$this$dp$iv	I
/*     */     //   836	547	35	$i$a$-Column-GrazieActivationPageKt$GrazieActivationPage$2	I
/*     */     //   833	550	34	$this$GrazieActivationPage_u24lambda_u248	Landroidx/compose/foundation/layout/ColumnScope;
/*     */     //   833	550	33	$composer	Landroidx/compose/runtime/Composer;
/*     */     //   833	550	32	$changed	I
/*     */     //   797	591	31	$i$a$-Layout-ColumnKt$Column$1$iv	I
/*     */     //   794	594	30	$composer$iv	Landroidx/compose/runtime/Composer;
/*     */     //   794	594	29	$changed$iv	I
/*     */     //   709	55	28	$i$a$-with-Updater$set$1$iv$iv$iv	I
/*     */     //   706	58	27	$this$set_impl_u24lambda_u240$iv$iv$iv	Landroidx/compose/runtime/Composer;
/*     */     //   702	64	26	$i$f$set-impl	I
/*     */     //   699	67	25	block$iv$iv$iv	Lkotlin/jvm/functions/Function2;
/*     */     //   665	115	24	$i$a$-ReusableComposeNode-LayoutKt$Layout$1$iv$iv	I
/*     */     //   662	118	23	$this$Layout_u24lambda_u240$iv$iv	Landroidx/compose/runtime/Composer;
/*     */     //   601	798	22	$i$f$ReusableComposeNode	I
/*     */     //   598	801	20	factory$iv$iv$iv	Lkotlin/jvm/functions/Function0;
/*     */     //   598	801	21	$changed$iv$iv$iv	I
/*     */     //   544	860	16	$i$f$Layout	I
/*     */     //   559	845	17	compositeKeyHash$iv$iv	I
/*     */     //   567	837	18	localMap$iv$iv	Landroidx/compose/runtime/CompositionLocalMap;
/*     */     //   575	829	19	materialized$iv$iv	Landroidx/compose/ui/Modifier;
/*     */     //   541	863	15	$changed$iv$iv	I
/*     */     //   482	927	13	$i$f$Column	I
/*     */     //   531	878	14	measurePolicy$iv	Landroidx/compose/ui/layout/MeasurePolicy;
/*     */     //   479	930	9	modifier$iv	Landroidx/compose/ui/Modifier;
/*     */     //   498	911	10	verticalArrangement$iv	Landroidx/compose/foundation/layout/Arrangement$Vertical;
/*     */     //   506	903	11	horizontalAlignment$iv	Landroidx/compose/ui/Alignment$Horizontal;
/*     */     //   479	930	12	$changed$iv	I
/*     */     //   163	1255	4	showFooter$delegate	Landroidx/compose/runtime/MutableState;
/*     */     //   173	1245	5	backgroundColor	J
/*     */     //   260	1158	7	username$delegate	Landroidx/compose/runtime/MutableState;
/*     */     //   380	1038	8	uiState$delegate	Landroidx/compose/runtime/State;
/*     */     //   17	1437	3	$dirty	I
/*     */     //   0	1454	0	model	Lcom/intellij/ml/llm/matterhorn/ej/ui/login/GrazieActivationPageVm;
/*     */     //   0	1454	1	$composer	Landroidx/compose/runtime/Composer;
/*     */     //   0	1454	2	$changed	I
/*     */   }
/*     */   
/*  40 */   private static final boolean GrazieActivationPage$lambda$1(MutableState $showFooter$delegate) { State state = (State)$showFooter$delegate; Object object = null; KProperty property$iv = null; int $i$f$getValue = 0; return (
/*     */ 
/*     */ 
/*     */ 
/*     */ 
/*     */ 
/*     */ 
/*     */ 
/*     */ 
/*     */ 
/*     */ 
/*     */ 
/*     */ 
/*     */ 
/*     */ 
/*     */ 
/*     */ 
/*     */ 
/*     */ 
/*     */ 
/*     */ 
/*     */ 
/*     */ 
/*     */ 
/*     */ 
/*     */ 
/*     */ 
/*     */ 
/*     */ 
/*     */ 
/*     */ 
/*     */ 
/*     */ 
/*     */ 
/*     */ 
/*     */ 
/*     */ 
/*     */ 
/*     */ 
/*     */ 
/*     */ 
/*     */ 
/*     */ 
/*     */ 
/*     */ 
/*     */ 
/*     */ 
/*     */ 
/*     */ 
/*     */ 
/*     */ 
/*     */ 
/*     */ 
/*     */ 
/*     */ 
/*     */ 
/*     */ 
/*     */ 
/*     */ 
/*     */ 
/*     */ 
/*     */ 
/*     */ 
/*     */ 
/*     */ 
/*     */ 
/*     */ 
/*     */ 
/*     */ 
/*     */ 
/*     */ 
/*     */ 
/*     */ 
/*     */ 
/*     */ 
/*     */ 
/*     */ 
/*     */ 
/*     */ 
/*     */ 
/*     */ 
/*     */ 
/*     */ 
/*     */ 
/*     */ 
/*     */ 
/*     */ 
/*     */ 
/*     */ 
/*     */ 
/*     */ 
/*     */ 
/*     */ 
/*     */ 
/*     */ 
/*     */ 
/*     */ 
/*     */ 
/*     */ 
/*     */ 
/*     */ 
/*     */ 
/*     */ 
/*     */ 
/*     */ 
/*     */ 
/*     */ 
/*     */ 
/*     */ 
/*     */ 
/*     */ 
/*     */ 
/*     */ 
/*     */ 
/*     */ 
/*     */ 
/*     */ 
/*     */ 
/*     */ 
/*     */ 
/*     */ 
/*     */ 
/*     */ 
/*     */ 
/*     */ 
/*     */ 
/*     */ 
/*     */ 
/*     */ 
/*     */ 
/*     */ 
/*     */ 
/*     */ 
/*     */ 
/*     */ 
/*     */ 
/*     */ 
/*     */ 
/*     */ 
/*     */ 
/*     */ 
/*     */ 
/*     */ 
/*     */ 
/*     */ 
/*     */ 
/*     */ 
/*     */ 
/*     */ 
/*     */ 
/*     */ 
/*     */ 
/*     */ 
/*     */ 
/*     */ 
/*     */ 
/*     */ 
/*     */ 
/*     */ 
/*     */ 
/*     */ 
/*     */ 
/*     */ 
/*     */ 
/*     */ 
/*     */ 
/*     */ 
/*     */ 
/*     */ 
/*     */ 
/*     */ 
/*     */ 
/*     */ 
/*     */ 
/*     */ 
/*     */ 
/*     */ 
/*     */ 
/*     */ 
/*     */ 
/*     */ 
/*     */ 
/*     */ 
/*     */ 
/*     */ 
/*     */ 
/*     */ 
/*     */ 
/*     */ 
/*     */ 
/*     */ 
/*     */ 
/*     */ 
/*     */ 
/*     */ 
/*     */ 
/*     */ 
/*     */ 
/*     */ 
/*     */ 
/*     */ 
/*     */ 
/*     */ 
/*     */ 
/*     */ 
/*     */ 
/*     */ 
/*     */ 
/*     */ 
/*     */ 
/*     */ 
/*     */ 
/*     */ 
/*     */ 
/*     */ 
/*     */ 
/*     */ 
/*     */ 
/*     */ 
/*     */ 
/*     */ 
/*     */ 
/*     */ 
/*     */ 
/*     */ 
/*     */ 
/*     */ 
/*     */ 
/*     */ 
/*     */ 
/*     */ 
/*     */ 
/*     */ 
/*     */ 
/*     */ 
/*     */ 
/*     */ 
/*     */ 
/*     */ 
/*     */ 
/*     */ 
/*     */ 
/*     */ 
/*     */ 
/*     */ 
/*     */ 
/*     */ 
/*     */ 
/*     */ 
/*     */ 
/*     */ 
/*     */ 
/*     */ 
/*     */ 
/*     */ 
/*     */ 
/*     */ 
/*     */ 
/*     */ 
/*     */ 
/*     */ 
/*     */ 
/*     */ 
/*     */ 
/*     */ 
/*     */ 
/*     */ 
/*     */ 
/*     */ 
/*     */ 
/*     */ 
/*     */ 
/*     */ 
/*     */ 
/*     */ 
/*     */ 
/*     */ 
/*     */ 
/*     */ 
/*     */ 
/*     */ 
/*     */ 
/*     */ 
/*     */ 
/*     */ 
/*     */ 
/*     */ 
/*     */ 
/*     */ 
/*     */ 
/*     */ 
/*     */ 
/*     */ 
/*     */ 
/*     */ 
/*     */ 
/*     */ 
/*     */ 
/*     */ 
/*     */ 
/*     */ 
/*     */ 
/*     */ 
/*     */ 
/*     */ 
/*     */ 
/*     */ 
/*     */ 
/*     */ 
/*     */ 
/*     */ 
/*     */ 
/*     */ 
/*     */ 
/*     */ 
/*     */ 
/*     */ 
/*     */ 
/*     */ 
/*     */ 
/*     */ 
/*     */ 
/*     */ 
/*     */ 
/*     */ 
/*     */ 
/*     */ 
/*     */ 
/*     */ 
/*     */ 
/*     */ 
/*     */ 
/*     */ 
/*     */ 
/*     */ 
/*     */ 
/*     */ 
/*     */ 
/*     */ 
/*     */ 
/*     */ 
/*     */ 
/*     */ 
/*     */ 
/*     */ 
/*     */ 
/*     */ 
/*     */ 
/*     */ 
/*     */ 
/*     */ 
/*     */ 
/*     */ 
/*     */ 
/*     */ 
/*     */ 
/*     */ 
/*     */ 
/*     */ 
/*     */ 
/*     */ 
/*     */ 
/*     */ 
/*     */ 
/*     */ 
/*     */ 
/*     */ 
/*     */ 
/*     */ 
/*     */ 
/*     */ 
/*     */ 
/*     */ 
/*     */ 
/*     */ 
/*     */ 
/*     */ 
/*     */ 
/*     */ 
/*     */ 
/*     */ 
/*     */ 
/*     */ 
/*     */ 
/*     */ 
/*     */ 
/*     */ 
/*     */ 
/*     */ 
/*     */ 
/*     */ 
/*     */ 
/*     */ 
/*     */ 
/*     */ 
/*     */ 
/*     */ 
/*     */ 
/*     */ 
/*     */ 
/*     */ 
/*     */ 
/*     */ 
/*     */ 
/*     */ 
/*     */ 
/*     */ 
/*     */ 
/*     */ 
/*     */ 
/*     */ 
/*     */ 
/*     */ 
/*     */ 
/*     */ 
/*     */ 
/*     */ 
/*     */ 
/*     */ 
/*     */ 
/*     */ 
/*     */ 
/*     */ 
/*     */ 
/*     */ 
/*     */ 
/*     */ 
/*     */ 
/*     */ 
/*     */ 
/*     */ 
/*     */ 
/*     */ 
/*     */ 
/*     */ 
/*     */ 
/*     */ 
/*     */ 
/*     */ 
/*     */ 
/*     */ 
/*     */ 
/*     */ 
/*     */ 
/*     */ 
/*     */ 
/*     */ 
/*     */ 
/*     */ 
/*     */ 
/*     */ 
/*     */ 
/*     */ 
/*     */ 
/*     */ 
/*     */ 
/*     */ 
/*     */ 
/*     */ 
/*     */ 
/*     */ 
/*     */ 
/*     */ 
/*     */ 
/*     */ 
/*     */ 
/*     */ 
/*     */ 
/*     */ 
/*     */ 
/*     */       
/* 511 */       (Boolean)state.getValue()).booleanValue(); } private static final String GrazieActivationPage$lambda$3(MutableState $username$delegate) { State state = (State)$username$delegate; Object object = null; KProperty property$iv = null; int $i$f$getValue = 0;
/* 512 */     return (String)state.getValue(); } @DebugMetadata(f = "GrazieActivationPage.kt", l = {44}, i = {}, s = {}, n = {}, m = "invokeSuspend", c = "com.intellij.ml.llm.matterhorn.ej.ui.login.GrazieActivationPageKt$GrazieActivationPage$1$1") @Metadata(mv = {2, 1, 0}, k = 3, xi = 48, d1 = {"\000\n\n\000\n\002\020\002\n\002\030\002\020\000\032\0020\001*\0020\002H\n"}, d2 = {"<anonymous>", "", "Lkotlinx/coroutines/CoroutineScope;"}) static final class GrazieActivationPageKt$GrazieActivationPage$1$1 extends SuspendLambda implements Function2<CoroutineScope, Continuation<? super Unit>, Object> {
/* 513 */     int label; GrazieActivationPageKt$GrazieActivationPage$1$1(MutableState<String> $username$delegate, Continuation $completion) { super(2, $completion); } public final Object invokeSuspend(Object $result) { Object object = IntrinsicsKt.getCOROUTINE_SUSPENDED(); switch (this.label) { case 0: ResultKt.throwOnFailure(SYNTHETIC_LOCAL_VARIABLE_1); this.label = 1; if (FlowKt.collectLatest(JunieJbaUserRepository.Companion.syncInstance().getAuthDataFlow(), new Function2<JbaAuthData, Continuation<? super Unit>, Object>(this.$username$delegate, null) { int label; public final Object invokeSuspend(Object $result) { JbaAuthData it; IntrinsicsKt.getCOROUTINE_SUSPENDED(); switch (this.label) { case 0: ResultKt.throwOnFailure(SYNTHETIC_LOCAL_VARIABLE_1); it = (JbaAuthData)this.L$0; it.getUser(); GrazieActivationPageKt.GrazieActivationPage$lambda$4(this.$username$delegate, (it != null && it.getUser() != null) ? it.getUser().getPresentableName() : null); return Unit.INSTANCE; }  throw new IllegalStateException("call to 'resume' before 'invoke' with coroutine"); } public final Continuation<Unit> create(Object value, Continuation<? super null> $completion) { Function2<JbaAuthData, Continuation<? super Unit>, Object> function2 = new Function2<>(this.$username$delegate, $completion); function2.L$0 = value; return (Continuation)function2; } public final Object invoke(JbaAuthData p1, Continuation<?> p2) { return ((null)create(p1, p2)).invokeSuspend(Unit.INSTANCE); } }(Continuation)this) == object) return object;  FlowKt.collectLatest(JunieJbaUserRepository.Companion.syncInstance().getAuthDataFlow(), new Function2<JbaAuthData, Continuation<? super Unit>, Object>(this.$username$delegate, null) { int label; public final Object invokeSuspend(Object $result) { JbaAuthData it; IntrinsicsKt.getCOROUTINE_SUSPENDED(); switch (this.label) { case 0: ResultKt.throwOnFailure(SYNTHETIC_LOCAL_VARIABLE_1); it = (JbaAuthData)this.L$0; it.getUser(); GrazieActivationPageKt.GrazieActivationPage$lambda$4(this.$username$delegate, (it != null && it.getUser() != null) ? it.getUser().getPresentableName() : null); return Unit.INSTANCE; }  throw new IllegalStateException("call to 'resume' before 'invoke' with coroutine"); } public final Continuation<Unit> create(Object value, Continuation<? super null> $completion) { Function2<JbaAuthData, Continuation<? super Unit>, Object> function2 = new Function2<>(this.$username$delegate, $completion); function2.L$0 = value; return (Continuation)function2; } public final Object invoke(JbaAuthData p1, Continuation<?> p2) { return ((null)create(p1, p2)).invokeSuspend(Unit.INSTANCE); } }(Continuation)this); return Unit.INSTANCE;case 1: ResultKt.throwOnFailure(SYNTHETIC_LOCAL_VARIABLE_1); return Unit.INSTANCE; }  throw new IllegalStateException("call to 'resume' before 'invoke' with coroutine"); } public final Continuation<Unit> create(Object value, Continuation<? super GrazieActivationPageKt$GrazieActivationPage$1$1> $completion) { return (Continuation<Unit>)new GrazieActivationPageKt$GrazieActivationPage$1$1(this.$username$delegate, $completion); } public final Object invoke(CoroutineScope p1, Continuation<?> p2) { return ((GrazieActivationPageKt$GrazieActivationPage$1$1)create(p1, p2)).invokeSuspend(Unit.INSTANCE); } } private static final void GrazieActivationPage$lambda$4(MutableState $username$delegate, String <set-?>) { MutableState mutableState = $username$delegate; Object object = null; KProperty property$iv = null; int $i$f$setValue = 0; mutableState.setValue(<set-?>); } private static final GrazieActivationState GrazieActivationPage$lambda$6(State $uiState$delegate) { State state = $uiState$delegate; Object object = null; KProperty property$iv = null;
/*     */     int $i$f$getValue = 0;
/* 515 */     return (GrazieActivationState)state.getValue(); } @Composable @ComposableTarget(applier = "androidx.compose.ui.UiComposable") private static final void GrazieActivationPageDebugMockControls-RPmYEkk(GrazieActivationPageVm model, long backgroundColor, Composer $composer, int $changed) { // Byte code:
/*     */     //   0: aload_3
/*     */     //   1: ldc_w 1014103518
/*     */     //   4: invokeinterface startRestartGroup : (I)Landroidx/compose/runtime/Composer;
/*     */     //   9: astore_3
/*     */     //   10: iload #4
/*     */     //   12: istore #5
/*     */     //   14: iload #4
/*     */     //   16: bipush #6
/*     */     //   18: iand
/*     */     //   19: ifne -> 42
/*     */     //   22: iload #5
/*     */     //   24: aload_3
/*     */     //   25: aload_0
/*     */     //   26: invokeinterface changedInstance : (Ljava/lang/Object;)Z
/*     */     //   31: ifeq -> 38
/*     */     //   34: iconst_4
/*     */     //   35: goto -> 39
/*     */     //   38: iconst_2
/*     */     //   39: ior
/*     */     //   40: istore #5
/*     */     //   42: iload #4
/*     */     //   44: bipush #48
/*     */     //   46: iand
/*     */     //   47: ifne -> 72
/*     */     //   50: iload #5
/*     */     //   52: aload_3
/*     */     //   53: lload_1
/*     */     //   54: invokeinterface changed : (J)Z
/*     */     //   59: ifeq -> 67
/*     */     //   62: bipush #32
/*     */     //   64: goto -> 69
/*     */     //   67: bipush #16
/*     */     //   69: ior
/*     */     //   70: istore #5
/*     */     //   72: iload #5
/*     */     //   74: bipush #19
/*     */     //   76: iand
/*     */     //   77: bipush #18
/*     */     //   79: if_icmpne -> 91
/*     */     //   82: aload_3
/*     */     //   83: invokeinterface getSkipping : ()Z
/*     */     //   88: ifne -> 1327
/*     */     //   91: invokestatic isTraceInProgress : ()Z
/*     */     //   94: ifeq -> 109
/*     */     //   97: ldc_w 1014103518
/*     */     //   100: iload #5
/*     */     //   102: iconst_m1
/*     */     //   103: ldc_w 'com.intellij.ml.llm.matterhorn.ej.ui.login.GrazieActivationPageDebugMockControls (GrazieActivationPage.kt:78)'
/*     */     //   106: invokestatic traceEventStart : (IIILjava/lang/String;)V
/*     */     //   109: aload_0
/*     */     //   110: invokevirtual getLoginVm : ()Lcom/intellij/ml/llm/matterhorn/ej/ui/login/GrazieActivationVm;
/*     */     //   113: invokevirtual getDebugMock : ()Lkotlinx/coroutines/flow/StateFlow;
/*     */     //   116: aconst_null
/*     */     //   117: aload_3
/*     */     //   118: iconst_0
/*     */     //   119: iconst_1
/*     */     //   120: invokestatic collectAsState : (Lkotlinx/coroutines/flow/StateFlow;Lkotlin/coroutines/CoroutineContext;Landroidx/compose/runtime/Composer;II)Landroidx/compose/runtime/State;
/*     */     //   123: astore #6
/*     */     //   125: aload #6
/*     */     //   127: invokestatic GrazieActivationPageDebugMockControls_RPmYEkk$lambda$10 : (Landroidx/compose/runtime/State;)Lkotlin/Pair;
/*     */     //   130: ifnull -> 1315
/*     */     //   133: getstatic androidx/compose/ui/Alignment.Companion : Landroidx/compose/ui/Alignment$Companion;
/*     */     //   136: invokevirtual getCenterVertically : ()Landroidx/compose/ui/Alignment$Vertical;
/*     */     //   139: astore #7
/*     */     //   141: getstatic androidx/compose/foundation/layout/Arrangement.INSTANCE : Landroidx/compose/foundation/layout/Arrangement;
/*     */     //   144: invokevirtual getSpaceBetween : ()Landroidx/compose/foundation/layout/Arrangement$HorizontalOrVertical;
/*     */     //   147: astore #8
/*     */     //   149: getstatic androidx/compose/ui/Modifier.Companion : Landroidx/compose/ui/Modifier$Companion;
/*     */     //   152: checkcast androidx/compose/ui/Modifier
/*     */     //   155: fconst_0
/*     */     //   156: iconst_1
/*     */     //   157: aconst_null
/*     */     //   158: invokestatic fillMaxWidth$default : (Landroidx/compose/ui/Modifier;FILjava/lang/Object;)Landroidx/compose/ui/Modifier;
/*     */     //   161: bipush #16
/*     */     //   163: istore #10
/*     */     //   165: iconst_0
/*     */     //   166: istore #11
/*     */     //   168: iload #10
/*     */     //   170: i2f
/*     */     //   171: invokestatic constructor-impl : (F)F
/*     */     //   174: bipush #8
/*     */     //   176: istore #10
/*     */     //   178: iconst_0
/*     */     //   179: istore #11
/*     */     //   181: iload #10
/*     */     //   183: i2f
/*     */     //   184: invokestatic constructor-impl : (F)F
/*     */     //   187: invokestatic padding-VpY3zN4 : (Landroidx/compose/ui/Modifier;FF)Landroidx/compose/ui/Modifier;
/*     */     //   190: lload_1
/*     */     //   191: aconst_null
/*     */     //   192: iconst_2
/*     */     //   193: aconst_null
/*     */     //   194: invokestatic background-bw27NRU$default : (Landroidx/compose/ui/Modifier;JLandroidx/compose/ui/graphics/Shape;ILjava/lang/Object;)Landroidx/compose/ui/Modifier;
/*     */     //   197: astore #9
/*     */     //   199: sipush #432
/*     */     //   202: istore #10
/*     */     //   204: nop
/*     */     //   205: iconst_0
/*     */     //   206: istore #11
/*     */     //   208: aload_3
/*     */     //   209: ldc_w 693286680
/*     */     //   212: ldc_w 'CC(Row)P(2,1,3)99@5018L58,100@5081L130:Row.kt#2w3rfo'
/*     */     //   215: invokestatic sourceInformationMarkerStart : (Landroidx/compose/runtime/Composer;ILjava/lang/String;)V
/*     */     //   218: aload #8
/*     */     //   220: checkcast androidx/compose/foundation/layout/Arrangement$Horizontal
/*     */     //   223: aload #7
/*     */     //   225: aload_3
/*     */     //   226: bipush #14
/*     */     //   228: iload #10
/*     */     //   230: iconst_3
/*     */     //   231: ishr
/*     */     //   232: iand
/*     */     //   233: bipush #112
/*     */     //   235: iload #10
/*     */     //   237: iconst_3
/*     */     //   238: ishr
/*     */     //   239: iand
/*     */     //   240: ior
/*     */     //   241: invokestatic rowMeasurePolicy : (Landroidx/compose/foundation/layout/Arrangement$Horizontal;Landroidx/compose/ui/Alignment$Vertical;Landroidx/compose/runtime/Composer;I)Landroidx/compose/ui/layout/MeasurePolicy;
/*     */     //   244: astore #12
/*     */     //   246: bipush #112
/*     */     //   248: iload #10
/*     */     //   250: iconst_3
/*     */     //   251: ishl
/*     */     //   252: iand
/*     */     //   253: istore #13
/*     */     //   255: nop
/*     */     //   256: iconst_0
/*     */     //   257: istore #14
/*     */     //   259: aload_3
/*     */     //   260: ldc -1323940314
/*     */     //   262: ldc 'CC(Layout)P(!1,2)79@3208L23,82@3359L411:Layout.kt#80mrfh'
/*     */     //   264: invokestatic sourceInformationMarkerStart : (Landroidx/compose/runtime/Composer;ILjava/lang/String;)V
/*     */     //   267: aload_3
/*     */     //   268: iconst_0
/*     */     //   269: invokestatic getCurrentCompositeKeyHash : (Landroidx/compose/runtime/Composer;I)I
/*     */     //   272: istore #15
/*     */     //   274: aload_3
/*     */     //   275: invokeinterface getCurrentCompositionLocalMap : ()Landroidx/compose/runtime/CompositionLocalMap;
/*     */     //   280: astore #16
/*     */     //   282: aload_3
/*     */     //   283: aload #9
/*     */     //   285: invokestatic materializeModifier : (Landroidx/compose/runtime/Composer;Landroidx/compose/ui/Modifier;)Landroidx/compose/ui/Modifier;
/*     */     //   288: astore #17
/*     */     //   290: getstatic androidx/compose/ui/node/ComposeUiNode.Companion : Landroidx/compose/ui/node/ComposeUiNode$Companion;
/*     */     //   293: invokevirtual getConstructor : ()Lkotlin/jvm/functions/Function0;
/*     */     //   296: astore #18
/*     */     //   298: bipush #6
/*     */     //   300: sipush #896
/*     */     //   303: iload #13
/*     */     //   305: bipush #6
/*     */     //   307: ishl
/*     */     //   308: iand
/*     */     //   309: ior
/*     */     //   310: istore #19
/*     */     //   312: nop
/*     */     //   313: iconst_0
/*     */     //   314: istore #20
/*     */     //   316: aload_3
/*     */     //   317: ldc -692256719
/*     */     //   319: ldc 'CC(ReusableComposeNode)P(1,2)376@14062L9:Composables.kt#9igjgp'
/*     */     //   321: invokestatic sourceInformationMarkerStart : (Landroidx/compose/runtime/Composer;ILjava/lang/String;)V
/*     */     //   324: aload_3
/*     */     //   325: invokeinterface getApplier : ()Landroidx/compose/runtime/Applier;
/*     */     //   330: instanceof androidx/compose/runtime/Applier
/*     */     //   333: ifne -> 339
/*     */     //   336: invokestatic invalidApplier : ()V
/*     */     //   339: aload_3
/*     */     //   340: invokeinterface startReusableNode : ()V
/*     */     //   345: aload_3
/*     */     //   346: invokeinterface getInserting : ()Z
/*     */     //   351: ifeq -> 365
/*     */     //   354: aload_3
/*     */     //   355: aload #18
/*     */     //   357: invokeinterface createNode : (Lkotlin/jvm/functions/Function0;)V
/*     */     //   362: goto -> 371
/*     */     //   365: aload_3
/*     */     //   366: invokeinterface useNode : ()V
/*     */     //   371: aload_3
/*     */     //   372: invokestatic constructor-impl : (Landroidx/compose/runtime/Composer;)Landroidx/compose/runtime/Composer;
/*     */     //   375: astore #21
/*     */     //   377: iconst_0
/*     */     //   378: istore #22
/*     */     //   380: aload #21
/*     */     //   382: aload #12
/*     */     //   384: getstatic androidx/compose/ui/node/ComposeUiNode.Companion : Landroidx/compose/ui/node/ComposeUiNode$Companion;
/*     */     //   387: invokevirtual getSetMeasurePolicy : ()Lkotlin/jvm/functions/Function2;
/*     */     //   390: invokestatic set-impl : (Landroidx/compose/runtime/Composer;Ljava/lang/Object;Lkotlin/jvm/functions/Function2;)V
/*     */     //   393: aload #21
/*     */     //   395: aload #16
/*     */     //   397: getstatic androidx/compose/ui/node/ComposeUiNode.Companion : Landroidx/compose/ui/node/ComposeUiNode$Companion;
/*     */     //   400: invokevirtual getSetResolvedCompositionLocals : ()Lkotlin/jvm/functions/Function2;
/*     */     //   403: invokestatic set-impl : (Landroidx/compose/runtime/Composer;Ljava/lang/Object;Lkotlin/jvm/functions/Function2;)V
/*     */     //   406: getstatic androidx/compose/ui/node/ComposeUiNode.Companion : Landroidx/compose/ui/node/ComposeUiNode$Companion;
/*     */     //   409: invokevirtual getSetCompositeKeyHash : ()Lkotlin/jvm/functions/Function2;
/*     */     //   412: astore #23
/*     */     //   414: iconst_0
/*     */     //   415: istore #24
/*     */     //   417: aload #21
/*     */     //   419: astore #25
/*     */     //   421: iconst_0
/*     */     //   422: istore #26
/*     */     //   424: aload #25
/*     */     //   426: invokeinterface getInserting : ()Z
/*     */     //   431: ifne -> 452
/*     */     //   434: aload #25
/*     */     //   436: invokeinterface rememberedValue : ()Ljava/lang/Object;
/*     */     //   441: iload #15
/*     */     //   443: invokestatic valueOf : (I)Ljava/lang/Integer;
/*     */     //   446: invokestatic areEqual : (Ljava/lang/Object;Ljava/lang/Object;)Z
/*     */     //   449: ifne -> 478
/*     */     //   452: aload #25
/*     */     //   454: iload #15
/*     */     //   456: invokestatic valueOf : (I)Ljava/lang/Integer;
/*     */     //   459: invokeinterface updateRememberedValue : (Ljava/lang/Object;)V
/*     */     //   464: aload #21
/*     */     //   466: iload #15
/*     */     //   468: invokestatic valueOf : (I)Ljava/lang/Integer;
/*     */     //   471: aload #23
/*     */     //   473: invokeinterface apply : (Ljava/lang/Object;Lkotlin/jvm/functions/Function2;)V
/*     */     //   478: nop
/*     */     //   479: nop
/*     */     //   480: nop
/*     */     //   481: aload #21
/*     */     //   483: aload #17
/*     */     //   485: getstatic androidx/compose/ui/node/ComposeUiNode.Companion : Landroidx/compose/ui/node/ComposeUiNode$Companion;
/*     */     //   488: invokevirtual getSetModifier : ()Lkotlin/jvm/functions/Function2;
/*     */     //   491: invokestatic set-impl : (Landroidx/compose/runtime/Composer;Ljava/lang/Object;Lkotlin/jvm/functions/Function2;)V
/*     */     //   494: nop
/*     */     //   495: nop
/*     */     //   496: aload_3
/*     */     //   497: bipush #14
/*     */     //   499: iload #19
/*     */     //   501: bipush #6
/*     */     //   503: ishr
/*     */     //   504: iand
/*     */     //   505: istore #27
/*     */     //   507: astore #28
/*     */     //   509: iconst_0
/*     */     //   510: istore #29
/*     */     //   512: aload #28
/*     */     //   514: ldc_w -407840262
/*     */     //   517: ldc_w 'C101@5126L9:Row.kt#2w3rfo'
/*     */     //   520: invokestatic sourceInformationMarkerStart : (Landroidx/compose/runtime/Composer;ILjava/lang/String;)V
/*     */     //   523: getstatic androidx/compose/foundation/layout/RowScopeInstance.INSTANCE : Landroidx/compose/foundation/layout/RowScopeInstance;
/*     */     //   526: aload #28
/*     */     //   528: bipush #6
/*     */     //   530: bipush #112
/*     */     //   532: iload #10
/*     */     //   534: bipush #6
/*     */     //   536: ishr
/*     */     //   537: iand
/*     */     //   538: ior
/*     */     //   539: istore #30
/*     */     //   541: astore #31
/*     */     //   543: checkcast androidx/compose/foundation/layout/RowScope
/*     */     //   546: astore #32
/*     */     //   548: iconst_0
/*     */     //   549: istore #33
/*     */     //   551: ldc_w 'Back'
/*     */     //   554: aconst_null
/*     */     //   555: iconst_0
/*     */     //   556: aload #31
/*     */     //   558: ldc_w 1351916940
/*     */     //   561: invokeinterface startReplaceGroup : (I)V
/*     */     //   566: aload #31
/*     */     //   568: astore #34
/*     */     //   570: aload_3
/*     */     //   571: aload_0
/*     */     //   572: invokeinterface changedInstance : (Ljava/lang/Object;)Z
/*     */     //   577: istore #35
/*     */     //   579: nop
/*     */     //   580: iconst_0
/*     */     //   581: istore #36
/*     */     //   583: aload #34
/*     */     //   585: invokeinterface rememberedValue : ()Ljava/lang/Object;
/*     */     //   590: astore #37
/*     */     //   592: iconst_0
/*     */     //   593: istore #38
/*     */     //   595: iload #35
/*     */     //   597: ifne -> 611
/*     */     //   600: aload #37
/*     */     //   602: getstatic androidx/compose/runtime/Composer.Companion : Landroidx/compose/runtime/Composer$Companion;
/*     */     //   605: invokevirtual getEmpty : ()Ljava/lang/Object;
/*     */     //   608: if_acmpne -> 652
/*     */     //   611: istore #39
/*     */     //   613: astore #40
/*     */     //   615: astore #41
/*     */     //   617: iconst_0
/*     */     //   618: istore #42
/*     */     //   620: aload_0
/*     */     //   621: <illegal opcode> invoke : (Lcom/intellij/ml/llm/matterhorn/ej/ui/login/GrazieActivationPageVm;)Lkotlin/jvm/functions/Function0;
/*     */     //   626: astore #43
/*     */     //   628: aload #41
/*     */     //   630: aload #40
/*     */     //   632: iload #39
/*     */     //   634: aload #43
/*     */     //   636: astore #44
/*     */     //   638: aload #34
/*     */     //   640: aload #44
/*     */     //   642: invokeinterface updateRememberedValue : (Ljava/lang/Object;)V
/*     */     //   647: aload #44
/*     */     //   649: goto -> 654
/*     */     //   652: aload #37
/*     */     //   654: nop
/*     */     //   655: nop
/*     */     //   656: nop
/*     */     //   657: checkcast kotlin/jvm/functions/Function0
/*     */     //   660: astore #45
/*     */     //   662: aload #31
/*     */     //   664: invokeinterface endReplaceGroup : ()V
/*     */     //   669: aload #45
/*     */     //   671: aconst_null
/*     */     //   672: aload #31
/*     */     //   674: bipush #6
/*     */     //   676: bipush #22
/*     */     //   678: invokestatic Button : (Ljava/lang/String;Landroidx/compose/ui/Modifier;ZLkotlin/jvm/functions/Function0;Lkotlin/jvm/functions/Function3;Landroidx/compose/runtime/Composer;II)V
/*     */     //   681: getstatic androidx/compose/ui/Alignment.Companion : Landroidx/compose/ui/Alignment$Companion;
/*     */     //   684: invokevirtual getCenterHorizontally : ()Landroidx/compose/ui/Alignment$Horizontal;
/*     */     //   687: astore #45
/*     */     //   689: getstatic androidx/compose/ui/Modifier.Companion : Landroidx/compose/ui/Modifier$Companion;
/*     */     //   692: checkcast androidx/compose/ui/Modifier
/*     */     //   695: bipush #8
/*     */     //   697: istore #35
/*     */     //   699: iconst_0
/*     */     //   700: istore #36
/*     */     //   702: iload #35
/*     */     //   704: i2f
/*     */     //   705: invokestatic constructor-impl : (F)F
/*     */     //   708: fconst_0
/*     */     //   709: iconst_2
/*     */     //   710: aconst_null
/*     */     //   711: invokestatic padding-VpY3zN4$default : (Landroidx/compose/ui/Modifier;FFILjava/lang/Object;)Landroidx/compose/ui/Modifier;
/*     */     //   714: astore #34
/*     */     //   716: sipush #390
/*     */     //   719: istore #36
/*     */     //   721: nop
/*     */     //   722: iconst_0
/*     */     //   723: istore #37
/*     */     //   725: aload #31
/*     */     //   727: ldc -483455358
/*     */     //   729: ldc 'CC(Column)P(2,3,1)86@4330L61,87@4396L133:Column.kt#2w3rfo'
/*     */     //   731: invokestatic sourceInformationMarkerStart : (Landroidx/compose/runtime/Composer;ILjava/lang/String;)V
/*     */     //   734: getstatic androidx/compose/foundation/layout/Arrangement.INSTANCE : Landroidx/compose/foundation/layout/Arrangement;
/*     */     //   737: invokevirtual getTop : ()Landroidx/compose/foundation/layout/Arrangement$Vertical;
/*     */     //   740: astore #35
/*     */     //   742: aload #35
/*     */     //   744: aload #45
/*     */     //   746: aload #31
/*     */     //   748: bipush #14
/*     */     //   750: iload #36
/*     */     //   752: iconst_3
/*     */     //   753: ishr
/*     */     //   754: iand
/*     */     //   755: bipush #112
/*     */     //   757: iload #36
/*     */     //   759: iconst_3
/*     */     //   760: ishr
/*     */     //   761: iand
/*     */     //   762: ior
/*     */     //   763: invokestatic columnMeasurePolicy : (Landroidx/compose/foundation/layout/Arrangement$Vertical;Landroidx/compose/ui/Alignment$Horizontal;Landroidx/compose/runtime/Composer;I)Landroidx/compose/ui/layout/MeasurePolicy;
/*     */     //   766: astore #38
/*     */     //   768: bipush #112
/*     */     //   770: iload #36
/*     */     //   772: iconst_3
/*     */     //   773: ishl
/*     */     //   774: iand
/*     */     //   775: istore #42
/*     */     //   777: nop
/*     */     //   778: iconst_0
/*     */     //   779: istore #44
/*     */     //   781: aload #31
/*     */     //   783: ldc -1323940314
/*     */     //   785: ldc 'CC(Layout)P(!1,2)79@3208L23,82@3359L411:Layout.kt#80mrfh'
/*     */     //   787: invokestatic sourceInformationMarkerStart : (Landroidx/compose/runtime/Composer;ILjava/lang/String;)V
/*     */     //   790: aload #31
/*     */     //   792: iconst_0
/*     */     //   793: invokestatic getCurrentCompositeKeyHash : (Landroidx/compose/runtime/Composer;I)I
/*     */     //   796: istore #46
/*     */     //   798: aload #31
/*     */     //   800: invokeinterface getCurrentCompositionLocalMap : ()Landroidx/compose/runtime/CompositionLocalMap;
/*     */     //   805: astore #47
/*     */     //   807: aload #31
/*     */     //   809: aload #34
/*     */     //   811: invokestatic materializeModifier : (Landroidx/compose/runtime/Composer;Landroidx/compose/ui/Modifier;)Landroidx/compose/ui/Modifier;
/*     */     //   814: astore #48
/*     */     //   816: getstatic androidx/compose/ui/node/ComposeUiNode.Companion : Landroidx/compose/ui/node/ComposeUiNode$Companion;
/*     */     //   819: invokevirtual getConstructor : ()Lkotlin/jvm/functions/Function0;
/*     */     //   822: astore #49
/*     */     //   824: bipush #6
/*     */     //   826: sipush #896
/*     */     //   829: iload #42
/*     */     //   831: bipush #6
/*     */     //   833: ishl
/*     */     //   834: iand
/*     */     //   835: ior
/*     */     //   836: istore #50
/*     */     //   838: nop
/*     */     //   839: iconst_0
/*     */     //   840: istore #51
/*     */     //   842: aload #31
/*     */     //   844: ldc -692256719
/*     */     //   846: ldc 'CC(ReusableComposeNode)P(1,2)376@14062L9:Composables.kt#9igjgp'
/*     */     //   848: invokestatic sourceInformationMarkerStart : (Landroidx/compose/runtime/Composer;ILjava/lang/String;)V
/*     */     //   851: aload #31
/*     */     //   853: invokeinterface getApplier : ()Landroidx/compose/runtime/Applier;
/*     */     //   858: instanceof androidx/compose/runtime/Applier
/*     */     //   861: ifne -> 867
/*     */     //   864: invokestatic invalidApplier : ()V
/*     */     //   867: aload #31
/*     */     //   869: invokeinterface startReusableNode : ()V
/*     */     //   874: aload #31
/*     */     //   876: invokeinterface getInserting : ()Z
/*     */     //   881: ifeq -> 896
/*     */     //   884: aload #31
/*     */     //   886: aload #49
/*     */     //   888: invokeinterface createNode : (Lkotlin/jvm/functions/Function0;)V
/*     */     //   893: goto -> 903
/*     */     //   896: aload #31
/*     */     //   898: invokeinterface useNode : ()V
/*     */     //   903: aload #31
/*     */     //   905: invokestatic constructor-impl : (Landroidx/compose/runtime/Composer;)Landroidx/compose/runtime/Composer;
/*     */     //   908: astore #52
/*     */     //   910: iconst_0
/*     */     //   911: istore #53
/*     */     //   913: aload #52
/*     */     //   915: aload #38
/*     */     //   917: getstatic androidx/compose/ui/node/ComposeUiNode.Companion : Landroidx/compose/ui/node/ComposeUiNode$Companion;
/*     */     //   920: invokevirtual getSetMeasurePolicy : ()Lkotlin/jvm/functions/Function2;
/*     */     //   923: invokestatic set-impl : (Landroidx/compose/runtime/Composer;Ljava/lang/Object;Lkotlin/jvm/functions/Function2;)V
/*     */     //   926: aload #52
/*     */     //   928: aload #47
/*     */     //   930: getstatic androidx/compose/ui/node/ComposeUiNode.Companion : Landroidx/compose/ui/node/ComposeUiNode$Companion;
/*     */     //   933: invokevirtual getSetResolvedCompositionLocals : ()Lkotlin/jvm/functions/Function2;
/*     */     //   936: invokestatic set-impl : (Landroidx/compose/runtime/Composer;Ljava/lang/Object;Lkotlin/jvm/functions/Function2;)V
/*     */     //   939: getstatic androidx/compose/ui/node/ComposeUiNode.Companion : Landroidx/compose/ui/node/ComposeUiNode$Companion;
/*     */     //   942: invokevirtual getSetCompositeKeyHash : ()Lkotlin/jvm/functions/Function2;
/*     */     //   945: astore #54
/*     */     //   947: iconst_0
/*     */     //   948: istore #55
/*     */     //   950: aload #52
/*     */     //   952: astore #56
/*     */     //   954: iconst_0
/*     */     //   955: istore #57
/*     */     //   957: aload #56
/*     */     //   959: invokeinterface getInserting : ()Z
/*     */     //   964: ifne -> 985
/*     */     //   967: aload #56
/*     */     //   969: invokeinterface rememberedValue : ()Ljava/lang/Object;
/*     */     //   974: iload #46
/*     */     //   976: invokestatic valueOf : (I)Ljava/lang/Integer;
/*     */     //   979: invokestatic areEqual : (Ljava/lang/Object;Ljava/lang/Object;)Z
/*     */     //   982: ifne -> 1011
/*     */     //   985: aload #56
/*     */     //   987: iload #46
/*     */     //   989: invokestatic valueOf : (I)Ljava/lang/Integer;
/*     */     //   992: invokeinterface updateRememberedValue : (Ljava/lang/Object;)V
/*     */     //   997: aload #52
/*     */     //   999: iload #46
/*     */     //   1001: invokestatic valueOf : (I)Ljava/lang/Integer;
/*     */     //   1004: aload #54
/*     */     //   1006: invokeinterface apply : (Ljava/lang/Object;Lkotlin/jvm/functions/Function2;)V
/*     */     //   1011: nop
/*     */     //   1012: nop
/*     */     //   1013: nop
/*     */     //   1014: aload #52
/*     */     //   1016: aload #48
/*     */     //   1018: getstatic androidx/compose/ui/node/ComposeUiNode.Companion : Landroidx/compose/ui/node/ComposeUiNode$Companion;
/*     */     //   1021: invokevirtual getSetModifier : ()Lkotlin/jvm/functions/Function2;
/*     */     //   1024: invokestatic set-impl : (Landroidx/compose/runtime/Composer;Ljava/lang/Object;Lkotlin/jvm/functions/Function2;)V
/*     */     //   1027: nop
/*     */     //   1028: nop
/*     */     //   1029: aload #31
/*     */     //   1031: bipush #14
/*     */     //   1033: iload #50
/*     */     //   1035: bipush #6
/*     */     //   1037: ishr
/*     */     //   1038: iand
/*     */     //   1039: istore #58
/*     */     //   1041: astore #59
/*     */     //   1043: iconst_0
/*     */     //   1044: istore #60
/*     */     //   1046: aload #59
/*     */     //   1048: ldc_w -384784025
/*     */     //   1051: ldc_w 'C88@4444L9:Column.kt#2w3rfo'
/*     */     //   1054: invokestatic sourceInformationMarkerStart : (Landroidx/compose/runtime/Composer;ILjava/lang/String;)V
/*     */     //   1057: getstatic androidx/compose/foundation/layout/ColumnScopeInstance.INSTANCE : Landroidx/compose/foundation/layout/ColumnScopeInstance;
/*     */     //   1060: aload #59
/*     */     //   1062: bipush #6
/*     */     //   1064: bipush #112
/*     */     //   1066: iload #36
/*     */     //   1068: bipush #6
/*     */     //   1070: ishr
/*     */     //   1071: iand
/*     */     //   1072: ior
/*     */     //   1073: istore #61
/*     */     //   1075: astore #62
/*     */     //   1077: checkcast androidx/compose/foundation/layout/ColumnScope
/*     */     //   1080: astore #63
/*     */     //   1082: iconst_0
/*     */     //   1083: istore #64
/*     */     //   1085: aload #6
/*     */     //   1087: invokestatic GrazieActivationPageDebugMockControls_RPmYEkk$lambda$10 : (Landroidx/compose/runtime/State;)Lkotlin/Pair;
/*     */     //   1090: dup
/*     */     //   1091: invokestatic checkNotNull : (Ljava/lang/Object;)V
/*     */     //   1094: invokevirtual getFirst : ()Ljava/lang/Object;
/*     */     //   1097: checkcast java/lang/String
/*     */     //   1100: aconst_null
/*     */     //   1101: lconst_0
/*     */     //   1102: lconst_0
/*     */     //   1103: aconst_null
/*     */     //   1104: aconst_null
/*     */     //   1105: aconst_null
/*     */     //   1106: lconst_0
/*     */     //   1107: aconst_null
/*     */     //   1108: iconst_0
/*     */     //   1109: lconst_0
/*     */     //   1110: iconst_0
/*     */     //   1111: iconst_0
/*     */     //   1112: iconst_1
/*     */     //   1113: aconst_null
/*     */     //   1114: aconst_null
/*     */     //   1115: aload #62
/*     */     //   1117: iconst_0
/*     */     //   1118: sipush #3072
/*     */     //   1121: ldc_w 57342
/*     */     //   1124: invokestatic Text-bAzTDeA : (Ljava/lang/String;Landroidx/compose/ui/Modifier;JJLandroidx/compose/ui/text/font/FontStyle;Landroidx/compose/ui/text/font/FontWeight;Landroidx/compose/ui/text/font/FontFamily;JLandroidx/compose/ui/text/style/TextDecoration;IJIZILkotlin/jvm/functions/Function1;Landroidx/compose/ui/text/TextStyle;Landroidx/compose/runtime/Composer;III)V
/*     */     //   1127: nop
/*     */     //   1128: aload #59
/*     */     //   1130: invokestatic sourceInformationMarkerEnd : (Landroidx/compose/runtime/Composer;)V
/*     */     //   1133: aload #31
/*     */     //   1135: invokeinterface endNode : ()V
/*     */     //   1140: aload #31
/*     */     //   1142: invokestatic sourceInformationMarkerEnd : (Landroidx/compose/runtime/Composer;)V
/*     */     //   1145: nop
/*     */     //   1146: aload #31
/*     */     //   1148: invokestatic sourceInformationMarkerEnd : (Landroidx/compose/runtime/Composer;)V
/*     */     //   1151: nop
/*     */     //   1152: aload #31
/*     */     //   1154: invokestatic sourceInformationMarkerEnd : (Landroidx/compose/runtime/Composer;)V
/*     */     //   1157: nop
/*     */     //   1158: ldc_w 'Next'
/*     */     //   1161: aconst_null
/*     */     //   1162: iconst_0
/*     */     //   1163: aload #31
/*     */     //   1165: ldc_w 1351929612
/*     */     //   1168: invokeinterface startReplaceGroup : (I)V
/*     */     //   1173: aload #31
/*     */     //   1175: astore #34
/*     */     //   1177: aload_3
/*     */     //   1178: aload_0
/*     */     //   1179: invokeinterface changedInstance : (Ljava/lang/Object;)Z
/*     */     //   1184: istore #35
/*     */     //   1186: nop
/*     */     //   1187: iconst_0
/*     */     //   1188: istore #36
/*     */     //   1190: aload #34
/*     */     //   1192: invokeinterface rememberedValue : ()Ljava/lang/Object;
/*     */     //   1197: astore #37
/*     */     //   1199: iconst_0
/*     */     //   1200: istore #38
/*     */     //   1202: iload #35
/*     */     //   1204: ifne -> 1218
/*     */     //   1207: aload #37
/*     */     //   1209: getstatic androidx/compose/runtime/Composer.Companion : Landroidx/compose/runtime/Composer$Companion;
/*     */     //   1212: invokevirtual getEmpty : ()Ljava/lang/Object;
/*     */     //   1215: if_acmpne -> 1259
/*     */     //   1218: istore #39
/*     */     //   1220: astore #40
/*     */     //   1222: astore #41
/*     */     //   1224: iconst_0
/*     */     //   1225: istore #42
/*     */     //   1227: aload_0
/*     */     //   1228: <illegal opcode> invoke : (Lcom/intellij/ml/llm/matterhorn/ej/ui/login/GrazieActivationPageVm;)Lkotlin/jvm/functions/Function0;
/*     */     //   1233: astore #43
/*     */     //   1235: aload #41
/*     */     //   1237: aload #40
/*     */     //   1239: iload #39
/*     */     //   1241: aload #43
/*     */     //   1243: astore #44
/*     */     //   1245: aload #34
/*     */     //   1247: aload #44
/*     */     //   1249: invokeinterface updateRememberedValue : (Ljava/lang/Object;)V
/*     */     //   1254: aload #44
/*     */     //   1256: goto -> 1261
/*     */     //   1259: aload #37
/*     */     //   1261: nop
/*     */     //   1262: nop
/*     */     //   1263: nop
/*     */     //   1264: checkcast kotlin/jvm/functions/Function0
/*     */     //   1267: astore #45
/*     */     //   1269: aload #31
/*     */     //   1271: invokeinterface endReplaceGroup : ()V
/*     */     //   1276: aload #45
/*     */     //   1278: aconst_null
/*     */     //   1279: aload #31
/*     */     //   1281: bipush #6
/*     */     //   1283: bipush #22
/*     */     //   1285: invokestatic Button : (Ljava/lang/String;Landroidx/compose/ui/Modifier;ZLkotlin/jvm/functions/Function0;Lkotlin/jvm/functions/Function3;Landroidx/compose/runtime/Composer;II)V
/*     */     //   1288: nop
/*     */     //   1289: aload #28
/*     */     //   1291: invokestatic sourceInformationMarkerEnd : (Landroidx/compose/runtime/Composer;)V
/*     */     //   1294: aload_3
/*     */     //   1295: invokeinterface endNode : ()V
/*     */     //   1300: aload_3
/*     */     //   1301: invokestatic sourceInformationMarkerEnd : (Landroidx/compose/runtime/Composer;)V
/*     */     //   1304: nop
/*     */     //   1305: aload_3
/*     */     //   1306: invokestatic sourceInformationMarkerEnd : (Landroidx/compose/runtime/Composer;)V
/*     */     //   1309: nop
/*     */     //   1310: aload_3
/*     */     //   1311: invokestatic sourceInformationMarkerEnd : (Landroidx/compose/runtime/Composer;)V
/*     */     //   1314: nop
/*     */     //   1315: invokestatic isTraceInProgress : ()Z
/*     */     //   1318: ifeq -> 1333
/*     */     //   1321: invokestatic traceEventEnd : ()V
/*     */     //   1324: goto -> 1333
/*     */     //   1327: aload_3
/*     */     //   1328: invokeinterface skipToGroupEnd : ()V
/*     */     //   1333: aload_3
/*     */     //   1334: invokeinterface endRestartGroup : ()Landroidx/compose/runtime/ScopeUpdateScope;
/*     */     //   1339: dup
/*     */     //   1340: ifnull -> 1360
/*     */     //   1343: aload_0
/*     */     //   1344: lload_1
/*     */     //   1345: iload #4
/*     */     //   1347: <illegal opcode> invoke : (Lcom/intellij/ml/llm/matterhorn/ej/ui/login/GrazieActivationPageVm;JI)Lkotlin/jvm/functions/Function2;
/*     */     //   1352: invokeinterface updateScope : (Lkotlin/jvm/functions/Function2;)V
/*     */     //   1357: goto -> 1361
/*     */     //   1360: pop
/*     */     //   1361: return
/*     */     // Line number table:
/*     */     //   Java source line number -> byte code offset
/*     */     //   #79	-> 0
/*     */     //   #80	-> 109
/*     */     //   #81	-> 125
/*     */     //   #83	-> 133
/*     */     //   #84	-> 141
/*     */     //   #85	-> 149
/*     */     //   #86	-> 155
/*     */     //   #87	-> 161
/*     */     //   #254	-> 168
/*     */     //   #87	-> 174
/*     */     //   #254	-> 181
/*     */     //   #87	-> 187
/*     */     //   #88	-> 190
/*     */     //   #82	-> 204
/*     */     //   #255	-> 215
/*     */     //   #256	-> 218
/*     */     //   #257	-> 255
/*     */     //   #258	-> 264
/*     */     //   #259	-> 269
/*     */     //   #260	-> 275
/*     */     //   #261	-> 283
/*     */     //   #263	-> 290
/*     */     //   #262	-> 312
/*     */     //   #264	-> 321
/*     */     //   #265	-> 324
/*     */     //   #266	-> 340
/*     */     //   #267	-> 345
/*     */     //   #268	-> 355
/*     */     //   #270	-> 366
/*     */     //   #272	-> 371
/*     */     //   #273	-> 380
/*     */     //   #274	-> 393
/*     */     //   #276	-> 406
/*     */     //   #277	-> 417
/*     */     //   #278	-> 424
/*     */     //   #279	-> 452
/*     */     //   #280	-> 464
/*     */     //   #282	-> 478
/*     */     //   #277	-> 479
/*     */     //   #282	-> 480
/*     */     //   #283	-> 481
/*     */     //   #284	-> 494
/*     */     //   #272	-> 495
/*     */     //   #285	-> 496
/*     */     //   #286	-> 520
/*     */     //   #91	-> 551
/*     */     //   #92	-> 579
/*     */     //   #287	-> 583
/*     */     //   #288	-> 595
/*     */     //   #289	-> 611
/*     */     //   #92	-> 620
/*     */     //   #289	-> 636
/*     */     //   #290	-> 638
/*     */     //   #291	-> 647
/*     */     //   #292	-> 652
/*     */     //   #288	-> 654
/*     */     //   #287	-> 655
/*     */     //   #287	-> 656
/*     */     //   #92	-> 657
/*     */     //   #90	-> 678
/*     */     //   #98	-> 681
/*     */     //   #99	-> 689
/*     */     //   #100	-> 695
/*     */     //   #293	-> 702
/*     */     //   #100	-> 708
/*     */     //   #97	-> 721
/*     */     //   #294	-> 731
/*     */     //   #295	-> 734
/*     */     //   #299	-> 742
/*     */     //   #300	-> 777
/*     */     //   #301	-> 787
/*     */     //   #302	-> 793
/*     */     //   #303	-> 800
/*     */     //   #304	-> 809
/*     */     //   #306	-> 816
/*     */     //   #305	-> 838
/*     */     //   #307	-> 848
/*     */     //   #308	-> 851
/*     */     //   #309	-> 869
/*     */     //   #310	-> 874
/*     */     //   #311	-> 886
/*     */     //   #313	-> 898
/*     */     //   #315	-> 903
/*     */     //   #316	-> 913
/*     */     //   #317	-> 926
/*     */     //   #319	-> 939
/*     */     //   #320	-> 950
/*     */     //   #321	-> 957
/*     */     //   #322	-> 985
/*     */     //   #323	-> 997
/*     */     //   #325	-> 1011
/*     */     //   #320	-> 1012
/*     */     //   #325	-> 1013
/*     */     //   #326	-> 1014
/*     */     //   #327	-> 1027
/*     */     //   #315	-> 1028
/*     */     //   #328	-> 1029
/*     */     //   #329	-> 1054
/*     */     //   #103	-> 1085
/*     */     //   #104	-> 1112
/*     */     //   #102	-> 1124
/*     */     //   #106	-> 1127
/*     */     //   #329	-> 1128
/*     */     //   #328	-> 1133
/*     */     //   #330	-> 1135
/*     */     //   #307	-> 1142
/*     */     //   #331	-> 1145
/*     */     //   #301	-> 1148
/*     */     //   #332	-> 1151
/*     */     //   #294	-> 1154
/*     */     //   #333	-> 1157
/*     */     //   #109	-> 1158
/*     */     //   #110	-> 1186
/*     */     //   #334	-> 1190
/*     */     //   #335	-> 1202
/*     */     //   #336	-> 1218
/*     */     //   #110	-> 1227
/*     */     //   #336	-> 1243
/*     */     //   #337	-> 1245
/*     */     //   #338	-> 1254
/*     */     //   #339	-> 1259
/*     */     //   #335	-> 1261
/*     */     //   #334	-> 1262
/*     */     //   #334	-> 1263
/*     */     //   #110	-> 1264
/*     */     //   #108	-> 1285
/*     */     //   #114	-> 1288
/*     */     //   #286	-> 1289
/*     */     //   #285	-> 1294
/*     */     //   #340	-> 1295
/*     */     //   #264	-> 1301
/*     */     //   #341	-> 1304
/*     */     //   #258	-> 1306
/*     */     //   #342	-> 1309
/*     */     //   #255	-> 1311
/*     */     //   #343	-> 1314
/*     */     //   #116	-> 1327
/*     */     // Local variable table:
/*     */     //   start	length	slot	name	descriptor
/*     */     //   168	6	11	$i$f$getDp	I
/*     */     //   165	9	10	$this$dp$iv	I
/*     */     //   181	6	11	$i$f$getDp	I
/*     */     //   178	9	10	$this$dp$iv	I
/*     */     //   620	6	42	$i$a$-cache-GrazieActivationPageKt$GrazieActivationPageDebugMockControls$1$1	I
/*     */     //   638	11	44	value$iv	Ljava/lang/Object;
/*     */     //   595	60	38	$i$a$-let-ComposerKt$cache$1$iv	I
/*     */     //   592	63	37	it$iv	Ljava/lang/Object;
/*     */     //   583	74	36	$i$f$cache	I
/*     */     //   580	77	34	$this$cache$iv	Landroidx/compose/runtime/Composer;
/*     */     //   580	77	35	invalid$iv	Z
/*     */     //   702	6	36	$i$f$getDp	I
/*     */     //   699	9	35	$this$dp$iv	I
/*     */     //   1085	43	64	$i$a$-Column-GrazieActivationPageKt$GrazieActivationPageDebugMockControls$1$2	I
/*     */     //   1082	46	63	$this$GrazieActivationPageDebugMockControls_RPmYEkk_u24lambda_u2416_u24lambda_u2413	Landroidx/compose/foundation/layout/ColumnScope;
/*     */     //   1082	46	62	$composer	Landroidx/compose/runtime/Composer;
/*     */     //   1082	46	61	$changed	I
/*     */     //   1046	87	60	$i$a$-Layout-ColumnKt$Column$1$iv	I
/*     */     //   1043	90	59	$composer$iv	Landroidx/compose/runtime/Composer;
/*     */     //   1043	90	58	$changed$iv	I
/*     */     //   957	55	57	$i$a$-with-Updater$set$1$iv$iv$iv	I
/*     */     //   954	58	56	$this$set_impl_u24lambda_u240$iv$iv$iv	Landroidx/compose/runtime/Composer;
/*     */     //   950	64	55	$i$f$set-impl	I
/*     */     //   947	67	54	block$iv$iv$iv	Lkotlin/jvm/functions/Function2;
/*     */     //   913	115	53	$i$a$-ReusableComposeNode-LayoutKt$Layout$1$iv$iv	I
/*     */     //   910	118	52	$this$Layout_u24lambda_u240$iv$iv	Landroidx/compose/runtime/Composer;
/*     */     //   842	304	51	$i$f$ReusableComposeNode	I
/*     */     //   839	307	49	factory$iv$iv$iv	Lkotlin/jvm/functions/Function0;
/*     */     //   839	307	50	$changed$iv$iv$iv	I
/*     */     //   781	371	44	$i$f$Layout	I
/*     */     //   798	354	46	compositeKeyHash$iv$iv	I
/*     */     //   807	345	47	localMap$iv$iv	Landroidx/compose/runtime/CompositionLocalMap;
/*     */     //   816	336	48	materialized$iv$iv	Landroidx/compose/ui/Modifier;
/*     */     //   778	374	42	$changed$iv$iv	I
/*     */     //   725	433	37	$i$f$Column	I
/*     */     //   768	390	38	measurePolicy$iv	Landroidx/compose/ui/layout/MeasurePolicy;
/*     */     //   742	416	35	verticalArrangement$iv	Landroidx/compose/foundation/layout/Arrangement$Vertical;
/*     */     //   722	436	36	$changed$iv	I
/*     */     //   1227	6	42	$i$a$-cache-GrazieActivationPageKt$GrazieActivationPageDebugMockControls$1$3	I
/*     */     //   1245	11	44	value$iv	Ljava/lang/Object;
/*     */     //   1202	60	38	$i$a$-let-ComposerKt$cache$1$iv	I
/*     */     //   1199	63	37	it$iv	Ljava/lang/Object;
/*     */     //   1190	74	36	$i$f$cache	I
/*     */     //   1187	77	34	$this$cache$iv	Landroidx/compose/runtime/Composer;
/*     */     //   1187	77	35	invalid$iv	Z
/*     */     //   551	738	33	$i$a$-Row-GrazieActivationPageKt$GrazieActivationPageDebugMockControls$1	I
/*     */     //   548	741	32	$this$GrazieActivationPageDebugMockControls_RPmYEkk_u24lambda_u2416	Landroidx/compose/foundation/layout/RowScope;
/*     */     //   548	741	31	$composer	Landroidx/compose/runtime/Composer;
/*     */     //   548	741	30	$changed	I
/*     */     //   512	782	29	$i$a$-Layout-RowKt$Row$1$iv	I
/*     */     //   509	785	28	$composer$iv	Landroidx/compose/runtime/Composer;
/*     */     //   509	785	27	$changed$iv	I
/*     */     //   424	55	26	$i$a$-with-Updater$set$1$iv$iv$iv	I
/*     */     //   421	58	25	$this$set_impl_u24lambda_u240$iv$iv$iv	Landroidx/compose/runtime/Composer;
/*     */     //   417	64	24	$i$f$set-impl	I
/*     */     //   414	67	23	block$iv$iv$iv	Lkotlin/jvm/functions/Function2;
/*     */     //   380	115	22	$i$a$-ReusableComposeNode-LayoutKt$Layout$1$iv$iv	I
/*     */     //   377	118	21	$this$Layout_u24lambda_u240$iv$iv	Landroidx/compose/runtime/Composer;
/*     */     //   316	989	20	$i$f$ReusableComposeNode	I
/*     */     //   313	992	18	factory$iv$iv$iv	Lkotlin/jvm/functions/Function0;
/*     */     //   313	992	19	$changed$iv$iv$iv	I
/*     */     //   259	1051	14	$i$f$Layout	I
/*     */     //   274	1036	15	compositeKeyHash$iv$iv	I
/*     */     //   282	1028	16	localMap$iv$iv	Landroidx/compose/runtime/CompositionLocalMap;
/*     */     //   290	1020	17	materialized$iv$iv	Landroidx/compose/ui/Modifier;
/*     */     //   256	1054	13	$changed$iv$iv	I
/*     */     //   208	1107	11	$i$f$Row	I
/*     */     //   246	1069	12	measurePolicy$iv	Landroidx/compose/ui/layout/MeasurePolicy;
/*     */     //   205	1110	10	$changed$iv	I
/*     */     //   125	1199	6	debugMock$delegate	Landroidx/compose/runtime/State;
/*     */     //   14	1348	5	$dirty	I
/*     */     //   0	1362	0	model	Lcom/intellij/ml/llm/matterhorn/ej/ui/login/GrazieActivationPageVm;
/*     */     //   0	1362	1	backgroundColor	J
/*     */     //   0	1362	3	$composer	Landroidx/compose/runtime/Composer;
/*     */     //   0	1362	4	$changed	I }
/* 516 */   private static final Pair<String, GrazieActivationState> GrazieActivationPageDebugMockControls_RPmYEkk$lambda$10(State $debugMock$delegate) { State state = $debugMock$delegate; Object object = null; KProperty property$iv = null; int $i$f$getValue = 0; return (Pair<String, GrazieActivationState>)state.getValue(); } private static final Unit GrazieActivationPageDebugMockControls_RPmYEkk$lambda$16$lambda$12$lambda$11(GrazieActivationPageVm $model) { ComponentManager $this$service$iv = (ComponentManager)$model.getLoginVm().getProject(); int $i$f$service = 0;
/* 517 */     Class<ActivationTestActionService> serviceClass$iv = ActivationTestActionService.class;
/* 518 */     if ($this$service$iv.getService(serviceClass$iv) == null) { $this$service$iv.getService(serviceClass$iv); throw ServicesKt.serviceNotFoundError($this$service$iv, serviceClass$iv); }  ((ActivationTestActionService)$this$service$iv.getService(serviceClass$iv)).back(); return Unit.INSTANCE; } private static final Unit GrazieActivationPageDebugMockControls_RPmYEkk$lambda$16$lambda$15$lambda$14(GrazieActivationPageVm $model) { ComponentManager $this$service$iv = (ComponentManager)$model.getLoginVm().getProject(); int $i$f$service = 0;
/* 519 */     Class<ActivationTestActionService> serviceClass$iv = ActivationTestActionService.class;
/* 520 */     if ($this$service$iv.getService(serviceClass$iv) == null) { $this$service$iv.getService(serviceClass$iv); throw ServicesKt.serviceNotFoundError($this$service$iv, serviceClass$iv); }  ((ActivationTestActionService)$this$service$iv.getService(serviceClass$iv)).next();
/*     */     return Unit.INSTANCE; }
/*     */ 
/*     */   
/*     */   @Composable
/*     */   @ComposableTarget(applier = "androidx.compose.ui.UiComposable")
/*     */   private static final void LoginFooter(Composer $composer, int $changed) {
/*     */     $composer = $composer.startRestartGroup(403893287);
/*     */     if ($changed != 0 || !$composer.getSkipping()) {
/*     */       if (ComposerKt.isTraceInProgress())
/*     */         ComposerKt.traceEventStart(403893287, $changed, -1, "com.intellij.ml.llm.matterhorn.ej.ui.login.LoginFooter (GrazieActivationPage.kt:119)"); 
/*     */       int $this$dp$iv = 12, $i$f$getDp = 0;
/*     */       $this$dp$iv = 16;
/*     */       $i$f$getDp = 0;
/*     */       Modifier modifier1 = PaddingKt.padding-qDBjuR0$default(SizeKt.fillMaxWidth$default((Modifier)Modifier.Companion, 0.0F, 1, null), 0.0F, Dp.constructor-impl($this$dp$iv), 0.0F, Dp.constructor-impl($this$dp$iv), 5, null);
/*     */       int i = 12, j = 0;
/*     */       Arrangement.Vertical vertical = (Arrangement.Vertical)Arrangement.INSTANCE.spacedBy-0680j_4(Dp.constructor-impl(i));
/*     */       int $changed$iv = 54;
/*     */       int $i$f$Column = 0;
/*     */       ComposerKt.sourceInformationMarkerStart($composer, -483455358, "CC(Column)P(2,3,1)86@4330L61,87@4396L133:Column.kt#2w3rfo");
/*     */       Alignment.Horizontal horizontalAlignment$iv = Alignment.Companion.getStart();
/*     */       MeasurePolicy measurePolicy$iv = ColumnKt.columnMeasurePolicy(vertical, horizontalAlignment$iv, $composer, 0xE & $changed$iv >> 3 | 0x70 & $changed$iv >> 3);
/*     */       int $changed$iv$iv = 0x70 & $changed$iv << 3;
/*     */       int $i$f$Layout = 0;
/*     */       ComposerKt.sourceInformationMarkerStart($composer, -1323940314, "CC(Layout)P(!1,2)79@3208L23,82@3359L411:Layout.kt#80mrfh");
/*     */       int compositeKeyHash$iv$iv = ComposablesKt.getCurrentCompositeKeyHash($composer, 0);
/*     */       CompositionLocalMap localMap$iv$iv = $composer.getCurrentCompositionLocalMap();
/*     */       Modifier materialized$iv$iv = ComposedModifierKt.materializeModifier($composer, modifier1);
/*     */       Function0 function01 = ComposeUiNode.Companion.getConstructor();
/*     */       int $changed$iv$iv$iv = 0x6 | 0x380 & $changed$iv$iv << 6;
/*     */       int $i$f$ReusableComposeNode = 0;
/*     */       ComposerKt.sourceInformationMarkerStart($composer, -692256719, "CC(ReusableComposeNode)P(1,2)376@14062L9:Composables.kt#9igjgp");
/*     */       if (!($composer.getApplier() instanceof androidx.compose.runtime.Applier))
/*     */         ComposablesKt.invalidApplier(); 
/*     */       $composer.startReusableNode();
/*     */       if ($composer.getInserting()) {
/*     */         $composer.createNode(function01);
/*     */       } else {
/*     */         $composer.useNode();
/*     */       } 
/*     */       Composer $this$Layout_u24lambda_u240$iv$iv = Updater.constructor-impl($composer);
/*     */       int $i$a$-ReusableComposeNode-LayoutKt$Layout$1$iv$iv = 0;
/*     */       Updater.set-impl($this$Layout_u24lambda_u240$iv$iv, measurePolicy$iv, ComposeUiNode.Companion.getSetMeasurePolicy());
/*     */       Updater.set-impl($this$Layout_u24lambda_u240$iv$iv, localMap$iv$iv, ComposeUiNode.Companion.getSetResolvedCompositionLocals());
/*     */       Function2 block$iv$iv$iv = ComposeUiNode.Companion.getSetCompositeKeyHash();
/*     */       int $i$f$set-impl = 0;
/*     */       Composer $this$set_impl_u24lambda_u240$iv$iv$iv = $this$Layout_u24lambda_u240$iv$iv;
/*     */       int $i$a$-with-Updater$set$1$iv$iv$iv = 0;
/*     */       if ($this$set_impl_u24lambda_u240$iv$iv$iv.getInserting() || !Intrinsics.areEqual($this$set_impl_u24lambda_u240$iv$iv$iv.rememberedValue(), Integer.valueOf(compositeKeyHash$iv$iv))) {
/*     */         $this$set_impl_u24lambda_u240$iv$iv$iv.updateRememberedValue(Integer.valueOf(compositeKeyHash$iv$iv));
/*     */         $this$Layout_u24lambda_u240$iv$iv.apply(Integer.valueOf(compositeKeyHash$iv$iv), block$iv$iv$iv);
/*     */       } 
/*     */       Updater.set-impl($this$Layout_u24lambda_u240$iv$iv, materialized$iv$iv, ComposeUiNode.Companion.getSetModifier());
/*     */       int k = 0xE & $changed$iv$iv$iv >> 6;
/*     */       Composer $composer$iv = $composer;
/*     */       int $i$a$-Layout-ColumnKt$Column$1$iv = 0;
/*     */       ComposerKt.sourceInformationMarkerStart($composer$iv, -384784025, "C88@4444L9:Column.kt#2w3rfo");
/*     */       int m = 0x6 | 0x70 & $changed$iv >> 6;
/*     */       Composer composer1 = $composer$iv;
/*     */       ColumnScope $this$LoginFooter_u24lambda_u2421 = (ColumnScope)ColumnScopeInstance.INSTANCE;
/*     */       int $i$a$-Column-GrazieActivationPageKt$LoginFooter$1 = 0;
/*     */       TextWithSeparatorKt.TextWithSeparator-fMjUOWI(null, "Your Coding Agent ", TextUnitKt.getSp(16), TextUnitKt.getSp(22), FontWeight.Companion.getW500(), Color.Companion.getUnspecified-0d7_KjU(), 0L, composer1, 224688, 65);
/*     */       Alignment.Vertical vertical1 = Alignment.Companion.getCenterVertically();
/*     */       int i2 = 8, i8 = 0;
/*     */       Arrangement.HorizontalOrVertical horizontalOrVertical = Arrangement.INSTANCE.spacedBy-0680j_4(Dp.constructor-impl(i2));
/*     */       int i7 = 432, $i$f$Row = 0;
/*     */       ComposerKt.sourceInformationMarkerStart(composer1, 693286680, "CC(Row)P(2,1,3)99@5018L58,100@5081L130:Row.kt#2w3rfo");
/*     */       Modifier modifier3 = (Modifier)Modifier.Companion;
/*     */       MeasurePolicy measurePolicy1 = RowKt.rowMeasurePolicy((Arrangement.Horizontal)horizontalOrVertical, vertical1, composer1, 0xE & i7 >> 3 | 0x70 & i7 >> 3);
/*     */       int i9 = 0x70 & i7 << 3;
/*     */       int i10 = 0;
/*     */       ComposerKt.sourceInformationMarkerStart(composer1, -1323940314, "CC(Layout)P(!1,2)79@3208L23,82@3359L411:Layout.kt#80mrfh");
/*     */       int i11 = ComposablesKt.getCurrentCompositeKeyHash(composer1, 0);
/*     */       CompositionLocalMap compositionLocalMap1 = composer1.getCurrentCompositionLocalMap();
/*     */       Modifier modifier4 = ComposedModifierKt.materializeModifier(composer1, modifier3);
/*     */       Function0 function02 = ComposeUiNode.Companion.getConstructor();
/*     */       int i12 = 0x6 | 0x380 & i9 << 6;
/*     */       int i13 = 0;
/*     */       ComposerKt.sourceInformationMarkerStart(composer1, -692256719, "CC(ReusableComposeNode)P(1,2)376@14062L9:Composables.kt#9igjgp");
/*     */       if (!(composer1.getApplier() instanceof androidx.compose.runtime.Applier))
/*     */         ComposablesKt.invalidApplier(); 
/*     */       composer1.startReusableNode();
/*     */       if (composer1.getInserting()) {
/*     */         composer1.createNode(function02);
/*     */       } else {
/*     */         composer1.useNode();
/*     */       } 
/*     */       Composer composer2 = Updater.constructor-impl(composer1);
/*     */       int i14 = 0;
/*     */       Updater.set-impl(composer2, measurePolicy1, ComposeUiNode.Companion.getSetMeasurePolicy());
/*     */       Updater.set-impl(composer2, compositionLocalMap1, ComposeUiNode.Companion.getSetResolvedCompositionLocals());
/*     */       Function2 function21 = ComposeUiNode.Companion.getSetCompositeKeyHash();
/*     */       int i15 = 0;
/*     */       Composer composer3 = composer2;
/*     */       int i16 = 0;
/*     */       if (composer3.getInserting() || !Intrinsics.areEqual(composer3.rememberedValue(), Integer.valueOf(i11))) {
/*     */         composer3.updateRememberedValue(Integer.valueOf(i11));
/*     */         composer2.apply(Integer.valueOf(i11), function21);
/*     */       } 
/*     */       Updater.set-impl(composer2, modifier4, ComposeUiNode.Companion.getSetModifier());
/*     */       int i18 = 0xE & i12 >> 6;
/*     */       Composer composer4 = composer1;
/*     */       int $i$a$-Layout-RowKt$Row$1$iv = 0;
/*     */       ComposerKt.sourceInformationMarkerStart(composer4, -407840262, "C101@5126L9:Row.kt#2w3rfo");
/*     */       int i20 = 0x6 | 0x70 & i7 >> 6;
/*     */       Composer composer6 = composer4;
/*     */       RowScope $this$LoginFooter_u24lambda_u2421_u24lambda_u2418 = (RowScope)RowScopeInstance.INSTANCE;
/*     */       int $i$a$-Row-GrazieActivationPageKt$LoginFooter$1$1 = 0;
/*     */       IconKt.Icon-FHprtrg((IconKey)MatterhornThemeDataKt.getMatterhornTheme(composer6, 0).getPromo1(), "promo icon 1", null, null, 0L, new org.jetbrains.jewel.ui.painter.PainterHint[0], composer6, 0x30 | PathIconKey.$stable, 28);
/*     */       TextKt.Text-bAzTDeA("Writes code, handles tasks", null, 0L, 0L, null, null, null, 0L, null, 0, 0L, 0, false, 0, null, null, composer6, 6, 0, 65534);
/*     */       ComposerKt.sourceInformationMarkerEnd(composer4);
/*     */       composer1.endNode();
/*     */       ComposerKt.sourceInformationMarkerEnd(composer1);
/*     */       ComposerKt.sourceInformationMarkerEnd(composer1);
/*     */       ComposerKt.sourceInformationMarkerEnd(composer1);
/*     */       vertical1 = Alignment.Companion.getCenterVertically();
/*     */       int i1 = 8, i6 = 0;
/*     */       horizontalOrVertical = Arrangement.INSTANCE.spacedBy-0680j_4(Dp.constructor-impl(i1));
/*     */       int i5 = 432;
/*     */       $i$f$Row = 0;
/*     */       ComposerKt.sourceInformationMarkerStart(composer1, 693286680, "CC(Row)P(2,1,3)99@5018L58,100@5081L130:Row.kt#2w3rfo");
/*     */       Modifier modifier2 = (Modifier)Modifier.Companion;
/*     */       measurePolicy1 = RowKt.rowMeasurePolicy((Arrangement.Horizontal)horizontalOrVertical, vertical1, composer1, 0xE & i5 >> 3 | 0x70 & i5 >> 3);
/*     */       i9 = 0x70 & i5 << 3;
/*     */       i10 = 0;
/*     */       ComposerKt.sourceInformationMarkerStart(composer1, -1323940314, "CC(Layout)P(!1,2)79@3208L23,82@3359L411:Layout.kt#80mrfh");
/*     */       i11 = ComposablesKt.getCurrentCompositeKeyHash(composer1, 0);
/*     */       compositionLocalMap1 = composer1.getCurrentCompositionLocalMap();
/*     */       modifier4 = ComposedModifierKt.materializeModifier(composer1, modifier2);
/*     */       Function0 factory$iv$iv$iv = ComposeUiNode.Companion.getConstructor();
/*     */       i12 = 0x6 | 0x380 & i9 << 6;
/*     */       i13 = 0;
/*     */       ComposerKt.sourceInformationMarkerStart(composer1, -692256719, "CC(ReusableComposeNode)P(1,2)376@14062L9:Composables.kt#9igjgp");
/*     */       if (!(composer1.getApplier() instanceof androidx.compose.runtime.Applier))
/*     */         ComposablesKt.invalidApplier(); 
/*     */       composer1.startReusableNode();
/*     */       if (composer1.getInserting()) {
/*     */         composer1.createNode(factory$iv$iv$iv);
/*     */       } else {
/*     */         composer1.useNode();
/*     */       } 
/*     */       composer2 = Updater.constructor-impl(composer1);
/*     */       i14 = 0;
/*     */       Updater.set-impl(composer2, measurePolicy1, ComposeUiNode.Companion.getSetMeasurePolicy());
/*     */       Updater.set-impl(composer2, compositionLocalMap1, ComposeUiNode.Companion.getSetResolvedCompositionLocals());
/*     */       function21 = ComposeUiNode.Companion.getSetCompositeKeyHash();
/*     */       i15 = 0;
/*     */       composer3 = composer2;
/*     */       i16 = 0;
/*     */       if (composer3.getInserting() || !Intrinsics.areEqual(composer3.rememberedValue(), Integer.valueOf(i11))) {
/*     */         composer3.updateRememberedValue(Integer.valueOf(i11));
/*     */         composer2.apply(Integer.valueOf(i11), function21);
/*     */       } 
/*     */       Updater.set-impl(composer2, modifier4, ComposeUiNode.Companion.getSetModifier());
/*     */       int i17 = 0xE & i12 >> 6;
/*     */       composer4 = composer1;
/*     */       $i$a$-Layout-RowKt$Row$1$iv = 0;
/*     */       ComposerKt.sourceInformationMarkerStart(composer4, -407840262, "C101@5126L9:Row.kt#2w3rfo");
/*     */       int i19 = 0x6 | 0x70 & i5 >> 6;
/*     */       Composer composer5 = composer4;
/*     */       RowScope $this$LoginFooter_u24lambda_u2421_u24lambda_u2419 = (RowScope)RowScopeInstance.INSTANCE;
/*     */       int $i$a$-Row-GrazieActivationPageKt$LoginFooter$1$2 = 0;
/*     */       IconKt.Icon-FHprtrg((IconKey)MatterhornThemeDataKt.getMatterhornTheme(composer5, 0).getPromo2(), "promo icon 2", null, null, 0L, new org.jetbrains.jewel.ui.painter.PainterHint[0], composer5, 0x30 | PathIconKey.$stable, 28);
/*     */       TextKt.Text-bAzTDeA("Understands your project", null, 0L, 0L, null, null, null, 0L, null, 0, 0L, 0, false, 0, null, null, composer5, 6, 0, 65534);
/*     */       ComposerKt.sourceInformationMarkerEnd(composer4);
/*     */       composer1.endNode();
/*     */       ComposerKt.sourceInformationMarkerEnd(composer1);
/*     */       ComposerKt.sourceInformationMarkerEnd(composer1);
/*     */       ComposerKt.sourceInformationMarkerEnd(composer1);
/*     */       vertical1 = Alignment.Companion.getCenterVertically();
/*     */       int n = 8, i4 = 0;
/*     */       horizontalOrVertical = Arrangement.INSTANCE.spacedBy-0680j_4(Dp.constructor-impl(n));
/*     */       int i3 = 432;
/*     */       $i$f$Row = 0;
/*     */       ComposerKt.sourceInformationMarkerStart(composer1, 693286680, "CC(Row)P(2,1,3)99@5018L58,100@5081L130:Row.kt#2w3rfo");
/*     */       Modifier modifier$iv = (Modifier)Modifier.Companion;
/*     */       measurePolicy1 = RowKt.rowMeasurePolicy((Arrangement.Horizontal)horizontalOrVertical, vertical1, composer1, 0xE & i3 >> 3 | 0x70 & i3 >> 3);
/*     */       i9 = 0x70 & i3 << 3;
/*     */       i10 = 0;
/*     */       ComposerKt.sourceInformationMarkerStart(composer1, -1323940314, "CC(Layout)P(!1,2)79@3208L23,82@3359L411:Layout.kt#80mrfh");
/*     */       i11 = ComposablesKt.getCurrentCompositeKeyHash(composer1, 0);
/*     */       compositionLocalMap1 = composer1.getCurrentCompositionLocalMap();
/*     */       modifier4 = ComposedModifierKt.materializeModifier(composer1, modifier$iv);
/*     */       factory$iv$iv$iv = ComposeUiNode.Companion.getConstructor();
/*     */       i12 = 0x6 | 0x380 & i9 << 6;
/*     */       i13 = 0;
/*     */       ComposerKt.sourceInformationMarkerStart(composer1, -692256719, "CC(ReusableComposeNode)P(1,2)376@14062L9:Composables.kt#9igjgp");
/*     */       if (!(composer1.getApplier() instanceof androidx.compose.runtime.Applier))
/*     */         ComposablesKt.invalidApplier(); 
/*     */       composer1.startReusableNode();
/*     */       if (composer1.getInserting()) {
/*     */         composer1.createNode(factory$iv$iv$iv);
/*     */       } else {
/*     */         composer1.useNode();
/*     */       } 
/*     */       composer2 = Updater.constructor-impl(composer1);
/*     */       i14 = 0;
/*     */       Updater.set-impl(composer2, measurePolicy1, ComposeUiNode.Companion.getSetMeasurePolicy());
/*     */       Updater.set-impl(composer2, compositionLocalMap1, ComposeUiNode.Companion.getSetResolvedCompositionLocals());
/*     */       function21 = ComposeUiNode.Companion.getSetCompositeKeyHash();
/*     */       i15 = 0;
/*     */       composer3 = composer2;
/*     */       i16 = 0;
/*     */       if (composer3.getInserting() || !Intrinsics.areEqual(composer3.rememberedValue(), Integer.valueOf(i11))) {
/*     */         composer3.updateRememberedValue(Integer.valueOf(i11));
/*     */         composer2.apply(Integer.valueOf(i11), function21);
/*     */       } 
/*     */       Updater.set-impl(composer2, modifier4, ComposeUiNode.Companion.getSetModifier());
/*     */       i17 = 0xE & i12 >> 6;
/*     */       composer4 = composer1;
/*     */       $i$a$-Layout-RowKt$Row$1$iv = 0;
/*     */       ComposerKt.sourceInformationMarkerStart(composer4, -407840262, "C101@5126L9:Row.kt#2w3rfo");
/*     */       i19 = 0x6 | 0x70 & i3 >> 6;
/*     */       composer5 = composer4;
/*     */       RowScope $this$LoginFooter_u24lambda_u2421_u24lambda_u2420 = (RowScope)RowScopeInstance.INSTANCE;
/*     */       int $i$a$-Row-GrazieActivationPageKt$LoginFooter$1$3 = 0;
/*     */       IconKt.Icon-FHprtrg((IconKey)MatterhornThemeDataKt.getMatterhornTheme(composer5, 0).getPromo3(), "promo icon 3", null, null, 0L, new org.jetbrains.jewel.ui.painter.PainterHint[0], composer5, 0x30 | PathIconKey.$stable, 28);
/*     */       TextKt.Text-bAzTDeA("Runs tests, ensures quality", null, 0L, 0L, null, null, null, 0L, null, 0, 0L, 0, false, 0, null, null, composer5, 6, 0, 65534);
/*     */       ComposerKt.sourceInformationMarkerEnd(composer4);
/*     */       composer1.endNode();
/*     */       ComposerKt.sourceInformationMarkerEnd(composer1);
/*     */       ComposerKt.sourceInformationMarkerEnd(composer1);
/*     */       ComposerKt.sourceInformationMarkerEnd(composer1);
/*     */       ComposerKt.sourceInformationMarkerEnd($composer$iv);
/*     */       $composer.endNode();
/*     */       ComposerKt.sourceInformationMarkerEnd($composer);
/*     */       ComposerKt.sourceInformationMarkerEnd($composer);
/*     */       ComposerKt.sourceInformationMarkerEnd($composer);
/*     */       if (ComposerKt.isTraceInProgress())
/*     */         ComposerKt.traceEventEnd(); 
/*     */     } else {
/*     */       $composer.skipToGroupEnd();
/*     */     } 
/*     */     if ($composer.endRestartGroup() != null) {
/*     */       $composer.endRestartGroup().updateScope($changed::LoginFooter$lambda$22);
/*     */     } else {
/*     */       $composer.endRestartGroup();
/*     */     } 
/*     */   }
/*     */   
/*     */   private static final Unit GrazieActivationPage$lambda$9(GrazieActivationPageVm $model, int $$changed, Composer $composer, int $force) {
/*     */     GrazieActivationPage($model, $composer, RecomposeScopeImplKt.updateChangedFlags($$changed | 0x1));
/*     */     return Unit.INSTANCE;
/*     */   }
/*     */   
/*     */   private static final Unit GrazieActivationPageDebugMockControls_RPmYEkk$lambda$17(GrazieActivationPageVm $model, long $backgroundColor, int $$changed, Composer $composer, int $force) {
/*     */     GrazieActivationPageDebugMockControls-RPmYEkk($model, $backgroundColor, $composer, RecomposeScopeImplKt.updateChangedFlags($$changed | 0x1));
/*     */     return Unit.INSTANCE;
/*     */   }
/*     */   
/*     */   private static final Unit LoginFooter$lambda$22(int $$changed, Composer $composer, int $force) {
/*     */     LoginFooter($composer, RecomposeScopeImplKt.updateChangedFlags($$changed | 0x1));
/*     */     return Unit.INSTANCE;
/*     */   }
/*     */ }


/* Location:              C:\Users\yuzum\Downloads\ej-release-243.132.63.zip!\ej\lib\ej-243.132.63.jar!\com\intellij\ml\llm\matterhorn\e\\ui\login\GrazieActivationPageKt.class
 * Java compiler version: 17 (61.0)
 * JD-Core Version:       1.1.3
 */