/*     */ package com.intellij.ml.llm.matterhorn.ej.ui.login.components;
/*     */ 
/*     */ import androidx.compose.runtime.Composer;
/*     */ import androidx.compose.runtime.MutableState;
/*     */ import androidx.compose.runtime.RecomposeScopeImplKt;
/*     */ import androidx.compose.runtime.State;
/*     */ import com.intellij.ml.llm.matterhorn.ej.ui.login.states.StepFail;
/*     */ import kotlin.Metadata;
/*     */ import kotlin.ResultKt;
/*     */ import kotlin.Unit;
/*     */ import kotlin.coroutines.Continuation;
/*     */ import kotlin.coroutines.jvm.internal.SuspendLambda;
/*     */ import kotlin.jvm.internal.SourceDebugExtension;
/*     */ import kotlin.reflect.KProperty;
/*     */ import kotlinx.coroutines.CoroutineScope;
/*     */ import kotlinx.coroutines.DelayKt;
/*     */ import org.jetbrains.annotations.NotNull;
/*     */ import org.jetbrains.annotations.Nullable;
/*     */ 
/*     */ @Metadata(mv = {2, 1, 0}, k = 2, xi = 48, d1 = {"\000\024\n\000\n\002\020\002\n\000\n\002\030\002\n\002\b\003\n\002\020\013\032\025\020\000\032\0020\0012\006\020\002\032\0020\003H\001¢\006\002\020\004¨\006\005²\006\n\020\006\032\0020\007X\002"}, d2 = {"GrazieActivationStepFail", "", "state", "Lcom/intellij/ml/llm/matterhorn/ej/ui/login/states/StepFail;", "(Lcom/intellij/ml/llm/matterhorn/ej/ui/login/states/StepFail;Landroidx/compose/runtime/Composer;I)V", "ej-ui", "loading", ""})
/*     */ @SourceDebugExtension({"SMAP\nGrazieActivationStepFail.kt\nKotlin\n*S Kotlin\n*F\n+ 1 GrazieActivationStepFail.kt\ncom/intellij/ml/llm/matterhorn/ej/ui/login/components/GrazieActivationStepFailKt\n+ 2 Composer.kt\nandroidx/compose/runtime/ComposerKt\n+ 3 Effects.kt\nandroidx/compose/runtime/EffectsKt\n+ 4 Effects.kt\nandroidx/compose/runtime/EffectsKt$rememberCoroutineScope$1\n+ 5 Dp.kt\nandroidx/compose/ui/unit/DpKt\n+ 6 Column.kt\nandroidx/compose/foundation/layout/ColumnKt\n+ 7 Layout.kt\nandroidx/compose/ui/layout/LayoutKt\n+ 8 Composables.kt\nandroidx/compose/runtime/ComposablesKt\n+ 9 Composer.kt\nandroidx/compose/runtime/Updater\n+ 10 SnapshotState.kt\nandroidx/compose/runtime/SnapshotStateKt__SnapshotStateKt\n*L\n1#1,46:1\n1225#2,6:47\n1225#2,3:58\n1228#2,3:64\n1225#2,6:104\n481#3:53\n480#3,4:54\n484#3,2:61\n488#3:67\n480#4:63\n149#5:68\n86#6:69\n84#6,5:70\n89#6:103\n93#6:113\n79#7,6:75\n86#7,4:90\n90#7,2:100\n94#7:112\n368#8,9:81\n377#8:102\n378#8,2:110\n4034#9,6:94\n81#10:114\n107#10,2:115\n*S KotlinDebug\n*F\n+ 1 GrazieActivationStepFail.kt\ncom/intellij/ml/llm/matterhorn/ej/ui/login/components/GrazieActivationStepFailKt\n*L\n23#1:47,6\n24#1:58,3\n24#1:64,3\n33#1:104,6\n24#1:53\n24#1:54,4\n24#1:61,2\n24#1:67\n24#1:63\n28#1:68\n25#1:69\n25#1:70,5\n25#1:103\n25#1:113\n25#1:75,6\n25#1:90,4\n25#1:100,2\n25#1:112\n25#1:81,9\n25#1:102\n25#1:110,2\n25#1:94,6\n23#1:114\n23#1:115,2\n*E\n"})
/*     */ public final class GrazieActivationStepFailKt {
/*  23 */   private static final boolean GrazieActivationStepFail$lambda$1(MutableState $loading$delegate) { State state = (State)$loading$delegate; Object object = null; KProperty property$iv = null; int $i$f$getValue = 0; return (
/*     */ 
/*     */ 
/*     */ 
/*     */ 
/*     */ 
/*     */ 
/*     */ 
/*     */ 
/*     */ 
/*     */ 
/*     */ 
/*     */ 
/*     */ 
/*     */ 
/*     */ 
/*     */ 
/*     */ 
/*     */ 
/*     */ 
/*     */ 
/*     */ 
/*     */ 
/*     */ 
/*     */ 
/*     */ 
/*     */ 
/*     */ 
/*     */ 
/*     */ 
/*     */ 
/*     */ 
/*     */ 
/*     */ 
/*     */ 
/*     */ 
/*     */ 
/*     */ 
/*     */ 
/*     */ 
/*     */ 
/*     */ 
/*     */ 
/*     */ 
/*     */ 
/*     */ 
/*     */ 
/*     */ 
/*     */ 
/*     */ 
/*     */ 
/*     */ 
/*     */ 
/*     */ 
/*     */ 
/*     */ 
/*     */ 
/*     */ 
/*     */ 
/*     */ 
/*     */ 
/*     */ 
/*     */ 
/*     */ 
/*     */ 
/*     */ 
/*     */ 
/*     */ 
/*     */ 
/*     */ 
/*     */ 
/*     */ 
/*     */ 
/*     */ 
/*     */ 
/*     */ 
/*     */ 
/*     */ 
/*     */ 
/*     */ 
/*     */ 
/*     */ 
/*     */ 
/*     */ 
/*     */ 
/*     */ 
/*     */ 
/*     */ 
/*     */ 
/*     */ 
/*     */       
/* 114 */       (Boolean)state.getValue()).booleanValue(); }
/*     */   @Composable @ComposableTarget(applier = "androidx.compose.ui.UiComposable") public static final void GrazieActivationStepFail(@NotNull StepFail state, @Nullable Composer $composer, int $changed) { // Byte code:
/*     */     //   0: aload_0
/*     */     //   1: ldc 'state'
/*     */     //   3: invokestatic checkNotNullParameter : (Ljava/lang/Object;Ljava/lang/String;)V
/*     */     //   6: aload_1
/*     */     //   7: ldc 8341900
/*     */     //   9: invokeinterface startRestartGroup : (I)Landroidx/compose/runtime/Composer;
/*     */     //   14: astore_1
/*     */     //   15: iload_2
/*     */     //   16: istore_3
/*     */     //   17: iload_2
/*     */     //   18: bipush #6
/*     */     //   20: iand
/*     */     //   21: ifne -> 42
/*     */     //   24: iload_3
/*     */     //   25: aload_1
/*     */     //   26: aload_0
/*     */     //   27: invokeinterface changed : (Ljava/lang/Object;)Z
/*     */     //   32: ifeq -> 39
/*     */     //   35: iconst_4
/*     */     //   36: goto -> 40
/*     */     //   39: iconst_2
/*     */     //   40: ior
/*     */     //   41: istore_3
/*     */     //   42: iload_3
/*     */     //   43: iconst_3
/*     */     //   44: iand
/*     */     //   45: iconst_2
/*     */     //   46: if_icmpne -> 58
/*     */     //   49: aload_1
/*     */     //   50: invokeinterface getSkipping : ()Z
/*     */     //   55: ifne -> 949
/*     */     //   58: invokestatic isTraceInProgress : ()Z
/*     */     //   61: ifeq -> 73
/*     */     //   64: ldc 8341900
/*     */     //   66: iload_3
/*     */     //   67: iconst_m1
/*     */     //   68: ldc 'com.intellij.ml.llm.matterhorn.ej.ui.login.components.GrazieActivationStepFail (GrazieActivationStepFail.kt:21)'
/*     */     //   70: invokestatic traceEventStart : (IIILjava/lang/String;)V
/*     */     //   73: aload_1
/*     */     //   74: ldc 16961767
/*     */     //   76: invokeinterface startReplaceGroup : (I)V
/*     */     //   81: aload_1
/*     */     //   82: astore #6
/*     */     //   84: iload_3
/*     */     //   85: bipush #14
/*     */     //   87: iand
/*     */     //   88: iconst_4
/*     */     //   89: if_icmpne -> 96
/*     */     //   92: iconst_1
/*     */     //   93: goto -> 97
/*     */     //   96: iconst_0
/*     */     //   97: istore #7
/*     */     //   99: nop
/*     */     //   100: iconst_0
/*     */     //   101: istore #8
/*     */     //   103: aload #6
/*     */     //   105: invokeinterface rememberedValue : ()Ljava/lang/Object;
/*     */     //   110: astore #9
/*     */     //   112: iconst_0
/*     */     //   113: istore #10
/*     */     //   115: iload #7
/*     */     //   117: ifne -> 131
/*     */     //   120: aload #9
/*     */     //   122: getstatic androidx/compose/runtime/Composer.Companion : Landroidx/compose/runtime/Composer$Companion;
/*     */     //   125: invokevirtual getEmpty : ()Ljava/lang/Object;
/*     */     //   128: if_acmpne -> 160
/*     */     //   131: iconst_0
/*     */     //   132: istore #11
/*     */     //   134: iconst_0
/*     */     //   135: invokestatic valueOf : (Z)Ljava/lang/Boolean;
/*     */     //   138: aconst_null
/*     */     //   139: iconst_2
/*     */     //   140: aconst_null
/*     */     //   141: invokestatic mutableStateOf$default : (Ljava/lang/Object;Landroidx/compose/runtime/SnapshotMutationPolicy;ILjava/lang/Object;)Landroidx/compose/runtime/MutableState;
/*     */     //   144: astore #11
/*     */     //   146: aload #6
/*     */     //   148: aload #11
/*     */     //   150: invokeinterface updateRememberedValue : (Ljava/lang/Object;)V
/*     */     //   155: aload #11
/*     */     //   157: goto -> 162
/*     */     //   160: aload #9
/*     */     //   162: nop
/*     */     //   163: nop
/*     */     //   164: nop
/*     */     //   165: checkcast androidx/compose/runtime/MutableState
/*     */     //   168: astore #5
/*     */     //   170: aload_1
/*     */     //   171: invokeinterface endReplaceGroup : ()V
/*     */     //   176: aload #5
/*     */     //   178: astore #4
/*     */     //   180: iconst_0
/*     */     //   181: istore #7
/*     */     //   183: nop
/*     */     //   184: iconst_0
/*     */     //   185: istore #8
/*     */     //   187: aload_1
/*     */     //   188: ldc 773894976
/*     */     //   190: ldc 'CC(rememberCoroutineScope)482@20254L144:Effects.kt#9igjgp'
/*     */     //   192: invokestatic sourceInformationMarkerStart : (Landroidx/compose/runtime/Composer;ILjava/lang/String;)V
/*     */     //   195: aload_1
/*     */     //   196: astore #9
/*     */     //   198: aload_1
/*     */     //   199: ldc -954370320
/*     */     //   201: ldc 'CC(remember):Effects.kt#9igjgp'
/*     */     //   203: invokestatic sourceInformationMarkerStart : (Landroidx/compose/runtime/Composer;ILjava/lang/String;)V
/*     */     //   206: aload_1
/*     */     //   207: astore #10
/*     */     //   209: iconst_0
/*     */     //   210: istore #11
/*     */     //   212: iconst_0
/*     */     //   213: istore #12
/*     */     //   215: aload #10
/*     */     //   217: invokeinterface rememberedValue : ()Ljava/lang/Object;
/*     */     //   222: astore #13
/*     */     //   224: iconst_0
/*     */     //   225: istore #14
/*     */     //   227: aload #13
/*     */     //   229: getstatic androidx/compose/runtime/Composer.Companion : Landroidx/compose/runtime/Composer$Companion;
/*     */     //   232: invokevirtual getEmpty : ()Ljava/lang/Object;
/*     */     //   235: if_acmpne -> 282
/*     */     //   238: iconst_0
/*     */     //   239: istore #15
/*     */     //   241: iconst_0
/*     */     //   242: istore #16
/*     */     //   244: getstatic kotlin/coroutines/EmptyCoroutineContext.INSTANCE : Lkotlin/coroutines/EmptyCoroutineContext;
/*     */     //   247: checkcast kotlin/coroutines/CoroutineContext
/*     */     //   250: aload #9
/*     */     //   252: invokestatic createCompositionCoroutineScope : (Lkotlin/coroutines/CoroutineContext;Landroidx/compose/runtime/Composer;)Lkotlinx/coroutines/CoroutineScope;
/*     */     //   255: astore #42
/*     */     //   257: new androidx/compose/runtime/CompositionScopedCoroutineScopeCanceller
/*     */     //   260: dup
/*     */     //   261: aload #42
/*     */     //   263: invokespecial <init> : (Lkotlinx/coroutines/CoroutineScope;)V
/*     */     //   266: astore #16
/*     */     //   268: aload #10
/*     */     //   270: aload #16
/*     */     //   272: invokeinterface updateRememberedValue : (Ljava/lang/Object;)V
/*     */     //   277: aload #16
/*     */     //   279: goto -> 284
/*     */     //   282: aload #13
/*     */     //   284: nop
/*     */     //   285: nop
/*     */     //   286: nop
/*     */     //   287: checkcast androidx/compose/runtime/CompositionScopedCoroutineScopeCanceller
/*     */     //   290: astore #17
/*     */     //   292: aload_1
/*     */     //   293: invokestatic sourceInformationMarkerEnd : (Landroidx/compose/runtime/Composer;)V
/*     */     //   296: aload #17
/*     */     //   298: astore #18
/*     */     //   300: aload #18
/*     */     //   302: invokevirtual getCoroutineScope : ()Lkotlinx/coroutines/CoroutineScope;
/*     */     //   305: astore #17
/*     */     //   307: aload_1
/*     */     //   308: invokestatic sourceInformationMarkerEnd : (Landroidx/compose/runtime/Composer;)V
/*     */     //   311: aload #17
/*     */     //   313: nop
/*     */     //   314: astore #5
/*     */     //   316: getstatic androidx/compose/ui/Modifier.Companion : Landroidx/compose/ui/Modifier$Companion;
/*     */     //   319: checkcast androidx/compose/ui/Modifier
/*     */     //   322: fconst_0
/*     */     //   323: invokestatic getActivationMinHeight : ()F
/*     */     //   326: iconst_1
/*     */     //   327: aconst_null
/*     */     //   328: invokestatic defaultMinSize-VpY3zN4$default : (Landroidx/compose/ui/Modifier;FFILjava/lang/Object;)Landroidx/compose/ui/Modifier;
/*     */     //   331: astore #6
/*     */     //   333: getstatic androidx/compose/foundation/layout/Arrangement.INSTANCE : Landroidx/compose/foundation/layout/Arrangement;
/*     */     //   336: bipush #16
/*     */     //   338: istore #7
/*     */     //   340: iconst_0
/*     */     //   341: istore #8
/*     */     //   343: iload #7
/*     */     //   345: i2f
/*     */     //   346: invokestatic constructor-impl : (F)F
/*     */     //   349: invokevirtual spacedBy-0680j_4 : (F)Landroidx/compose/foundation/layout/Arrangement$HorizontalOrVertical;
/*     */     //   352: checkcast androidx/compose/foundation/layout/Arrangement$Vertical
/*     */     //   355: astore #7
/*     */     //   357: bipush #54
/*     */     //   359: istore #9
/*     */     //   361: nop
/*     */     //   362: iconst_0
/*     */     //   363: istore #10
/*     */     //   365: aload_1
/*     */     //   366: ldc -483455358
/*     */     //   368: ldc 'CC(Column)P(2,3,1)86@4330L61,87@4396L133:Column.kt#2w3rfo'
/*     */     //   370: invokestatic sourceInformationMarkerStart : (Landroidx/compose/runtime/Composer;ILjava/lang/String;)V
/*     */     //   373: getstatic androidx/compose/ui/Alignment.Companion : Landroidx/compose/ui/Alignment$Companion;
/*     */     //   376: invokevirtual getStart : ()Landroidx/compose/ui/Alignment$Horizontal;
/*     */     //   379: astore #8
/*     */     //   381: aload #7
/*     */     //   383: aload #8
/*     */     //   385: aload_1
/*     */     //   386: bipush #14
/*     */     //   388: iload #9
/*     */     //   390: iconst_3
/*     */     //   391: ishr
/*     */     //   392: iand
/*     */     //   393: bipush #112
/*     */     //   395: iload #9
/*     */     //   397: iconst_3
/*     */     //   398: ishr
/*     */     //   399: iand
/*     */     //   400: ior
/*     */     //   401: invokestatic columnMeasurePolicy : (Landroidx/compose/foundation/layout/Arrangement$Vertical;Landroidx/compose/ui/Alignment$Horizontal;Landroidx/compose/runtime/Composer;I)Landroidx/compose/ui/layout/MeasurePolicy;
/*     */     //   404: astore #11
/*     */     //   406: bipush #112
/*     */     //   408: iload #9
/*     */     //   410: iconst_3
/*     */     //   411: ishl
/*     */     //   412: iand
/*     */     //   413: istore #12
/*     */     //   415: nop
/*     */     //   416: iconst_0
/*     */     //   417: istore #13
/*     */     //   419: aload_1
/*     */     //   420: ldc -1323940314
/*     */     //   422: ldc 'CC(Layout)P(!1,2)79@3208L23,82@3359L411:Layout.kt#80mrfh'
/*     */     //   424: invokestatic sourceInformationMarkerStart : (Landroidx/compose/runtime/Composer;ILjava/lang/String;)V
/*     */     //   427: aload_1
/*     */     //   428: iconst_0
/*     */     //   429: invokestatic getCurrentCompositeKeyHash : (Landroidx/compose/runtime/Composer;I)I
/*     */     //   432: istore #14
/*     */     //   434: aload_1
/*     */     //   435: invokeinterface getCurrentCompositionLocalMap : ()Landroidx/compose/runtime/CompositionLocalMap;
/*     */     //   440: astore #15
/*     */     //   442: aload_1
/*     */     //   443: aload #6
/*     */     //   445: invokestatic materializeModifier : (Landroidx/compose/runtime/Composer;Landroidx/compose/ui/Modifier;)Landroidx/compose/ui/Modifier;
/*     */     //   448: astore #16
/*     */     //   450: getstatic androidx/compose/ui/node/ComposeUiNode.Companion : Landroidx/compose/ui/node/ComposeUiNode$Companion;
/*     */     //   453: invokevirtual getConstructor : ()Lkotlin/jvm/functions/Function0;
/*     */     //   456: astore #17
/*     */     //   458: bipush #6
/*     */     //   460: sipush #896
/*     */     //   463: iload #12
/*     */     //   465: bipush #6
/*     */     //   467: ishl
/*     */     //   468: iand
/*     */     //   469: ior
/*     */     //   470: istore #18
/*     */     //   472: nop
/*     */     //   473: iconst_0
/*     */     //   474: istore #19
/*     */     //   476: aload_1
/*     */     //   477: ldc -692256719
/*     */     //   479: ldc 'CC(ReusableComposeNode)P(1,2)376@14062L9:Composables.kt#9igjgp'
/*     */     //   481: invokestatic sourceInformationMarkerStart : (Landroidx/compose/runtime/Composer;ILjava/lang/String;)V
/*     */     //   484: aload_1
/*     */     //   485: invokeinterface getApplier : ()Landroidx/compose/runtime/Applier;
/*     */     //   490: instanceof androidx/compose/runtime/Applier
/*     */     //   493: ifne -> 499
/*     */     //   496: invokestatic invalidApplier : ()V
/*     */     //   499: aload_1
/*     */     //   500: invokeinterface startReusableNode : ()V
/*     */     //   505: aload_1
/*     */     //   506: invokeinterface getInserting : ()Z
/*     */     //   511: ifeq -> 525
/*     */     //   514: aload_1
/*     */     //   515: aload #17
/*     */     //   517: invokeinterface createNode : (Lkotlin/jvm/functions/Function0;)V
/*     */     //   522: goto -> 531
/*     */     //   525: aload_1
/*     */     //   526: invokeinterface useNode : ()V
/*     */     //   531: aload_1
/*     */     //   532: invokestatic constructor-impl : (Landroidx/compose/runtime/Composer;)Landroidx/compose/runtime/Composer;
/*     */     //   535: astore #20
/*     */     //   537: iconst_0
/*     */     //   538: istore #21
/*     */     //   540: aload #20
/*     */     //   542: aload #11
/*     */     //   544: getstatic androidx/compose/ui/node/ComposeUiNode.Companion : Landroidx/compose/ui/node/ComposeUiNode$Companion;
/*     */     //   547: invokevirtual getSetMeasurePolicy : ()Lkotlin/jvm/functions/Function2;
/*     */     //   550: invokestatic set-impl : (Landroidx/compose/runtime/Composer;Ljava/lang/Object;Lkotlin/jvm/functions/Function2;)V
/*     */     //   553: aload #20
/*     */     //   555: aload #15
/*     */     //   557: getstatic androidx/compose/ui/node/ComposeUiNode.Companion : Landroidx/compose/ui/node/ComposeUiNode$Companion;
/*     */     //   560: invokevirtual getSetResolvedCompositionLocals : ()Lkotlin/jvm/functions/Function2;
/*     */     //   563: invokestatic set-impl : (Landroidx/compose/runtime/Composer;Ljava/lang/Object;Lkotlin/jvm/functions/Function2;)V
/*     */     //   566: getstatic androidx/compose/ui/node/ComposeUiNode.Companion : Landroidx/compose/ui/node/ComposeUiNode$Companion;
/*     */     //   569: invokevirtual getSetCompositeKeyHash : ()Lkotlin/jvm/functions/Function2;
/*     */     //   572: astore #22
/*     */     //   574: iconst_0
/*     */     //   575: istore #23
/*     */     //   577: aload #20
/*     */     //   579: astore #24
/*     */     //   581: iconst_0
/*     */     //   582: istore #25
/*     */     //   584: aload #24
/*     */     //   586: invokeinterface getInserting : ()Z
/*     */     //   591: ifne -> 612
/*     */     //   594: aload #24
/*     */     //   596: invokeinterface rememberedValue : ()Ljava/lang/Object;
/*     */     //   601: iload #14
/*     */     //   603: invokestatic valueOf : (I)Ljava/lang/Integer;
/*     */     //   606: invokestatic areEqual : (Ljava/lang/Object;Ljava/lang/Object;)Z
/*     */     //   609: ifne -> 638
/*     */     //   612: aload #24
/*     */     //   614: iload #14
/*     */     //   616: invokestatic valueOf : (I)Ljava/lang/Integer;
/*     */     //   619: invokeinterface updateRememberedValue : (Ljava/lang/Object;)V
/*     */     //   624: aload #20
/*     */     //   626: iload #14
/*     */     //   628: invokestatic valueOf : (I)Ljava/lang/Integer;
/*     */     //   631: aload #22
/*     */     //   633: invokeinterface apply : (Ljava/lang/Object;Lkotlin/jvm/functions/Function2;)V
/*     */     //   638: nop
/*     */     //   639: nop
/*     */     //   640: nop
/*     */     //   641: aload #20
/*     */     //   643: aload #16
/*     */     //   645: getstatic androidx/compose/ui/node/ComposeUiNode.Companion : Landroidx/compose/ui/node/ComposeUiNode$Companion;
/*     */     //   648: invokevirtual getSetModifier : ()Lkotlin/jvm/functions/Function2;
/*     */     //   651: invokestatic set-impl : (Landroidx/compose/runtime/Composer;Ljava/lang/Object;Lkotlin/jvm/functions/Function2;)V
/*     */     //   654: nop
/*     */     //   655: nop
/*     */     //   656: aload_1
/*     */     //   657: bipush #14
/*     */     //   659: iload #18
/*     */     //   661: bipush #6
/*     */     //   663: ishr
/*     */     //   664: iand
/*     */     //   665: istore #26
/*     */     //   667: astore #27
/*     */     //   669: iconst_0
/*     */     //   670: istore #28
/*     */     //   672: aload #27
/*     */     //   674: ldc_w -384784025
/*     */     //   677: ldc_w 'C88@4444L9:Column.kt#2w3rfo'
/*     */     //   680: invokestatic sourceInformationMarkerStart : (Landroidx/compose/runtime/Composer;ILjava/lang/String;)V
/*     */     //   683: getstatic androidx/compose/foundation/layout/ColumnScopeInstance.INSTANCE : Landroidx/compose/foundation/layout/ColumnScopeInstance;
/*     */     //   686: aload #27
/*     */     //   688: bipush #6
/*     */     //   690: bipush #112
/*     */     //   692: iload #9
/*     */     //   694: bipush #6
/*     */     //   696: ishr
/*     */     //   697: iand
/*     */     //   698: ior
/*     */     //   699: istore #29
/*     */     //   701: astore #30
/*     */     //   703: checkcast androidx/compose/foundation/layout/ColumnScope
/*     */     //   706: astore #31
/*     */     //   708: iconst_0
/*     */     //   709: istore #32
/*     */     //   711: aload_0
/*     */     //   712: invokevirtual getFailure : ()Ljava/lang/String;
/*     */     //   715: lconst_0
/*     */     //   716: aload #30
/*     */     //   718: iconst_0
/*     */     //   719: iconst_2
/*     */     //   720: invokestatic Title-iJQMabo : (Ljava/lang/String;JLandroidx/compose/runtime/Composer;II)V
/*     */     //   723: ldc_w 'Retry'
/*     */     //   726: aload #30
/*     */     //   728: ldc_w -344589723
/*     */     //   731: invokeinterface startReplaceGroup : (I)V
/*     */     //   736: aload #30
/*     */     //   738: astore #33
/*     */     //   740: aload_1
/*     */     //   741: aload #4
/*     */     //   743: invokeinterface changed : (Ljava/lang/Object;)Z
/*     */     //   748: iload_3
/*     */     //   749: bipush #14
/*     */     //   751: iand
/*     */     //   752: iconst_4
/*     */     //   753: if_icmpne -> 760
/*     */     //   756: iconst_1
/*     */     //   757: goto -> 761
/*     */     //   760: iconst_0
/*     */     //   761: ior
/*     */     //   762: aload_1
/*     */     //   763: aload #5
/*     */     //   765: invokeinterface changedInstance : (Ljava/lang/Object;)Z
/*     */     //   770: ior
/*     */     //   771: istore #34
/*     */     //   773: nop
/*     */     //   774: iconst_0
/*     */     //   775: istore #35
/*     */     //   777: aload #33
/*     */     //   779: invokeinterface rememberedValue : ()Ljava/lang/Object;
/*     */     //   784: astore #36
/*     */     //   786: iconst_0
/*     */     //   787: istore #37
/*     */     //   789: iload #34
/*     */     //   791: ifne -> 805
/*     */     //   794: aload #36
/*     */     //   796: getstatic androidx/compose/runtime/Composer.Companion : Landroidx/compose/runtime/Composer$Companion;
/*     */     //   799: invokevirtual getEmpty : ()Ljava/lang/Object;
/*     */     //   802: if_acmpne -> 839
/*     */     //   805: astore #38
/*     */     //   807: iconst_0
/*     */     //   808: istore #39
/*     */     //   810: aload_0
/*     */     //   811: aload #5
/*     */     //   813: aload #4
/*     */     //   815: <illegal opcode> invoke : (Lcom/intellij/ml/llm/matterhorn/ej/ui/login/states/StepFail;Lkotlinx/coroutines/CoroutineScope;Landroidx/compose/runtime/MutableState;)Lkotlin/jvm/functions/Function0;
/*     */     //   820: aload #38
/*     */     //   822: swap
/*     */     //   823: astore #40
/*     */     //   825: aload #33
/*     */     //   827: aload #40
/*     */     //   829: invokeinterface updateRememberedValue : (Ljava/lang/Object;)V
/*     */     //   834: aload #40
/*     */     //   836: goto -> 841
/*     */     //   839: aload #36
/*     */     //   841: nop
/*     */     //   842: nop
/*     */     //   843: nop
/*     */     //   844: checkcast kotlin/jvm/functions/Function0
/*     */     //   847: astore #41
/*     */     //   849: aload #30
/*     */     //   851: invokeinterface endReplaceGroup : ()V
/*     */     //   856: aload #41
/*     */     //   858: aconst_null
/*     */     //   859: iconst_0
/*     */     //   860: aconst_null
/*     */     //   861: iconst_0
/*     */     //   862: aconst_null
/*     */     //   863: aconst_null
/*     */     //   864: aload #30
/*     */     //   866: bipush #6
/*     */     //   868: sipush #252
/*     */     //   871: invokestatic Link-kye4rC8 : (Ljava/lang/String;Lkotlin/jvm/functions/Function0;Landroidx/compose/ui/Modifier;ZLandroidx/compose/ui/text/TextStyle;ILandroidx/compose/foundation/interaction/MutableInteractionSource;Lorg/jetbrains/jewel/ui/component/styling/LinkStyle;Landroidx/compose/runtime/Composer;II)V
/*     */     //   874: aload #30
/*     */     //   876: ldc_w -344585110
/*     */     //   879: invokeinterface startReplaceGroup : (I)V
/*     */     //   884: aload #4
/*     */     //   886: invokestatic GrazieActivationStepFail$lambda$1 : (Landroidx/compose/runtime/MutableState;)Z
/*     */     //   889: ifeq -> 903
/*     */     //   892: aconst_null
/*     */     //   893: lconst_0
/*     */     //   894: aconst_null
/*     */     //   895: aload #30
/*     */     //   897: iconst_0
/*     */     //   898: bipush #7
/*     */     //   900: invokestatic JunieCircularProgressIndicator-3IgeMak : (Landroidx/compose/ui/Modifier;JLjava/lang/String;Landroidx/compose/runtime/Composer;II)V
/*     */     //   903: aload #30
/*     */     //   905: invokeinterface endReplaceGroup : ()V
/*     */     //   910: nop
/*     */     //   911: aload #27
/*     */     //   913: invokestatic sourceInformationMarkerEnd : (Landroidx/compose/runtime/Composer;)V
/*     */     //   916: aload_1
/*     */     //   917: invokeinterface endNode : ()V
/*     */     //   922: aload_1
/*     */     //   923: invokestatic sourceInformationMarkerEnd : (Landroidx/compose/runtime/Composer;)V
/*     */     //   926: nop
/*     */     //   927: aload_1
/*     */     //   928: invokestatic sourceInformationMarkerEnd : (Landroidx/compose/runtime/Composer;)V
/*     */     //   931: nop
/*     */     //   932: aload_1
/*     */     //   933: invokestatic sourceInformationMarkerEnd : (Landroidx/compose/runtime/Composer;)V
/*     */     //   936: nop
/*     */     //   937: invokestatic isTraceInProgress : ()Z
/*     */     //   940: ifeq -> 955
/*     */     //   943: invokestatic traceEventEnd : ()V
/*     */     //   946: goto -> 955
/*     */     //   949: aload_1
/*     */     //   950: invokeinterface skipToGroupEnd : ()V
/*     */     //   955: aload_1
/*     */     //   956: invokeinterface endRestartGroup : ()Landroidx/compose/runtime/ScopeUpdateScope;
/*     */     //   961: dup
/*     */     //   962: ifnull -> 980
/*     */     //   965: aload_0
/*     */     //   966: iload_2
/*     */     //   967: <illegal opcode> invoke : (Lcom/intellij/ml/llm/matterhorn/ej/ui/login/states/StepFail;I)Lkotlin/jvm/functions/Function2;
/*     */     //   972: invokeinterface updateScope : (Lkotlin/jvm/functions/Function2;)V
/*     */     //   977: goto -> 981
/*     */     //   980: pop
/*     */     //   981: return
/*     */     // Line number table:
/*     */     //   Java source line number -> byte code offset
/*     */     //   #22	-> 6
/*     */     //   #23	-> 99
/*     */     //   #47	-> 103
/*     */     //   #48	-> 115
/*     */     //   #49	-> 131
/*     */     //   #23	-> 134
/*     */     //   #49	-> 144
/*     */     //   #50	-> 146
/*     */     //   #51	-> 155
/*     */     //   #52	-> 160
/*     */     //   #48	-> 162
/*     */     //   #47	-> 163
/*     */     //   #47	-> 164
/*     */     //   #23	-> 165
/*     */     //   #24	-> 183
/*     */     //   #53	-> 192
/*     */     //   #54	-> 195
/*     */     //   #56	-> 196
/*     */     //   #57	-> 203
/*     */     //   #58	-> 215
/*     */     //   #59	-> 227
/*     */     //   #60	-> 238
/*     */     //   #61	-> 241
/*     */     //   #62	-> 241
/*     */     //   #63	-> 244
/*     */     //   #62	-> 247
/*     */     //   #61	-> 255
/*     */     //   #60	-> 266
/*     */     //   #64	-> 268
/*     */     //   #65	-> 277
/*     */     //   #66	-> 282
/*     */     //   #59	-> 284
/*     */     //   #58	-> 285
/*     */     //   #58	-> 286
/*     */     //   #57	-> 287
/*     */     //   #67	-> 300
/*     */     //   #53	-> 308
/*     */     //   #67	-> 313
/*     */     //   #24	-> 314
/*     */     //   #26	-> 316
/*     */     //   #27	-> 322
/*     */     //   #28	-> 333
/*     */     //   #68	-> 343
/*     */     //   #28	-> 349
/*     */     //   #25	-> 361
/*     */     //   #69	-> 370
/*     */     //   #70	-> 373
/*     */     //   #73	-> 381
/*     */     //   #74	-> 415
/*     */     //   #75	-> 424
/*     */     //   #76	-> 429
/*     */     //   #77	-> 435
/*     */     //   #78	-> 443
/*     */     //   #80	-> 450
/*     */     //   #79	-> 472
/*     */     //   #81	-> 481
/*     */     //   #82	-> 484
/*     */     //   #83	-> 500
/*     */     //   #84	-> 505
/*     */     //   #85	-> 515
/*     */     //   #87	-> 526
/*     */     //   #89	-> 531
/*     */     //   #90	-> 540
/*     */     //   #91	-> 553
/*     */     //   #93	-> 566
/*     */     //   #94	-> 577
/*     */     //   #95	-> 584
/*     */     //   #96	-> 612
/*     */     //   #97	-> 624
/*     */     //   #99	-> 638
/*     */     //   #94	-> 639
/*     */     //   #99	-> 640
/*     */     //   #100	-> 641
/*     */     //   #101	-> 654
/*     */     //   #89	-> 655
/*     */     //   #102	-> 656
/*     */     //   #103	-> 680
/*     */     //   #30	-> 711
/*     */     //   #32	-> 723
/*     */     //   #33	-> 773
/*     */     //   #104	-> 777
/*     */     //   #105	-> 789
/*     */     //   #106	-> 805
/*     */     //   #33	-> 810
/*     */     //   #106	-> 823
/*     */     //   #107	-> 825
/*     */     //   #108	-> 834
/*     */     //   #109	-> 839
/*     */     //   #105	-> 841
/*     */     //   #104	-> 842
/*     */     //   #104	-> 843
/*     */     //   #33	-> 844
/*     */     //   #31	-> 871
/*     */     //   #42	-> 884
/*     */     //   #44	-> 910
/*     */     //   #103	-> 911
/*     */     //   #102	-> 916
/*     */     //   #110	-> 917
/*     */     //   #81	-> 923
/*     */     //   #111	-> 926
/*     */     //   #75	-> 928
/*     */     //   #112	-> 931
/*     */     //   #69	-> 933
/*     */     //   #113	-> 936
/*     */     //   #45	-> 949
/*     */     // Local variable table:
/*     */     //   start	length	slot	name	descriptor
/*     */     //   134	10	11	$i$a$-cache-GrazieActivationStepFailKt$GrazieActivationStepFail$loading$2	I
/*     */     //   146	11	11	value$iv	Ljava/lang/Object;
/*     */     //   115	48	10	$i$a$-let-ComposerKt$cache$1$iv	I
/*     */     //   112	51	9	it$iv	Ljava/lang/Object;
/*     */     //   103	62	8	$i$f$cache	I
/*     */     //   100	65	6	$this$cache$iv	Landroidx/compose/runtime/Composer;
/*     */     //   100	65	7	invalid$iv	Z
/*     */     //   244	3	16	$i$a$-rememberCoroutineScope-EffectsKt$rememberCoroutineScope$1	I
/*     */     //   241	25	15	$i$a$-cache-EffectsKt$rememberCoroutineScope$wrapper$1$iv	I
/*     */     //   268	11	16	value$iv$iv	Ljava/lang/Object;
/*     */     //   227	58	14	$i$a$-let-ComposerKt$cache$1$iv$iv	I
/*     */     //   224	61	13	it$iv$iv	Ljava/lang/Object;
/*     */     //   215	72	12	$i$f$cache	I
/*     */     //   212	75	10	$this$cache$iv$iv	Landroidx/compose/runtime/Composer;
/*     */     //   212	75	11	invalid$iv$iv	Z
/*     */     //   187	127	8	$i$f$rememberCoroutineScope	I
/*     */     //   198	116	9	composer$iv	Landroidx/compose/runtime/Composer;
/*     */     //   300	14	18	wrapper$iv	Landroidx/compose/runtime/CompositionScopedCoroutineScopeCanceller;
/*     */     //   184	130	7	$changed$iv	I
/*     */     //   343	6	8	$i$f$getDp	I
/*     */     //   340	9	7	$this$dp$iv	I
/*     */     //   810	10	39	$i$a$-cache-GrazieActivationStepFailKt$GrazieActivationStepFail$1$1	I
/*     */     //   825	11	40	value$iv	Ljava/lang/Object;
/*     */     //   789	53	37	$i$a$-let-ComposerKt$cache$1$iv	I
/*     */     //   786	56	36	it$iv	Ljava/lang/Object;
/*     */     //   777	67	35	$i$f$cache	I
/*     */     //   774	70	33	$this$cache$iv	Landroidx/compose/runtime/Composer;
/*     */     //   774	70	34	invalid$iv	Z
/*     */     //   711	200	32	$i$a$-Column-GrazieActivationStepFailKt$GrazieActivationStepFail$1	I
/*     */     //   708	203	31	$this$GrazieActivationStepFail_u24lambda_u245	Landroidx/compose/foundation/layout/ColumnScope;
/*     */     //   708	203	30	$composer	Landroidx/compose/runtime/Composer;
/*     */     //   708	203	29	$changed	I
/*     */     //   672	244	28	$i$a$-Layout-ColumnKt$Column$1$iv	I
/*     */     //   669	247	27	$composer$iv	Landroidx/compose/runtime/Composer;
/*     */     //   669	247	26	$changed$iv	I
/*     */     //   584	55	25	$i$a$-with-Updater$set$1$iv$iv$iv	I
/*     */     //   581	58	24	$this$set_impl_u24lambda_u240$iv$iv$iv	Landroidx/compose/runtime/Composer;
/*     */     //   577	64	23	$i$f$set-impl	I
/*     */     //   574	67	22	block$iv$iv$iv	Lkotlin/jvm/functions/Function2;
/*     */     //   540	115	21	$i$a$-ReusableComposeNode-LayoutKt$Layout$1$iv$iv	I
/*     */     //   537	118	20	$this$Layout_u24lambda_u240$iv$iv	Landroidx/compose/runtime/Composer;
/*     */     //   476	451	19	$i$f$ReusableComposeNode	I
/*     */     //   473	454	17	factory$iv$iv$iv	Lkotlin/jvm/functions/Function0;
/*     */     //   473	454	18	$changed$iv$iv$iv	I
/*     */     //   419	513	13	$i$f$Layout	I
/*     */     //   434	498	14	compositeKeyHash$iv$iv	I
/*     */     //   442	490	15	localMap$iv$iv	Landroidx/compose/runtime/CompositionLocalMap;
/*     */     //   450	482	16	materialized$iv$iv	Landroidx/compose/ui/Modifier;
/*     */     //   416	516	12	$changed$iv$iv	I
/*     */     //   365	572	10	$i$f$Column	I
/*     */     //   406	531	11	measurePolicy$iv	Landroidx/compose/ui/layout/MeasurePolicy;
/*     */     //   362	575	6	modifier$iv	Landroidx/compose/ui/Modifier;
/*     */     //   362	575	7	verticalArrangement$iv	Landroidx/compose/foundation/layout/Arrangement$Vertical;
/*     */     //   381	556	8	horizontalAlignment$iv	Landroidx/compose/ui/Alignment$Horizontal;
/*     */     //   362	575	9	$changed$iv	I
/*     */     //   180	766	4	loading$delegate	Landroidx/compose/runtime/MutableState;
/*     */     //   316	630	5	scope	Lkotlinx/coroutines/CoroutineScope;
/*     */     //   17	965	3	$dirty	I
/*     */     //   0	982	0	state	Lcom/intellij/ml/llm/matterhorn/ej/ui/login/states/StepFail;
/*     */     //   0	982	1	$composer	Landroidx/compose/runtime/Composer;
/* 115 */     //   0	982	2	$changed	I } private static final void GrazieActivationStepFail$lambda$2(MutableState $loading$delegate, boolean <set-?>) { MutableState mutableState = $loading$delegate; Object object1 = null, object2 = null; Object value$iv = Boolean.valueOf(<set-?>); int $i$f$setValue = 0; mutableState.setValue(value$iv); }
/*     */ 
/*     */   
/*     */   private static final Unit GrazieActivationStepFail$lambda$5$lambda$4$lambda$3(StepFail $state, CoroutineScope $scope, MutableState<Boolean> $loading$delegate) {
/*     */     GrazieActivationStepFail$lambda$2($loading$delegate, true);
/*     */     $state.getOnRetry().invoke();
/*     */     BuildersKt.launch$default($scope, null, null, new GrazieActivationStepFailKt$GrazieActivationStepFail$1$1$1$1($loading$delegate, null), 3, null);
/*     */     return Unit.INSTANCE;
/*     */   }
/*     */   
/*     */   private static final Unit GrazieActivationStepFail$lambda$6(StepFail $state, int $$changed, Composer $composer, int $force) {
/*     */     GrazieActivationStepFail($state, $composer, RecomposeScopeImplKt.updateChangedFlags($$changed | 0x1));
/*     */     return Unit.INSTANCE;
/*     */   }
/*     */   
/*     */   @DebugMetadata(f = "GrazieActivationStepFail.kt", l = {37}, i = {}, s = {}, n = {}, m = "invokeSuspend", c = "com.intellij.ml.llm.matterhorn.ej.ui.login.components.GrazieActivationStepFailKt$GrazieActivationStepFail$1$1$1$1")
/*     */   @Metadata(mv = {2, 1, 0}, k = 3, xi = 48, d1 = {"\000\n\n\000\n\002\020\002\n\002\030\002\020\000\032\0020\001*\0020\002H\n"}, d2 = {"<anonymous>", "", "Lkotlinx/coroutines/CoroutineScope;"})
/*     */   static final class GrazieActivationStepFailKt$GrazieActivationStepFail$1$1$1$1 extends SuspendLambda implements Function2<CoroutineScope, Continuation<? super Unit>, Object> {
/*     */     int label;
/*     */     
/*     */     GrazieActivationStepFailKt$GrazieActivationStepFail$1$1$1$1(MutableState<Boolean> $loading$delegate, Continuation $completion) {
/*     */       super(2, $completion);
/*     */     }
/*     */     
/*     */     public final Object invokeSuspend(Object $result) {
/*     */       Object object = IntrinsicsKt.getCOROUTINE_SUSPENDED();
/*     */       switch (this.label) {
/*     */         case 0:
/*     */           ResultKt.throwOnFailure(SYNTHETIC_LOCAL_VARIABLE_1);
/*     */           this.label = 1;
/*     */           if (DelayKt.delay(500L, (Continuation)this) == object)
/*     */             return object; 
/*     */           DelayKt.delay(500L, (Continuation)this);
/*     */           GrazieActivationStepFailKt.GrazieActivationStepFail$lambda$2(this.$loading$delegate, false);
/*     */           return Unit.INSTANCE;
/*     */         case 1:
/*     */           ResultKt.throwOnFailure(SYNTHETIC_LOCAL_VARIABLE_1);
/*     */           GrazieActivationStepFailKt.GrazieActivationStepFail$lambda$2(this.$loading$delegate, false);
/*     */           return Unit.INSTANCE;
/*     */       } 
/*     */       throw new IllegalStateException("call to 'resume' before 'invoke' with coroutine");
/*     */     }
/*     */     
/*     */     public final Continuation<Unit> create(Object value, Continuation<? super GrazieActivationStepFailKt$GrazieActivationStepFail$1$1$1$1> $completion) {
/*     */       return (Continuation<Unit>)new GrazieActivationStepFailKt$GrazieActivationStepFail$1$1$1$1(this.$loading$delegate, $completion);
/*     */     }
/*     */     
/*     */     public final Object invoke(CoroutineScope p1, Continuation<?> p2) {
/*     */       return ((GrazieActivationStepFailKt$GrazieActivationStepFail$1$1$1$1)create(p1, p2)).invokeSuspend(Unit.INSTANCE);
/*     */     }
/*     */   }
/*     */ }


/* Location:              C:\Users\yuzum\Downloads\ej-release-243.132.63.zip!\ej\lib\ej-243.132.63.jar!\com\intellij\ml\llm\matterhorn\e\\ui\login\components\GrazieActivationStepFailKt.class
 * Java compiler version: 17 (61.0)
 * JD-Core Version:       1.1.3
 */