/*    */ package ai.grazie.utils.cache;
/*    */ import ai.grazie.utils.mpp.MutexKt;
/*    */ import java.util.Map;
/*    */ import java.util.Set;
/*    */ import kotlin.Unit;
/*    */ import kotlin.coroutines.Continuation;
/*    */ import kotlin.jvm.functions.Function1;
/*    */ 
/*    */ @Metadata(mv = {1, 7, 0}, k = 1, xi = 48, d1 = {"\000.\n\000\n\002\030\002\n\000\n\002\b\003\n\002\030\002\n\000\n\002\020\002\n\002\b\006\n\002\030\002\n\002\030\002\n\002\020\000\n\002\b\006*\002\000\003\b\n\030\0002\016\022\004\022\0028\000\022\004\022\0028\0010\001J\016\020\007\032\0020\bH@¢\006\002\020\tJ\030\020\n\032\004\030\0018\0012\006\020\013\032\0028\000H@¢\006\002\020\fJ4\020\r\032\0028\0012\006\020\013\032\0028\0002\034\020\016\032\030\b\001\022\n\022\b\022\004\022\0028\0010\020\022\006\022\004\030\0010\0210\017H@¢\006\002\020\022J\026\020\023\032\0020\b2\006\020\013\032\0028\000H@¢\006\002\020\fJ\036\020\024\032\0020\b2\006\020\013\032\0028\0002\006\020\025\032\0028\001H@¢\006\002\020\026R\034\020\002\032\016\022\004\022\0028\000\022\004\022\0028\0010\003X\004¢\006\004\n\002\020\004R\016\020\005\032\0020\006X\004¢\006\002\n\000¨\006\027"}, d2 = {"ai/grazie/utils/cache/StandardSuspendableCacheKt$standardSuspendableCache$1", "Lai/grazie/utils/cache/SuspendableCache;", "data", "ai/grazie/utils/cache/StandardSuspendableCacheKt$standardSuspendableCache$1$data$1", "Lai/grazie/utils/cache/StandardSuspendableCacheKt$standardSuspendableCache$1$data$1;", "mutex", "Lkotlinx/coroutines/sync/Mutex;", "clear", "", "(Lkotlin/coroutines/Continuation;)Ljava/lang/Object;", "get", "key", "(Ljava/lang/Object;Lkotlin/coroutines/Continuation;)Ljava/lang/Object;", "getOrPut", "loader", "Lkotlin/Function1;", "Lkotlin/coroutines/Continuation;", "", "(Ljava/lang/Object;Lkotlin/jvm/functions/Function1;Lkotlin/coroutines/Continuation;)Ljava/lang/Object;", "invalidate", "put", "value", "(Ljava/lang/Object;Ljava/lang/Object;Lkotlin/coroutines/Continuation;)Ljava/lang/Object;", "utils-common"})
/*    */ public final class StandardSuspendableCacheKt$standardSuspendableCache$1 implements SuspendableCache<Key, Value> {
/* 11 */   private final Mutex mutex = MutexKt.Mutex(false); private final StandardSuspendableCacheKt$standardSuspendableCache$1$data$1 data;
/*    */   
/* 13 */   StandardSuspendableCacheKt$standardSuspendableCache$1(int $total, Integer $maxMillis) { int i = Math.max(16, $total / 4); this.data = new StandardSuspendableCacheKt$standardSuspendableCache$1$data$1($total, i); } @Metadata(mv = {1, 7, 0}, k = 1, xi = 48, d1 = {"\000\037\n\000\n\002\030\002\n\002\030\002\n\002\030\002\n\000\n\002\020\013\n\000\n\002\020&\n\000*\001\000\b\n\030\0002*\022\004\022\0028\000\022\n\022\b\022\004\022\0028\0010\0020\001j\024\022\004\022\0028\000\022\n\022\b\022\004\022\0028\0010\002`\003J\"\020\004\032\0020\0052\030\020\006\032\024\022\004\022\0028\000\022\n\022\b\022\004\022\0028\0010\0020\007H\024¨\006\b"}, d2 = {"ai/grazie/utils/cache/StandardSuspendableCacheKt$standardSuspendableCache$1$data$1", "Ljava/util/LinkedHashMap;", "Lai/grazie/utils/cache/CacheValue$WithTime;", "Lkotlin/collections/LinkedHashMap;", "removeEldestEntry", "", "eldest", "", "utils-common"}) public static final class StandardSuspendableCacheKt$standardSuspendableCache$1$data$1 extends LinkedHashMap<Key, CacheValue.WithTime<Value>> { StandardSuspendableCacheKt$standardSuspendableCache$1$data$1(int $total, int $super_call_param$1) { super($super_call_param$1, 0.75F, false); }
/*    */      protected boolean removeEldestEntry(Map.Entry eldest) {
/* 15 */       Intrinsics.checkNotNullParameter(eldest, "eldest"); return (size() > this.$total);
/*    */     } }
/*    */ 
/*    */   
/*    */   public Object get(Object key, Continuation $completion) {
/* 20 */     return MutexKt.withReentrantLock$default(this.mutex, null, new StandardSuspendableCacheKt$standardSuspendableCache$1$get$2((Key)key, null), $completion, 1, null); } @DebugMetadata(f = "StandardSuspendableCache.kt", l = {}, i = {}, s = {}, n = {}, m = "invokeSuspend", c = "ai.grazie.utils.cache.StandardSuspendableCacheKt$standardSuspendableCache$1$get$2") @Metadata(mv = {1, 7, 0}, k = 3, xi = 48, d1 = {"\000\b\n\002\b\003\n\002\020\000\020\000\032\004\030\001H\001\"\b\b\000\020\002*\0020\003\"\b\b\001\020\001*\0020\003H@"}, d2 = {"<anonymous>", "Value", "Key", ""}) static final class StandardSuspendableCacheKt$standardSuspendableCache$1$get$2 extends SuspendLambda implements Function1<Continuation<? super Value>, Object> { int label; StandardSuspendableCacheKt$standardSuspendableCache$1$get$2(Object $key, Continuation $completion) { super(1, $completion); } public final Object invokeSuspend(Object $result) { IntrinsicsKt.getCOROUTINE_SUSPENDED(); switch (this.label) { case 0: ResultKt.throwOnFailure(SYNTHETIC_LOCAL_VARIABLE_1);
/* 21 */           StandardSuspendableCacheKt$standardSuspendableCache$1.this.data.get(this.$key); return (StandardSuspendableCacheKt$standardSuspendableCache$1.this.data.get(this.$key) != null) ? StandardSuspendableCacheKt$standardSuspendableCache$1.this.data.get(this.$key).getValue() : null; }  throw new IllegalStateException("call to 'resume' before 'invoke' with coroutine"); }
/*    */     public final Continuation<Unit> create(Continuation<? super StandardSuspendableCacheKt$standardSuspendableCache$1$get$2> $completion) { return (Continuation<Unit>)new StandardSuspendableCacheKt$standardSuspendableCache$1$get$2(this.$key, $completion); }
/*    */     public final Object invoke(Continuation<?> p1) { return ((StandardSuspendableCacheKt$standardSuspendableCache$1$get$2)create(p1)).invokeSuspend(Unit.INSTANCE); } }
/*    */   @DebugMetadata(f = "StandardSuspendableCache.kt", l = {}, i = {}, s = {}, n = {}, m = "invokeSuspend", c = "ai.grazie.utils.cache.StandardSuspendableCacheKt$standardSuspendableCache$1$put$2") @Metadata(mv = {1, 7, 0}, k = 3, xi = 48, d1 = {"\000\016\n\000\n\002\020\002\n\000\n\002\020\000\n\000\020\000\032\0020\001\"\b\b\000\020\002*\0020\003\"\b\b\001\020\004*\0020\003H@"}, d2 = {"<anonymous>", "", "Key", "", "Value"}) static final class StandardSuspendableCacheKt$standardSuspendableCache$1$put$2 extends SuspendLambda implements Function1<Continuation<? super Unit>, Object> {
/*    */     int label; StandardSuspendableCacheKt$standardSuspendableCache$1$put$2(Object $key, Object $value, Integer $maxMillis, Continuation $completion) { super(1, $completion); } public final Object invokeSuspend(Object $result) { IntrinsicsKt.getCOROUTINE_SUSPENDED(); switch (this.label) { case 0: ResultKt.throwOnFailure(SYNTHETIC_LOCAL_VARIABLE_1); StandardSuspendableCacheKt$standardSuspendableCache$1.this.data.remove(this.$key); StandardSuspendableCacheKt$standardSuspendableCache$1.this.data.put(this.$key, new CacheValue.WithTime.Default(this.$value, 0L, 2, null)); if (this.$maxMillis != null) { long now = Time.INSTANCE.epochMillis$utils_common(); long border = now - this.$maxMillis.intValue(); Iterator<Map.Entry> iterator = StandardSuspendableCacheKt$standardSuspendableCache$1.this.data.entrySet().iterator(); while (iterator.hasNext() && ((CacheValue.WithTime)((Map.Entry)iterator.next()).getValue()).getEpoch() < border) iterator.remove();  }  return Unit.INSTANCE; }  throw new IllegalStateException("call to 'resume' before 'invoke' with coroutine"); } public final Continuation<Unit> create(Continuation<? super StandardSuspendableCacheKt$standardSuspendableCache$1$put$2> $completion) { return (Continuation<Unit>)new StandardSuspendableCacheKt$standardSuspendableCache$1$put$2(this.$key, this.$value, this.$maxMillis, $completion); } public final Object invoke(Continuation<?> p1) { return ((StandardSuspendableCacheKt$standardSuspendableCache$1$put$2)create(p1)).invokeSuspend(Unit.INSTANCE); }
/* 26 */   } public Object put(Object key, Object value, Continuation $completion) { if (MutexKt.withReentrantLock$default(this.mutex, null, new StandardSuspendableCacheKt$standardSuspendableCache$1$put$2((Key)key, (Value)value, this.$maxMillis, null), $completion, 1, null) == IntrinsicsKt.getCOROUTINE_SUSPENDED()) return MutexKt.withReentrantLock$default(this.mutex, null, new StandardSuspendableCacheKt$standardSuspendableCache$1$put$2((Key)key, (Value)value, this.$maxMillis, null), $completion, 1, null);  MutexKt.withReentrantLock$default(this.mutex, null, new StandardSuspendableCacheKt$standardSuspendableCache$1$put$2((Key)key, (Value)value, this.$maxMillis, null), $completion, 1, null);
/*    */ 
/*    */ 
/*    */ 
/*    */ 
/*    */ 
/*    */ 
/*    */ 
/*    */ 
/*    */ 
/*    */ 
/*    */ 
/*    */ 
/*    */ 
/*    */ 
/*    */ 
/*    */ 
/*    */ 
/*    */     
/* 45 */     return Unit.INSTANCE; }
/*    */   
/*    */   public Object invalidate(Object key, Continuation $completion) {
/* 48 */     if (MutexKt.withReentrantLock$default(this.mutex, null, new StandardSuspendableCacheKt$standardSuspendableCache$1$invalidate$2((Key)key, null), $completion, 1, null) == IntrinsicsKt.getCOROUTINE_SUSPENDED()) return MutexKt.withReentrantLock$default(this.mutex, null, new StandardSuspendableCacheKt$standardSuspendableCache$1$invalidate$2((Key)key, null), $completion, 1, null);  MutexKt.withReentrantLock$default(this.mutex, null, new StandardSuspendableCacheKt$standardSuspendableCache$1$invalidate$2((Key)key, null), $completion, 1, null);
/*    */ 
/*    */     
/* 51 */     return Unit.INSTANCE; } @DebugMetadata(f = "StandardSuspendableCache.kt", l = {}, i = {}, s = {}, n = {}, m = "invokeSuspend", c = "ai.grazie.utils.cache.StandardSuspendableCacheKt$standardSuspendableCache$1$invalidate$2") @Metadata(mv = {1, 7, 0}, k = 3, xi = 48, d1 = {"\000\016\n\000\n\002\030\002\n\002\b\002\n\002\020\000\020\000\032\n\022\004\022\002H\002\030\0010\001\"\b\b\000\020\003*\0020\004\"\b\b\001\020\002*\0020\004H@"}, d2 = {"<anonymous>", "Lai/grazie/utils/cache/CacheValue$WithTime;", "Value", "Key", ""}) static final class StandardSuspendableCacheKt$standardSuspendableCache$1$invalidate$2 extends SuspendLambda implements Function1<Continuation<? super CacheValue.WithTime<Value>>, Object> {
/*    */     int label; StandardSuspendableCacheKt$standardSuspendableCache$1$invalidate$2(Object $key, Continuation $completion) { super(1, $completion); } public final Object invokeSuspend(Object $result) { IntrinsicsKt.getCOROUTINE_SUSPENDED(); switch (this.label) { case 0: ResultKt.throwOnFailure(SYNTHETIC_LOCAL_VARIABLE_1); return StandardSuspendableCacheKt$standardSuspendableCache$1.this.data.remove(this.$key); }  throw new IllegalStateException("call to 'resume' before 'invoke' with coroutine"); } public final Continuation<Unit> create(Continuation<? super StandardSuspendableCacheKt$standardSuspendableCache$1$invalidate$2> $completion) { return (Continuation<Unit>)new StandardSuspendableCacheKt$standardSuspendableCache$1$invalidate$2(this.$key, $completion); }
/*    */     public final Object invoke(Continuation<?> p1) { return ((StandardSuspendableCacheKt$standardSuspendableCache$1$invalidate$2)create(p1)).invokeSuspend(Unit.INSTANCE); } }
/* 54 */   public Object clear(Continuation $completion) { if (MutexKt.withReentrantLock$default(this.mutex, null, new StandardSuspendableCacheKt$standardSuspendableCache$1$clear$2(null), $completion, 1, null) == IntrinsicsKt.getCOROUTINE_SUSPENDED()) return MutexKt.withReentrantLock$default(this.mutex, null, new StandardSuspendableCacheKt$standardSuspendableCache$1$clear$2(null), $completion, 1, null);  MutexKt.withReentrantLock$default(this.mutex, null, new StandardSuspendableCacheKt$standardSuspendableCache$1$clear$2(null), $completion, 1, null);
/*    */ 
/*    */     
/* 57 */     return Unit.INSTANCE; } @DebugMetadata(f = "StandardSuspendableCache.kt", l = {}, i = {}, s = {}, n = {}, m = "invokeSuspend", c = "ai.grazie.utils.cache.StandardSuspendableCacheKt$standardSuspendableCache$1$clear$2") @Metadata(mv = {1, 7, 0}, k = 3, xi = 48, d1 = {"\000\016\n\000\n\002\020\002\n\000\n\002\020\000\n\000\020\000\032\0020\001\"\b\b\000\020\002*\0020\003\"\b\b\001\020\004*\0020\003H@"}, d2 = {"<anonymous>", "", "Key", "", "Value"}) static final class StandardSuspendableCacheKt$standardSuspendableCache$1$clear$2 extends SuspendLambda implements Function1<Continuation<? super Unit>, Object> {
/*    */     int label; StandardSuspendableCacheKt$standardSuspendableCache$1$clear$2(Continuation $completion) { super(1, $completion); } public final Object invokeSuspend(Object $result) { IntrinsicsKt.getCOROUTINE_SUSPENDED(); switch (this.label) { case 0: ResultKt.throwOnFailure(SYNTHETIC_LOCAL_VARIABLE_1); StandardSuspendableCacheKt$standardSuspendableCache$1.this.data.clear(); return Unit.INSTANCE; }  throw new IllegalStateException("call to 'resume' before 'invoke' with coroutine"); } public final Continuation<Unit> create(Continuation<? super StandardSuspendableCacheKt$standardSuspendableCache$1$clear$2> $completion) { return (Continuation<Unit>)new StandardSuspendableCacheKt$standardSuspendableCache$1$clear$2($completion); }
/*    */     public final Object invoke(Continuation<?> p1) { return ((StandardSuspendableCacheKt$standardSuspendableCache$1$clear$2)create(p1)).invokeSuspend(Unit.INSTANCE); } }
/* 60 */   public Object getOrPut(Object key, Function1<? super Continuation<? super Value>, ? extends Object> loader, Continuation $completion) { return MutexKt.withReentrantLock$default(this.mutex, null, new StandardSuspendableCacheKt$standardSuspendableCache$1$getOrPut$2((Key)key, loader, null), $completion, 1, null); }
/*    */ 
/*    */   
/*    */   @DebugMetadata(f = "StandardSuspendableCache.kt", l = {61, 63, 63, 65}, i = {}, s = {}, n = {}, m = "invokeSuspend", c = "ai.grazie.utils.cache.StandardSuspendableCacheKt$standardSuspendableCache$1$getOrPut$2")
/*    */   @Metadata(mv = {1, 7, 0}, k = 3, xi = 48, d1 = {"\000\b\n\002\b\003\n\002\020\000\020\000\032\002H\001\"\b\b\000\020\002*\0020\003\"\b\b\001\020\001*\0020\003H@"}, d2 = {"<anonymous>", "Value", "Key", ""})
/*    */   static final class StandardSuspendableCacheKt$standardSuspendableCache$1$getOrPut$2 extends SuspendLambda implements Function1<Continuation<? super Value>, Object> {
/*    */     Object L$0;
/*    */     Object L$1;
/*    */     int label;
/*    */     
/*    */     StandardSuspendableCacheKt$standardSuspendableCache$1$getOrPut$2(Object $key, Function1<Continuation<? super Value>, Object> $loader, Continuation $completion) {
/*    */       super(1, $completion);
/*    */     }
/*    */     
/*    */     public final Object invokeSuspend(Object $result) {
/*    */       // Byte code:
/*    */       //   0: invokestatic getCOROUTINE_SUSPENDED : ()Ljava/lang/Object;
/*    */       //   3: astore #6
/*    */       //   5: aload_0
/*    */       //   6: getfield label : I
/*    */       //   9: tableswitch default -> 235, 0 -> 44, 1 -> 77, 2 -> 133, 3 -> 190, 4 -> 225
/*    */       //   44: aload_1
/*    */       //   45: invokestatic throwOnFailure : (Ljava/lang/Object;)V
/*    */       //   48: aload_0
/*    */       //   49: getfield this$0 : Lai/grazie/utils/cache/StandardSuspendableCacheKt$standardSuspendableCache$1;
/*    */       //   52: aload_0
/*    */       //   53: getfield $key : Ljava/lang/Object;
/*    */       //   56: aload_0
/*    */       //   57: checkcast kotlin/coroutines/Continuation
/*    */       //   60: aload_0
/*    */       //   61: iconst_1
/*    */       //   62: putfield label : I
/*    */       //   65: invokevirtual get : (Ljava/lang/Object;Lkotlin/coroutines/Continuation;)Ljava/lang/Object;
/*    */       //   68: dup
/*    */       //   69: aload #6
/*    */       //   71: if_acmpne -> 82
/*    */       //   74: aload #6
/*    */       //   76: areturn
/*    */       //   77: aload_1
/*    */       //   78: invokestatic throwOnFailure : (Ljava/lang/Object;)V
/*    */       //   81: aload_1
/*    */       //   82: astore_2
/*    */       //   83: aload_2
/*    */       //   84: ifnonnull -> 196
/*    */       //   87: aload_0
/*    */       //   88: getfield this$0 : Lai/grazie/utils/cache/StandardSuspendableCacheKt$standardSuspendableCache$1;
/*    */       //   91: aload_0
/*    */       //   92: getfield $key : Ljava/lang/Object;
/*    */       //   95: astore #4
/*    */       //   97: astore_3
/*    */       //   98: aload_0
/*    */       //   99: getfield $loader : Lkotlin/jvm/functions/Function1;
/*    */       //   102: aload_0
/*    */       //   103: aload_0
/*    */       //   104: aload_3
/*    */       //   105: putfield L$0 : Ljava/lang/Object;
/*    */       //   108: aload_0
/*    */       //   109: aload #4
/*    */       //   111: putfield L$1 : Ljava/lang/Object;
/*    */       //   114: aload_0
/*    */       //   115: iconst_2
/*    */       //   116: putfield label : I
/*    */       //   119: invokeinterface invoke : (Ljava/lang/Object;)Ljava/lang/Object;
/*    */       //   124: dup
/*    */       //   125: aload #6
/*    */       //   127: if_acmpne -> 152
/*    */       //   130: aload #6
/*    */       //   132: areturn
/*    */       //   133: aload_0
/*    */       //   134: getfield L$1 : Ljava/lang/Object;
/*    */       //   137: astore #4
/*    */       //   139: aload_0
/*    */       //   140: getfield L$0 : Ljava/lang/Object;
/*    */       //   143: checkcast ai/grazie/utils/cache/StandardSuspendableCacheKt$standardSuspendableCache$1
/*    */       //   146: astore_3
/*    */       //   147: aload_1
/*    */       //   148: invokestatic throwOnFailure : (Ljava/lang/Object;)V
/*    */       //   151: aload_1
/*    */       //   152: astore #5
/*    */       //   154: aload_3
/*    */       //   155: aload #4
/*    */       //   157: aload #5
/*    */       //   159: aload_0
/*    */       //   160: checkcast kotlin/coroutines/Continuation
/*    */       //   163: aload_0
/*    */       //   164: aconst_null
/*    */       //   165: putfield L$0 : Ljava/lang/Object;
/*    */       //   168: aload_0
/*    */       //   169: aconst_null
/*    */       //   170: putfield L$1 : Ljava/lang/Object;
/*    */       //   173: aload_0
/*    */       //   174: iconst_3
/*    */       //   175: putfield label : I
/*    */       //   178: invokevirtual put : (Ljava/lang/Object;Ljava/lang/Object;Lkotlin/coroutines/Continuation;)Ljava/lang/Object;
/*    */       //   181: dup
/*    */       //   182: aload #6
/*    */       //   184: if_acmpne -> 195
/*    */       //   187: aload #6
/*    */       //   189: areturn
/*    */       //   190: aload_1
/*    */       //   191: invokestatic throwOnFailure : (Ljava/lang/Object;)V
/*    */       //   194: aload_1
/*    */       //   195: pop
/*    */       //   196: aload_0
/*    */       //   197: getfield this$0 : Lai/grazie/utils/cache/StandardSuspendableCacheKt$standardSuspendableCache$1;
/*    */       //   200: aload_0
/*    */       //   201: getfield $key : Ljava/lang/Object;
/*    */       //   204: aload_0
/*    */       //   205: checkcast kotlin/coroutines/Continuation
/*    */       //   208: aload_0
/*    */       //   209: iconst_4
/*    */       //   210: putfield label : I
/*    */       //   213: invokevirtual get : (Ljava/lang/Object;Lkotlin/coroutines/Continuation;)Ljava/lang/Object;
/*    */       //   216: dup
/*    */       //   217: aload #6
/*    */       //   219: if_acmpne -> 230
/*    */       //   222: aload #6
/*    */       //   224: areturn
/*    */       //   225: aload_1
/*    */       //   226: invokestatic throwOnFailure : (Ljava/lang/Object;)V
/*    */       //   229: aload_1
/*    */       //   230: dup
/*    */       //   231: invokestatic checkNotNull : (Ljava/lang/Object;)V
/*    */       //   234: areturn
/*    */       //   235: new java/lang/IllegalStateException
/*    */       //   238: dup
/*    */       //   239: ldc 'call to 'resume' before 'invoke' with coroutine'
/*    */       //   241: invokespecial <init> : (Ljava/lang/String;)V
/*    */       //   244: athrow
/*    */       // Line number table:
/*    */       //   Java source line number -> byte code offset
/*    */       //   #60	-> 3
/*    */       //   #61	-> 48
/*    */       //   #60	-> 74
/*    */       //   #62	-> 83
/*    */       //   #63	-> 87
/*    */       //   #60	-> 130
/*    */       //   #63	-> 152
/*    */       //   #60	-> 187
/*    */       //   #65	-> 195
/*    */       //   #60	-> 222
/*    */       //   #65	-> 230
/*    */       //   #60	-> 235
/*    */       // Local variable table:
/*    */       //   start	length	slot	name	descriptor
/*    */       //   83	4	2	value	Ljava/lang/Object;
/*    */       //   0	245	0	this	Lai/grazie/utils/cache/StandardSuspendableCacheKt$standardSuspendableCache$1$getOrPut$2;
/*    */       //   48	187	1	$result	Ljava/lang/Object;
/*    */     }
/*    */     
/*    */     public final Continuation<Unit> create(Continuation<? super StandardSuspendableCacheKt$standardSuspendableCache$1$getOrPut$2> $completion) {
/*    */       return (Continuation<Unit>)new StandardSuspendableCacheKt$standardSuspendableCache$1$getOrPut$2(this.$key, this.$loader, $completion);
/*    */     }
/*    */     
/*    */     public final Object invoke(Continuation<?> p1) {
/*    */       return ((StandardSuspendableCacheKt$standardSuspendableCache$1$getOrPut$2)create(p1)).invokeSuspend(Unit.INSTANCE);
/*    */     }
/*    */   }
/*    */ }


/* Location:              C:\Users\yuzum\Downloads\ej-release-243.132.63.zip!\ej\li\\utils-common-jvm-0.4.32.jar!\ai\grazi\\utils\cache\StandardSuspendableCacheKt$standardSuspendableCache$1.class
 * Java compiler version: 17 (61.0)
 * JD-Core Version:       1.1.3
 */