/*    */ package com.intellij.ml.llm.matterhorn.ej.core.tasks;
/*    */ 
/*    */ import kotlin.Metadata;
/*    */ import kotlin.enums.EnumEntries;
/*    */ import kotlin.enums.EnumEntriesKt;
/*    */ import kotlin.jvm.internal.DefaultConstructorMarker;
/*    */ import kotlin.jvm.internal.SourceDebugExtension;
/*    */ import org.jetbrains.annotations.NotNull;
/*    */ 
/*    */ 
/*    */ 
/*    */ 
/*    */ 
/*    */ 
/*    */ 
/*    */ 
/*    */ 
/*    */ 
/*    */ 
/*    */ 
/*    */ 
/*    */ 
/*    */ @Metadata(mv = {2, 1, 0}, k = 1, xi = 48, d1 = {"\000\022\n\002\030\002\n\002\020\020\n\000\n\002\020\f\n\002\b\n\b\002\030\000 \f2\b\022\004\022\0020\0000\001:\001\fB\021\b\002\022\006\020\002\032\0020\003¢\006\004\b\004\020\005R\021\020\002\032\0020\003¢\006\b\n\000\032\004\b\006\020\007j\002\b\bj\002\b\tj\002\b\nj\002\b\013¨\006\r"}, d2 = {"Lcom/intellij/ml/llm/matterhorn/ej/core/tasks/Status;", "", "symbol", "", "<init>", "(Ljava/lang/String;IC)V", "getSymbol", "()C", "DONE", "ERROR", "IN_PROGRESS", "PENDING", "Companion", "ej-core"})
/*    */ public enum Status
/*    */ {
/*    */   @NotNull
/*    */   public static final Companion Companion;
/*    */   private final char symbol;
/*    */   
/*    */   Status(char symbol) {
/*    */     this.symbol = symbol;
/*    */   }
/*    */   
/* 34 */   DONE('✓'),
/* 35 */   ERROR('!'),
/* 36 */   IN_PROGRESS('*'),
/* 37 */   PENDING(' '); static { Companion = new Companion(null); }
/*    */   
/*    */   public final char getSymbol() {
/*    */     return this.symbol;
/*    */   }
/*    */   @NotNull
/*    */   public static EnumEntries<Status> getEntries() {
/* 44 */     return $ENTRIES;
/*    */   }
/*    */   
/*    */   @Metadata(mv = {2, 1, 0}, k = 1, xi = 48, d1 = {"\000\030\n\002\030\002\n\002\020\000\n\002\b\003\n\002\030\002\n\000\n\002\020\f\n\000\b\003\030\0002\0020\001B\t\b\002¢\006\004\b\002\020\003J\016\020\004\032\0020\0052\006\020\006\032\0020\007¨\006\b"}, d2 = {"Lcom/intellij/ml/llm/matterhorn/ej/core/tasks/Status$Companion;", "", "<init>", "()V", "fromSymbol", "Lcom/intellij/ml/llm/matterhorn/ej/core/tasks/Status;", "symbol", "", "ej-core"})
/*    */   @SourceDebugExtension({"SMAP\nPlan.kt\nKotlin\n*S Kotlin\n*F\n+ 1 Plan.kt\ncom/intellij/ml/llm/matterhorn/ej/core/tasks/Status$Companion\n+ 2 fake.kt\nkotlin/jvm/internal/FakeKt\n*L\n1#1,44:1\n1#2:45\n*E\n"})
/*    */   public static final class Companion {
/*    */     private Companion() {}
/*    */     
/*    */     @NotNull
/*    */     public final Status fromSymbol(char symbol) {
/*    */       // Byte code:
/*    */       //   0: invokestatic getEntries : ()Lkotlin/enums/EnumEntries;
/*    */       //   3: checkcast java/lang/Iterable
/*    */       //   6: astore_2
/*    */       //   7: aload_2
/*    */       //   8: invokeinterface iterator : ()Ljava/util/Iterator;
/*    */       //   13: astore_3
/*    */       //   14: aload_3
/*    */       //   15: invokeinterface hasNext : ()Z
/*    */       //   20: ifeq -> 63
/*    */       //   23: aload_3
/*    */       //   24: invokeinterface next : ()Ljava/lang/Object;
/*    */       //   29: astore #4
/*    */       //   31: aload #4
/*    */       //   33: checkcast com/intellij/ml/llm/matterhorn/ej/core/tasks/Status
/*    */       //   36: astore #5
/*    */       //   38: iconst_0
/*    */       //   39: istore #6
/*    */       //   41: aload #5
/*    */       //   43: invokevirtual getSymbol : ()C
/*    */       //   46: iload_1
/*    */       //   47: if_icmpne -> 54
/*    */       //   50: iconst_1
/*    */       //   51: goto -> 55
/*    */       //   54: iconst_0
/*    */       //   55: ifeq -> 14
/*    */       //   58: aload #4
/*    */       //   60: goto -> 64
/*    */       //   63: aconst_null
/*    */       //   64: checkcast com/intellij/ml/llm/matterhorn/ej/core/tasks/Status
/*    */       //   67: dup
/*    */       //   68: ifnonnull -> 75
/*    */       //   71: pop
/*    */       //   72: getstatic com/intellij/ml/llm/matterhorn/ej/core/tasks/Status.PENDING : Lcom/intellij/ml/llm/matterhorn/ej/core/tasks/Status;
/*    */       //   75: areturn
/*    */       // Line number table:
/*    */       //   Java source line number -> byte code offset
/*    */       //   #41	-> 0
/*    */       //   #45	-> 38
/*    */       //   #41	-> 41
/*    */       //   #41	-> 55
/*    */       //   #41	-> 64
/*    */       // Local variable table:
/*    */       //   start	length	slot	name	descriptor
/*    */       //   41	14	6	$i$a$-find-Status$Companion$fromSymbol$1	I
/*    */       //   38	17	5	it	Lcom/intellij/ml/llm/matterhorn/ej/core/tasks/Status;
/*    */       //   0	76	0	this	Lcom/intellij/ml/llm/matterhorn/ej/core/tasks/Status$Companion;
/*    */       //   0	76	1	symbol	C
/*    */     }
/*    */   }
/*    */ }


/* Location:              C:\Users\yuzum\Downloads\ej-release-243.132.63.zip!\ej\lib\ej-243.132.63.jar!\com\intellij\ml\llm\matterhorn\ej\core\tasks\Status.class
 * Java compiler version: 17 (61.0)
 * JD-Core Version:       1.1.3
 */