/*     */ package androidx.compose.runtime.snapshots;@Metadata(mv = {1, 9, 0}, k = 1, xi = 48, d1 = {"\000v\n\002\030\002\n\002\b\002\n\002\030\002\n\002\020%\n\002\b\002\n\002\020$\n\002\b\004\n\002\020#\n\002\020'\n\002\b\003\n\002\030\002\n\002\b\006\n\002\020\b\n\002\b\003\n\002\030\002\n\002\b\006\n\002\020\037\n\002\b\003\n\002\020\013\n\000\n\002\030\002\n\002\020&\n\002\b\004\n\002\020\002\n\002\b\030\n\002\020\016\n\000\n\002\030\002\n\000\n\002\030\002\n\002\b\003\b\007\030\000*\004\b\000\020\001*\004\b\001\020\0022\0020\0032\016\022\004\022\002H\001\022\004\022\002H\0020\004:\001NB\005¢\006\002\020\005J1\020&\032\0020'2\036\020(\032\032\022\020\022\016\022\004\022\0028\000\022\004\022\0028\0010*\022\004\022\0020'0)H\bø\001\000¢\006\002\b+J1\020,\032\0020'2\036\020(\032\032\022\020\022\016\022\004\022\0028\000\022\004\022\0028\0010*\022\004\022\0020'0)H\bø\001\000¢\006\002\b-J\b\020.\032\0020/H\026J\025\0200\032\0020'2\006\0201\032\0028\000H\026¢\006\002\0202J\025\0203\032\0020'2\006\0204\032\0028\001H\026¢\006\002\0202J\030\0205\032\004\030\0018\0012\006\0201\032\0028\000H\002¢\006\002\0206J\b\0207\032\0020'H\026J4\0208\032\002H9\"\004\b\002\02092\036\020:\032\032\022\020\022\016\022\004\022\0028\000\022\004\022\0028\0010\004\022\004\022\002H90)H\b¢\006\002\020;J\020\020<\032\0020/2\006\0204\032\0020\021H\026J\037\020=\032\004\030\0018\0012\006\0201\032\0028\0002\006\0204\032\0028\001H\026¢\006\002\020>J\036\020?\032\0020/2\024\020@\032\020\022\006\b\001\022\0028\000\022\004\022\0028\0010\007H\026J\027\020A\032\004\030\0018\0012\006\0201\032\0028\000H\026¢\006\002\0206J1\020B\032\0020'2\036\020(\032\032\022\020\022\016\022\004\022\0028\000\022\004\022\0028\0010\r\022\004\022\0020'0)H\bø\001\000¢\006\002\bCJ\027\020D\032\0020'2\006\0204\032\0028\001H\000¢\006\004\bE\0202J\022\020F\032\016\022\004\022\0028\000\022\004\022\0028\0010\007J\b\020G\032\0020HH\026J5\020I\032\0020/2*\020:\032&\022\020\022\016\022\004\022\0028\000\022\004\022\0028\0010J\022\020\022\016\022\004\022\0028\000\022\004\022\0028\0010J0)H\bJ9\020K\032\002H9\"\004\b\002\02092#\020:\032\037\022\020\022\016\022\004\022\0028\000\022\004\022\0028\0010\034\022\004\022\002H90)¢\006\002\bLH\b¢\006\002\020;J9\020M\032\002H9\"\004\b\002\02092#\020:\032\037\022\020\022\016\022\004\022\0028\000\022\004\022\0028\0010\034\022\004\022\002H90)¢\006\002\bLH\b¢\006\002\020;R&\020\006\032\016\022\004\022\0028\000\022\004\022\0028\0010\0078AX\004¢\006\f\022\004\b\b\020\005\032\004\b\t\020\nR&\020\013\032\024\022\020\022\016\022\004\022\0028\000\022\004\022\0028\0010\r0\fX\004¢\006\b\n\000\032\004\b\016\020\017R\036\020\022\032\0020\0212\006\020\020\032\0020\021@RX\016¢\006\b\n\000\032\004\b\023\020\024R\032\020\025\032\b\022\004\022\0028\0000\fX\004¢\006\b\n\000\032\004\b\026\020\017R\024\020\027\032\0020\0308@X\004¢\006\006\032\004\b\031\020\032R&\020\033\032\016\022\004\022\0028\000\022\004\022\0028\0010\0348@X\004¢\006\f\022\004\b\035\020\005\032\004\b\036\020\037R\024\020 \032\0020\0308VX\004¢\006\006\032\004\b!\020\032R\032\020\"\032\b\022\004\022\0028\0010#X\004¢\006\b\n\000\032\004\b$\020%\002\007\n\005\b20\001¨\006O"}, d2 = {"Landroidx/compose/runtime/snapshots/SnapshotStateMap;", "K", "V", "Landroidx/compose/runtime/snapshots/StateObject;", "", "()V", "debuggerDisplayValue", "", "getDebuggerDisplayValue$annotations", "getDebuggerDisplayValue", "()Ljava/util/Map;", "entries", "", "", "getEntries", "()Ljava/util/Set;", "<set-?>", "Landroidx/compose/runtime/snapshots/StateRecord;", "firstStateRecord", "getFirstStateRecord", "()Landroidx/compose/runtime/snapshots/StateRecord;", "keys", "getKeys", "modification", "", "getModification$runtime", "()I", "readable", "Landroidx/compose/runtime/snapshots/SnapshotStateMap$StateMapStateRecord;", "getReadable$runtime$annotations", "getReadable$runtime", "()Landroidx/compose/runtime/snapshots/SnapshotStateMap$StateMapStateRecord;", "size", "getSize", "values", "", "getValues", "()Ljava/util/Collection;", "all", "", "predicate", "Lkotlin/Function1;", "", "all$runtime", "any", "any$runtime", "clear", "", "containsKey", "key", "(Ljava/lang/Object;)Z", "containsValue", "value", "get", "(Ljava/lang/Object;)Ljava/lang/Object;", "isEmpty", "mutate", "R", "block", "(Lkotlin/jvm/functions/Function1;)Ljava/lang/Object;", "prependStateRecord", "put", "(Ljava/lang/Object;Ljava/lang/Object;)Ljava/lang/Object;", "putAll", "from", "remove", "removeIf", "removeIf$runtime", "removeValue", "removeValue$runtime", "toMap", "toString", "", "update", "Landroidx/compose/runtime/external/kotlinx/collections/immutable/PersistentMap;", "withCurrent", "Lkotlin/ExtensionFunctionType;", "writable", "StateMapStateRecord", "runtime"})
/*     */ @Stable
/*     */ @SourceDebugExtension({"SMAP\nSnapshotStateMap.kt\nKotlin\n*S Kotlin\n*F\n+ 1 SnapshotStateMap.kt\nandroidx/compose/runtime/snapshots/SnapshotStateMap\n+ 2 Snapshot.kt\nandroidx/compose/runtime/snapshots/SnapshotKt\n+ 3 SynchronizedObject.jvm.kt\nandroidx/compose/runtime/ActualJvm_jvmKt__SynchronizedObject_jvmKt\n+ 4 _Collections.kt\nkotlin/collections/CollectionsKt___CollectionsKt\n+ 5 fake.kt\nkotlin/jvm/internal/FakeKt\n*L\n1#1,373:1\n167#1:375\n134#1:376\n168#1,2:378\n138#1:380\n170#1,3:387\n175#1:393\n141#1,5:394\n146#1:400\n134#1:401\n147#1,7:403\n138#1:410\n154#1,6:416\n162#1,3:425\n141#1,5:428\n146#1:434\n134#1:435\n147#1,7:437\n138#1:444\n154#1,6:450\n162#1,3:459\n141#1,5:462\n146#1:468\n134#1:469\n147#1,7:471\n138#1:478\n154#1,6:484\n162#1,3:493\n141#1,5:499\n146#1:505\n134#1:506\n147#1,7:508\n138#1:515\n154#1,6:521\n162#1,3:530\n134#1:533\n134#1:546\n138#1:548\n134#1:559\n138#1:561\n2421#2:374\n2421#2:377\n2314#2,2:381\n1844#2:383\n2316#2,2:385\n2318#2,3:390\n2421#2:402\n2314#2,2:411\n1844#2:413\n2316#2,2:414\n2318#2,3:422\n2421#2:436\n2314#2,2:445\n1844#2:447\n2316#2,2:448\n2318#2,3:456\n2421#2:470\n2314#2,2:479\n1844#2:481\n2316#2,2:482\n2318#2,3:490\n2421#2:507\n2314#2,2:516\n1844#2:518\n2316#2,2:519\n2318#2,3:527\n2421#2:534\n2421#2:535\n2314#2,2:536\n1844#2:538\n2316#2,5:540\n2421#2:547\n2314#2,2:549\n1844#2:551\n2316#2,2:553\n2318#2,3:556\n2421#2:560\n2314#2,2:562\n1844#2:564\n2316#2,2:566\n2318#2,3:569\n26#3:384\n26#3:399\n26#3:433\n26#3:467\n26#3:504\n26#3:539\n26#3:545\n26#3:552\n26#3:555\n26#3:565\n26#3:568\n288#4,2:496\n1#5:498\n*S KotlinDebug\n*F\n+ 1 SnapshotStateMap.kt\nandroidx/compose/runtime/snapshots/SnapshotStateMap\n*L\n82#1:375\n82#1:376\n82#1:378,2\n82#1:380\n82#1:387,3\n82#1:393\n83#1:394,5\n83#1:400\n83#1:401\n83#1:403,7\n83#1:410\n83#1:416,6\n83#1:425,3\n84#1:428,5\n84#1:434\n84#1:435\n84#1:437,7\n84#1:444\n84#1:450,6\n84#1:459,3\n85#1:462,5\n85#1:468\n85#1:469\n85#1:471,7\n85#1:478\n85#1:484,6\n85#1:493,3\n98#1:499,5\n98#1:505\n98#1:506\n98#1:508,7\n98#1:515\n98#1:521,6\n98#1:530,3\n130#1:533\n146#1:546\n153#1:548\n167#1:559\n169#1:561\n78#1:374\n82#1:377\n82#1:381,2\n82#1:383\n82#1:385,2\n82#1:390,3\n83#1:402\n83#1:411,2\n83#1:413\n83#1:414,2\n83#1:422,3\n84#1:436\n84#1:445,2\n84#1:447\n84#1:448,2\n84#1:456,3\n85#1:470\n85#1:479,2\n85#1:481\n85#1:482,2\n85#1:490,3\n98#1:507\n98#1:516,2\n98#1:518\n98#1:519,2\n98#1:527,3\n130#1:534\n134#1:535\n138#1:536,2\n138#1:538\n138#1:540,5\n146#1:547\n153#1:549,2\n153#1:551\n153#1:553,2\n153#1:556,3\n167#1:560\n169#1:562,2\n169#1:564\n169#1:566,2\n169#1:569,3\n82#1:384\n83#1:399\n84#1:433\n85#1:467\n98#1:504\n138#1:539\n145#1:545\n153#1:552\n154#1:555\n169#1:565\n170#1:568\n90#1:496,2\n*E\n"})
/*     */ public final class SnapshotStateMap<K, V> implements StateObject, Map<K, V>, KMutableMap { @NotNull
/*     */   private StateRecord firstStateRecord;
/*     */   @NotNull
/*     */   private final Set<Map.Entry<K, V>> entries;
/*     */   @NotNull
/*     */   private final Set<K> keys;
/*     */   @NotNull
/*     */   private final Collection<V> values;
/*     */   public static final int $stable;
/*     */   
/*     */   @NotNull
/*     */   public StateRecord getFirstStateRecord() {
/*     */     return this.firstStateRecord;
/*     */   }
/*     */   
/*     */   public void prependStateRecord(@NotNull StateRecord value) {
/*     */     Intrinsics.checkNotNullParameter(value, "value");
/*     */     this.firstStateRecord = value;
/*     */   }
/*     */   
/*     */   @NotNull
/*     */   public final Map<K, V> toMap() {
/*     */     return (Map<K, V>)getReadable$runtime().getMap$runtime();
/*     */   }
/*     */   
/*     */   public int getSize() {
/*     */     return getReadable$runtime().getMap$runtime().size();
/*     */   }
/*     */   
/*     */   public boolean containsKey(Object key) {
/*     */     return getReadable$runtime().getMap$runtime().containsKey(key);
/*     */   }
/*     */   
/*  37 */   public SnapshotStateMap() { PersistentMap<?, ?> persistentMap = ExtensionsKt.persistentHashMapOf(); SnapshotStateMap snapshotStateMap = this; int $i$a$-let-SnapshotStateMap$firstStateRecord$1 = 0;
/*  38 */     StateMapStateRecord<Object, Object> stateMapStateRecord1 = new StateMapStateRecord<>(persistentMap), it = stateMapStateRecord1; int $i$a$-also-SnapshotStateMap$firstStateRecord$1$1 = 0;
/*  39 */     if (Snapshot.Companion.isInSnapshot()) {
/*  40 */       StateMapStateRecord<Object, Object> stateMapStateRecord2 = new StateMapStateRecord<>(persistentMap), stateMapStateRecord3 = stateMapStateRecord2, stateMapStateRecord4 = it; int $i$a$-also-SnapshotStateMap$firstStateRecord$1$1$1 = 0;
/*  41 */       stateMapStateRecord3.setSnapshotId$runtime(1);
/*  42 */       stateMapStateRecord4.setNext$runtime(stateMapStateRecord2);
/*     */     } 
/*     */ 
/*     */ 
/*     */ 
/*     */ 
/*     */ 
/*     */ 
/*     */ 
/*     */ 
/*     */ 
/*     */ 
/*     */ 
/*     */ 
/*     */ 
/*     */ 
/*     */     
/*     */     snapshotStateMap.firstStateRecord = stateMapStateRecord1;
/*     */ 
/*     */ 
/*     */ 
/*     */ 
/*     */ 
/*     */ 
/*     */ 
/*     */ 
/*     */ 
/*     */ 
/*     */ 
/*     */ 
/*     */ 
/*     */     
/*  74 */     this.entries = new SnapshotMapEntrySet<>(this);
/*  75 */     this.keys = new SnapshotMapKeySet<>(this);
/*  76 */     this.values = new SnapshotMapValueSet<>(this); } public boolean containsValue(Object value) { return getReadable$runtime().getMap$runtime().containsValue(value); } @Nullable public V get(Object key) { return (V)getReadable$runtime().getMap$runtime().get(key); } @NotNull public Collection<V> getValues() { return this.values; }
/*     */   public boolean isEmpty() { return getReadable$runtime().getMap$runtime().isEmpty(); }
/*  78 */   @NotNull public Set<Map.Entry<K, V>> getEntries() { return this.entries; } @NotNull public Set<K> getKeys() { return this.keys; } @NotNull public String toString() { Intrinsics.checkNotNull(getFirstStateRecord(), "null cannot be cast to non-null type androidx.compose.runtime.snapshots.SnapshotStateMap.StateMapStateRecord<K of androidx.compose.runtime.snapshots.SnapshotStateMap, V of androidx.compose.runtime.snapshots.SnapshotStateMap>"); StateRecord $this$withCurrent$iv = getFirstStateRecord(); int $i$f$withCurrent = 0;
/*     */ 
/*     */ 
/*     */ 
/*     */ 
/*     */ 
/*     */ 
/*     */ 
/*     */ 
/*     */ 
/*     */ 
/*     */ 
/*     */ 
/*     */ 
/*     */ 
/*     */ 
/*     */ 
/*     */ 
/*     */ 
/*     */ 
/*     */ 
/*     */ 
/*     */ 
/*     */ 
/*     */ 
/*     */ 
/*     */ 
/*     */ 
/*     */ 
/*     */ 
/*     */ 
/*     */ 
/*     */ 
/*     */ 
/*     */ 
/*     */ 
/*     */ 
/*     */ 
/*     */ 
/*     */ 
/*     */ 
/*     */ 
/*     */ 
/*     */ 
/*     */ 
/*     */ 
/*     */ 
/*     */ 
/*     */ 
/*     */ 
/*     */ 
/*     */ 
/*     */ 
/*     */ 
/*     */ 
/*     */ 
/*     */ 
/*     */ 
/*     */ 
/*     */ 
/*     */ 
/*     */ 
/*     */ 
/*     */ 
/*     */ 
/*     */ 
/*     */ 
/*     */ 
/*     */ 
/*     */ 
/*     */ 
/*     */ 
/*     */ 
/*     */ 
/*     */ 
/*     */ 
/*     */ 
/*     */ 
/*     */ 
/*     */ 
/*     */ 
/*     */ 
/*     */ 
/*     */ 
/*     */ 
/*     */ 
/*     */ 
/*     */ 
/*     */ 
/*     */ 
/*     */ 
/*     */ 
/*     */ 
/*     */ 
/*     */ 
/*     */ 
/*     */ 
/*     */ 
/*     */ 
/*     */ 
/*     */ 
/*     */ 
/*     */ 
/*     */ 
/*     */ 
/*     */ 
/*     */ 
/*     */ 
/*     */ 
/*     */ 
/*     */ 
/*     */ 
/*     */ 
/*     */ 
/*     */ 
/*     */ 
/*     */ 
/*     */ 
/*     */ 
/*     */ 
/*     */ 
/*     */ 
/*     */ 
/*     */ 
/*     */ 
/*     */ 
/*     */ 
/*     */ 
/*     */ 
/*     */ 
/*     */ 
/*     */ 
/*     */ 
/*     */ 
/*     */ 
/*     */ 
/*     */ 
/*     */ 
/*     */ 
/*     */ 
/*     */ 
/*     */ 
/*     */ 
/*     */ 
/*     */ 
/*     */ 
/*     */ 
/*     */ 
/*     */ 
/*     */ 
/*     */ 
/*     */ 
/*     */ 
/*     */ 
/*     */ 
/*     */ 
/*     */ 
/*     */ 
/*     */ 
/*     */ 
/*     */ 
/*     */ 
/*     */ 
/*     */ 
/*     */ 
/*     */ 
/*     */ 
/*     */ 
/*     */ 
/*     */ 
/*     */ 
/*     */ 
/*     */ 
/*     */ 
/*     */ 
/*     */ 
/*     */ 
/*     */ 
/*     */ 
/*     */ 
/*     */ 
/*     */ 
/*     */ 
/*     */ 
/*     */ 
/*     */ 
/*     */ 
/*     */ 
/*     */ 
/*     */ 
/*     */ 
/*     */ 
/*     */ 
/*     */ 
/*     */ 
/*     */ 
/*     */ 
/*     */ 
/*     */ 
/*     */ 
/*     */ 
/*     */ 
/*     */ 
/*     */ 
/*     */ 
/*     */ 
/*     */ 
/*     */ 
/*     */ 
/*     */ 
/*     */ 
/*     */ 
/*     */ 
/*     */ 
/*     */ 
/*     */ 
/*     */ 
/*     */ 
/*     */ 
/*     */ 
/*     */ 
/*     */ 
/*     */ 
/*     */ 
/*     */ 
/*     */ 
/*     */ 
/*     */ 
/*     */ 
/*     */ 
/*     */ 
/*     */ 
/*     */ 
/*     */ 
/*     */ 
/*     */ 
/*     */ 
/*     */ 
/*     */ 
/*     */ 
/*     */ 
/*     */ 
/*     */ 
/*     */ 
/*     */ 
/*     */ 
/*     */ 
/*     */ 
/*     */ 
/*     */ 
/*     */ 
/*     */ 
/*     */ 
/*     */ 
/*     */ 
/*     */ 
/*     */ 
/*     */ 
/*     */ 
/*     */ 
/*     */ 
/*     */ 
/*     */ 
/*     */ 
/*     */ 
/*     */ 
/*     */ 
/*     */ 
/*     */ 
/*     */ 
/*     */ 
/*     */ 
/*     */ 
/*     */ 
/*     */ 
/*     */ 
/*     */ 
/*     */ 
/*     */ 
/*     */ 
/*     */ 
/*     */ 
/*     */ 
/*     */ 
/*     */ 
/*     */ 
/*     */ 
/*     */ 
/*     */ 
/*     */ 
/*     */ 
/*     */ 
/*     */ 
/*     */ 
/*     */ 
/*     */     
/* 374 */     StateMapStateRecord it = (StateMapStateRecord)SnapshotKt.<StateRecord>current($this$withCurrent$iv); int $i$a$-withCurrent-SnapshotStateMap$toString$1 = 0; return "SnapshotStateMap(value=" + it.getMap$runtime() + ")@" + hashCode(); } public void clear() { SnapshotStateMap this_$iv = this; int $i$f$update = 0;
/* 375 */     SnapshotStateMap this_$iv$iv = this_$iv; int $i$f$withCurrent = 0;
/* 376 */     Intrinsics.checkNotNull(this_$iv$iv.getFirstStateRecord(), "null cannot be cast to non-null type androidx.compose.runtime.snapshots.SnapshotStateMap.StateMapStateRecord<K of androidx.compose.runtime.snapshots.SnapshotStateMap, V of androidx.compose.runtime.snapshots.SnapshotStateMap>"); StateRecord $this$withCurrent$iv$iv$iv = this_$iv$iv.getFirstStateRecord(); int i = 0;
/* 377 */     StateMapStateRecord $this$update_u24lambda_u2418$iv = (StateMapStateRecord)SnapshotKt.<StateRecord>current($this$withCurrent$iv$iv$iv); int $i$a$-withCurrent-SnapshotStateMap$update$1$iv = 0;
/* 378 */     PersistentMap it = $this$update_u24lambda_u2418$iv.getMap$runtime(); int $i$a$-update-SnapshotStateMap$clear$1 = 0; PersistentMap newMap$iv = ExtensionsKt.persistentHashMapOf();
/* 379 */     if (newMap$iv != $this$update_u24lambda_u2418$iv.getMap$runtime()) { SnapshotStateMap snapshotStateMap = this_$iv; int $i$f$writable = 0;
/* 380 */       Intrinsics.checkNotNull(snapshotStateMap.getFirstStateRecord(), "null cannot be cast to non-null type androidx.compose.runtime.snapshots.SnapshotStateMap.StateMapStateRecord<K of androidx.compose.runtime.snapshots.SnapshotStateMap, V of androidx.compose.runtime.snapshots.SnapshotStateMap>"); StateRecord $this$writable$iv$iv$iv = snapshotStateMap.getFirstStateRecord(); int j = 0;
/* 381 */       Object snapshot$iv$iv$iv = null; snapshot$iv$iv$iv = SnapshotKt.getSnapshotInitializer();
/* 382 */       int $i$f$sync = 0;
/* 383 */       SynchronizedObject lock$iv$iv$iv$iv$iv = SnapshotKt.getLock(); int $i$f$synchronized = 0;
/* 384 */       synchronized (lock$iv$iv$iv$iv$iv) { int $i$a$-sync-SnapshotKt$writable$3$iv$iv$iv = 0;
/* 385 */         snapshot$iv$iv$iv = Snapshot.Companion.getCurrent();
/* 386 */         StateMapStateRecord $this$update_u24lambda_u2418_u24lambda_u2417$iv = (StateMapStateRecord)SnapshotKt.<StateRecord>writableRecord($this$writable$iv$iv$iv, snapshotStateMap, (Snapshot)snapshot$iv$iv$iv); int $i$a$-writable-SnapshotStateMap$update$1$1$iv = 0;
/* 387 */         SynchronizedObject lock$iv$iv = SnapshotStateMapKt.access$getSync$p(); int k = 0; synchronized (lock$iv$iv)
/* 388 */         { int $i$a$-synchronized-SnapshotStateMap$update$1$1$1$iv = 0; $this$update_u24lambda_u2418_u24lambda_u2417$iv.setMap$runtime(newMap$iv);
/* 389 */           int n = $this$update_u24lambda_u2418_u24lambda_u2417$iv.getModification$runtime(); $this$update_u24lambda_u2418_u24lambda_u2417$iv.setModification$runtime(n + 1); $i$a$-update-SnapshotStateMap$clear$1 = n; }  int m = $i$a$-update-SnapshotStateMap$clear$1; }
/* 390 */        $i$f$sync = m; int it$iv$iv$iv = $i$f$sync, $i$a$-also-SnapshotKt$writable$4$iv$iv$iv = 0;
/* 391 */       SnapshotKt.notifyWrite((Snapshot)snapshot$iv$iv$iv, snapshotStateMap); }
/*     */      } @Nullable public V put(Object key, Object value) { SnapshotStateMap this_$iv = this;
/*     */     int $i$f$mutate = 0;
/* 394 */     Object result$iv = null;
/*     */     while (true) {
/* 396 */       Object oldMap$iv = null;
/* 397 */       int currentModification$iv = 0;
/* 398 */       SynchronizedObject lock$iv$iv = SnapshotStateMapKt.access$getSync$p(); int $i$f$synchronized = 0;
/* 399 */       synchronized (lock$iv$iv) { int $i$a$-synchronized-SnapshotStateMap$mutate$1$iv = 0;
/* 400 */         SnapshotStateMap this_$iv$iv = this_$iv; int $i$f$withCurrent = 0;
/* 401 */         Intrinsics.checkNotNull(this_$iv$iv.getFirstStateRecord(), "null cannot be cast to non-null type androidx.compose.runtime.snapshots.SnapshotStateMap.StateMapStateRecord<K of androidx.compose.runtime.snapshots.SnapshotStateMap, V of androidx.compose.runtime.snapshots.SnapshotStateMap>"); StateRecord $this$withCurrent$iv$iv$iv = this_$iv$iv.getFirstStateRecord(); int i = 0;
/* 402 */         StateMapStateRecord $this$mutate_u24lambda_u2413_u24lambda_u2412$iv = (StateMapStateRecord)SnapshotKt.<StateRecord>current($this$withCurrent$iv$iv$iv); int $i$a$-withCurrent-SnapshotStateMap$mutate$1$current$1$iv = 0; StateMapStateRecord current$iv = $this$mutate_u24lambda_u2413_u24lambda_u2412$iv;
/* 403 */         oldMap$iv = current$iv.getMap$runtime();
/* 404 */         currentModification$iv = current$iv.getModification$runtime();
/* 405 */         Unit unit = Unit.INSTANCE; }
/* 406 */        Intrinsics.checkNotNull(oldMap$iv); PersistentMap.Builder builder$iv = oldMap$iv.builder();
/* 407 */       Map<Object, Object> it = (Map)builder$iv; int $i$a$-mutate-SnapshotStateMap$put$1 = 0; result$iv = it.put(key, value);
/* 408 */       PersistentMap newMap$iv = builder$iv.build();
/* 409 */       if (!Intrinsics.areEqual(newMap$iv, oldMap$iv)) { SnapshotStateMap this_$iv$iv = this_$iv; int $i$f$writable = 0;
/* 410 */         Intrinsics.checkNotNull(this_$iv$iv.getFirstStateRecord(), "null cannot be cast to non-null type androidx.compose.runtime.snapshots.SnapshotStateMap.StateMapStateRecord<K of androidx.compose.runtime.snapshots.SnapshotStateMap, V of androidx.compose.runtime.snapshots.SnapshotStateMap>"); StateRecord $this$writable$iv$iv$iv = this_$iv$iv.getFirstStateRecord(); int i = 0;
/* 411 */         Object snapshot$iv$iv$iv = null; snapshot$iv$iv$iv = SnapshotKt.getSnapshotInitializer();
/* 412 */         int $i$f$sync = 0;
/* 413 */         SynchronizedObject lock$iv$iv$iv$iv$iv = SnapshotKt.getLock(); int j = 0;
/*     */ 
/*     */         
/*     */         SynchronizedObject synchronizedObject1 = lock$iv$iv$iv$iv$iv;
/*     */ 
/*     */         
/*     */         /* monitor enter ClassFileLocalVariableReferenceExpression{type=ObjectType{androidx/compose/runtime/SynchronizedObject}, name=null} */ }
/*     */ 
/*     */ 
/*     */       
/*     */       break;
/*     */     } 
/*     */ 
/*     */     
/* 427 */     return (V)result$iv; } public void putAll(@NotNull Map from) { Intrinsics.checkNotNullParameter(from, "from"); SnapshotStateMap this_$iv = this; int $i$f$mutate = 0;
/* 428 */     Object result$iv = null;
/*     */     while (true) {
/* 430 */       Object oldMap$iv = null;
/* 431 */       int currentModification$iv = 0;
/* 432 */       SynchronizedObject lock$iv$iv = SnapshotStateMapKt.access$getSync$p(); int $i$f$synchronized = 0;
/* 433 */       synchronized (lock$iv$iv) { int $i$a$-synchronized-SnapshotStateMap$mutate$1$iv = 0;
/* 434 */         SnapshotStateMap this_$iv$iv = this_$iv; int $i$f$withCurrent = 0;
/* 435 */         Intrinsics.checkNotNull(this_$iv$iv.getFirstStateRecord(), "null cannot be cast to non-null type androidx.compose.runtime.snapshots.SnapshotStateMap.StateMapStateRecord<K of androidx.compose.runtime.snapshots.SnapshotStateMap, V of androidx.compose.runtime.snapshots.SnapshotStateMap>"); StateRecord $this$withCurrent$iv$iv$iv = this_$iv$iv.getFirstStateRecord(); int i = 0;
/* 436 */         StateMapStateRecord $this$mutate_u24lambda_u2413_u24lambda_u2412$iv = (StateMapStateRecord)SnapshotKt.<StateRecord>current($this$withCurrent$iv$iv$iv); int $i$a$-withCurrent-SnapshotStateMap$mutate$1$current$1$iv = 0; StateMapStateRecord current$iv = $this$mutate_u24lambda_u2413_u24lambda_u2412$iv;
/* 437 */         oldMap$iv = current$iv.getMap$runtime();
/* 438 */         currentModification$iv = current$iv.getModification$runtime();
/* 439 */         Unit unit = Unit.INSTANCE; }
/* 440 */        Intrinsics.checkNotNull(oldMap$iv); PersistentMap.Builder builder$iv = oldMap$iv.builder();
/* 441 */       Map it = (Map)builder$iv; int $i$a$-mutate-SnapshotStateMap$putAll$1 = 0; it.putAll(from); result$iv = Unit.INSTANCE;
/* 442 */       PersistentMap newMap$iv = builder$iv.build();
/* 443 */       if (!Intrinsics.areEqual(newMap$iv, oldMap$iv)) { SnapshotStateMap this_$iv$iv = this_$iv; int $i$f$writable = 0;
/* 444 */         Intrinsics.checkNotNull(this_$iv$iv.getFirstStateRecord(), "null cannot be cast to non-null type androidx.compose.runtime.snapshots.SnapshotStateMap.StateMapStateRecord<K of androidx.compose.runtime.snapshots.SnapshotStateMap, V of androidx.compose.runtime.snapshots.SnapshotStateMap>"); StateRecord $this$writable$iv$iv$iv = this_$iv$iv.getFirstStateRecord(); int i = 0;
/* 445 */         Object snapshot$iv$iv$iv = null; snapshot$iv$iv$iv = SnapshotKt.getSnapshotInitializer();
/* 446 */         int $i$f$sync = 0;
/* 447 */         SynchronizedObject lock$iv$iv$iv$iv$iv = SnapshotKt.getLock(); int j = 0;
/*     */         SynchronizedObject synchronizedObject1 = lock$iv$iv$iv$iv$iv;
/*     */         /* monitor enter ClassFileLocalVariableReferenceExpression{type=ObjectType{androidx/compose/runtime/SynchronizedObject}, name=null} */ }
/*     */       
/*     */       break;
/*     */     }  }
/*     */ 
/*     */ 
/*     */ 
/*     */ 
/*     */   
/*     */   @Nullable
/*     */   public V remove(Object key) {
/*     */     SnapshotStateMap this_$iv = this;
/*     */     int $i$f$mutate = 0;
/* 462 */     Object result$iv = null;
/*     */     while (true) {
/* 464 */       Object oldMap$iv = null;
/* 465 */       int currentModification$iv = 0;
/* 466 */       SynchronizedObject lock$iv$iv = SnapshotStateMapKt.access$getSync$p(); int $i$f$synchronized = 0;
/* 467 */       synchronized (lock$iv$iv) { int $i$a$-synchronized-SnapshotStateMap$mutate$1$iv = 0;
/* 468 */         SnapshotStateMap this_$iv$iv = this_$iv; int $i$f$withCurrent = 0;
/* 469 */         Intrinsics.checkNotNull(this_$iv$iv.getFirstStateRecord(), "null cannot be cast to non-null type androidx.compose.runtime.snapshots.SnapshotStateMap.StateMapStateRecord<K of androidx.compose.runtime.snapshots.SnapshotStateMap, V of androidx.compose.runtime.snapshots.SnapshotStateMap>"); StateRecord $this$withCurrent$iv$iv$iv = this_$iv$iv.getFirstStateRecord(); int i = 0;
/* 470 */         StateMapStateRecord $this$mutate_u24lambda_u2413_u24lambda_u2412$iv = (StateMapStateRecord)SnapshotKt.<StateRecord>current($this$withCurrent$iv$iv$iv); int $i$a$-withCurrent-SnapshotStateMap$mutate$1$current$1$iv = 0; StateMapStateRecord current$iv = $this$mutate_u24lambda_u2413_u24lambda_u2412$iv;
/* 471 */         oldMap$iv = current$iv.getMap$runtime();
/* 472 */         currentModification$iv = current$iv.getModification$runtime();
/* 473 */         Unit unit = Unit.INSTANCE; }
/* 474 */        Intrinsics.checkNotNull(oldMap$iv); PersistentMap.Builder builder$iv = oldMap$iv.builder();
/* 475 */       Map it = (Map)builder$iv; int $i$a$-mutate-SnapshotStateMap$remove$1 = 0; result$iv = it.remove(key);
/* 476 */       PersistentMap newMap$iv = builder$iv.build();
/* 477 */       if (!Intrinsics.areEqual(newMap$iv, oldMap$iv)) { SnapshotStateMap this_$iv$iv = this_$iv; int $i$f$writable = 0;
/* 478 */         Intrinsics.checkNotNull(this_$iv$iv.getFirstStateRecord(), "null cannot be cast to non-null type androidx.compose.runtime.snapshots.SnapshotStateMap.StateMapStateRecord<K of androidx.compose.runtime.snapshots.SnapshotStateMap, V of androidx.compose.runtime.snapshots.SnapshotStateMap>"); StateRecord $this$writable$iv$iv$iv = this_$iv$iv.getFirstStateRecord(); int i = 0;
/* 479 */         Object snapshot$iv$iv$iv = null; snapshot$iv$iv$iv = SnapshotKt.getSnapshotInitializer();
/* 480 */         int $i$f$sync = 0;
/* 481 */         SynchronizedObject lock$iv$iv$iv$iv$iv = SnapshotKt.getLock(); int j = 0;
/*     */ 
/*     */         
/*     */         SynchronizedObject synchronizedObject1 = lock$iv$iv$iv$iv$iv;
/*     */ 
/*     */         
/*     */         /* monitor enter ClassFileLocalVariableReferenceExpression{type=ObjectType{androidx/compose/runtime/SynchronizedObject}, name=null} */ }
/*     */ 
/*     */ 
/*     */       
/*     */       break;
/*     */     } 
/*     */ 
/*     */     
/* 495 */     return (V)result$iv;
/*     */   } public final int getModification$runtime() { return getReadable$runtime().getModification$runtime(); } public final boolean removeValue$runtime(Object value) { // Byte code:
/*     */     //   0: aload_0
/*     */     //   1: invokevirtual entrySet : ()Ljava/util/Set;
/*     */     //   4: checkcast java/lang/Iterable
/*     */     //   7: astore_2
/*     */     //   8: iconst_0
/*     */     //   9: istore_3
/*     */     //   10: aload_2
/*     */     //   11: invokeinterface iterator : ()Ljava/util/Iterator;
/*     */     //   16: astore #4
/*     */     //   18: aload #4
/*     */     //   20: invokeinterface hasNext : ()Z
/*     */     //   25: ifeq -> 66
/*     */     //   28: aload #4
/*     */     //   30: invokeinterface next : ()Ljava/lang/Object;
/*     */     //   35: astore #5
/*     */     //   37: aload #5
/*     */     //   39: checkcast java/util/Map$Entry
/*     */     //   42: astore #6
/*     */     //   44: iconst_0
/*     */     //   45: istore #7
/*     */     //   47: aload #6
/*     */     //   49: invokeinterface getValue : ()Ljava/lang/Object;
/*     */     //   54: aload_1
/*     */     //   55: invokestatic areEqual : (Ljava/lang/Object;Ljava/lang/Object;)Z
/*     */     //   58: ifeq -> 18
/*     */     //   61: aload #5
/*     */     //   63: goto -> 67
/*     */     //   66: aconst_null
/*     */     //   67: checkcast java/util/Map$Entry
/*     */     //   70: dup
/*     */     //   71: ifnull -> 103
/*     */     //   74: astore_3
/*     */     //   75: iconst_0
/*     */     //   76: istore #4
/*     */     //   78: aload_0
/*     */     //   79: aload_3
/*     */     //   80: invokeinterface getKey : ()Ljava/lang/Object;
/*     */     //   85: invokevirtual remove : (Ljava/lang/Object;)Ljava/lang/Object;
/*     */     //   88: pop
/*     */     //   89: iconst_1
/*     */     //   90: nop
/*     */     //   91: iconst_1
/*     */     //   92: if_icmpne -> 99
/*     */     //   95: iconst_1
/*     */     //   96: goto -> 105
/*     */     //   99: iconst_0
/*     */     //   100: goto -> 105
/*     */     //   103: pop
/*     */     //   104: iconst_0
/*     */     //   105: ireturn
/*     */     // Line number table:
/*     */     //   Java source line number -> byte code offset
/*     */     //   #90	-> 0
/*     */     //   #496	-> 10
/*     */     //   #90	-> 47
/*     */     //   #496	-> 58
/*     */     //   #497	-> 66
/*     */     //   #90	-> 67
/*     */     //   #498	-> 75
/*     */     //   #90	-> 78
/*     */     //   #90	-> 90
/*     */     //   #90	-> 91
/*     */     // Local variable table:
/*     */     //   start	length	slot	name	descriptor
/*     */     //   47	11	7	$i$a$-firstOrNull-SnapshotStateMap$removeValue$1	I
/*     */     //   44	14	6	it	Ljava/util/Map$Entry;
/*     */     //   37	29	5	element$iv	Ljava/lang/Object;
/*     */     //   10	57	3	$i$f$firstOrNull	I
/*     */     //   8	59	2	$this$firstOrNull$iv	Ljava/lang/Iterable;
/*     */     //   78	12	4	$i$a$-let-SnapshotStateMap$removeValue$2	I
/*     */     //   75	15	3	it	Ljava/util/Map$Entry;
/*     */     //   0	106	0	this	Landroidx/compose/runtime/snapshots/SnapshotStateMap;
/*     */     //   0	106	1	value	Ljava/lang/Object; }
/*     */   @NotNull public final StateMapStateRecord<K, V> getReadable$runtime() { Intrinsics.checkNotNull(getFirstStateRecord(), "null cannot be cast to non-null type androidx.compose.runtime.snapshots.SnapshotStateMap.StateMapStateRecord<K of androidx.compose.runtime.snapshots.SnapshotStateMap, V of androidx.compose.runtime.snapshots.SnapshotStateMap>"); return SnapshotKt.<StateMapStateRecord<K, V>>readable((StateMapStateRecord<K, V>)getFirstStateRecord(), this); }
/*     */   public final boolean removeIf$runtime(@NotNull Function1 predicate) { Intrinsics.checkNotNullParameter(predicate, "predicate"); int $i$f$removeIf$runtime = 0; boolean removed = false; SnapshotStateMap this_$iv = this; int $i$f$mutate = 0;
/* 499 */     Object result$iv = null;
/*     */     while (true) {
/* 501 */       Object oldMap$iv = null;
/* 502 */       int currentModification$iv = 0;
/* 503 */       SynchronizedObject lock$iv$iv = SnapshotStateMapKt.access$getSync$p(); int $i$f$synchronized = 0;
/* 504 */       SynchronizedObject synchronizedObject1 = lock$iv$iv; /* monitor enter ClassFileLocalVariableReferenceExpression{type=ObjectType{androidx/compose/runtime/SynchronizedObject}, name=null} */ try { int $i$a$-synchronized-SnapshotStateMap$mutate$1$iv = 0;
/* 505 */         SnapshotStateMap this_$iv$iv = this_$iv; int $i$f$withCurrent = 0;
/* 506 */         Intrinsics.checkNotNull(this_$iv$iv.getFirstStateRecord(), "null cannot be cast to non-null type androidx.compose.runtime.snapshots.SnapshotStateMap.StateMapStateRecord<K of androidx.compose.runtime.snapshots.SnapshotStateMap, V of androidx.compose.runtime.snapshots.SnapshotStateMap>"); StateRecord $this$withCurrent$iv$iv$iv = this_$iv$iv.getFirstStateRecord(); int i = 0;
/* 507 */         StateMapStateRecord $this$mutate_u24lambda_u2413_u24lambda_u2412$iv = (StateMapStateRecord)SnapshotKt.<StateRecord>current($this$withCurrent$iv$iv$iv); int $i$a$-withCurrent-SnapshotStateMap$mutate$1$current$1$iv = 0; StateMapStateRecord current$iv = $this$mutate_u24lambda_u2413_u24lambda_u2412$iv;
/* 508 */         oldMap$iv = current$iv.getMap$runtime();
/* 509 */         currentModification$iv = current$iv.getModification$runtime();
/* 510 */         Unit unit = Unit.INSTANCE; } finally { InlineMarker.finallyStart(1); /* monitor exit ClassFileLocalVariableReferenceExpression{type=ObjectType{androidx/compose/runtime/SynchronizedObject}, name=null} */ InlineMarker.finallyEnd(1); }
/* 511 */        Intrinsics.checkNotNull(oldMap$iv); PersistentMap.Builder builder$iv = oldMap$iv.builder();
/* 512 */       Map it = (Map)builder$iv; int $i$a$-mutate-SnapshotStateMap$removeIf$1 = 0; for (Map.Entry<K, V> entry : entrySet()) { if (((Boolean)predicate.invoke(entry)).booleanValue()) { it.remove(entry.getKey()); removed = true; }  }  result$iv = Unit.INSTANCE;
/* 513 */       PersistentMap newMap$iv = builder$iv.build();
/* 514 */       if (!Intrinsics.areEqual(newMap$iv, oldMap$iv)) { SnapshotStateMap this_$iv$iv = this_$iv; int $i$f$writable = 0;
/* 515 */         Intrinsics.checkNotNull(this_$iv$iv.getFirstStateRecord(), "null cannot be cast to non-null type androidx.compose.runtime.snapshots.SnapshotStateMap.StateMapStateRecord<K of androidx.compose.runtime.snapshots.SnapshotStateMap, V of androidx.compose.runtime.snapshots.SnapshotStateMap>"); StateRecord $this$writable$iv$iv$iv = this_$iv$iv.getFirstStateRecord(); int i = 0;
/* 516 */         Object snapshot$iv$iv$iv = null; snapshot$iv$iv$iv = SnapshotKt.getSnapshotInitializer();
/* 517 */         int $i$f$sync = 0;
/* 518 */         SynchronizedObject lock$iv$iv$iv$iv$iv = SnapshotKt.getLock(); int j = 0; SynchronizedObject synchronizedObject2 = lock$iv$iv$iv$iv$iv; /* monitor enter ClassFileLocalVariableReferenceExpression{type=ObjectType{androidx/compose/runtime/SynchronizedObject}, name=null} */ }
/*     */        break;
/*     */     }  return removed; } public final boolean any$runtime(@NotNull Function1 predicate) { Intrinsics.checkNotNullParameter(predicate, "predicate"); int $i$f$any$runtime = 0; for (Map.Entry entry : getReadable$runtime().getMap$runtime().entrySet()) {
/*     */       if (((Boolean)predicate.invoke(entry)).booleanValue())
/*     */         return true; 
/*     */     }  return false; }
/*     */   public final boolean all$runtime(@NotNull Function1 predicate) { Intrinsics.checkNotNullParameter(predicate, "predicate");
/*     */     int $i$f$all$runtime = 0;
/*     */     for (Map.Entry entry : getReadable$runtime().getMap$runtime().entrySet()) {
/*     */       if (!((Boolean)predicate.invoke(entry)).booleanValue())
/*     */         return false; 
/*     */     } 
/*     */     return true; }
/*     */   @JvmName(name = "getDebuggerDisplayValue") @NotNull public final Map<K, V> getDebuggerDisplayValue() { SnapshotStateMap this_$iv = this;
/*     */     int $i$f$withCurrent = 0;
/* 533 */     Intrinsics.checkNotNull(this_$iv.getFirstStateRecord(), "null cannot be cast to non-null type androidx.compose.runtime.snapshots.SnapshotStateMap.StateMapStateRecord<K of androidx.compose.runtime.snapshots.SnapshotStateMap, V of androidx.compose.runtime.snapshots.SnapshotStateMap>"); StateRecord $this$withCurrent$iv$iv = this_$iv.getFirstStateRecord(); int i = 0;
/* 534 */     StateMapStateRecord $this$_get_debuggerDisplayValue__u24lambda_u2411 = (StateMapStateRecord)SnapshotKt.<StateRecord>current($this$withCurrent$iv$iv); int $i$a$-withCurrent-SnapshotStateMap$debuggerDisplayValue$1 = 0; return (Map<K, V>)$this$_get_debuggerDisplayValue__u24lambda_u2411.getMap$runtime(); } private final <R> R withCurrent(Function1 block) { int $i$f$withCurrent = 0; Intrinsics.checkNotNull(getFirstStateRecord(), "null cannot be cast to non-null type androidx.compose.runtime.snapshots.SnapshotStateMap.StateMapStateRecord<K of androidx.compose.runtime.snapshots.SnapshotStateMap, V of androidx.compose.runtime.snapshots.SnapshotStateMap>"); StateRecord $this$withCurrent$iv = getFirstStateRecord(); int i = 0;
/* 535 */     return (R)block.invoke(SnapshotKt.current($this$withCurrent$iv)); } private final <R> R writable(Function1 block) { int $i$f$writable = 0; Intrinsics.checkNotNull(getFirstStateRecord(), "null cannot be cast to non-null type androidx.compose.runtime.snapshots.SnapshotStateMap.StateMapStateRecord<K of androidx.compose.runtime.snapshots.SnapshotStateMap, V of androidx.compose.runtime.snapshots.SnapshotStateMap>"); StateRecord $this$writable$iv = getFirstStateRecord(); int i = 0;
/* 536 */     Object snapshot$iv = null; snapshot$iv = SnapshotKt.getSnapshotInitializer();
/* 537 */     int $i$f$sync = 0;
/* 538 */     SynchronizedObject lock$iv$iv$iv = SnapshotKt.getLock(); int $i$f$synchronized = 0;
/* 539 */     SynchronizedObject synchronizedObject1 = lock$iv$iv$iv; /* monitor enter ClassFileLocalVariableReferenceExpression{type=ObjectType{androidx/compose/runtime/SynchronizedObject}, name=null} */ try { int $i$a$-sync-SnapshotKt$writable$3$iv = 0;
/* 540 */       snapshot$iv = Snapshot.Companion.getCurrent();
/* 541 */       Object object = block.invoke(SnapshotKt.writableRecord($this$writable$iv, this, (Snapshot)snapshot$iv)); } finally { InlineMarker.finallyStart(1); /* monitor exit ClassFileLocalVariableReferenceExpression{type=ObjectType{androidx/compose/runtime/SynchronizedObject}, name=null} */ InlineMarker.finallyEnd(1); }
/* 542 */      Object object1 = object; Object it$iv = object1; int $i$a$-also-SnapshotKt$writable$4$iv = 0;
/* 543 */     SnapshotKt.notifyWrite((Snapshot)snapshot$iv, this); return (R)object1; } private final <R> R mutate(Function1 block) { int $i$f$mutate = 0; Object result = null; while (true) {
/*     */       Object oldMap = null; int currentModification = 0; SynchronizedObject lock$iv = SnapshotStateMapKt.access$getSync$p(); int $i$f$synchronized = 0;
/* 545 */       SynchronizedObject synchronizedObject1 = lock$iv; /* monitor enter ClassFileLocalVariableReferenceExpression{type=ObjectType{androidx/compose/runtime/SynchronizedObject}, name=null} */ try { int $i$a$-synchronized-SnapshotStateMap$mutate$1 = 0; SnapshotStateMap this_$iv = this; int $i$f$withCurrent = 0;
/* 546 */         Intrinsics.checkNotNull(this_$iv.getFirstStateRecord(), "null cannot be cast to non-null type androidx.compose.runtime.snapshots.SnapshotStateMap.StateMapStateRecord<K of androidx.compose.runtime.snapshots.SnapshotStateMap, V of androidx.compose.runtime.snapshots.SnapshotStateMap>"); StateRecord $this$withCurrent$iv$iv = this_$iv.getFirstStateRecord(); int i = 0;
/* 547 */         StateMapStateRecord $this$mutate_u24lambda_u2413_u24lambda_u2412 = (StateMapStateRecord)SnapshotKt.<StateRecord>current($this$withCurrent$iv$iv); int $i$a$-withCurrent-SnapshotStateMap$mutate$1$current$1 = 0; StateMapStateRecord current = $this$mutate_u24lambda_u2413_u24lambda_u2412; oldMap = current.getMap$runtime(); currentModification = current.getModification$runtime(); Unit unit = Unit.INSTANCE; } finally { InlineMarker.finallyStart(1); /* monitor exit ClassFileLocalVariableReferenceExpression{type=ObjectType{androidx/compose/runtime/SynchronizedObject}, name=null} */ InlineMarker.finallyEnd(1); }
/* 548 */        Intrinsics.checkNotNull(oldMap); PersistentMap.Builder builder = oldMap.builder(); result = block.invoke(builder); PersistentMap newMap = builder.build(); if (!Intrinsics.areEqual(newMap, oldMap)) { SnapshotStateMap this_$iv = this; int $i$f$writable = 0; Intrinsics.checkNotNull(this_$iv.getFirstStateRecord(), "null cannot be cast to non-null type androidx.compose.runtime.snapshots.SnapshotStateMap.StateMapStateRecord<K of androidx.compose.runtime.snapshots.SnapshotStateMap, V of androidx.compose.runtime.snapshots.SnapshotStateMap>"); StateRecord $this$writable$iv$iv = this_$iv.getFirstStateRecord(); int i = 0;
/* 549 */         Object snapshot$iv$iv = null; snapshot$iv$iv = SnapshotKt.getSnapshotInitializer();
/* 550 */         int $i$f$sync = 0;
/* 551 */         SynchronizedObject lock$iv$iv$iv$iv = SnapshotKt.getLock(); int k = 0;
/* 552 */         SynchronizedObject synchronizedObject2 = lock$iv$iv$iv$iv; /* monitor enter ClassFileLocalVariableReferenceExpression{type=ObjectType{androidx/compose/runtime/SynchronizedObject}, name=null} */ try { int $i$a$-sync-SnapshotKt$writable$3$iv$iv = 0;
/* 553 */           snapshot$iv$iv = Snapshot.Companion.getCurrent();
/* 554 */           StateMapStateRecord $this$mutate_u24lambda_u2415 = (StateMapStateRecord)SnapshotKt.<StateRecord>writableRecord($this$writable$iv$iv, this_$iv, (Snapshot)snapshot$iv$iv); int $i$a$-writable-SnapshotStateMap$mutate$2 = 0; SynchronizedObject synchronizedObject3 = SnapshotStateMapKt.access$getSync$p(); int m = 0;
/* 555 */           SynchronizedObject synchronizedObject4 = synchronizedObject3; /* monitor enter ClassFileLocalVariableReferenceExpression{type=ObjectType{androidx/compose/runtime/SynchronizedObject}, name=null} */ try { int $i$a$-synchronized-SnapshotStateMap$mutate$2$1 = 0; $this$mutate_u24lambda_u2415.setMap$runtime(newMap); int n = $this$mutate_u24lambda_u2415.getModification$runtime(); $this$mutate_u24lambda_u2415.setModification$runtime(n + 1); boolean bool1 = ($this$mutate_u24lambda_u2415.getModification$runtime() == currentModification) ? true : false; } finally { InlineMarker.finallyStart(1); /* monitor exit ClassFileLocalVariableReferenceExpression{type=ObjectType{androidx/compose/runtime/SynchronizedObject}, name=null} */ InlineMarker.finallyEnd(1); }  boolean bool = bool1; } finally { InlineMarker.finallyStart(1); /* monitor exit ClassFileLocalVariableReferenceExpression{type=ObjectType{androidx/compose/runtime/SynchronizedObject}, name=null} */ InlineMarker.finallyEnd(1); }
/* 556 */          $i$f$sync = bool; int j = $i$f$sync, $i$a$-also-SnapshotKt$writable$4$iv$iv = 0;
/* 557 */         SnapshotKt.notifyWrite((Snapshot)snapshot$iv$iv, this_$iv); if ($i$f$sync != 0)
/*     */           break;  continue; }  break;
/* 559 */     }  return (R)result; } private final void update(Function1 block) { int $i$f$update = 0; SnapshotStateMap this_$iv = this; int $i$f$withCurrent = 0; Intrinsics.checkNotNull(this_$iv.getFirstStateRecord(), "null cannot be cast to non-null type androidx.compose.runtime.snapshots.SnapshotStateMap.StateMapStateRecord<K of androidx.compose.runtime.snapshots.SnapshotStateMap, V of androidx.compose.runtime.snapshots.SnapshotStateMap>"); StateRecord $this$withCurrent$iv$iv = this_$iv.getFirstStateRecord(); int i = 0;
/* 560 */     StateMapStateRecord $this$update_u24lambda_u2418 = (StateMapStateRecord)SnapshotKt.<StateRecord>current($this$withCurrent$iv$iv); int $i$a$-withCurrent-SnapshotStateMap$update$1 = 0; PersistentMap newMap = (PersistentMap)block.invoke($this$update_u24lambda_u2418.getMap$runtime()); if (newMap != $this$update_u24lambda_u2418.getMap$runtime()) {
/* 561 */       SnapshotStateMap snapshotStateMap = this; int $i$f$writable = 0; Intrinsics.checkNotNull(snapshotStateMap.getFirstStateRecord(), "null cannot be cast to non-null type androidx.compose.runtime.snapshots.SnapshotStateMap.StateMapStateRecord<K of androidx.compose.runtime.snapshots.SnapshotStateMap, V of androidx.compose.runtime.snapshots.SnapshotStateMap>"); StateRecord $this$writable$iv$iv = snapshotStateMap.getFirstStateRecord(); int j = 0;
/* 562 */       Object snapshot$iv$iv = null; snapshot$iv$iv = SnapshotKt.getSnapshotInitializer();
/* 563 */       int $i$f$sync = 0;
/* 564 */       SynchronizedObject lock$iv$iv$iv$iv = SnapshotKt.getLock(); int $i$f$synchronized = 0;
/* 565 */       SynchronizedObject synchronizedObject1 = lock$iv$iv$iv$iv; /* monitor enter ClassFileLocalVariableReferenceExpression{type=ObjectType{androidx/compose/runtime/SynchronizedObject}, name=null} */ try { int $i$a$-sync-SnapshotKt$writable$3$iv$iv = 0;
/* 566 */         snapshot$iv$iv = Snapshot.Companion.getCurrent();
/* 567 */         StateMapStateRecord $this$update_u24lambda_u2418_u24lambda_u2417 = (StateMapStateRecord)SnapshotKt.<StateRecord>writableRecord($this$writable$iv$iv, snapshotStateMap, (Snapshot)snapshot$iv$iv); int $i$a$-writable-SnapshotStateMap$update$1$1 = 0; SynchronizedObject lock$iv = SnapshotStateMapKt.access$getSync$p(); int k = 0;
/* 568 */         SynchronizedObject synchronizedObject2 = lock$iv; /* monitor enter ClassFileLocalVariableReferenceExpression{type=ObjectType{androidx/compose/runtime/SynchronizedObject}, name=null} */ try { int $i$a$-synchronized-SnapshotStateMap$update$1$1$1 = 0; $this$update_u24lambda_u2418_u24lambda_u2417.setMap$runtime(newMap); int n = $this$update_u24lambda_u2418_u24lambda_u2417.getModification$runtime(); $this$update_u24lambda_u2418_u24lambda_u2417.setModification$runtime(n + 1); int i1 = n; } finally { InlineMarker.finallyStart(1); /* monitor exit ClassFileLocalVariableReferenceExpression{type=ObjectType{androidx/compose/runtime/SynchronizedObject}, name=null} */ InlineMarker.finallyEnd(1); }  int m = i1; } finally { InlineMarker.finallyStart(1); /* monitor exit ClassFileLocalVariableReferenceExpression{type=ObjectType{androidx/compose/runtime/SynchronizedObject}, name=null} */ InlineMarker.finallyEnd(1); }
/* 569 */        $i$f$sync = m; int it$iv$iv = $i$f$sync, $i$a$-also-SnapshotKt$writable$4$iv$iv = 0;
/* 570 */       SnapshotKt.notifyWrite((Snapshot)snapshot$iv$iv, snapshotStateMap);
/*     */     }  }
/*     */ 
/*     */   
/*     */   @Metadata(mv = {1, 9, 0}, k = 1, xi = 48, d1 = {"\000&\n\002\030\002\n\002\b\002\n\002\030\002\n\000\n\002\030\002\n\002\b\005\n\002\020\b\n\002\b\005\n\002\020\002\n\002\b\003\b\000\030\000*\004\b\002\020\001*\004\b\003\020\0022\0020\003B\033\b\000\022\022\020\004\032\016\022\004\022\0028\002\022\004\022\0028\0030\005¢\006\002\020\006J\020\020\020\032\0020\0212\006\020\022\032\0020\003H\026J\b\020\023\032\0020\003H\026R&\020\004\032\016\022\004\022\0028\002\022\004\022\0028\0030\005X\016¢\006\016\n\000\032\004\b\007\020\b\"\004\b\t\020\006R\032\020\n\032\0020\013X\016¢\006\016\n\000\032\004\b\f\020\r\"\004\b\016\020\017¨\006\024"}, d2 = {"Landroidx/compose/runtime/snapshots/SnapshotStateMap$StateMapStateRecord;", "K", "V", "Landroidx/compose/runtime/snapshots/StateRecord;", "map", "Landroidx/compose/runtime/external/kotlinx/collections/immutable/PersistentMap;", "(Landroidx/compose/runtime/external/kotlinx/collections/immutable/PersistentMap;)V", "getMap$runtime", "()Landroidx/compose/runtime/external/kotlinx/collections/immutable/PersistentMap;", "setMap$runtime", "modification", "", "getModification$runtime", "()I", "setModification$runtime", "(I)V", "assign", "", "value", "create", "runtime"})
/*     */   @StabilityInferred(parameters = 0)
/*     */   @SourceDebugExtension({"SMAP\nSnapshotStateMap.kt\nKotlin\n*S Kotlin\n*F\n+ 1 SnapshotStateMap.kt\nandroidx/compose/runtime/snapshots/SnapshotStateMap$StateMapStateRecord\n+ 2 SynchronizedObject.jvm.kt\nandroidx/compose/runtime/ActualJvm_jvmKt__SynchronizedObject_jvmKt\n*L\n1#1,373:1\n26#2:374\n*S KotlinDebug\n*F\n+ 1 SnapshotStateMap.kt\nandroidx/compose/runtime/snapshots/SnapshotStateMap$StateMapStateRecord\n*L\n187#1:374\n*E\n"})
/*     */   public static final class StateMapStateRecord<K, V> extends StateRecord {
/*     */     @NotNull
/*     */     private PersistentMap<K, ? extends V> map;
/*     */     private int modification;
/*     */     public static final int $stable = 8;
/*     */     
/*     */     @NotNull
/*     */     public final PersistentMap<K, V> getMap$runtime() {
/*     */       return (PersistentMap)this.map;
/*     */     }
/*     */     
/*     */     public final void setMap$runtime(@NotNull PersistentMap<K, ? extends V> <set-?>) {
/*     */       Intrinsics.checkNotNullParameter(<set-?>, "<set-?>");
/*     */       this.map = <set-?>;
/*     */     }
/*     */     
/*     */     public StateMapStateRecord(@NotNull PersistentMap<K, ? extends V> map) {
/*     */       this.map = map;
/*     */     }
/*     */     
/*     */     public final int getModification$runtime() {
/*     */       return this.modification;
/*     */     }
/*     */     
/*     */     public final void setModification$runtime(int <set-?>) {
/*     */       this.modification = <set-?>;
/*     */     }
/*     */     
/*     */     public void assign(@NotNull StateRecord value) {
/*     */       Intrinsics.checkNotNullParameter(value, "value");
/*     */       StateMapStateRecord other = (StateMapStateRecord)value;
/*     */       SynchronizedObject lock$iv = SnapshotStateMapKt.access$getSync$p();
/*     */       int $i$f$synchronized = 0;
/*     */       synchronized (lock$iv) {
/*     */         int $i$a$-synchronized-SnapshotStateMap$StateMapStateRecord$assign$1 = 0;
/*     */         this.map = other.map;
/*     */         this.modification = other.modification;
/*     */         Unit unit = Unit.INSTANCE;
/*     */       } 
/*     */     }
/*     */     
/*     */     @NotNull
/*     */     public StateRecord create() {
/*     */       return new StateMapStateRecord(this.map);
/*     */     }
/*     */   } }


/* Location:              C:\Users\yuzum\Downloads\ej-release-243.132.63.zip!\ej\lib\runtime-desktop-1.7.3.jar!\androidx\compose\runtime\snapshots\SnapshotStateMap.class
 * Java compiler version: 8 (52.0)
 * JD-Core Version:       1.1.3
 */