/*     */ package com.intellij.ml.llm.matterhorn.ej.idea.actions;
/*     */ 
/*     */ import com.intellij.ml.llm.matterhorn.ej.idea.run.RunEvent;
/*     */ import com.intellij.ml.llm.matterhorn.ej.idea.run.TestResult;
/*     */ import java.util.List;
/*     */ import kotlin.Metadata;
/*     */ import kotlin.ResultKt;
/*     */ import kotlin.Unit;
/*     */ import kotlin.coroutines.Continuation;
/*     */ import kotlin.coroutines.intrinsics.IntrinsicsKt;
/*     */ import kotlin.coroutines.jvm.internal.ContinuationImpl;
/*     */ import kotlin.coroutines.jvm.internal.DebugMetadata;
/*     */ import kotlin.coroutines.jvm.internal.SuspendLambda;
/*     */ import kotlin.jvm.functions.Function2;
/*     */ import kotlin.jvm.internal.DefaultConstructorMarker;
/*     */ import kotlinx.coroutines.flow.Flow;
/*     */ import kotlinx.coroutines.flow.FlowCollector;
/*     */ import org.jetbrains.annotations.NotNull;
/*     */ import org.jetbrains.annotations.Nullable;
/*     */ 
/*     */ 
/*     */ 
/*     */ 
/*     */ 
/*     */ 
/*     */ 
/*     */ 
/*     */ 
/*     */ 
/*     */ 
/*     */ 
/*     */ 
/*     */ 
/*     */ 
/*     */ 
/*     */ 
/*     */ 
/*     */ 
/*     */ 
/*     */ 
/*     */ 
/*     */ 
/*     */ 
/*     */ 
/*     */ 
/*     */ 
/*     */ 
/*     */ 
/*     */ 
/*     */ 
/*     */ 
/*     */ 
/*     */ 
/*     */ 
/*     */ 
/*     */ 
/*     */ 
/*     */ 
/*     */ 
/*     */ 
/*     */ 
/*     */ 
/*     */ 
/*     */ 
/*     */ 
/*     */ 
/*     */ 
/*     */ 
/*     */ 
/*     */ 
/*     */ 
/*     */ 
/*     */ 
/*     */ 
/*     */ 
/*     */ 
/*     */ 
/*     */ 
/*     */ 
/*     */ 
/*     */ 
/*     */ 
/*     */ 
/*     */ 
/*     */ 
/*     */ 
/*     */ 
/*     */ 
/*     */ 
/*     */ 
/*     */ 
/*     */ 
/*     */ 
/*     */ 
/*     */ 
/*     */ 
/*     */ 
/*     */ 
/*     */ 
/*     */ 
/*     */ 
/*     */ 
/*     */ 
/*     */ 
/*     */ 
/*     */ 
/*     */ 
/*     */ 
/*     */ 
/*     */ 
/*     */ 
/*     */ 
/*     */ 
/*     */ 
/*     */ 
/*     */ 
/*     */ 
/*     */ 
/*     */ 
/*     */ 
/*     */ 
/*     */ 
/*     */ 
/*     */ 
/*     */ 
/*     */ 
/*     */ 
/*     */ 
/*     */ 
/*     */ 
/*     */ 
/*     */ 
/*     */ 
/*     */ 
/*     */ 
/*     */ 
/*     */ 
/*     */ 
/*     */ 
/*     */ 
/*     */ 
/*     */ 
/*     */ 
/*     */ 
/*     */ 
/*     */ 
/*     */ 
/*     */ 
/*     */ 
/*     */ 
/*     */ 
/*     */ 
/*     */ 
/*     */ 
/*     */ 
/*     */ 
/*     */ 
/*     */ @Metadata(mv = {2, 1, 0}, k = 1, xi = 48, d1 = {"\000.\n\002\030\002\n\002\020\000\n\002\b\003\n\002\030\002\n\000\n\002\020\016\n\002\b\004\n\002\030\002\n\002\b\002\n\002\030\002\n\002\030\002\n\002\b\002\b\003\030\0002\0020\001B\t\b\002¢\006\004\b\002\020\003J$\020\013\032\0020\f2\006\020\r\032\0020\0072\f\020\016\032\b\022\004\022\0020\0200\017H@¢\006\002\020\021R\016\020\004\032\0020\005X\004¢\006\002\n\000R\016\020\006\032\0020\007XT¢\006\002\n\000R\016\020\b\032\0020\007XT¢\006\002\n\000R\016\020\t\032\0020\007XT¢\006\002\n\000R\016\020\n\032\0020\007XT¢\006\002\n\000¨\006\022"}, d2 = {"Lcom/intellij/ml/llm/matterhorn/ej/idea/actions/RunTestAgentAction$Companion;", "", "<init>", "()V", "logger", "Lcom/intellij/openapi/diagnostic/Logger;", "DEBUG_LOG_PREFIX", "", "PATH_ARGUMENT", "TEST_NAME", "PATH_SEPARATOR", "handleEvents", "Lcom/intellij/ml/llm/matterhorn/ej/idea/actions/RunResult;", "classFQName", "events", "Lkotlinx/coroutines/flow/Flow;", "Lcom/intellij/ml/llm/matterhorn/ej/idea/run/RunEvent;", "(Ljava/lang/String;Lkotlinx/coroutines/flow/Flow;Lkotlin/coroutines/Continuation;)Ljava/lang/Object;", "ej-idea"})
/*     */ public final class Companion
/*     */ {
/*     */   private Companion() {}
/*     */   
/*     */   @Nullable
/*     */   public final Object handleEvents(@NotNull String classFQName, @NotNull Flow events, @NotNull Continuation $completion) {
/*     */     // Byte code:
/*     */     //   0: aload_3
/*     */     //   1: instanceof com/intellij/ml/llm/matterhorn/ej/idea/actions/RunTestAgentAction$Companion$handleEvents$1
/*     */     //   4: ifeq -> 39
/*     */     //   7: aload_3
/*     */     //   8: checkcast com/intellij/ml/llm/matterhorn/ej/idea/actions/RunTestAgentAction$Companion$handleEvents$1
/*     */     //   11: astore #9
/*     */     //   13: aload #9
/*     */     //   15: getfield label : I
/*     */     //   18: ldc -2147483648
/*     */     //   20: iand
/*     */     //   21: ifeq -> 39
/*     */     //   24: aload #9
/*     */     //   26: dup
/*     */     //   27: getfield label : I
/*     */     //   30: ldc -2147483648
/*     */     //   32: isub
/*     */     //   33: putfield label : I
/*     */     //   36: goto -> 50
/*     */     //   39: new com/intellij/ml/llm/matterhorn/ej/idea/actions/RunTestAgentAction$Companion$handleEvents$1
/*     */     //   42: dup
/*     */     //   43: aload_0
/*     */     //   44: aload_3
/*     */     //   45: invokespecial <init> : (Lcom/intellij/ml/llm/matterhorn/ej/idea/actions/RunTestAgentAction$Companion;Lkotlin/coroutines/Continuation;)V
/*     */     //   48: astore #9
/*     */     //   50: aload #9
/*     */     //   52: getfield result : Ljava/lang/Object;
/*     */     //   55: astore #8
/*     */     //   57: invokestatic getCOROUTINE_SUSPENDED : ()Ljava/lang/Object;
/*     */     //   60: astore #10
/*     */     //   62: aload #9
/*     */     //   64: getfield label : I
/*     */     //   67: tableswitch default -> 324, 0 -> 88, 1 -> 221
/*     */     //   88: aload #8
/*     */     //   90: invokestatic throwOnFailure : (Ljava/lang/Object;)V
/*     */     //   93: new java/util/ArrayList
/*     */     //   96: dup
/*     */     //   97: invokespecial <init> : ()V
/*     */     //   100: checkcast java/util/List
/*     */     //   103: astore #4
/*     */     //   105: new java/util/ArrayList
/*     */     //   108: dup
/*     */     //   109: invokespecial <init> : ()V
/*     */     //   112: checkcast java/util/List
/*     */     //   115: astore #5
/*     */     //   117: new java/util/ArrayList
/*     */     //   120: dup
/*     */     //   121: invokespecial <init> : ()V
/*     */     //   124: checkcast java/util/List
/*     */     //   127: astore #6
/*     */     //   129: invokestatic access$getLogger$cp : ()Lcom/intellij/openapi/diagnostic/Logger;
/*     */     //   132: invokevirtual isDebugEnabled : ()Z
/*     */     //   135: ifeq -> 156
/*     */     //   138: aload_2
/*     */     //   139: new com/intellij/ml/llm/matterhorn/ej/idea/actions/RunTestAgentAction$Companion$handleEvents$eventsWithMaybeLogging$1
/*     */     //   142: dup
/*     */     //   143: aconst_null
/*     */     //   144: invokespecial <init> : (Lkotlin/coroutines/Continuation;)V
/*     */     //   147: checkcast kotlin/jvm/functions/Function2
/*     */     //   150: invokestatic onEach : (Lkotlinx/coroutines/flow/Flow;Lkotlin/jvm/functions/Function2;)Lkotlinx/coroutines/flow/Flow;
/*     */     //   153: goto -> 157
/*     */     //   156: aload_2
/*     */     //   157: astore #7
/*     */     //   159: aload #7
/*     */     //   161: new com/intellij/ml/llm/matterhorn/ej/idea/actions/RunTestAgentAction$Companion$handleEvents$2
/*     */     //   164: dup
/*     */     //   165: aload #4
/*     */     //   167: aload #5
/*     */     //   169: aload_1
/*     */     //   170: aload #6
/*     */     //   172: invokespecial <init> : (Ljava/util/List;Ljava/util/List;Ljava/lang/String;Ljava/util/List;)V
/*     */     //   175: checkcast kotlinx/coroutines/flow/FlowCollector
/*     */     //   178: aload #9
/*     */     //   180: aload #9
/*     */     //   182: aload #4
/*     */     //   184: putfield L$0 : Ljava/lang/Object;
/*     */     //   187: aload #9
/*     */     //   189: aload #5
/*     */     //   191: putfield L$1 : Ljava/lang/Object;
/*     */     //   194: aload #9
/*     */     //   196: aload #6
/*     */     //   198: putfield L$2 : Ljava/lang/Object;
/*     */     //   201: aload #9
/*     */     //   203: iconst_1
/*     */     //   204: putfield label : I
/*     */     //   207: invokeinterface collect : (Lkotlinx/coroutines/flow/FlowCollector;Lkotlin/coroutines/Continuation;)Ljava/lang/Object;
/*     */     //   212: dup
/*     */     //   213: aload #10
/*     */     //   215: if_acmpne -> 258
/*     */     //   218: aload #10
/*     */     //   220: areturn
/*     */     //   221: aload #9
/*     */     //   223: getfield L$2 : Ljava/lang/Object;
/*     */     //   226: checkcast java/util/List
/*     */     //   229: astore #6
/*     */     //   231: aload #9
/*     */     //   233: getfield L$1 : Ljava/lang/Object;
/*     */     //   236: checkcast java/util/List
/*     */     //   239: astore #5
/*     */     //   241: aload #9
/*     */     //   243: getfield L$0 : Ljava/lang/Object;
/*     */     //   246: checkcast java/util/List
/*     */     //   249: astore #4
/*     */     //   251: aload #8
/*     */     //   253: invokestatic throwOnFailure : (Ljava/lang/Object;)V
/*     */     //   256: aload #8
/*     */     //   258: pop
/*     */     //   259: aload #4
/*     */     //   261: checkcast java/util/Collection
/*     */     //   264: invokeinterface isEmpty : ()Z
/*     */     //   269: ifne -> 276
/*     */     //   272: iconst_1
/*     */     //   273: goto -> 277
/*     */     //   276: iconst_0
/*     */     //   277: ifeq -> 310
/*     */     //   280: aload #5
/*     */     //   282: invokeinterface isEmpty : ()Z
/*     */     //   287: ifeq -> 310
/*     */     //   290: aload #6
/*     */     //   292: invokeinterface isEmpty : ()Z
/*     */     //   297: ifeq -> 310
/*     */     //   300: new com/intellij/ml/llm/matterhorn/ej/idea/actions/BuildFailed
/*     */     //   303: dup
/*     */     //   304: aload #4
/*     */     //   306: invokespecial <init> : (Ljava/util/List;)V
/*     */     //   309: areturn
/*     */     //   310: new com/intellij/ml/llm/matterhorn/ej/idea/actions/TestsResult
/*     */     //   313: dup
/*     */     //   314: aload #5
/*     */     //   316: aload #6
/*     */     //   318: aload #4
/*     */     //   320: invokespecial <init> : (Ljava/util/List;Ljava/util/List;Ljava/util/List;)V
/*     */     //   323: areturn
/*     */     //   324: new java/lang/IllegalStateException
/*     */     //   327: dup
/*     */     //   328: ldc 'call to 'resume' before 'invoke' with coroutine'
/*     */     //   330: invokespecial <init> : (Ljava/lang/String;)V
/*     */     //   333: athrow
/*     */     // Line number table:
/*     */     //   Java source line number -> byte code offset
/*     */     //   #199	-> 60
/*     */     //   #200	-> 93
/*     */     //   #200	-> 103
/*     */     //   #201	-> 105
/*     */     //   #201	-> 115
/*     */     //   #202	-> 117
/*     */     //   #202	-> 127
/*     */     //   #203	-> 129
/*     */     //   #204	-> 138
/*     */     //   #208	-> 156
/*     */     //   #203	-> 157
/*     */     //   #210	-> 159
/*     */     //   #199	-> 218
/*     */     //   #234	-> 258
/*     */     //   #234	-> 277
/*     */     //   #235	-> 300
/*     */     //   #237	-> 310
/*     */     //   #199	-> 324
/*     */     // Local variable table:
/*     */     //   start	length	slot	name	descriptor
/*     */     //   93	10	1	classFQName	Ljava/lang/String;
/*     */     //   103	12	1	classFQName	Ljava/lang/String;
/*     */     //   115	12	1	classFQName	Ljava/lang/String;
/*     */     //   127	85	1	classFQName	Ljava/lang/String;
/*     */     //   93	10	2	events	Lkotlinx/coroutines/flow/Flow;
/*     */     //   103	12	2	events	Lkotlinx/coroutines/flow/Flow;
/*     */     //   115	12	2	events	Lkotlinx/coroutines/flow/Flow;
/*     */     //   127	29	2	events	Lkotlinx/coroutines/flow/Flow;
/*     */     //   156	1	2	events	Lkotlinx/coroutines/flow/Flow;
/*     */     //   105	10	4	buildMessages	Ljava/util/List;
/*     */     //   115	12	4	buildMessages	Ljava/util/List;
/*     */     //   127	94	4	buildMessages	Ljava/util/List;
/*     */     //   251	26	4	buildMessages	Ljava/util/List;
/*     */     //   277	33	4	buildMessages	Ljava/util/List;
/*     */     //   310	14	4	buildMessages	Ljava/util/List;
/*     */     //   117	10	5	passedTestNames	Ljava/util/List;
/*     */     //   127	94	5	passedTestNames	Ljava/util/List;
/*     */     //   241	36	5	passedTestNames	Ljava/util/List;
/*     */     //   277	23	5	passedTestNames	Ljava/util/List;
/*     */     //   310	14	5	passedTestNames	Ljava/util/List;
/*     */     //   129	92	6	failedTests	Ljava/util/List;
/*     */     //   231	46	6	failedTests	Ljava/util/List;
/*     */     //   277	23	6	failedTests	Ljava/util/List;
/*     */     //   310	14	6	failedTests	Ljava/util/List;
/*     */     //   159	53	7	eventsWithMaybeLogging	Lkotlinx/coroutines/flow/Flow;
/*     */     //   0	334	3	$completion	Lkotlin/coroutines/Continuation;
/*     */     //   50	274	9	$continuation	Lkotlin/coroutines/Continuation;
/*     */     //   57	267	8	$result	Ljava/lang/Object;
/*     */   }
/*     */   
/*     */   @DebugMetadata(f = "RunTestAgentAction.kt", l = {210}, i = {0, 0, 0}, s = {"L$0", "L$1", "L$2"}, n = {"buildMessages", "passedTestNames", "failedTests"}, m = "handleEvents", c = "com.intellij.ml.llm.matterhorn.ej.idea.actions.RunTestAgentAction$Companion")
/*     */   @Metadata(mv = {2, 1, 0}, k = 3, xi = 48)
/*     */   static final class RunTestAgentAction$Companion$handleEvents$1
/*     */     extends ContinuationImpl
/*     */   {
/*     */     Object L$0;
/*     */     Object L$1;
/*     */     Object L$2;
/*     */     int label;
/*     */     
/*     */     RunTestAgentAction$Companion$handleEvents$1(Continuation $completion) {
/*     */       super($completion);
/*     */     }
/*     */     
/*     */     @Nullable
/*     */     public final Object invokeSuspend(@NotNull Object $result) {
/*     */       this.result = $result;
/*     */       this.label |= Integer.MIN_VALUE;
/*     */       return RunTestAgentAction.Companion.this.handleEvents(null, null, (Continuation<? super RunResult>)this);
/*     */     }
/*     */   }
/*     */   
/*     */   @DebugMetadata(f = "RunTestAgentAction.kt", l = {}, i = {}, s = {}, n = {}, m = "invokeSuspend", c = "com.intellij.ml.llm.matterhorn.ej.idea.actions.RunTestAgentAction$Companion$handleEvents$eventsWithMaybeLogging$1")
/*     */   @Metadata(mv = {2, 1, 0}, k = 3, xi = 48, d1 = {"\000\f\n\000\n\002\020\002\n\000\n\002\030\002\020\000\032\0020\0012\006\020\002\032\0020\003H\n"}, d2 = {"<anonymous>", "", "it", "Lcom/intellij/ml/llm/matterhorn/ej/idea/run/RunEvent;"})
/*     */   static final class RunTestAgentAction$Companion$handleEvents$eventsWithMaybeLogging$1
/*     */     extends SuspendLambda
/*     */     implements Function2<RunEvent, Continuation<? super Unit>, Object>
/*     */   {
/*     */     int label;
/*     */     
/*     */     RunTestAgentAction$Companion$handleEvents$eventsWithMaybeLogging$1(Continuation $completion) {
/*     */       super(2, $completion);
/*     */     }
/*     */     
/*     */     public final Object invokeSuspend(Object $result) {
/*     */       RunEvent it;
/* 204 */       IntrinsicsKt.getCOROUTINE_SUSPENDED(); switch (this.label) { case 0: ResultKt.throwOnFailure(SYNTHETIC_LOCAL_VARIABLE_1); it = (RunEvent)this.L$0;
/* 205 */           RunTestAgentAction.access$getLogger$cp().debug(it.toString());
/* 206 */           return Unit.INSTANCE; }
/*     */       
/*     */       throw new IllegalStateException("call to 'resume' before 'invoke' with coroutine");
/*     */     }
/*     */     
/*     */     public final Continuation<Unit> create(Object value, Continuation<? super RunTestAgentAction$Companion$handleEvents$eventsWithMaybeLogging$1> $completion) {
/*     */       RunTestAgentAction$Companion$handleEvents$eventsWithMaybeLogging$1 runTestAgentAction$Companion$handleEvents$eventsWithMaybeLogging$1 = new RunTestAgentAction$Companion$handleEvents$eventsWithMaybeLogging$1($completion);
/*     */       runTestAgentAction$Companion$handleEvents$eventsWithMaybeLogging$1.L$0 = value;
/*     */       return (Continuation<Unit>)runTestAgentAction$Companion$handleEvents$eventsWithMaybeLogging$1;
/*     */     }
/*     */     
/*     */     public final Object invoke(RunEvent p1, Continuation<?> p2) {
/*     */       return ((RunTestAgentAction$Companion$handleEvents$eventsWithMaybeLogging$1)create(p1, p2)).invokeSuspend(Unit.INSTANCE);
/*     */     }
/*     */   }
/*     */   
/*     */   @Metadata(mv = {2, 1, 0}, k = 3, xi = 48)
/*     */   static final class RunTestAgentAction$Companion$handleEvents$2<T> implements FlowCollector {
/*     */     public final Object emit(RunEvent it, Continuation $completion) {
/*     */       // Byte code:
/*     */       //   0: aload_1
/*     */       //   1: astore_3
/*     */       //   2: aload_3
/*     */       //   3: instanceof com/intellij/ml/llm/matterhorn/ej/idea/run/BuildErrorEvent
/*     */       //   6: ifeq -> 46
/*     */       //   9: aload_0
/*     */       //   10: getfield $buildMessages : Ljava/util/List;
/*     */       //   13: new com/intellij/ml/llm/matterhorn/ej/idea/actions/BuildMessage
/*     */       //   16: dup
/*     */       //   17: aload_1
/*     */       //   18: checkcast com/intellij/ml/llm/matterhorn/ej/idea/run/BuildErrorEvent
/*     */       //   21: invokevirtual getPosition : ()Lcom/intellij/build/FilePosition;
/*     */       //   24: aload_1
/*     */       //   25: checkcast com/intellij/ml/llm/matterhorn/ej/idea/run/BuildErrorEvent
/*     */       //   28: invokevirtual getMessage : ()Ljava/lang/String;
/*     */       //   31: invokespecial <init> : (Lcom/intellij/build/FilePosition;Ljava/lang/String;)V
/*     */       //   34: invokeinterface add : (Ljava/lang/Object;)Z
/*     */       //   39: invokestatic boxBoolean : (Z)Ljava/lang/Boolean;
/*     */       //   42: pop
/*     */       //   43: goto -> 228
/*     */       //   46: aload_3
/*     */       //   47: instanceof com/intellij/ml/llm/matterhorn/ej/idea/run/BuildStartEvent
/*     */       //   50: ifne -> 228
/*     */       //   53: aload_3
/*     */       //   54: instanceof com/intellij/ml/llm/matterhorn/ej/idea/run/BuildStartedEvent
/*     */       //   57: ifne -> 228
/*     */       //   60: aload_3
/*     */       //   61: instanceof com/intellij/ml/llm/matterhorn/ej/idea/run/OutputEvent
/*     */       //   64: ifne -> 228
/*     */       //   67: aload_3
/*     */       //   68: instanceof com/intellij/ml/llm/matterhorn/ej/idea/run/RunFinishedEvent
/*     */       //   71: ifne -> 228
/*     */       //   74: aload_3
/*     */       //   75: instanceof com/intellij/ml/llm/matterhorn/ej/idea/run/RunStartedEvent
/*     */       //   78: ifne -> 228
/*     */       //   81: aload_3
/*     */       //   82: instanceof com/intellij/ml/llm/matterhorn/ej/idea/run/TestEvent
/*     */       //   85: ifeq -> 220
/*     */       //   88: aload_1
/*     */       //   89: checkcast com/intellij/ml/llm/matterhorn/ej/idea/run/TestEvent
/*     */       //   92: invokevirtual getTestResult : ()Lcom/intellij/ml/llm/matterhorn/ej/idea/run/TestResult;
/*     */       //   95: getstatic com/intellij/ml/llm/matterhorn/ej/idea/actions/RunTestAgentAction$Companion$handleEvents$2$WhenMappings.$EnumSwitchMapping$0 : [I
/*     */       //   98: swap
/*     */       //   99: invokevirtual ordinal : ()I
/*     */       //   102: iaload
/*     */       //   103: tableswitch default -> 205, 1 -> 124, 2 -> 154
/*     */       //   124: aload_0
/*     */       //   125: getfield $passedTestNames : Ljava/util/List;
/*     */       //   128: new com/intellij/ml/llm/matterhorn/ej/idea/actions/PassedTest
/*     */       //   131: dup
/*     */       //   132: aload_0
/*     */       //   133: getfield $classFQName : Ljava/lang/String;
/*     */       //   136: aload_1
/*     */       //   137: checkcast com/intellij/ml/llm/matterhorn/ej/idea/run/TestEvent
/*     */       //   140: invokevirtual getName : ()Ljava/lang/String;
/*     */       //   143: invokespecial <init> : (Ljava/lang/String;Ljava/lang/String;)V
/*     */       //   146: invokeinterface add : (Ljava/lang/Object;)Z
/*     */       //   151: goto -> 213
/*     */       //   154: aload_0
/*     */       //   155: getfield $failedTests : Ljava/util/List;
/*     */       //   158: new com/intellij/ml/llm/matterhorn/ej/idea/actions/FailedTest
/*     */       //   161: dup
/*     */       //   162: aload_0
/*     */       //   163: getfield $classFQName : Ljava/lang/String;
/*     */       //   166: aload_1
/*     */       //   167: checkcast com/intellij/ml/llm/matterhorn/ej/idea/run/TestEvent
/*     */       //   170: invokevirtual getName : ()Ljava/lang/String;
/*     */       //   173: aload_1
/*     */       //   174: checkcast com/intellij/ml/llm/matterhorn/ej/idea/run/TestEvent
/*     */       //   177: invokevirtual getText : ()Ljava/lang/String;
/*     */       //   180: aload_1
/*     */       //   181: checkcast com/intellij/ml/llm/matterhorn/ej/idea/run/TestEvent
/*     */       //   184: invokevirtual getStackTrace : ()Ljava/lang/String;
/*     */       //   187: aload_1
/*     */       //   188: checkcast com/intellij/ml/llm/matterhorn/ej/idea/run/TestEvent
/*     */       //   191: invokevirtual getErrorMessage : ()Ljava/lang/String;
/*     */       //   194: invokespecial <init> : (Ljava/lang/String;Ljava/lang/String;Ljava/lang/String;Ljava/lang/String;Ljava/lang/String;)V
/*     */       //   197: invokeinterface add : (Ljava/lang/Object;)Z
/*     */       //   202: goto -> 213
/*     */       //   205: new kotlin/NoWhenBranchMatchedException
/*     */       //   208: dup
/*     */       //   209: invokespecial <init> : ()V
/*     */       //   212: athrow
/*     */       //   213: invokestatic boxBoolean : (Z)Ljava/lang/Boolean;
/*     */       //   216: pop
/*     */       //   217: goto -> 228
/*     */       //   220: new kotlin/NoWhenBranchMatchedException
/*     */       //   223: dup
/*     */       //   224: invokespecial <init> : ()V
/*     */       //   227: athrow
/*     */       //   228: getstatic kotlin/Unit.INSTANCE : Lkotlin/Unit;
/*     */       //   231: areturn
/*     */       // Line number table:
/*     */       //   Java source line number -> byte code offset
/*     */       //   #211	-> 0
/*     */       //   #212	-> 2
/*     */       //   #213	-> 46
/*     */       //   #214	-> 53
/*     */       //   #215	-> 60
/*     */       //   #216	-> 67
/*     */       //   #217	-> 74
/*     */       //   #218	-> 81
/*     */       //   #219	-> 88
/*     */       //   #220	-> 124
/*     */       //   #221	-> 154
/*     */       //   #222	-> 158
/*     */       //   #223	-> 162
/*     */       //   #224	-> 166
/*     */       //   #225	-> 173
/*     */       //   #226	-> 180
/*     */       //   #227	-> 187
/*     */       //   #222	-> 194
/*     */       //   #221	-> 197
/*     */       //   #219	-> 205
/*     */       //   #211	-> 220
/*     */       //   #233	-> 228
/*     */       // Local variable table:
/*     */       //   start	length	slot	name	descriptor
/*     */       //   0	232	0	this	Lcom/intellij/ml/llm/matterhorn/ej/idea/actions/RunTestAgentAction$Companion$handleEvents$2;
/*     */       //   0	232	1	it	Lcom/intellij/ml/llm/matterhorn/ej/idea/run/RunEvent;
/*     */       //   0	232	2	$completion	Lkotlin/coroutines/Continuation;
/*     */     }
/*     */     
/*     */     RunTestAgentAction$Companion$handleEvents$2(List<BuildMessage> $buildMessages, List<PassedTest> $passedTestNames, String $classFQName, List<FailedTest> $failedTests) {}
/*     */   }
/*     */ }


/* Location:              C:\Users\yuzum\Downloads\ej-release-243.132.63.zip!\ej\lib\ej-243.132.63.jar!\com\intellij\ml\llm\matterhorn\ej\idea\actions\RunTestAgentAction$Companion.class
 * Java compiler version: 17 (61.0)
 * JD-Core Version:       1.1.3
 */