/*    */ package com.intellij.ml.llm.matterhorn.ej.core.run.docker;
/*    */ 
/*    */ import java.util.List;
/*    */ import kotlin.Metadata;
/*    */ import org.jetbrains.annotations.NotNull;
/*    */ 
/*    */ 
/*    */ 
/*    */ 
/*    */ 
/*    */ 
/*    */ 
/*    */ 
/*    */ 
/*    */ 
/*    */ 
/*    */ 
/*    */ 
/*    */ 
/*    */ 
/*    */ 
/*    */ 
/*    */ 
/*    */ 
/*    */ 
/*    */ 
/*    */ 
/*    */ 
/*    */ 
/*    */ 
/*    */ 
/*    */ 
/*    */ 
/*    */ 
/*    */ 
/*    */ 
/*    */ 
/*    */ 
/*    */ 
/*    */ 
/*    */ 
/*    */ 
/*    */ 
/*    */ 
/*    */ 
/*    */ 
/*    */ 
/*    */ 
/*    */ 
/*    */ 
/*    */ 
/*    */ 
/*    */ 
/*    */ 
/*    */ 
/*    */ 
/*    */ 
/*    */ 
/*    */ 
/*    */ 
/*    */ 
/*    */ 
/*    */ 
/*    */ @Metadata(mv = {2, 1, 0}, k = 1, xi = 48, d1 = {"\000\034\n\002\030\002\n\002\020\000\n\000\n\002\020\016\n\000\n\002\020 \n\002\030\002\n\002\b\n\030\0002\0020\001B%\022\006\020\002\032\0020\003\022\f\020\004\032\b\022\004\022\0020\0060\005\022\006\020\007\032\0020\003¢\006\004\b\b\020\tJ\b\020\017\032\0020\003H\026R\021\020\002\032\0020\003¢\006\b\n\000\032\004\b\n\020\013R\027\020\004\032\b\022\004\022\0020\0060\005¢\006\b\n\000\032\004\b\f\020\rR\021\020\007\032\0020\003¢\006\b\n\000\032\004\b\016\020\013¨\006\020"}, d2 = {"Lcom/intellij/ml/llm/matterhorn/ej/core/run/docker/DockerFile;", "", "baseImage", "", "runCommands", "", "Lcom/intellij/ml/llm/matterhorn/ej/core/run/docker/DockerfileCommand;", "cmd", "<init>", "(Ljava/lang/String;Ljava/util/List;Ljava/lang/String;)V", "getBaseImage", "()Ljava/lang/String;", "getRunCommands", "()Ljava/util/List;", "getCmd", "toString", "ej-core"})
/*    */ public final class DockerFile
/*    */ {
/*    */   @NotNull
/*    */   private final String baseImage;
/*    */   @NotNull
/*    */   private final List<DockerfileCommand> runCommands;
/*    */   @NotNull
/*    */   private final String cmd;
/*    */   
/*    */   public DockerFile(@NotNull String baseImage, @NotNull List<DockerfileCommand> runCommands, @NotNull String cmd) {
/* 75 */     this.baseImage = baseImage; this.runCommands = runCommands; this.cmd = cmd; } @NotNull public final String getBaseImage() { return this.baseImage; } @NotNull public final List<DockerfileCommand> getRunCommands() { return this.runCommands; } @NotNull public final String getCmd() { return this.cmd; }
/*    */ 
/*    */   
/*    */   @NotNull
/*    */   public String toString() {
/*    */     // Byte code:
/*    */     //   0: new java/lang/StringBuilder
/*    */     //   3: dup
/*    */     //   4: invokespecial <init> : ()V
/*    */     //   7: astore_1
/*    */     //   8: aload_1
/*    */     //   9: astore_2
/*    */     //   10: iconst_0
/*    */     //   11: istore_3
/*    */     //   12: aload_2
/*    */     //   13: aload_0
/*    */     //   14: getfield baseImage : Ljava/lang/String;
/*    */     //   17: <illegal opcode> makeConcatWithConstants : (Ljava/lang/String;)Ljava/lang/String;
/*    */     //   22: invokevirtual append : (Ljava/lang/String;)Ljava/lang/StringBuilder;
/*    */     //   25: dup
/*    */     //   26: ldc 'append(...)'
/*    */     //   28: invokestatic checkNotNullExpressionValue : (Ljava/lang/Object;Ljava/lang/String;)V
/*    */     //   31: bipush #10
/*    */     //   33: invokevirtual append : (C)Ljava/lang/StringBuilder;
/*    */     //   36: dup
/*    */     //   37: ldc 'append(...)'
/*    */     //   39: invokestatic checkNotNullExpressionValue : (Ljava/lang/Object;Ljava/lang/String;)V
/*    */     //   42: pop
/*    */     //   43: aload_0
/*    */     //   44: getfield runCommands : Ljava/util/List;
/*    */     //   47: invokeinterface iterator : ()Ljava/util/Iterator;
/*    */     //   52: astore #4
/*    */     //   54: aload #4
/*    */     //   56: invokeinterface hasNext : ()Z
/*    */     //   61: ifeq -> 268
/*    */     //   64: aload #4
/*    */     //   66: invokeinterface next : ()Ljava/lang/Object;
/*    */     //   71: checkcast com/intellij/ml/llm/matterhorn/ej/core/run/docker/DockerfileCommand
/*    */     //   74: astore #5
/*    */     //   76: aload #5
/*    */     //   78: invokevirtual getType : ()Lcom/intellij/ml/llm/matterhorn/ej/core/run/docker/DockerfileCommandType;
/*    */     //   81: getstatic com/intellij/ml/llm/matterhorn/ej/core/run/docker/DockerFile$WhenMappings.$EnumSwitchMapping$0 : [I
/*    */     //   84: swap
/*    */     //   85: invokevirtual ordinal : ()I
/*    */     //   88: iaload
/*    */     //   89: tableswitch default -> 256, 1 -> 120, 2 -> 154, 3 -> 188, 4 -> 222
/*    */     //   120: aload_2
/*    */     //   121: aload #5
/*    */     //   123: invokevirtual getText : ()Ljava/lang/String;
/*    */     //   126: <illegal opcode> makeConcatWithConstants : (Ljava/lang/String;)Ljava/lang/String;
/*    */     //   131: invokevirtual append : (Ljava/lang/String;)Ljava/lang/StringBuilder;
/*    */     //   134: dup
/*    */     //   135: ldc 'append(...)'
/*    */     //   137: invokestatic checkNotNullExpressionValue : (Ljava/lang/Object;Ljava/lang/String;)V
/*    */     //   140: bipush #10
/*    */     //   142: invokevirtual append : (C)Ljava/lang/StringBuilder;
/*    */     //   145: dup
/*    */     //   146: ldc 'append(...)'
/*    */     //   148: invokestatic checkNotNullExpressionValue : (Ljava/lang/Object;Ljava/lang/String;)V
/*    */     //   151: goto -> 264
/*    */     //   154: aload_2
/*    */     //   155: aload #5
/*    */     //   157: invokevirtual getText : ()Ljava/lang/String;
/*    */     //   160: <illegal opcode> makeConcatWithConstants : (Ljava/lang/String;)Ljava/lang/String;
/*    */     //   165: invokevirtual append : (Ljava/lang/String;)Ljava/lang/StringBuilder;
/*    */     //   168: dup
/*    */     //   169: ldc 'append(...)'
/*    */     //   171: invokestatic checkNotNullExpressionValue : (Ljava/lang/Object;Ljava/lang/String;)V
/*    */     //   174: bipush #10
/*    */     //   176: invokevirtual append : (C)Ljava/lang/StringBuilder;
/*    */     //   179: dup
/*    */     //   180: ldc 'append(...)'
/*    */     //   182: invokestatic checkNotNullExpressionValue : (Ljava/lang/Object;Ljava/lang/String;)V
/*    */     //   185: goto -> 264
/*    */     //   188: aload_2
/*    */     //   189: aload #5
/*    */     //   191: invokevirtual getText : ()Ljava/lang/String;
/*    */     //   194: <illegal opcode> makeConcatWithConstants : (Ljava/lang/String;)Ljava/lang/String;
/*    */     //   199: invokevirtual append : (Ljava/lang/String;)Ljava/lang/StringBuilder;
/*    */     //   202: dup
/*    */     //   203: ldc 'append(...)'
/*    */     //   205: invokestatic checkNotNullExpressionValue : (Ljava/lang/Object;Ljava/lang/String;)V
/*    */     //   208: bipush #10
/*    */     //   210: invokevirtual append : (C)Ljava/lang/StringBuilder;
/*    */     //   213: dup
/*    */     //   214: ldc 'append(...)'
/*    */     //   216: invokestatic checkNotNullExpressionValue : (Ljava/lang/Object;Ljava/lang/String;)V
/*    */     //   219: goto -> 264
/*    */     //   222: aload_2
/*    */     //   223: aload #5
/*    */     //   225: invokevirtual getText : ()Ljava/lang/String;
/*    */     //   228: <illegal opcode> makeConcatWithConstants : (Ljava/lang/String;)Ljava/lang/String;
/*    */     //   233: invokevirtual append : (Ljava/lang/String;)Ljava/lang/StringBuilder;
/*    */     //   236: dup
/*    */     //   237: ldc 'append(...)'
/*    */     //   239: invokestatic checkNotNullExpressionValue : (Ljava/lang/Object;Ljava/lang/String;)V
/*    */     //   242: bipush #10
/*    */     //   244: invokevirtual append : (C)Ljava/lang/StringBuilder;
/*    */     //   247: dup
/*    */     //   248: ldc 'append(...)'
/*    */     //   250: invokestatic checkNotNullExpressionValue : (Ljava/lang/Object;Ljava/lang/String;)V
/*    */     //   253: goto -> 264
/*    */     //   256: new kotlin/NoWhenBranchMatchedException
/*    */     //   259: dup
/*    */     //   260: invokespecial <init> : ()V
/*    */     //   263: athrow
/*    */     //   264: pop
/*    */     //   265: goto -> 54
/*    */     //   268: aload_2
/*    */     //   269: aload_0
/*    */     //   270: getfield cmd : Ljava/lang/String;
/*    */     //   273: <illegal opcode> makeConcatWithConstants : (Ljava/lang/String;)Ljava/lang/String;
/*    */     //   278: invokevirtual append : (Ljava/lang/String;)Ljava/lang/StringBuilder;
/*    */     //   281: dup
/*    */     //   282: ldc 'append(...)'
/*    */     //   284: invokestatic checkNotNullExpressionValue : (Ljava/lang/Object;Ljava/lang/String;)V
/*    */     //   287: bipush #10
/*    */     //   289: invokevirtual append : (C)Ljava/lang/StringBuilder;
/*    */     //   292: dup
/*    */     //   293: ldc 'append(...)'
/*    */     //   295: invokestatic checkNotNullExpressionValue : (Ljava/lang/Object;Ljava/lang/String;)V
/*    */     //   298: pop
/*    */     //   299: nop
/*    */     //   300: aload_1
/*    */     //   301: invokevirtual toString : ()Ljava/lang/String;
/*    */     //   304: dup
/*    */     //   305: ldc 'toString(...)'
/*    */     //   307: invokestatic checkNotNullExpressionValue : (Ljava/lang/Object;Ljava/lang/String;)V
/*    */     //   310: areturn
/*    */     // Line number table:
/*    */     //   Java source line number -> byte code offset
/*    */     //   #78	-> 0
/*    */     //   #79	-> 12
/*    */     //   #80	-> 43
/*    */     //   #81	-> 76
/*    */     //   #82	-> 120
/*    */     //   #83	-> 154
/*    */     //   #84	-> 188
/*    */     //   #85	-> 222
/*    */     //   #81	-> 256
/*    */     //   #88	-> 268
/*    */     //   #89	-> 299
/*    */     //   #78	-> 300
/*    */     //   #78	-> 310
/*    */     // Local variable table:
/*    */     //   start	length	slot	name	descriptor
/*    */     //   76	189	5	command	Lcom/intellij/ml/llm/matterhorn/ej/core/run/docker/DockerfileCommand;
/*    */     //   12	288	3	$i$a$-buildString-DockerFile$toString$1	I
/*    */     //   10	290	2	$this$toString_u24lambda_u240	Ljava/lang/StringBuilder;
/*    */     //   0	311	0	this	Lcom/intellij/ml/llm/matterhorn/ej/core/run/docker/DockerFile;
/*    */   }
/*    */ }


/* Location:              C:\Users\yuzum\Downloads\ej-release-243.132.63.zip!\ej\lib\ej-243.132.63.jar!\com\intellij\ml\llm\matterhorn\ej\core\run\docker\DockerFile.class
 * Java compiler version: 17 (61.0)
 * JD-Core Version:       1.1.3
 */