/*     */ package ai.grazie.nlp.langs;
/*     */ 
/*     */ import kotlin.Metadata;
/*     */ import kotlin.jvm.internal.DefaultConstructorMarker;
/*     */ import kotlin.jvm.internal.SourceDebugExtension;
/*     */ import kotlinx.serialization.KSerializer;
/*     */ import org.jetbrains.annotations.NotNull;
/*     */ import org.jetbrains.annotations.Nullable;
/*     */ 
/*     */ 
/*     */ 
/*     */ 
/*     */ 
/*     */ 
/*     */ 
/*     */ 
/*     */ 
/*     */ 
/*     */ 
/*     */ 
/*     */ 
/*     */ 
/*     */ 
/*     */ 
/*     */ 
/*     */ 
/*     */ 
/*     */ 
/*     */ 
/*     */ 
/*     */ 
/*     */ 
/*     */ 
/*     */ 
/*     */ 
/*     */ 
/*     */ 
/*     */ 
/*     */ 
/*     */ 
/*     */ 
/*     */ 
/*     */ 
/*     */ 
/*     */ 
/*     */ 
/*     */ 
/*     */ 
/*     */ 
/*     */ 
/*     */ 
/*     */ 
/*     */ 
/*     */ 
/*     */ 
/*     */ 
/*     */ 
/*     */ 
/*     */ 
/*     */ 
/*     */ 
/*     */ 
/*     */ 
/*     */ 
/*     */ 
/*     */ 
/*     */ 
/*     */ 
/*     */ 
/*     */ 
/*     */ 
/*     */ 
/*     */ 
/*     */ 
/*     */ 
/*     */ 
/*     */ 
/*     */ 
/*     */ 
/*     */ 
/*     */ 
/*     */ 
/*     */ 
/*     */ 
/*     */ 
/*     */ 
/*     */ 
/*     */ 
/*     */ 
/*     */ 
/*     */ 
/*     */ 
/*     */ 
/*     */ 
/*     */ 
/*     */ 
/*     */ 
/*     */ 
/*     */ 
/*     */ 
/*     */ 
/*     */ 
/*     */ 
/*     */ 
/*     */ 
/*     */ 
/*     */ 
/*     */ 
/*     */ 
/*     */ 
/*     */ 
/*     */ 
/*     */ 
/*     */ 
/*     */ 
/*     */ 
/*     */ 
/*     */ 
/*     */ 
/*     */ 
/*     */ 
/*     */ 
/*     */ 
/*     */ 
/*     */ 
/*     */ 
/*     */ 
/*     */ 
/*     */ 
/*     */ 
/*     */ 
/*     */ 
/*     */ 
/*     */ 
/*     */ 
/*     */ 
/*     */ 
/*     */ 
/*     */ 
/*     */ 
/*     */ 
/*     */ 
/*     */ 
/*     */ 
/*     */ 
/*     */ 
/*     */ 
/*     */ 
/*     */ 
/*     */ 
/*     */ 
/*     */ 
/*     */ 
/*     */ 
/*     */ 
/*     */ 
/*     */ 
/*     */ 
/*     */ 
/*     */ 
/*     */ 
/*     */ 
/*     */ 
/*     */ 
/*     */ 
/*     */ 
/*     */ 
/*     */ 
/*     */ 
/*     */ 
/*     */ 
/*     */ 
/*     */ 
/*     */ 
/*     */ 
/*     */ 
/*     */ 
/*     */ 
/*     */ 
/*     */ 
/*     */ 
/*     */ 
/*     */ 
/*     */ 
/*     */ @Metadata(mv = {1, 7, 0}, k = 1, xi = 48, d1 = {"\000\036\n\002\030\002\n\002\020\000\n\002\b\002\n\002\030\002\n\000\n\002\020\016\n\000\n\002\030\002\n\000\b\003\030\0002\0020\001B\007\b\002¢\006\002\020\002J\020\020\003\032\004\030\0010\0042\006\020\005\032\0020\006J\017\020\007\032\b\022\004\022\0020\0040\bHÆ\001¨\006\t"}, d2 = {"Lai/grazie/nlp/langs/LanguageISO$Companion;", "", "()V", "parse", "Lai/grazie/nlp/langs/LanguageISO;", "code", "", "serializer", "Lkotlinx/serialization/KSerializer;", "nlp-langs"})
/*     */ @SourceDebugExtension({"SMAP\nLanguageISO.kt\nKotlin\n*S Kotlin\n*F\n+ 1 LanguageISO.kt\nai/grazie/nlp/langs/LanguageISO$Companion\n+ 2 fake.kt\nkotlin/jvm/internal/FakeKt\n*L\n1#1,199:1\n1#2:200\n*E\n"})
/*     */ public final class Companion
/*     */ {
/*     */   private Companion() {}
/*     */   
/*     */   @NotNull
/*     */   public final KSerializer<LanguageISO> serializer() {
/* 193 */     return get$cachedSerializer();
/*     */   }
/*     */   
/*     */   @Nullable
/*     */   public final LanguageISO parse(@NotNull String code) {
/*     */     // Byte code:
/*     */     //   0: aload_1
/*     */     //   1: ldc 'code'
/*     */     //   3: invokestatic checkNotNullParameter : (Ljava/lang/Object;Ljava/lang/String;)V
/*     */     //   6: invokestatic values : ()[Lai/grazie/nlp/langs/LanguageISO;
/*     */     //   9: astore_2
/*     */     //   10: iconst_0
/*     */     //   11: istore_3
/*     */     //   12: aload_2
/*     */     //   13: arraylength
/*     */     //   14: istore #4
/*     */     //   16: iload_3
/*     */     //   17: iload #4
/*     */     //   19: if_icmpge -> 81
/*     */     //   22: aload_2
/*     */     //   23: iload_3
/*     */     //   24: aaload
/*     */     //   25: astore #5
/*     */     //   27: aload #5
/*     */     //   29: astore #6
/*     */     //   31: iconst_0
/*     */     //   32: istore #7
/*     */     //   34: aload #6
/*     */     //   36: invokevirtual name : ()Ljava/lang/String;
/*     */     //   39: getstatic java/util/Locale.ROOT : Ljava/util/Locale;
/*     */     //   42: invokevirtual toLowerCase : (Ljava/util/Locale;)Ljava/lang/String;
/*     */     //   45: dup
/*     */     //   46: ldc 'toLowerCase(...)'
/*     */     //   48: invokestatic checkNotNullExpressionValue : (Ljava/lang/Object;Ljava/lang/String;)V
/*     */     //   51: aload_1
/*     */     //   52: getstatic java/util/Locale.ROOT : Ljava/util/Locale;
/*     */     //   55: invokevirtual toLowerCase : (Ljava/util/Locale;)Ljava/lang/String;
/*     */     //   58: dup
/*     */     //   59: ldc 'toLowerCase(...)'
/*     */     //   61: invokestatic checkNotNullExpressionValue : (Ljava/lang/Object;Ljava/lang/String;)V
/*     */     //   64: invokestatic areEqual : (Ljava/lang/Object;Ljava/lang/Object;)Z
/*     */     //   67: ifeq -> 75
/*     */     //   70: aload #5
/*     */     //   72: goto -> 82
/*     */     //   75: iinc #3, 1
/*     */     //   78: goto -> 16
/*     */     //   81: aconst_null
/*     */     //   82: areturn
/*     */     // Line number table:
/*     */     //   Java source line number -> byte code offset
/*     */     //   #195	-> 6
/*     */     //   #200	-> 31
/*     */     //   #195	-> 34
/*     */     //   #195	-> 51
/*     */     //   #195	-> 64
/*     */     //   #195	-> 67
/*     */     //   #195	-> 82
/*     */     // Local variable table:
/*     */     //   start	length	slot	name	descriptor
/*     */     //   34	33	7	$i$a$-find-LanguageISO$Companion$parse$1	I
/*     */     //   31	36	6	it	Lai/grazie/nlp/langs/LanguageISO;
/*     */     //   0	83	0	this	Lai/grazie/nlp/langs/LanguageISO$Companion;
/*     */     //   0	83	1	code	Ljava/lang/String;
/*     */   }
/*     */ }


/* Location:              C:\Users\yuzum\Downloads\ej-release-243.132.63.zip!\ej\lib\nlp-langs-jvm-0.4.32.jar!\ai\grazie\nlp\langs\LanguageISO$Companion.class
 * Java compiler version: 17 (61.0)
 * JD-Core Version:       1.1.3
 */