/*     */ package org.jetbrains.jewel.ui.component;
/*     */ 
/*     */ import androidx.compose.foundation.interaction.Interaction;
/*     */ import androidx.compose.foundation.interaction.MutableInteractionSource;
/*     */ import androidx.compose.foundation.layout.RowScope;
/*     */ import androidx.compose.runtime.Composable;
/*     */ import androidx.compose.runtime.ComposableInferredTarget;
/*     */ import androidx.compose.runtime.ComposableTarget;
/*     */ import androidx.compose.runtime.Composer;
/*     */ import androidx.compose.runtime.ComposerKt;
/*     */ import androidx.compose.runtime.MutableState;
/*     */ import androidx.compose.runtime.RecomposeScopeImplKt;
/*     */ import androidx.compose.runtime.State;
/*     */ import androidx.compose.ui.Alignment;
/*     */ import androidx.compose.ui.Modifier;
/*     */ import androidx.compose.ui.graphics.Color;
/*     */ import androidx.compose.ui.graphics.painter.Painter;
/*     */ import androidx.compose.ui.text.TextStyle;
/*     */ import kotlin.Metadata;
/*     */ import kotlin.ResultKt;
/*     */ import kotlin.Unit;
/*     */ import kotlin.coroutines.Continuation;
/*     */ import kotlin.coroutines.intrinsics.IntrinsicsKt;
/*     */ import kotlin.coroutines.jvm.internal.DebugMetadata;
/*     */ import kotlin.coroutines.jvm.internal.SuspendLambda;
/*     */ import kotlin.jvm.functions.Function0;
/*     */ import kotlin.jvm.functions.Function2;
/*     */ import kotlin.jvm.functions.Function3;
/*     */ import kotlin.jvm.internal.Intrinsics;
/*     */ import kotlin.jvm.internal.SourceDebugExtension;
/*     */ import kotlin.reflect.KProperty;
/*     */ import kotlinx.coroutines.CoroutineScope;
/*     */ import kotlinx.coroutines.flow.FlowCollector;
/*     */ import org.jetbrains.annotations.NotNull;
/*     */ import org.jetbrains.annotations.Nullable;
/*     */ import org.jetbrains.jewel.ui.Outline;
/*     */ import org.jetbrains.jewel.ui.component.styling.RadioButtonStyle;
/*     */ 
/*     */ 
/*     */ 
/*     */ 
/*     */ 
/*     */ 
/*     */ 
/*     */ 
/*     */ 
/*     */ 
/*     */ 
/*     */ 
/*     */ 
/*     */ 
/*     */ 
/*     */ 
/*     */ 
/*     */ 
/*     */ 
/*     */ 
/*     */ 
/*     */ 
/*     */ 
/*     */ 
/*     */ 
/*     */ 
/*     */ 
/*     */ 
/*     */ 
/*     */ 
/*     */ 
/*     */ 
/*     */ 
/*     */ 
/*     */ 
/*     */ 
/*     */ 
/*     */ 
/*     */ @Metadata(mv = {2, 0, 0}, k = 2, xi = 48, d1 = {"\000j\n\000\n\002\020\002\n\000\n\002\020\013\n\000\n\002\030\002\n\000\n\002\030\002\n\002\b\002\n\002\030\002\n\000\n\002\030\002\n\000\n\002\030\002\n\000\n\002\030\002\n\000\n\002\030\002\n\002\b\003\n\002\020\016\n\002\b\002\n\002\030\002\n\002\030\002\n\002\030\002\n\002\030\002\n\002\b\005\n\002\030\002\n\002\b\003\n\002\030\002\n\000\n\002\030\002\032i\020\000\032\0020\0012\006\020\002\032\0020\0032\f\020\004\032\b\022\004\022\0020\0010\0052\b\b\002\020\006\032\0020\0072\b\b\002\020\b\032\0020\0032\b\b\002\020\t\032\0020\n2\b\b\002\020\013\032\0020\f2\b\b\002\020\r\032\0020\0162\b\b\002\020\017\032\0020\0202\b\b\002\020\021\032\0020\022H\007¢\006\002\020\023\032q\020\024\032\0020\0012\006\020\025\032\0020\0262\006\020\002\032\0020\0032\f\020\004\032\b\022\004\022\0020\0010\0052\b\b\002\020\006\032\0020\0072\b\b\002\020\b\032\0020\0032\b\b\002\020\t\032\0020\n2\b\b\002\020\013\032\0020\f2\b\b\002\020\r\032\0020\0162\b\b\002\020\017\032\0020\0202\b\b\002\020\021\032\0020\022H\007¢\006\002\020\027\032\001\020\024\032\0020\0012\006\020\002\032\0020\0032\f\020\004\032\b\022\004\022\0020\0010\0052\b\b\002\020\006\032\0020\0072\b\b\002\020\b\032\0020\0032\b\b\002\020\t\032\0020\n2\b\b\002\020\013\032\0020\f2\b\b\002\020\r\032\0020\0162\b\b\002\020\017\032\0020\0202\b\b\002\020\021\032\0020\0222\034\020\030\032\030\022\004\022\0020\032\022\004\022\0020\0010\031¢\006\002\b\033¢\006\002\b\034H\007¢\006\002\020\035\032{\020\036\032\0020\0012\006\020\002\032\0020\0032\f\020\004\032\b\022\004\022\0020\0010\0052\006\020\006\032\0020\0072\006\020\b\032\0020\0032\006\020\t\032\0020\n2\006\020\013\032\0020\f2\006\020\r\032\0020\0162\006\020\017\032\0020\0202\006\020\021\032\0020\0222\036\020\030\032\032\022\004\022\0020\032\022\004\022\0020\001\030\0010\031¢\006\002\b\033¢\006\002\b\034H\003¢\006\002\020\037\032\037\020 \032\0020\0012\006\020!\032\0020\"2\b\b\002\020\006\032\0020\007H\003¢\006\002\020#¨\006$²\006\n\020%\032\0020&X\002²\006\n\020!\032\0020\"X\002²\006\n\020'\032\0020(X\002"}, d2 = {"RadioButton", "", "selected", "", "onClick", "Lkotlin/Function0;", "modifier", "Landroidx/compose/ui/Modifier;", "enabled", "outline", "Lorg/jetbrains/jewel/ui/Outline;", "interactionSource", "Landroidx/compose/foundation/interaction/MutableInteractionSource;", "style", "Lorg/jetbrains/jewel/ui/component/styling/RadioButtonStyle;", "textStyle", "Landroidx/compose/ui/text/TextStyle;", "verticalAlignment", "Landroidx/compose/ui/Alignment$Vertical;", "(ZLkotlin/jvm/functions/Function0;Landroidx/compose/ui/Modifier;ZLorg/jetbrains/jewel/ui/Outline;Landroidx/compose/foundation/interaction/MutableInteractionSource;Lorg/jetbrains/jewel/ui/component/styling/RadioButtonStyle;Landroidx/compose/ui/text/TextStyle;Landroidx/compose/ui/Alignment$Vertical;Landroidx/compose/runtime/Composer;II)V", "RadioButtonRow", "text", "", "(Ljava/lang/String;ZLkotlin/jvm/functions/Function0;Landroidx/compose/ui/Modifier;ZLorg/jetbrains/jewel/ui/Outline;Landroidx/compose/foundation/interaction/MutableInteractionSource;Lorg/jetbrains/jewel/ui/component/styling/RadioButtonStyle;Landroidx/compose/ui/text/TextStyle;Landroidx/compose/ui/Alignment$Vertical;Landroidx/compose/runtime/Composer;II)V", "content", "Lkotlin/Function1;", "Landroidx/compose/foundation/layout/RowScope;", "Lkotlin/ExtensionFunctionType;", "Landroidx/compose/runtime/Composable;", "(ZLkotlin/jvm/functions/Function0;Landroidx/compose/ui/Modifier;ZLorg/jetbrains/jewel/ui/Outline;Landroidx/compose/foundation/interaction/MutableInteractionSource;Lorg/jetbrains/jewel/ui/component/styling/RadioButtonStyle;Landroidx/compose/ui/text/TextStyle;Landroidx/compose/ui/Alignment$Vertical;Lkotlin/jvm/functions/Function3;Landroidx/compose/runtime/Composer;II)V", "RadioButtonImpl", "(ZLkotlin/jvm/functions/Function0;Landroidx/compose/ui/Modifier;ZLorg/jetbrains/jewel/ui/Outline;Landroidx/compose/foundation/interaction/MutableInteractionSource;Lorg/jetbrains/jewel/ui/component/styling/RadioButtonStyle;Landroidx/compose/ui/text/TextStyle;Landroidx/compose/ui/Alignment$Vertical;Lkotlin/jvm/functions/Function3;Landroidx/compose/runtime/Composer;I)V", "RadioButtonImage", "radioButtonPainter", "Landroidx/compose/ui/graphics/painter/Painter;", "(Landroidx/compose/ui/graphics/painter/Painter;Landroidx/compose/ui/Modifier;Landroidx/compose/runtime/Composer;II)V", "ui", "radioButtonState", "Lorg/jetbrains/jewel/ui/component/RadioButtonState;", "contentColor", "Landroidx/compose/ui/graphics/Color;"})
/*     */ @SourceDebugExtension({"SMAP\nRadioButton.kt\nKotlin\n*S Kotlin\n*F\n+ 1 RadioButton.kt\norg/jetbrains/jewel/ui/component/RadioButtonKt\n+ 2 Composer.kt\nandroidx/compose/runtime/ComposerKt\n+ 3 Box.kt\nandroidx/compose/foundation/layout/BoxKt\n+ 4 Layout.kt\nandroidx/compose/ui/layout/LayoutKt\n+ 5 Composables.kt\nandroidx/compose/runtime/ComposablesKt\n+ 6 Composer.kt\nandroidx/compose/runtime/Updater\n+ 7 Row.kt\nandroidx/compose/foundation/layout/RowKt\n+ 8 Color.kt\nandroidx/compose/ui/graphics/ColorKt\n+ 9 CompositionLocal.kt\nandroidx/compose/runtime/CompositionLocal\n+ 10 SnapshotState.kt\nandroidx/compose/runtime/SnapshotStateKt__SnapshotStateKt\n*L\n1#1,288:1\n1225#2,6:289\n1225#2,6:295\n1225#2,6:301\n1225#2,6:307\n1225#2,6:313\n1225#2,6:319\n71#3:325\n69#3,5:326\n74#3:359\n78#3:363\n71#3:396\n69#3,5:397\n74#3:430\n78#3:434\n79#4,6:331\n86#4,4:346\n90#4,2:356\n94#4:362\n79#4,6:367\n86#4,4:382\n90#4,2:392\n79#4,6:402\n86#4,4:417\n90#4,2:427\n94#4:433\n94#4:442\n368#5,9:337\n377#5:358\n378#5,2:360\n368#5,9:373\n377#5:394\n368#5,9:408\n377#5:429\n378#5,2:431\n378#5,2:440\n4034#6,6:350\n4034#6,6:386\n4034#6,6:421\n99#7,3:364\n102#7:395\n106#7:443\n708#8:435\n696#8:436\n708#8:438\n696#8:439\n77#9:437\n81#10:444\n107#10,2:445\n81#10:447\n81#10:448\n*S KotlinDebug\n*F\n+ 1 RadioButton.kt\norg/jetbrains/jewel/ui/component/RadioButtonKt\n*L\n56#1:289,6\n83#1:295,6\n110#1:301,6\n143#1:307,6\n145#1:313,6\n148#1:319,6\n193#1:325\n193#1:326,5\n193#1:359\n193#1:363\n203#1:396\n203#1:397,5\n203#1:430\n203#1:434\n193#1:331,6\n193#1:346,4\n193#1:356,2\n193#1:362\n198#1:367,6\n198#1:382,4\n198#1:392,2\n203#1:402,6\n203#1:417,4\n203#1:427,2\n203#1:433\n198#1:442\n193#1:337,9\n193#1:358\n193#1:360,2\n198#1:373,9\n198#1:394\n203#1:408,9\n203#1:429\n203#1:431,2\n198#1:440,2\n193#1:350,6\n198#1:386,6\n203#1:421,6\n198#1:364,3\n198#1:395\n198#1:443\n210#1:435\n210#1:436\n213#1:438\n213#1:439\n210#1:437\n143#1:444\n143#1:445,2\n188#1:447\n208#1:448\n*E\n"})
/*     */ public final class RadioButtonKt
/*     */ {
/*     */   @Composable
/*     */   @ComposableTarget(applier = "androidx.compose.ui.UiComposable")
/*     */   public static final void RadioButton(boolean selected, @NotNull Function0 onClick, @Nullable Modifier modifier, boolean enabled, @Nullable Outline outline, @Nullable MutableInteractionSource interactionSource, @Nullable RadioButtonStyle style, @Nullable TextStyle textStyle, @Nullable Alignment.Vertical verticalAlignment, @Nullable Composer $composer, int $changed, int paramInt1) {
/*     */     // Byte code:
/*     */     //   0: aload_1
/*     */     //   1: ldc 'onClick'
/*     */     //   3: invokestatic checkNotNullParameter : (Ljava/lang/Object;Ljava/lang/String;)V
/*     */     //   6: aload #9
/*     */     //   8: ldc 2145800322
/*     */     //   10: invokeinterface startRestartGroup : (I)Landroidx/compose/runtime/Composer;
/*     */     //   15: astore #9
/*     */     //   17: iload #10
/*     */     //   19: istore #12
/*     */     //   21: iload #11
/*     */     //   23: iconst_1
/*     */     //   24: iand
/*     */     //   25: ifeq -> 38
/*     */     //   28: iload #12
/*     */     //   30: bipush #6
/*     */     //   32: ior
/*     */     //   33: istore #12
/*     */     //   35: goto -> 67
/*     */     //   38: iload #10
/*     */     //   40: bipush #6
/*     */     //   42: iand
/*     */     //   43: ifne -> 67
/*     */     //   46: iload #12
/*     */     //   48: aload #9
/*     */     //   50: iload_0
/*     */     //   51: invokeinterface changed : (Z)Z
/*     */     //   56: ifeq -> 63
/*     */     //   59: iconst_4
/*     */     //   60: goto -> 64
/*     */     //   63: iconst_2
/*     */     //   64: ior
/*     */     //   65: istore #12
/*     */     //   67: iload #11
/*     */     //   69: iconst_2
/*     */     //   70: iand
/*     */     //   71: ifeq -> 84
/*     */     //   74: iload #12
/*     */     //   76: bipush #48
/*     */     //   78: ior
/*     */     //   79: istore #12
/*     */     //   81: goto -> 115
/*     */     //   84: iload #10
/*     */     //   86: bipush #48
/*     */     //   88: iand
/*     */     //   89: ifne -> 115
/*     */     //   92: iload #12
/*     */     //   94: aload #9
/*     */     //   96: aload_1
/*     */     //   97: invokeinterface changedInstance : (Ljava/lang/Object;)Z
/*     */     //   102: ifeq -> 110
/*     */     //   105: bipush #32
/*     */     //   107: goto -> 112
/*     */     //   110: bipush #16
/*     */     //   112: ior
/*     */     //   113: istore #12
/*     */     //   115: iload #11
/*     */     //   117: iconst_4
/*     */     //   118: iand
/*     */     //   119: ifeq -> 133
/*     */     //   122: iload #12
/*     */     //   124: sipush #384
/*     */     //   127: ior
/*     */     //   128: istore #12
/*     */     //   130: goto -> 167
/*     */     //   133: iload #10
/*     */     //   135: sipush #384
/*     */     //   138: iand
/*     */     //   139: ifne -> 167
/*     */     //   142: iload #12
/*     */     //   144: aload #9
/*     */     //   146: aload_2
/*     */     //   147: invokeinterface changed : (Ljava/lang/Object;)Z
/*     */     //   152: ifeq -> 161
/*     */     //   155: sipush #256
/*     */     //   158: goto -> 164
/*     */     //   161: sipush #128
/*     */     //   164: ior
/*     */     //   165: istore #12
/*     */     //   167: iload #11
/*     */     //   169: bipush #8
/*     */     //   171: iand
/*     */     //   172: ifeq -> 186
/*     */     //   175: iload #12
/*     */     //   177: sipush #3072
/*     */     //   180: ior
/*     */     //   181: istore #12
/*     */     //   183: goto -> 220
/*     */     //   186: iload #10
/*     */     //   188: sipush #3072
/*     */     //   191: iand
/*     */     //   192: ifne -> 220
/*     */     //   195: iload #12
/*     */     //   197: aload #9
/*     */     //   199: iload_3
/*     */     //   200: invokeinterface changed : (Z)Z
/*     */     //   205: ifeq -> 214
/*     */     //   208: sipush #2048
/*     */     //   211: goto -> 217
/*     */     //   214: sipush #1024
/*     */     //   217: ior
/*     */     //   218: istore #12
/*     */     //   220: iload #11
/*     */     //   222: bipush #16
/*     */     //   224: iand
/*     */     //   225: ifeq -> 239
/*     */     //   228: iload #12
/*     */     //   230: sipush #24576
/*     */     //   233: ior
/*     */     //   234: istore #12
/*     */     //   236: goto -> 274
/*     */     //   239: iload #10
/*     */     //   241: sipush #24576
/*     */     //   244: iand
/*     */     //   245: ifne -> 274
/*     */     //   248: iload #12
/*     */     //   250: aload #9
/*     */     //   252: aload #4
/*     */     //   254: invokeinterface changed : (Ljava/lang/Object;)Z
/*     */     //   259: ifeq -> 268
/*     */     //   262: sipush #16384
/*     */     //   265: goto -> 271
/*     */     //   268: sipush #8192
/*     */     //   271: ior
/*     */     //   272: istore #12
/*     */     //   274: iload #11
/*     */     //   276: bipush #32
/*     */     //   278: iand
/*     */     //   279: ifeq -> 292
/*     */     //   282: iload #12
/*     */     //   284: ldc 196608
/*     */     //   286: ior
/*     */     //   287: istore #12
/*     */     //   289: goto -> 324
/*     */     //   292: iload #10
/*     */     //   294: ldc 196608
/*     */     //   296: iand
/*     */     //   297: ifne -> 324
/*     */     //   300: iload #12
/*     */     //   302: aload #9
/*     */     //   304: aload #5
/*     */     //   306: invokeinterface changed : (Ljava/lang/Object;)Z
/*     */     //   311: ifeq -> 319
/*     */     //   314: ldc 131072
/*     */     //   316: goto -> 321
/*     */     //   319: ldc 65536
/*     */     //   321: ior
/*     */     //   322: istore #12
/*     */     //   324: iload #10
/*     */     //   326: ldc 1572864
/*     */     //   328: iand
/*     */     //   329: ifne -> 364
/*     */     //   332: iload #12
/*     */     //   334: iload #11
/*     */     //   336: bipush #64
/*     */     //   338: iand
/*     */     //   339: ifne -> 359
/*     */     //   342: aload #9
/*     */     //   344: aload #6
/*     */     //   346: invokeinterface changed : (Ljava/lang/Object;)Z
/*     */     //   351: ifeq -> 359
/*     */     //   354: ldc 1048576
/*     */     //   356: goto -> 361
/*     */     //   359: ldc 524288
/*     */     //   361: ior
/*     */     //   362: istore #12
/*     */     //   364: iload #10
/*     */     //   366: ldc 12582912
/*     */     //   368: iand
/*     */     //   369: ifne -> 405
/*     */     //   372: iload #12
/*     */     //   374: iload #11
/*     */     //   376: sipush #128
/*     */     //   379: iand
/*     */     //   380: ifne -> 400
/*     */     //   383: aload #9
/*     */     //   385: aload #7
/*     */     //   387: invokeinterface changed : (Ljava/lang/Object;)Z
/*     */     //   392: ifeq -> 400
/*     */     //   395: ldc 8388608
/*     */     //   397: goto -> 402
/*     */     //   400: ldc 4194304
/*     */     //   402: ior
/*     */     //   403: istore #12
/*     */     //   405: iload #11
/*     */     //   407: sipush #256
/*     */     //   410: iand
/*     */     //   411: ifeq -> 424
/*     */     //   414: iload #12
/*     */     //   416: ldc 100663296
/*     */     //   418: ior
/*     */     //   419: istore #12
/*     */     //   421: goto -> 456
/*     */     //   424: iload #10
/*     */     //   426: ldc 100663296
/*     */     //   428: iand
/*     */     //   429: ifne -> 456
/*     */     //   432: iload #12
/*     */     //   434: aload #9
/*     */     //   436: aload #8
/*     */     //   438: invokeinterface changed : (Ljava/lang/Object;)Z
/*     */     //   443: ifeq -> 451
/*     */     //   446: ldc 67108864
/*     */     //   448: goto -> 453
/*     */     //   451: ldc 33554432
/*     */     //   453: ior
/*     */     //   454: istore #12
/*     */     //   456: iload #12
/*     */     //   458: ldc 38347923
/*     */     //   460: iand
/*     */     //   461: ldc 38347922
/*     */     //   463: if_icmpne -> 476
/*     */     //   466: aload #9
/*     */     //   468: invokeinterface getSkipping : ()Z
/*     */     //   473: ifne -> 856
/*     */     //   476: aload #9
/*     */     //   478: invokeinterface startDefaults : ()V
/*     */     //   483: iload #10
/*     */     //   485: iconst_1
/*     */     //   486: iand
/*     */     //   487: ifeq -> 500
/*     */     //   490: aload #9
/*     */     //   492: invokeinterface getDefaultsInvalid : ()Z
/*     */     //   497: ifeq -> 705
/*     */     //   500: iload #11
/*     */     //   502: iconst_4
/*     */     //   503: iand
/*     */     //   504: ifeq -> 514
/*     */     //   507: getstatic androidx/compose/ui/Modifier.Companion : Landroidx/compose/ui/Modifier$Companion;
/*     */     //   510: checkcast androidx/compose/ui/Modifier
/*     */     //   513: astore_2
/*     */     //   514: iload #11
/*     */     //   516: bipush #8
/*     */     //   518: iand
/*     */     //   519: ifeq -> 524
/*     */     //   522: iconst_1
/*     */     //   523: istore_3
/*     */     //   524: iload #11
/*     */     //   526: bipush #16
/*     */     //   528: iand
/*     */     //   529: ifeq -> 537
/*     */     //   532: getstatic org/jetbrains/jewel/ui/Outline.None : Lorg/jetbrains/jewel/ui/Outline;
/*     */     //   535: astore #4
/*     */     //   537: iload #11
/*     */     //   539: bipush #32
/*     */     //   541: iand
/*     */     //   542: ifeq -> 630
/*     */     //   545: aload #9
/*     */     //   547: ldc 896492982
/*     */     //   549: invokeinterface startReplaceGroup : (I)V
/*     */     //   554: aload #9
/*     */     //   556: astore #14
/*     */     //   558: iconst_0
/*     */     //   559: istore #15
/*     */     //   561: iconst_0
/*     */     //   562: istore #16
/*     */     //   564: aload #14
/*     */     //   566: invokeinterface rememberedValue : ()Ljava/lang/Object;
/*     */     //   571: astore #17
/*     */     //   573: iconst_0
/*     */     //   574: istore #18
/*     */     //   576: aload #17
/*     */     //   578: getstatic androidx/compose/runtime/Composer.Companion : Landroidx/compose/runtime/Composer$Companion;
/*     */     //   581: invokevirtual getEmpty : ()Ljava/lang/Object;
/*     */     //   584: if_acmpne -> 609
/*     */     //   587: iconst_0
/*     */     //   588: istore #19
/*     */     //   590: invokestatic MutableInteractionSource : ()Landroidx/compose/foundation/interaction/MutableInteractionSource;
/*     */     //   593: astore #19
/*     */     //   595: aload #14
/*     */     //   597: aload #19
/*     */     //   599: invokeinterface updateRememberedValue : (Ljava/lang/Object;)V
/*     */     //   604: aload #19
/*     */     //   606: goto -> 611
/*     */     //   609: aload #17
/*     */     //   611: nop
/*     */     //   612: nop
/*     */     //   613: nop
/*     */     //   614: checkcast androidx/compose/foundation/interaction/MutableInteractionSource
/*     */     //   617: astore #13
/*     */     //   619: aload #9
/*     */     //   621: invokeinterface endReplaceGroup : ()V
/*     */     //   626: aload #13
/*     */     //   628: astore #5
/*     */     //   630: iload #11
/*     */     //   632: bipush #64
/*     */     //   634: iand
/*     */     //   635: ifeq -> 657
/*     */     //   638: getstatic org/jetbrains/jewel/foundation/theme/JewelTheme.Companion : Lorg/jetbrains/jewel/foundation/theme/JewelTheme$Companion;
/*     */     //   641: aload #9
/*     */     //   643: bipush #6
/*     */     //   645: invokestatic getRadioButtonStyle : (Lorg/jetbrains/jewel/foundation/theme/JewelTheme$Companion;Landroidx/compose/runtime/Composer;I)Lorg/jetbrains/jewel/ui/component/styling/RadioButtonStyle;
/*     */     //   648: astore #6
/*     */     //   650: iload #12
/*     */     //   652: ldc -3670017
/*     */     //   654: iand
/*     */     //   655: istore #12
/*     */     //   657: iload #11
/*     */     //   659: sipush #128
/*     */     //   662: iand
/*     */     //   663: ifeq -> 685
/*     */     //   666: getstatic org/jetbrains/jewel/foundation/theme/JewelTheme.Companion : Lorg/jetbrains/jewel/foundation/theme/JewelTheme$Companion;
/*     */     //   669: aload #9
/*     */     //   671: bipush #6
/*     */     //   673: invokevirtual getDefaultTextStyle : (Landroidx/compose/runtime/Composer;I)Landroidx/compose/ui/text/TextStyle;
/*     */     //   676: astore #7
/*     */     //   678: iload #12
/*     */     //   680: ldc -29360129
/*     */     //   682: iand
/*     */     //   683: istore #12
/*     */     //   685: iload #11
/*     */     //   687: sipush #256
/*     */     //   690: iand
/*     */     //   691: ifeq -> 743
/*     */     //   694: getstatic androidx/compose/ui/Alignment.Companion : Landroidx/compose/ui/Alignment$Companion;
/*     */     //   697: invokevirtual getCenterVertically : ()Landroidx/compose/ui/Alignment$Vertical;
/*     */     //   700: astore #8
/*     */     //   702: goto -> 743
/*     */     //   705: aload #9
/*     */     //   707: invokeinterface skipToGroupEnd : ()V
/*     */     //   712: iload #11
/*     */     //   714: bipush #64
/*     */     //   716: iand
/*     */     //   717: ifeq -> 727
/*     */     //   720: iload #12
/*     */     //   722: ldc -3670017
/*     */     //   724: iand
/*     */     //   725: istore #12
/*     */     //   727: iload #11
/*     */     //   729: sipush #128
/*     */     //   732: iand
/*     */     //   733: ifeq -> 743
/*     */     //   736: iload #12
/*     */     //   738: ldc -29360129
/*     */     //   740: iand
/*     */     //   741: istore #12
/*     */     //   743: aload #9
/*     */     //   745: invokeinterface endDefaults : ()V
/*     */     //   750: invokestatic isTraceInProgress : ()Z
/*     */     //   753: ifeq -> 766
/*     */     //   756: ldc 2145800322
/*     */     //   758: iload #12
/*     */     //   760: iconst_m1
/*     */     //   761: ldc 'org.jetbrains.jewel.ui.component.RadioButton (RadioButton.kt:59)'
/*     */     //   763: invokestatic traceEventStart : (IIILjava/lang/String;)V
/*     */     //   766: iload_0
/*     */     //   767: aload_1
/*     */     //   768: aload_2
/*     */     //   769: iload_3
/*     */     //   770: aload #4
/*     */     //   772: aload #5
/*     */     //   774: aload #6
/*     */     //   776: aload #7
/*     */     //   778: aload #8
/*     */     //   780: aconst_null
/*     */     //   781: aload #9
/*     */     //   783: ldc 805306368
/*     */     //   785: bipush #14
/*     */     //   787: iload #12
/*     */     //   789: iand
/*     */     //   790: ior
/*     */     //   791: bipush #112
/*     */     //   793: iload #12
/*     */     //   795: iand
/*     */     //   796: ior
/*     */     //   797: sipush #896
/*     */     //   800: iload #12
/*     */     //   802: iand
/*     */     //   803: ior
/*     */     //   804: sipush #7168
/*     */     //   807: iload #12
/*     */     //   809: iand
/*     */     //   810: ior
/*     */     //   811: ldc 57344
/*     */     //   813: iload #12
/*     */     //   815: iand
/*     */     //   816: ior
/*     */     //   817: ldc 458752
/*     */     //   819: iload #12
/*     */     //   821: iand
/*     */     //   822: ior
/*     */     //   823: ldc 3670016
/*     */     //   825: iload #12
/*     */     //   827: iand
/*     */     //   828: ior
/*     */     //   829: ldc 29360128
/*     */     //   831: iload #12
/*     */     //   833: iand
/*     */     //   834: ior
/*     */     //   835: ldc 234881024
/*     */     //   837: iload #12
/*     */     //   839: iand
/*     */     //   840: ior
/*     */     //   841: invokestatic RadioButtonImpl : (ZLkotlin/jvm/functions/Function0;Landroidx/compose/ui/Modifier;ZLorg/jetbrains/jewel/ui/Outline;Landroidx/compose/foundation/interaction/MutableInteractionSource;Lorg/jetbrains/jewel/ui/component/styling/RadioButtonStyle;Landroidx/compose/ui/text/TextStyle;Landroidx/compose/ui/Alignment$Vertical;Lkotlin/jvm/functions/Function3;Landroidx/compose/runtime/Composer;I)V
/*     */     //   844: invokestatic isTraceInProgress : ()Z
/*     */     //   847: ifeq -> 863
/*     */     //   850: invokestatic traceEventEnd : ()V
/*     */     //   853: goto -> 863
/*     */     //   856: aload #9
/*     */     //   858: invokeinterface skipToGroupEnd : ()V
/*     */     //   863: aload #9
/*     */     //   865: invokeinterface endRestartGroup : ()Landroidx/compose/runtime/ScopeUpdateScope;
/*     */     //   870: dup
/*     */     //   871: ifnull -> 905
/*     */     //   874: iload_0
/*     */     //   875: aload_1
/*     */     //   876: aload_2
/*     */     //   877: iload_3
/*     */     //   878: aload #4
/*     */     //   880: aload #5
/*     */     //   882: aload #6
/*     */     //   884: aload #7
/*     */     //   886: aload #8
/*     */     //   888: iload #10
/*     */     //   890: iload #11
/*     */     //   892: <illegal opcode> invoke : (ZLkotlin/jvm/functions/Function0;Landroidx/compose/ui/Modifier;ZLorg/jetbrains/jewel/ui/Outline;Landroidx/compose/foundation/interaction/MutableInteractionSource;Lorg/jetbrains/jewel/ui/component/styling/RadioButtonStyle;Landroidx/compose/ui/text/TextStyle;Landroidx/compose/ui/Alignment$Vertical;II)Lkotlin/jvm/functions/Function2;
/*     */     //   897: invokeinterface updateScope : (Lkotlin/jvm/functions/Function2;)V
/*     */     //   902: goto -> 906
/*     */     //   905: pop
/*     */     //   906: return
/*     */     // Line number table:
/*     */     //   Java source line number -> byte code offset
/*     */     //   #60	-> 6
/*     */     //   #53	-> 507
/*     */     //   #54	-> 522
/*     */     //   #55	-> 532
/*     */     //   #56	-> 545
/*     */     //   #289	-> 564
/*     */     //   #290	-> 576
/*     */     //   #291	-> 587
/*     */     //   #56	-> 590
/*     */     //   #291	-> 593
/*     */     //   #292	-> 595
/*     */     //   #293	-> 604
/*     */     //   #294	-> 609
/*     */     //   #290	-> 611
/*     */     //   #289	-> 612
/*     */     //   #289	-> 613
/*     */     //   #56	-> 614
/*     */     //   #57	-> 638
/*     */     //   #58	-> 666
/*     */     //   #59	-> 694
/*     */     //   #60	-> 763
/*     */     //   #62	-> 766
/*     */     //   #63	-> 767
/*     */     //   #64	-> 768
/*     */     //   #65	-> 769
/*     */     //   #66	-> 770
/*     */     //   #67	-> 772
/*     */     //   #68	-> 774
/*     */     //   #69	-> 776
/*     */     //   #70	-> 778
/*     */     //   #71	-> 780
/*     */     //   #61	-> 841
/*     */     //   #73	-> 856
/*     */     // Local variable table:
/*     */     //   start	length	slot	name	descriptor
/*     */     //   590	3	19	$i$a$-cache-RadioButtonKt$RadioButton$1	I
/*     */     //   595	11	19	value$iv	Ljava/lang/Object;
/*     */     //   576	36	18	$i$a$-let-ComposerKt$cache$1$iv	I
/*     */     //   573	39	17	it$iv	Ljava/lang/Object;
/*     */     //   564	50	16	$i$f$cache	I
/*     */     //   561	53	14	$this$cache$iv	Landroidx/compose/runtime/Composer;
/*     */     //   561	53	15	invalid$iv	Z
/*     */     //   21	886	12	$dirty	I
/*     */     //   0	907	0	selected	Z
/*     */     //   0	907	1	onClick	Lkotlin/jvm/functions/Function0;
/*     */     //   0	907	2	modifier	Landroidx/compose/ui/Modifier;
/*     */     //   0	907	3	enabled	Z
/*     */     //   0	907	4	outline	Lorg/jetbrains/jewel/ui/Outline;
/*     */     //   0	907	5	interactionSource	Landroidx/compose/foundation/interaction/MutableInteractionSource;
/*     */     //   0	907	6	style	Lorg/jetbrains/jewel/ui/component/styling/RadioButtonStyle;
/*     */     //   0	907	7	textStyle	Landroidx/compose/ui/text/TextStyle;
/*     */     //   0	907	8	verticalAlignment	Landroidx/compose/ui/Alignment$Vertical;
/*     */     //   0	907	9	$composer	Landroidx/compose/runtime/Composer;
/*     */     //   0	907	10	$changed	I
/*     */   }
/*     */   
/*     */   @Composable
/*     */   @ComposableTarget(applier = "androidx.compose.ui.UiComposable")
/*     */   public static final void RadioButtonRow(@NotNull String text, boolean selected, @NotNull Function0 onClick, @Nullable Modifier modifier, boolean enabled, @Nullable Outline outline, @Nullable MutableInteractionSource interactionSource, @Nullable RadioButtonStyle style, @Nullable TextStyle textStyle, @Nullable Alignment.Vertical verticalAlignment, @Nullable Composer $composer, int $changed, int paramInt1) {
/*     */     // Byte code:
/*     */     //   0: aload_0
/*     */     //   1: ldc 'text'
/*     */     //   3: invokestatic checkNotNullParameter : (Ljava/lang/Object;Ljava/lang/String;)V
/*     */     //   6: aload_2
/*     */     //   7: ldc 'onClick'
/*     */     //   9: invokestatic checkNotNullParameter : (Ljava/lang/Object;Ljava/lang/String;)V
/*     */     //   12: aload #10
/*     */     //   14: ldc 1022537821
/*     */     //   16: invokeinterface startRestartGroup : (I)Landroidx/compose/runtime/Composer;
/*     */     //   21: astore #10
/*     */     //   23: iload #11
/*     */     //   25: istore #13
/*     */     //   27: iload #12
/*     */     //   29: iconst_1
/*     */     //   30: iand
/*     */     //   31: ifeq -> 44
/*     */     //   34: iload #13
/*     */     //   36: bipush #6
/*     */     //   38: ior
/*     */     //   39: istore #13
/*     */     //   41: goto -> 73
/*     */     //   44: iload #11
/*     */     //   46: bipush #6
/*     */     //   48: iand
/*     */     //   49: ifne -> 73
/*     */     //   52: iload #13
/*     */     //   54: aload #10
/*     */     //   56: aload_0
/*     */     //   57: invokeinterface changed : (Ljava/lang/Object;)Z
/*     */     //   62: ifeq -> 69
/*     */     //   65: iconst_4
/*     */     //   66: goto -> 70
/*     */     //   69: iconst_2
/*     */     //   70: ior
/*     */     //   71: istore #13
/*     */     //   73: iload #12
/*     */     //   75: iconst_2
/*     */     //   76: iand
/*     */     //   77: ifeq -> 90
/*     */     //   80: iload #13
/*     */     //   82: bipush #48
/*     */     //   84: ior
/*     */     //   85: istore #13
/*     */     //   87: goto -> 121
/*     */     //   90: iload #11
/*     */     //   92: bipush #48
/*     */     //   94: iand
/*     */     //   95: ifne -> 121
/*     */     //   98: iload #13
/*     */     //   100: aload #10
/*     */     //   102: iload_1
/*     */     //   103: invokeinterface changed : (Z)Z
/*     */     //   108: ifeq -> 116
/*     */     //   111: bipush #32
/*     */     //   113: goto -> 118
/*     */     //   116: bipush #16
/*     */     //   118: ior
/*     */     //   119: istore #13
/*     */     //   121: iload #12
/*     */     //   123: iconst_4
/*     */     //   124: iand
/*     */     //   125: ifeq -> 139
/*     */     //   128: iload #13
/*     */     //   130: sipush #384
/*     */     //   133: ior
/*     */     //   134: istore #13
/*     */     //   136: goto -> 173
/*     */     //   139: iload #11
/*     */     //   141: sipush #384
/*     */     //   144: iand
/*     */     //   145: ifne -> 173
/*     */     //   148: iload #13
/*     */     //   150: aload #10
/*     */     //   152: aload_2
/*     */     //   153: invokeinterface changedInstance : (Ljava/lang/Object;)Z
/*     */     //   158: ifeq -> 167
/*     */     //   161: sipush #256
/*     */     //   164: goto -> 170
/*     */     //   167: sipush #128
/*     */     //   170: ior
/*     */     //   171: istore #13
/*     */     //   173: iload #12
/*     */     //   175: bipush #8
/*     */     //   177: iand
/*     */     //   178: ifeq -> 192
/*     */     //   181: iload #13
/*     */     //   183: sipush #3072
/*     */     //   186: ior
/*     */     //   187: istore #13
/*     */     //   189: goto -> 226
/*     */     //   192: iload #11
/*     */     //   194: sipush #3072
/*     */     //   197: iand
/*     */     //   198: ifne -> 226
/*     */     //   201: iload #13
/*     */     //   203: aload #10
/*     */     //   205: aload_3
/*     */     //   206: invokeinterface changed : (Ljava/lang/Object;)Z
/*     */     //   211: ifeq -> 220
/*     */     //   214: sipush #2048
/*     */     //   217: goto -> 223
/*     */     //   220: sipush #1024
/*     */     //   223: ior
/*     */     //   224: istore #13
/*     */     //   226: iload #12
/*     */     //   228: bipush #16
/*     */     //   230: iand
/*     */     //   231: ifeq -> 245
/*     */     //   234: iload #13
/*     */     //   236: sipush #24576
/*     */     //   239: ior
/*     */     //   240: istore #13
/*     */     //   242: goto -> 280
/*     */     //   245: iload #11
/*     */     //   247: sipush #24576
/*     */     //   250: iand
/*     */     //   251: ifne -> 280
/*     */     //   254: iload #13
/*     */     //   256: aload #10
/*     */     //   258: iload #4
/*     */     //   260: invokeinterface changed : (Z)Z
/*     */     //   265: ifeq -> 274
/*     */     //   268: sipush #16384
/*     */     //   271: goto -> 277
/*     */     //   274: sipush #8192
/*     */     //   277: ior
/*     */     //   278: istore #13
/*     */     //   280: iload #12
/*     */     //   282: bipush #32
/*     */     //   284: iand
/*     */     //   285: ifeq -> 298
/*     */     //   288: iload #13
/*     */     //   290: ldc 196608
/*     */     //   292: ior
/*     */     //   293: istore #13
/*     */     //   295: goto -> 330
/*     */     //   298: iload #11
/*     */     //   300: ldc 196608
/*     */     //   302: iand
/*     */     //   303: ifne -> 330
/*     */     //   306: iload #13
/*     */     //   308: aload #10
/*     */     //   310: aload #5
/*     */     //   312: invokeinterface changed : (Ljava/lang/Object;)Z
/*     */     //   317: ifeq -> 325
/*     */     //   320: ldc 131072
/*     */     //   322: goto -> 327
/*     */     //   325: ldc 65536
/*     */     //   327: ior
/*     */     //   328: istore #13
/*     */     //   330: iload #12
/*     */     //   332: bipush #64
/*     */     //   334: iand
/*     */     //   335: ifeq -> 348
/*     */     //   338: iload #13
/*     */     //   340: ldc 1572864
/*     */     //   342: ior
/*     */     //   343: istore #13
/*     */     //   345: goto -> 380
/*     */     //   348: iload #11
/*     */     //   350: ldc 1572864
/*     */     //   352: iand
/*     */     //   353: ifne -> 380
/*     */     //   356: iload #13
/*     */     //   358: aload #10
/*     */     //   360: aload #6
/*     */     //   362: invokeinterface changed : (Ljava/lang/Object;)Z
/*     */     //   367: ifeq -> 375
/*     */     //   370: ldc 1048576
/*     */     //   372: goto -> 377
/*     */     //   375: ldc 524288
/*     */     //   377: ior
/*     */     //   378: istore #13
/*     */     //   380: iload #11
/*     */     //   382: ldc 12582912
/*     */     //   384: iand
/*     */     //   385: ifne -> 421
/*     */     //   388: iload #13
/*     */     //   390: iload #12
/*     */     //   392: sipush #128
/*     */     //   395: iand
/*     */     //   396: ifne -> 416
/*     */     //   399: aload #10
/*     */     //   401: aload #7
/*     */     //   403: invokeinterface changed : (Ljava/lang/Object;)Z
/*     */     //   408: ifeq -> 416
/*     */     //   411: ldc 8388608
/*     */     //   413: goto -> 418
/*     */     //   416: ldc 4194304
/*     */     //   418: ior
/*     */     //   419: istore #13
/*     */     //   421: iload #11
/*     */     //   423: ldc 100663296
/*     */     //   425: iand
/*     */     //   426: ifne -> 462
/*     */     //   429: iload #13
/*     */     //   431: iload #12
/*     */     //   433: sipush #256
/*     */     //   436: iand
/*     */     //   437: ifne -> 457
/*     */     //   440: aload #10
/*     */     //   442: aload #8
/*     */     //   444: invokeinterface changed : (Ljava/lang/Object;)Z
/*     */     //   449: ifeq -> 457
/*     */     //   452: ldc 67108864
/*     */     //   454: goto -> 459
/*     */     //   457: ldc 33554432
/*     */     //   459: ior
/*     */     //   460: istore #13
/*     */     //   462: iload #12
/*     */     //   464: sipush #512
/*     */     //   467: iand
/*     */     //   468: ifeq -> 481
/*     */     //   471: iload #13
/*     */     //   473: ldc 805306368
/*     */     //   475: ior
/*     */     //   476: istore #13
/*     */     //   478: goto -> 513
/*     */     //   481: iload #11
/*     */     //   483: ldc 805306368
/*     */     //   485: iand
/*     */     //   486: ifne -> 513
/*     */     //   489: iload #13
/*     */     //   491: aload #10
/*     */     //   493: aload #9
/*     */     //   495: invokeinterface changed : (Ljava/lang/Object;)Z
/*     */     //   500: ifeq -> 508
/*     */     //   503: ldc 536870912
/*     */     //   505: goto -> 510
/*     */     //   508: ldc 268435456
/*     */     //   510: ior
/*     */     //   511: istore #13
/*     */     //   513: iload #13
/*     */     //   515: ldc 306783379
/*     */     //   517: iand
/*     */     //   518: ldc 306783378
/*     */     //   520: if_icmpne -> 533
/*     */     //   523: aload #10
/*     */     //   525: invokeinterface getSkipping : ()Z
/*     */     //   530: ifne -> 956
/*     */     //   533: aload #10
/*     */     //   535: invokeinterface startDefaults : ()V
/*     */     //   540: iload #11
/*     */     //   542: iconst_1
/*     */     //   543: iand
/*     */     //   544: ifeq -> 557
/*     */     //   547: aload #10
/*     */     //   549: invokeinterface getDefaultsInvalid : ()Z
/*     */     //   554: ifeq -> 765
/*     */     //   557: iload #12
/*     */     //   559: bipush #8
/*     */     //   561: iand
/*     */     //   562: ifeq -> 572
/*     */     //   565: getstatic androidx/compose/ui/Modifier.Companion : Landroidx/compose/ui/Modifier$Companion;
/*     */     //   568: checkcast androidx/compose/ui/Modifier
/*     */     //   571: astore_3
/*     */     //   572: iload #12
/*     */     //   574: bipush #16
/*     */     //   576: iand
/*     */     //   577: ifeq -> 583
/*     */     //   580: iconst_1
/*     */     //   581: istore #4
/*     */     //   583: iload #12
/*     */     //   585: bipush #32
/*     */     //   587: iand
/*     */     //   588: ifeq -> 596
/*     */     //   591: getstatic org/jetbrains/jewel/ui/Outline.None : Lorg/jetbrains/jewel/ui/Outline;
/*     */     //   594: astore #5
/*     */     //   596: iload #12
/*     */     //   598: bipush #64
/*     */     //   600: iand
/*     */     //   601: ifeq -> 689
/*     */     //   604: aload #10
/*     */     //   606: ldc -1181967726
/*     */     //   608: invokeinterface startReplaceGroup : (I)V
/*     */     //   613: aload #10
/*     */     //   615: astore #15
/*     */     //   617: iconst_0
/*     */     //   618: istore #16
/*     */     //   620: iconst_0
/*     */     //   621: istore #17
/*     */     //   623: aload #15
/*     */     //   625: invokeinterface rememberedValue : ()Ljava/lang/Object;
/*     */     //   630: astore #18
/*     */     //   632: iconst_0
/*     */     //   633: istore #19
/*     */     //   635: aload #18
/*     */     //   637: getstatic androidx/compose/runtime/Composer.Companion : Landroidx/compose/runtime/Composer$Companion;
/*     */     //   640: invokevirtual getEmpty : ()Ljava/lang/Object;
/*     */     //   643: if_acmpne -> 668
/*     */     //   646: iconst_0
/*     */     //   647: istore #20
/*     */     //   649: invokestatic MutableInteractionSource : ()Landroidx/compose/foundation/interaction/MutableInteractionSource;
/*     */     //   652: astore #20
/*     */     //   654: aload #15
/*     */     //   656: aload #20
/*     */     //   658: invokeinterface updateRememberedValue : (Ljava/lang/Object;)V
/*     */     //   663: aload #20
/*     */     //   665: goto -> 670
/*     */     //   668: aload #18
/*     */     //   670: nop
/*     */     //   671: nop
/*     */     //   672: nop
/*     */     //   673: checkcast androidx/compose/foundation/interaction/MutableInteractionSource
/*     */     //   676: astore #14
/*     */     //   678: aload #10
/*     */     //   680: invokeinterface endReplaceGroup : ()V
/*     */     //   685: aload #14
/*     */     //   687: astore #6
/*     */     //   689: iload #12
/*     */     //   691: sipush #128
/*     */     //   694: iand
/*     */     //   695: ifeq -> 717
/*     */     //   698: getstatic org/jetbrains/jewel/foundation/theme/JewelTheme.Companion : Lorg/jetbrains/jewel/foundation/theme/JewelTheme$Companion;
/*     */     //   701: aload #10
/*     */     //   703: bipush #6
/*     */     //   705: invokestatic getRadioButtonStyle : (Lorg/jetbrains/jewel/foundation/theme/JewelTheme$Companion;Landroidx/compose/runtime/Composer;I)Lorg/jetbrains/jewel/ui/component/styling/RadioButtonStyle;
/*     */     //   708: astore #7
/*     */     //   710: iload #13
/*     */     //   712: ldc -29360129
/*     */     //   714: iand
/*     */     //   715: istore #13
/*     */     //   717: iload #12
/*     */     //   719: sipush #256
/*     */     //   722: iand
/*     */     //   723: ifeq -> 745
/*     */     //   726: getstatic org/jetbrains/jewel/foundation/theme/JewelTheme.Companion : Lorg/jetbrains/jewel/foundation/theme/JewelTheme$Companion;
/*     */     //   729: aload #10
/*     */     //   731: bipush #6
/*     */     //   733: invokevirtual getDefaultTextStyle : (Landroidx/compose/runtime/Composer;I)Landroidx/compose/ui/text/TextStyle;
/*     */     //   736: astore #8
/*     */     //   738: iload #13
/*     */     //   740: ldc -234881025
/*     */     //   742: iand
/*     */     //   743: istore #13
/*     */     //   745: iload #12
/*     */     //   747: sipush #512
/*     */     //   750: iand
/*     */     //   751: ifeq -> 804
/*     */     //   754: getstatic androidx/compose/ui/Alignment.Companion : Landroidx/compose/ui/Alignment$Companion;
/*     */     //   757: invokevirtual getCenterVertically : ()Landroidx/compose/ui/Alignment$Vertical;
/*     */     //   760: astore #9
/*     */     //   762: goto -> 804
/*     */     //   765: aload #10
/*     */     //   767: invokeinterface skipToGroupEnd : ()V
/*     */     //   772: iload #12
/*     */     //   774: sipush #128
/*     */     //   777: iand
/*     */     //   778: ifeq -> 788
/*     */     //   781: iload #13
/*     */     //   783: ldc -29360129
/*     */     //   785: iand
/*     */     //   786: istore #13
/*     */     //   788: iload #12
/*     */     //   790: sipush #256
/*     */     //   793: iand
/*     */     //   794: ifeq -> 804
/*     */     //   797: iload #13
/*     */     //   799: ldc -234881025
/*     */     //   801: iand
/*     */     //   802: istore #13
/*     */     //   804: aload #10
/*     */     //   806: invokeinterface endDefaults : ()V
/*     */     //   811: invokestatic isTraceInProgress : ()Z
/*     */     //   814: ifeq -> 827
/*     */     //   817: ldc 1022537821
/*     */     //   819: iload #13
/*     */     //   821: iconst_m1
/*     */     //   822: ldc 'org.jetbrains.jewel.ui.component.RadioButtonRow (RadioButton.kt:86)'
/*     */     //   824: invokestatic traceEventStart : (IIILjava/lang/String;)V
/*     */     //   827: iload_1
/*     */     //   828: aload_2
/*     */     //   829: aload_3
/*     */     //   830: iload #4
/*     */     //   832: aload #5
/*     */     //   834: aload #6
/*     */     //   836: aload #7
/*     */     //   838: aload #8
/*     */     //   840: aload #9
/*     */     //   842: ldc 851051758
/*     */     //   844: iconst_1
/*     */     //   845: new org/jetbrains/jewel/ui/component/RadioButtonKt$RadioButtonRow$2
/*     */     //   848: dup
/*     */     //   849: aload_0
/*     */     //   850: invokespecial <init> : (Ljava/lang/String;)V
/*     */     //   853: aload #10
/*     */     //   855: bipush #54
/*     */     //   857: invokestatic rememberComposableLambda : (IZLjava/lang/Object;Landroidx/compose/runtime/Composer;I)Landroidx/compose/runtime/internal/ComposableLambda;
/*     */     //   860: checkcast kotlin/jvm/functions/Function3
/*     */     //   863: aload #10
/*     */     //   865: ldc 805306368
/*     */     //   867: bipush #14
/*     */     //   869: iload #13
/*     */     //   871: iconst_3
/*     */     //   872: ishr
/*     */     //   873: iand
/*     */     //   874: ior
/*     */     //   875: bipush #112
/*     */     //   877: iload #13
/*     */     //   879: iconst_3
/*     */     //   880: ishr
/*     */     //   881: iand
/*     */     //   882: ior
/*     */     //   883: sipush #896
/*     */     //   886: iload #13
/*     */     //   888: iconst_3
/*     */     //   889: ishr
/*     */     //   890: iand
/*     */     //   891: ior
/*     */     //   892: sipush #7168
/*     */     //   895: iload #13
/*     */     //   897: iconst_3
/*     */     //   898: ishr
/*     */     //   899: iand
/*     */     //   900: ior
/*     */     //   901: ldc 57344
/*     */     //   903: iload #13
/*     */     //   905: iconst_3
/*     */     //   906: ishr
/*     */     //   907: iand
/*     */     //   908: ior
/*     */     //   909: ldc 458752
/*     */     //   911: iload #13
/*     */     //   913: iconst_3
/*     */     //   914: ishr
/*     */     //   915: iand
/*     */     //   916: ior
/*     */     //   917: ldc 3670016
/*     */     //   919: iload #13
/*     */     //   921: iconst_3
/*     */     //   922: ishr
/*     */     //   923: iand
/*     */     //   924: ior
/*     */     //   925: ldc 29360128
/*     */     //   927: iload #13
/*     */     //   929: iconst_3
/*     */     //   930: ishr
/*     */     //   931: iand
/*     */     //   932: ior
/*     */     //   933: ldc 234881024
/*     */     //   935: iload #13
/*     */     //   937: iconst_3
/*     */     //   938: ishr
/*     */     //   939: iand
/*     */     //   940: ior
/*     */     //   941: invokestatic RadioButtonImpl : (ZLkotlin/jvm/functions/Function0;Landroidx/compose/ui/Modifier;ZLorg/jetbrains/jewel/ui/Outline;Landroidx/compose/foundation/interaction/MutableInteractionSource;Lorg/jetbrains/jewel/ui/component/styling/RadioButtonStyle;Landroidx/compose/ui/text/TextStyle;Landroidx/compose/ui/Alignment$Vertical;Lkotlin/jvm/functions/Function3;Landroidx/compose/runtime/Composer;I)V
/*     */     //   944: invokestatic isTraceInProgress : ()Z
/*     */     //   947: ifeq -> 963
/*     */     //   950: invokestatic traceEventEnd : ()V
/*     */     //   953: goto -> 963
/*     */     //   956: aload #10
/*     */     //   958: invokeinterface skipToGroupEnd : ()V
/*     */     //   963: aload #10
/*     */     //   965: invokeinterface endRestartGroup : ()Landroidx/compose/runtime/ScopeUpdateScope;
/*     */     //   970: dup
/*     */     //   971: ifnull -> 1007
/*     */     //   974: aload_0
/*     */     //   975: iload_1
/*     */     //   976: aload_2
/*     */     //   977: aload_3
/*     */     //   978: iload #4
/*     */     //   980: aload #5
/*     */     //   982: aload #6
/*     */     //   984: aload #7
/*     */     //   986: aload #8
/*     */     //   988: aload #9
/*     */     //   990: iload #11
/*     */     //   992: iload #12
/*     */     //   994: <illegal opcode> invoke : (Ljava/lang/String;ZLkotlin/jvm/functions/Function0;Landroidx/compose/ui/Modifier;ZLorg/jetbrains/jewel/ui/Outline;Landroidx/compose/foundation/interaction/MutableInteractionSource;Lorg/jetbrains/jewel/ui/component/styling/RadioButtonStyle;Landroidx/compose/ui/text/TextStyle;Landroidx/compose/ui/Alignment$Vertical;II)Lkotlin/jvm/functions/Function2;
/*     */     //   999: invokeinterface updateScope : (Lkotlin/jvm/functions/Function2;)V
/*     */     //   1004: goto -> 1008
/*     */     //   1007: pop
/*     */     //   1008: return
/*     */     // Line number table:
/*     */     //   Java source line number -> byte code offset
/*     */     //   #87	-> 12
/*     */     //   #80	-> 565
/*     */     //   #81	-> 580
/*     */     //   #82	-> 591
/*     */     //   #83	-> 604
/*     */     //   #295	-> 623
/*     */     //   #296	-> 635
/*     */     //   #297	-> 646
/*     */     //   #83	-> 649
/*     */     //   #297	-> 652
/*     */     //   #298	-> 654
/*     */     //   #299	-> 663
/*     */     //   #300	-> 668
/*     */     //   #296	-> 670
/*     */     //   #295	-> 671
/*     */     //   #295	-> 672
/*     */     //   #83	-> 673
/*     */     //   #84	-> 698
/*     */     //   #85	-> 726
/*     */     //   #86	-> 754
/*     */     //   #87	-> 824
/*     */     //   #89	-> 827
/*     */     //   #90	-> 828
/*     */     //   #91	-> 829
/*     */     //   #92	-> 830
/*     */     //   #93	-> 832
/*     */     //   #94	-> 834
/*     */     //   #95	-> 836
/*     */     //   #96	-> 838
/*     */     //   #97	-> 840
/*     */     //   #98	-> 842
/*     */     //   #88	-> 941
/*     */     //   #101	-> 956
/*     */     // Local variable table:
/*     */     //   start	length	slot	name	descriptor
/*     */     //   649	3	20	$i$a$-cache-RadioButtonKt$RadioButtonRow$1	I
/*     */     //   654	11	20	value$iv	Ljava/lang/Object;
/*     */     //   635	36	19	$i$a$-let-ComposerKt$cache$1$iv	I
/*     */     //   632	39	18	it$iv	Ljava/lang/Object;
/*     */     //   623	50	17	$i$f$cache	I
/*     */     //   620	53	15	$this$cache$iv	Landroidx/compose/runtime/Composer;
/*     */     //   620	53	16	invalid$iv	Z
/*     */     //   27	982	13	$dirty	I
/*     */     //   0	1009	0	text	Ljava/lang/String;
/*     */     //   0	1009	1	selected	Z
/*     */     //   0	1009	2	onClick	Lkotlin/jvm/functions/Function0;
/*     */     //   0	1009	3	modifier	Landroidx/compose/ui/Modifier;
/*     */     //   0	1009	4	enabled	Z
/*     */     //   0	1009	5	outline	Lorg/jetbrains/jewel/ui/Outline;
/*     */     //   0	1009	6	interactionSource	Landroidx/compose/foundation/interaction/MutableInteractionSource;
/*     */     //   0	1009	7	style	Lorg/jetbrains/jewel/ui/component/styling/RadioButtonStyle;
/*     */     //   0	1009	8	textStyle	Landroidx/compose/ui/text/TextStyle;
/*     */     //   0	1009	9	verticalAlignment	Landroidx/compose/ui/Alignment$Vertical;
/*     */     //   0	1009	10	$composer	Landroidx/compose/runtime/Composer;
/*     */     //   0	1009	11	$changed	I
/*     */   }
/*     */   
/*     */   @Metadata(mv = {2, 0, 0}, k = 3, xi = 48)
/*     */   static final class RadioButtonKt$RadioButtonRow$2
/*     */     implements Function3<RowScope, Composer, Integer, Unit>
/*     */   {
/*     */     @Composable
/*     */     @ComposableTarget(applier = "androidx.compose.ui.UiComposable")
/*     */     public final void invoke(RowScope $this$RadioButtonImpl, Composer $composer, int $changed) {
/*  99 */       Intrinsics.checkNotNullParameter($this$RadioButtonImpl, "$this$RadioButtonImpl"); if (($changed & 0x11) != 16 || !$composer.getSkipping()) { if (ComposerKt.isTraceInProgress()) ComposerKt.traceEventStart(851051758, $changed, -1, "org.jetbrains.jewel.ui.component.RadioButtonRow.<anonymous> (RadioButton.kt:98)");  TextKt.Text-bAzTDeA(this.$text, null, 0L, 0L, null, null, null, 0L, null, 0, 0L, 0, false, 0, null, null, $composer, 0, 0, 65534); if (ComposerKt.isTraceInProgress()) ComposerKt.traceEventEnd();  } else { $composer.skipToGroupEnd(); }
/*     */     
/*     */     }
/*     */ 
/*     */ 
/*     */ 
/*     */ 
/*     */ 
/*     */ 
/*     */     
/*     */     RadioButtonKt$RadioButtonRow$2(String $text) {}
/*     */   }
/*     */ 
/*     */ 
/*     */ 
/*     */ 
/*     */ 
/*     */ 
/*     */   
/*     */   @Composable
/*     */   @ComposableInferredTarget(scheme = "[androidx.compose.ui.UiComposable[androidx.compose.ui.UiComposable]]")
/*     */   public static final void RadioButtonRow(boolean selected, @NotNull Function0 onClick, @Nullable Modifier modifier, boolean enabled, @Nullable Outline outline, @Nullable MutableInteractionSource interactionSource, @Nullable RadioButtonStyle style, @Nullable TextStyle textStyle, @Nullable Alignment.Vertical verticalAlignment, @NotNull Function3 content, @Nullable Composer $composer, int $changed, int paramInt1) {
/*     */     // Byte code:
/*     */     //   0: aload_1
/*     */     //   1: ldc 'onClick'
/*     */     //   3: invokestatic checkNotNullParameter : (Ljava/lang/Object;Ljava/lang/String;)V
/*     */     //   6: aload #9
/*     */     //   8: ldc_w 'content'
/*     */     //   11: invokestatic checkNotNullParameter : (Ljava/lang/Object;Ljava/lang/String;)V
/*     */     //   14: aload #10
/*     */     //   16: ldc_w -1099260642
/*     */     //   19: invokeinterface startRestartGroup : (I)Landroidx/compose/runtime/Composer;
/*     */     //   24: astore #10
/*     */     //   26: iload #11
/*     */     //   28: istore #13
/*     */     //   30: iload #12
/*     */     //   32: iconst_1
/*     */     //   33: iand
/*     */     //   34: ifeq -> 47
/*     */     //   37: iload #13
/*     */     //   39: bipush #6
/*     */     //   41: ior
/*     */     //   42: istore #13
/*     */     //   44: goto -> 76
/*     */     //   47: iload #11
/*     */     //   49: bipush #6
/*     */     //   51: iand
/*     */     //   52: ifne -> 76
/*     */     //   55: iload #13
/*     */     //   57: aload #10
/*     */     //   59: iload_0
/*     */     //   60: invokeinterface changed : (Z)Z
/*     */     //   65: ifeq -> 72
/*     */     //   68: iconst_4
/*     */     //   69: goto -> 73
/*     */     //   72: iconst_2
/*     */     //   73: ior
/*     */     //   74: istore #13
/*     */     //   76: iload #12
/*     */     //   78: iconst_2
/*     */     //   79: iand
/*     */     //   80: ifeq -> 93
/*     */     //   83: iload #13
/*     */     //   85: bipush #48
/*     */     //   87: ior
/*     */     //   88: istore #13
/*     */     //   90: goto -> 124
/*     */     //   93: iload #11
/*     */     //   95: bipush #48
/*     */     //   97: iand
/*     */     //   98: ifne -> 124
/*     */     //   101: iload #13
/*     */     //   103: aload #10
/*     */     //   105: aload_1
/*     */     //   106: invokeinterface changedInstance : (Ljava/lang/Object;)Z
/*     */     //   111: ifeq -> 119
/*     */     //   114: bipush #32
/*     */     //   116: goto -> 121
/*     */     //   119: bipush #16
/*     */     //   121: ior
/*     */     //   122: istore #13
/*     */     //   124: iload #12
/*     */     //   126: iconst_4
/*     */     //   127: iand
/*     */     //   128: ifeq -> 142
/*     */     //   131: iload #13
/*     */     //   133: sipush #384
/*     */     //   136: ior
/*     */     //   137: istore #13
/*     */     //   139: goto -> 176
/*     */     //   142: iload #11
/*     */     //   144: sipush #384
/*     */     //   147: iand
/*     */     //   148: ifne -> 176
/*     */     //   151: iload #13
/*     */     //   153: aload #10
/*     */     //   155: aload_2
/*     */     //   156: invokeinterface changed : (Ljava/lang/Object;)Z
/*     */     //   161: ifeq -> 170
/*     */     //   164: sipush #256
/*     */     //   167: goto -> 173
/*     */     //   170: sipush #128
/*     */     //   173: ior
/*     */     //   174: istore #13
/*     */     //   176: iload #12
/*     */     //   178: bipush #8
/*     */     //   180: iand
/*     */     //   181: ifeq -> 195
/*     */     //   184: iload #13
/*     */     //   186: sipush #3072
/*     */     //   189: ior
/*     */     //   190: istore #13
/*     */     //   192: goto -> 229
/*     */     //   195: iload #11
/*     */     //   197: sipush #3072
/*     */     //   200: iand
/*     */     //   201: ifne -> 229
/*     */     //   204: iload #13
/*     */     //   206: aload #10
/*     */     //   208: iload_3
/*     */     //   209: invokeinterface changed : (Z)Z
/*     */     //   214: ifeq -> 223
/*     */     //   217: sipush #2048
/*     */     //   220: goto -> 226
/*     */     //   223: sipush #1024
/*     */     //   226: ior
/*     */     //   227: istore #13
/*     */     //   229: iload #12
/*     */     //   231: bipush #16
/*     */     //   233: iand
/*     */     //   234: ifeq -> 248
/*     */     //   237: iload #13
/*     */     //   239: sipush #24576
/*     */     //   242: ior
/*     */     //   243: istore #13
/*     */     //   245: goto -> 283
/*     */     //   248: iload #11
/*     */     //   250: sipush #24576
/*     */     //   253: iand
/*     */     //   254: ifne -> 283
/*     */     //   257: iload #13
/*     */     //   259: aload #10
/*     */     //   261: aload #4
/*     */     //   263: invokeinterface changed : (Ljava/lang/Object;)Z
/*     */     //   268: ifeq -> 277
/*     */     //   271: sipush #16384
/*     */     //   274: goto -> 280
/*     */     //   277: sipush #8192
/*     */     //   280: ior
/*     */     //   281: istore #13
/*     */     //   283: iload #12
/*     */     //   285: bipush #32
/*     */     //   287: iand
/*     */     //   288: ifeq -> 301
/*     */     //   291: iload #13
/*     */     //   293: ldc 196608
/*     */     //   295: ior
/*     */     //   296: istore #13
/*     */     //   298: goto -> 333
/*     */     //   301: iload #11
/*     */     //   303: ldc 196608
/*     */     //   305: iand
/*     */     //   306: ifne -> 333
/*     */     //   309: iload #13
/*     */     //   311: aload #10
/*     */     //   313: aload #5
/*     */     //   315: invokeinterface changed : (Ljava/lang/Object;)Z
/*     */     //   320: ifeq -> 328
/*     */     //   323: ldc 131072
/*     */     //   325: goto -> 330
/*     */     //   328: ldc 65536
/*     */     //   330: ior
/*     */     //   331: istore #13
/*     */     //   333: iload #11
/*     */     //   335: ldc 1572864
/*     */     //   337: iand
/*     */     //   338: ifne -> 373
/*     */     //   341: iload #13
/*     */     //   343: iload #12
/*     */     //   345: bipush #64
/*     */     //   347: iand
/*     */     //   348: ifne -> 368
/*     */     //   351: aload #10
/*     */     //   353: aload #6
/*     */     //   355: invokeinterface changed : (Ljava/lang/Object;)Z
/*     */     //   360: ifeq -> 368
/*     */     //   363: ldc 1048576
/*     */     //   365: goto -> 370
/*     */     //   368: ldc 524288
/*     */     //   370: ior
/*     */     //   371: istore #13
/*     */     //   373: iload #11
/*     */     //   375: ldc 12582912
/*     */     //   377: iand
/*     */     //   378: ifne -> 414
/*     */     //   381: iload #13
/*     */     //   383: iload #12
/*     */     //   385: sipush #128
/*     */     //   388: iand
/*     */     //   389: ifne -> 409
/*     */     //   392: aload #10
/*     */     //   394: aload #7
/*     */     //   396: invokeinterface changed : (Ljava/lang/Object;)Z
/*     */     //   401: ifeq -> 409
/*     */     //   404: ldc 8388608
/*     */     //   406: goto -> 411
/*     */     //   409: ldc 4194304
/*     */     //   411: ior
/*     */     //   412: istore #13
/*     */     //   414: iload #12
/*     */     //   416: sipush #256
/*     */     //   419: iand
/*     */     //   420: ifeq -> 433
/*     */     //   423: iload #13
/*     */     //   425: ldc 100663296
/*     */     //   427: ior
/*     */     //   428: istore #13
/*     */     //   430: goto -> 465
/*     */     //   433: iload #11
/*     */     //   435: ldc 100663296
/*     */     //   437: iand
/*     */     //   438: ifne -> 465
/*     */     //   441: iload #13
/*     */     //   443: aload #10
/*     */     //   445: aload #8
/*     */     //   447: invokeinterface changed : (Ljava/lang/Object;)Z
/*     */     //   452: ifeq -> 460
/*     */     //   455: ldc 67108864
/*     */     //   457: goto -> 462
/*     */     //   460: ldc 33554432
/*     */     //   462: ior
/*     */     //   463: istore #13
/*     */     //   465: iload #12
/*     */     //   467: sipush #512
/*     */     //   470: iand
/*     */     //   471: ifeq -> 484
/*     */     //   474: iload #13
/*     */     //   476: ldc 805306368
/*     */     //   478: ior
/*     */     //   479: istore #13
/*     */     //   481: goto -> 516
/*     */     //   484: iload #11
/*     */     //   486: ldc 805306368
/*     */     //   488: iand
/*     */     //   489: ifne -> 516
/*     */     //   492: iload #13
/*     */     //   494: aload #10
/*     */     //   496: aload #9
/*     */     //   498: invokeinterface changedInstance : (Ljava/lang/Object;)Z
/*     */     //   503: ifeq -> 511
/*     */     //   506: ldc 536870912
/*     */     //   508: goto -> 513
/*     */     //   511: ldc 268435456
/*     */     //   513: ior
/*     */     //   514: istore #13
/*     */     //   516: iload #13
/*     */     //   518: ldc 306783379
/*     */     //   520: iand
/*     */     //   521: ldc 306783378
/*     */     //   523: if_icmpne -> 536
/*     */     //   526: aload #10
/*     */     //   528: invokeinterface getSkipping : ()Z
/*     */     //   533: ifne -> 924
/*     */     //   536: aload #10
/*     */     //   538: invokeinterface startDefaults : ()V
/*     */     //   543: iload #11
/*     */     //   545: iconst_1
/*     */     //   546: iand
/*     */     //   547: ifeq -> 560
/*     */     //   550: aload #10
/*     */     //   552: invokeinterface getDefaultsInvalid : ()Z
/*     */     //   557: ifeq -> 766
/*     */     //   560: iload #12
/*     */     //   562: iconst_4
/*     */     //   563: iand
/*     */     //   564: ifeq -> 574
/*     */     //   567: getstatic androidx/compose/ui/Modifier.Companion : Landroidx/compose/ui/Modifier$Companion;
/*     */     //   570: checkcast androidx/compose/ui/Modifier
/*     */     //   573: astore_2
/*     */     //   574: iload #12
/*     */     //   576: bipush #8
/*     */     //   578: iand
/*     */     //   579: ifeq -> 584
/*     */     //   582: iconst_1
/*     */     //   583: istore_3
/*     */     //   584: iload #12
/*     */     //   586: bipush #16
/*     */     //   588: iand
/*     */     //   589: ifeq -> 597
/*     */     //   592: getstatic org/jetbrains/jewel/ui/Outline.None : Lorg/jetbrains/jewel/ui/Outline;
/*     */     //   595: astore #4
/*     */     //   597: iload #12
/*     */     //   599: bipush #32
/*     */     //   601: iand
/*     */     //   602: ifeq -> 691
/*     */     //   605: aload #10
/*     */     //   607: ldc_w -1181941678
/*     */     //   610: invokeinterface startReplaceGroup : (I)V
/*     */     //   615: aload #10
/*     */     //   617: astore #15
/*     */     //   619: iconst_0
/*     */     //   620: istore #16
/*     */     //   622: iconst_0
/*     */     //   623: istore #17
/*     */     //   625: aload #15
/*     */     //   627: invokeinterface rememberedValue : ()Ljava/lang/Object;
/*     */     //   632: astore #18
/*     */     //   634: iconst_0
/*     */     //   635: istore #19
/*     */     //   637: aload #18
/*     */     //   639: getstatic androidx/compose/runtime/Composer.Companion : Landroidx/compose/runtime/Composer$Companion;
/*     */     //   642: invokevirtual getEmpty : ()Ljava/lang/Object;
/*     */     //   645: if_acmpne -> 670
/*     */     //   648: iconst_0
/*     */     //   649: istore #20
/*     */     //   651: invokestatic MutableInteractionSource : ()Landroidx/compose/foundation/interaction/MutableInteractionSource;
/*     */     //   654: astore #20
/*     */     //   656: aload #15
/*     */     //   658: aload #20
/*     */     //   660: invokeinterface updateRememberedValue : (Ljava/lang/Object;)V
/*     */     //   665: aload #20
/*     */     //   667: goto -> 672
/*     */     //   670: aload #18
/*     */     //   672: nop
/*     */     //   673: nop
/*     */     //   674: nop
/*     */     //   675: checkcast androidx/compose/foundation/interaction/MutableInteractionSource
/*     */     //   678: astore #14
/*     */     //   680: aload #10
/*     */     //   682: invokeinterface endReplaceGroup : ()V
/*     */     //   687: aload #14
/*     */     //   689: astore #5
/*     */     //   691: iload #12
/*     */     //   693: bipush #64
/*     */     //   695: iand
/*     */     //   696: ifeq -> 718
/*     */     //   699: getstatic org/jetbrains/jewel/foundation/theme/JewelTheme.Companion : Lorg/jetbrains/jewel/foundation/theme/JewelTheme$Companion;
/*     */     //   702: aload #10
/*     */     //   704: bipush #6
/*     */     //   706: invokestatic getRadioButtonStyle : (Lorg/jetbrains/jewel/foundation/theme/JewelTheme$Companion;Landroidx/compose/runtime/Composer;I)Lorg/jetbrains/jewel/ui/component/styling/RadioButtonStyle;
/*     */     //   709: astore #6
/*     */     //   711: iload #13
/*     */     //   713: ldc -3670017
/*     */     //   715: iand
/*     */     //   716: istore #13
/*     */     //   718: iload #12
/*     */     //   720: sipush #128
/*     */     //   723: iand
/*     */     //   724: ifeq -> 746
/*     */     //   727: getstatic org/jetbrains/jewel/foundation/theme/JewelTheme.Companion : Lorg/jetbrains/jewel/foundation/theme/JewelTheme$Companion;
/*     */     //   730: aload #10
/*     */     //   732: bipush #6
/*     */     //   734: invokevirtual getDefaultTextStyle : (Landroidx/compose/runtime/Composer;I)Landroidx/compose/ui/text/TextStyle;
/*     */     //   737: astore #7
/*     */     //   739: iload #13
/*     */     //   741: ldc -29360129
/*     */     //   743: iand
/*     */     //   744: istore #13
/*     */     //   746: iload #12
/*     */     //   748: sipush #256
/*     */     //   751: iand
/*     */     //   752: ifeq -> 804
/*     */     //   755: getstatic androidx/compose/ui/Alignment.Companion : Landroidx/compose/ui/Alignment$Companion;
/*     */     //   758: invokevirtual getCenterVertically : ()Landroidx/compose/ui/Alignment$Vertical;
/*     */     //   761: astore #8
/*     */     //   763: goto -> 804
/*     */     //   766: aload #10
/*     */     //   768: invokeinterface skipToGroupEnd : ()V
/*     */     //   773: iload #12
/*     */     //   775: bipush #64
/*     */     //   777: iand
/*     */     //   778: ifeq -> 788
/*     */     //   781: iload #13
/*     */     //   783: ldc -3670017
/*     */     //   785: iand
/*     */     //   786: istore #13
/*     */     //   788: iload #12
/*     */     //   790: sipush #128
/*     */     //   793: iand
/*     */     //   794: ifeq -> 804
/*     */     //   797: iload #13
/*     */     //   799: ldc -29360129
/*     */     //   801: iand
/*     */     //   802: istore #13
/*     */     //   804: aload #10
/*     */     //   806: invokeinterface endDefaults : ()V
/*     */     //   811: invokestatic isTraceInProgress : ()Z
/*     */     //   814: ifeq -> 829
/*     */     //   817: ldc_w -1099260642
/*     */     //   820: iload #13
/*     */     //   822: iconst_m1
/*     */     //   823: ldc_w 'org.jetbrains.jewel.ui.component.RadioButtonRow (RadioButton.kt:114)'
/*     */     //   826: invokestatic traceEventStart : (IIILjava/lang/String;)V
/*     */     //   829: iload_0
/*     */     //   830: aload_1
/*     */     //   831: aload_2
/*     */     //   832: iload_3
/*     */     //   833: aload #4
/*     */     //   835: aload #5
/*     */     //   837: aload #6
/*     */     //   839: aload #7
/*     */     //   841: aload #8
/*     */     //   843: aload #9
/*     */     //   845: aload #10
/*     */     //   847: bipush #14
/*     */     //   849: iload #13
/*     */     //   851: iand
/*     */     //   852: bipush #112
/*     */     //   854: iload #13
/*     */     //   856: iand
/*     */     //   857: ior
/*     */     //   858: sipush #896
/*     */     //   861: iload #13
/*     */     //   863: iand
/*     */     //   864: ior
/*     */     //   865: sipush #7168
/*     */     //   868: iload #13
/*     */     //   870: iand
/*     */     //   871: ior
/*     */     //   872: ldc 57344
/*     */     //   874: iload #13
/*     */     //   876: iand
/*     */     //   877: ior
/*     */     //   878: ldc 458752
/*     */     //   880: iload #13
/*     */     //   882: iand
/*     */     //   883: ior
/*     */     //   884: ldc 3670016
/*     */     //   886: iload #13
/*     */     //   888: iand
/*     */     //   889: ior
/*     */     //   890: ldc 29360128
/*     */     //   892: iload #13
/*     */     //   894: iand
/*     */     //   895: ior
/*     */     //   896: ldc 234881024
/*     */     //   898: iload #13
/*     */     //   900: iand
/*     */     //   901: ior
/*     */     //   902: ldc_w 1879048192
/*     */     //   905: iload #13
/*     */     //   907: iand
/*     */     //   908: ior
/*     */     //   909: invokestatic RadioButtonImpl : (ZLkotlin/jvm/functions/Function0;Landroidx/compose/ui/Modifier;ZLorg/jetbrains/jewel/ui/Outline;Landroidx/compose/foundation/interaction/MutableInteractionSource;Lorg/jetbrains/jewel/ui/component/styling/RadioButtonStyle;Landroidx/compose/ui/text/TextStyle;Landroidx/compose/ui/Alignment$Vertical;Lkotlin/jvm/functions/Function3;Landroidx/compose/runtime/Composer;I)V
/*     */     //   912: invokestatic isTraceInProgress : ()Z
/*     */     //   915: ifeq -> 931
/*     */     //   918: invokestatic traceEventEnd : ()V
/*     */     //   921: goto -> 931
/*     */     //   924: aload #10
/*     */     //   926: invokeinterface skipToGroupEnd : ()V
/*     */     //   931: aload #10
/*     */     //   933: invokeinterface endRestartGroup : ()Landroidx/compose/runtime/ScopeUpdateScope;
/*     */     //   938: dup
/*     */     //   939: ifnull -> 975
/*     */     //   942: iload_0
/*     */     //   943: aload_1
/*     */     //   944: aload_2
/*     */     //   945: iload_3
/*     */     //   946: aload #4
/*     */     //   948: aload #5
/*     */     //   950: aload #6
/*     */     //   952: aload #7
/*     */     //   954: aload #8
/*     */     //   956: aload #9
/*     */     //   958: iload #11
/*     */     //   960: iload #12
/*     */     //   962: <illegal opcode> invoke : (ZLkotlin/jvm/functions/Function0;Landroidx/compose/ui/Modifier;ZLorg/jetbrains/jewel/ui/Outline;Landroidx/compose/foundation/interaction/MutableInteractionSource;Lorg/jetbrains/jewel/ui/component/styling/RadioButtonStyle;Landroidx/compose/ui/text/TextStyle;Landroidx/compose/ui/Alignment$Vertical;Lkotlin/jvm/functions/Function3;II)Lkotlin/jvm/functions/Function2;
/*     */     //   967: invokeinterface updateScope : (Lkotlin/jvm/functions/Function2;)V
/*     */     //   972: goto -> 976
/*     */     //   975: pop
/*     */     //   976: return
/*     */     // Line number table:
/*     */     //   Java source line number -> byte code offset
/*     */     //   #115	-> 14
/*     */     //   #107	-> 567
/*     */     //   #108	-> 582
/*     */     //   #109	-> 592
/*     */     //   #110	-> 605
/*     */     //   #301	-> 625
/*     */     //   #302	-> 637
/*     */     //   #303	-> 648
/*     */     //   #110	-> 651
/*     */     //   #303	-> 654
/*     */     //   #304	-> 656
/*     */     //   #305	-> 665
/*     */     //   #306	-> 670
/*     */     //   #302	-> 672
/*     */     //   #301	-> 673
/*     */     //   #301	-> 674
/*     */     //   #110	-> 675
/*     */     //   #111	-> 699
/*     */     //   #112	-> 727
/*     */     //   #113	-> 755
/*     */     //   #115	-> 826
/*     */     //   #117	-> 829
/*     */     //   #118	-> 830
/*     */     //   #119	-> 831
/*     */     //   #120	-> 832
/*     */     //   #121	-> 833
/*     */     //   #122	-> 835
/*     */     //   #123	-> 837
/*     */     //   #124	-> 839
/*     */     //   #125	-> 841
/*     */     //   #126	-> 843
/*     */     //   #116	-> 909
/*     */     //   #128	-> 924
/*     */     // Local variable table:
/*     */     //   start	length	slot	name	descriptor
/*     */     //   651	3	20	$i$a$-cache-RadioButtonKt$RadioButtonRow$4	I
/*     */     //   656	11	20	value$iv	Ljava/lang/Object;
/*     */     //   637	36	19	$i$a$-let-ComposerKt$cache$1$iv	I
/*     */     //   634	39	18	it$iv	Ljava/lang/Object;
/*     */     //   625	50	17	$i$f$cache	I
/*     */     //   622	53	15	$this$cache$iv	Landroidx/compose/runtime/Composer;
/*     */     //   622	53	16	invalid$iv	Z
/*     */     //   30	947	13	$dirty	I
/*     */     //   0	977	0	selected	Z
/*     */     //   0	977	1	onClick	Lkotlin/jvm/functions/Function0;
/*     */     //   0	977	2	modifier	Landroidx/compose/ui/Modifier;
/*     */     //   0	977	3	enabled	Z
/*     */     //   0	977	4	outline	Lorg/jetbrains/jewel/ui/Outline;
/*     */     //   0	977	5	interactionSource	Landroidx/compose/foundation/interaction/MutableInteractionSource;
/*     */     //   0	977	6	style	Lorg/jetbrains/jewel/ui/component/styling/RadioButtonStyle;
/*     */     //   0	977	7	textStyle	Landroidx/compose/ui/text/TextStyle;
/*     */     //   0	977	8	verticalAlignment	Landroidx/compose/ui/Alignment$Vertical;
/*     */     //   0	977	9	content	Lkotlin/jvm/functions/Function3;
/*     */     //   0	977	10	$composer	Landroidx/compose/runtime/Composer;
/*     */     //   0	977	11	$changed	I
/*     */   }
/*     */ 
/*     */ 
/*     */ 
/*     */ 
/*     */ 
/*     */ 
/*     */   
/*     */   @Composable
/*     */   @ComposableInferredTarget(scheme = "[androidx.compose.ui.UiComposable[androidx.compose.ui.UiComposable]]")
/*     */   private static final void RadioButtonImpl(boolean selected, Function0 onClick, Modifier modifier, boolean enabled, Outline outline, MutableInteractionSource interactionSource, RadioButtonStyle style, TextStyle textStyle, Alignment.Vertical verticalAlignment, Function3 content, Composer $composer, int $changed) {
/*     */     // Byte code:
/*     */     //   0: aload #10
/*     */     //   2: ldc_w -350532414
/*     */     //   5: invokeinterface startRestartGroup : (I)Landroidx/compose/runtime/Composer;
/*     */     //   10: astore #10
/*     */     //   12: iload #11
/*     */     //   14: istore #12
/*     */     //   16: iload #11
/*     */     //   18: bipush #6
/*     */     //   20: iand
/*     */     //   21: ifne -> 45
/*     */     //   24: iload #12
/*     */     //   26: aload #10
/*     */     //   28: iload_0
/*     */     //   29: invokeinterface changed : (Z)Z
/*     */     //   34: ifeq -> 41
/*     */     //   37: iconst_4
/*     */     //   38: goto -> 42
/*     */     //   41: iconst_2
/*     */     //   42: ior
/*     */     //   43: istore #12
/*     */     //   45: iload #11
/*     */     //   47: bipush #48
/*     */     //   49: iand
/*     */     //   50: ifne -> 76
/*     */     //   53: iload #12
/*     */     //   55: aload #10
/*     */     //   57: aload_1
/*     */     //   58: invokeinterface changedInstance : (Ljava/lang/Object;)Z
/*     */     //   63: ifeq -> 71
/*     */     //   66: bipush #32
/*     */     //   68: goto -> 73
/*     */     //   71: bipush #16
/*     */     //   73: ior
/*     */     //   74: istore #12
/*     */     //   76: iload #11
/*     */     //   78: sipush #384
/*     */     //   81: iand
/*     */     //   82: ifne -> 110
/*     */     //   85: iload #12
/*     */     //   87: aload #10
/*     */     //   89: aload_2
/*     */     //   90: invokeinterface changed : (Ljava/lang/Object;)Z
/*     */     //   95: ifeq -> 104
/*     */     //   98: sipush #256
/*     */     //   101: goto -> 107
/*     */     //   104: sipush #128
/*     */     //   107: ior
/*     */     //   108: istore #12
/*     */     //   110: iload #11
/*     */     //   112: sipush #3072
/*     */     //   115: iand
/*     */     //   116: ifne -> 144
/*     */     //   119: iload #12
/*     */     //   121: aload #10
/*     */     //   123: iload_3
/*     */     //   124: invokeinterface changed : (Z)Z
/*     */     //   129: ifeq -> 138
/*     */     //   132: sipush #2048
/*     */     //   135: goto -> 141
/*     */     //   138: sipush #1024
/*     */     //   141: ior
/*     */     //   142: istore #12
/*     */     //   144: iload #11
/*     */     //   146: sipush #24576
/*     */     //   149: iand
/*     */     //   150: ifne -> 179
/*     */     //   153: iload #12
/*     */     //   155: aload #10
/*     */     //   157: aload #4
/*     */     //   159: invokeinterface changed : (Ljava/lang/Object;)Z
/*     */     //   164: ifeq -> 173
/*     */     //   167: sipush #16384
/*     */     //   170: goto -> 176
/*     */     //   173: sipush #8192
/*     */     //   176: ior
/*     */     //   177: istore #12
/*     */     //   179: iload #11
/*     */     //   181: ldc 196608
/*     */     //   183: iand
/*     */     //   184: ifne -> 211
/*     */     //   187: iload #12
/*     */     //   189: aload #10
/*     */     //   191: aload #5
/*     */     //   193: invokeinterface changed : (Ljava/lang/Object;)Z
/*     */     //   198: ifeq -> 206
/*     */     //   201: ldc 131072
/*     */     //   203: goto -> 208
/*     */     //   206: ldc 65536
/*     */     //   208: ior
/*     */     //   209: istore #12
/*     */     //   211: iload #11
/*     */     //   213: ldc 1572864
/*     */     //   215: iand
/*     */     //   216: ifne -> 243
/*     */     //   219: iload #12
/*     */     //   221: aload #10
/*     */     //   223: aload #6
/*     */     //   225: invokeinterface changed : (Ljava/lang/Object;)Z
/*     */     //   230: ifeq -> 238
/*     */     //   233: ldc 1048576
/*     */     //   235: goto -> 240
/*     */     //   238: ldc 524288
/*     */     //   240: ior
/*     */     //   241: istore #12
/*     */     //   243: iload #11
/*     */     //   245: ldc 12582912
/*     */     //   247: iand
/*     */     //   248: ifne -> 275
/*     */     //   251: iload #12
/*     */     //   253: aload #10
/*     */     //   255: aload #7
/*     */     //   257: invokeinterface changed : (Ljava/lang/Object;)Z
/*     */     //   262: ifeq -> 270
/*     */     //   265: ldc 8388608
/*     */     //   267: goto -> 272
/*     */     //   270: ldc 4194304
/*     */     //   272: ior
/*     */     //   273: istore #12
/*     */     //   275: iload #11
/*     */     //   277: ldc 100663296
/*     */     //   279: iand
/*     */     //   280: ifne -> 307
/*     */     //   283: iload #12
/*     */     //   285: aload #10
/*     */     //   287: aload #8
/*     */     //   289: invokeinterface changed : (Ljava/lang/Object;)Z
/*     */     //   294: ifeq -> 302
/*     */     //   297: ldc 67108864
/*     */     //   299: goto -> 304
/*     */     //   302: ldc 33554432
/*     */     //   304: ior
/*     */     //   305: istore #12
/*     */     //   307: iload #11
/*     */     //   309: ldc 805306368
/*     */     //   311: iand
/*     */     //   312: ifne -> 339
/*     */     //   315: iload #12
/*     */     //   317: aload #10
/*     */     //   319: aload #9
/*     */     //   321: invokeinterface changedInstance : (Ljava/lang/Object;)Z
/*     */     //   326: ifeq -> 334
/*     */     //   329: ldc 536870912
/*     */     //   331: goto -> 336
/*     */     //   334: ldc 268435456
/*     */     //   336: ior
/*     */     //   337: istore #12
/*     */     //   339: iload #12
/*     */     //   341: ldc 306783379
/*     */     //   343: iand
/*     */     //   344: ldc 306783378
/*     */     //   346: if_icmpne -> 359
/*     */     //   349: aload #10
/*     */     //   351: invokeinterface getSkipping : ()Z
/*     */     //   356: ifne -> 2630
/*     */     //   359: invokestatic isTraceInProgress : ()Z
/*     */     //   362: ifeq -> 377
/*     */     //   365: ldc_w -350532414
/*     */     //   368: iload #12
/*     */     //   370: iconst_m1
/*     */     //   371: ldc_w 'org.jetbrains.jewel.ui.component.RadioButtonImpl (RadioButton.kt:141)'
/*     */     //   374: invokestatic traceEventStart : (IIILjava/lang/String;)V
/*     */     //   377: aload #10
/*     */     //   379: ldc_w 1750759399
/*     */     //   382: invokeinterface startReplaceGroup : (I)V
/*     */     //   387: aload #10
/*     */     //   389: astore #15
/*     */     //   391: iconst_0
/*     */     //   392: istore #16
/*     */     //   394: nop
/*     */     //   395: iconst_0
/*     */     //   396: istore #17
/*     */     //   398: aload #15
/*     */     //   400: invokeinterface rememberedValue : ()Ljava/lang/Object;
/*     */     //   405: astore #18
/*     */     //   407: iconst_0
/*     */     //   408: istore #19
/*     */     //   410: aload #18
/*     */     //   412: getstatic androidx/compose/runtime/Composer.Companion : Landroidx/compose/runtime/Composer$Companion;
/*     */     //   415: invokevirtual getEmpty : ()Ljava/lang/Object;
/*     */     //   418: if_acmpne -> 464
/*     */     //   421: iconst_0
/*     */     //   422: istore #20
/*     */     //   424: getstatic org/jetbrains/jewel/ui/component/RadioButtonState.Companion : Lorg/jetbrains/jewel/ui/component/RadioButtonState$Companion;
/*     */     //   427: iload_0
/*     */     //   428: iload_3
/*     */     //   429: iconst_0
/*     */     //   430: iconst_0
/*     */     //   431: iconst_0
/*     */     //   432: iconst_0
/*     */     //   433: bipush #60
/*     */     //   435: aconst_null
/*     */     //   436: invokestatic of-fp8g3n8$default : (Lorg/jetbrains/jewel/ui/component/RadioButtonState$Companion;ZZZZZZILjava/lang/Object;)J
/*     */     //   439: invokestatic box-impl : (J)Lorg/jetbrains/jewel/ui/component/RadioButtonState;
/*     */     //   442: aconst_null
/*     */     //   443: iconst_2
/*     */     //   444: aconst_null
/*     */     //   445: invokestatic mutableStateOf$default : (Ljava/lang/Object;Landroidx/compose/runtime/SnapshotMutationPolicy;ILjava/lang/Object;)Landroidx/compose/runtime/MutableState;
/*     */     //   448: astore #21
/*     */     //   450: aload #15
/*     */     //   452: aload #21
/*     */     //   454: invokeinterface updateRememberedValue : (Ljava/lang/Object;)V
/*     */     //   459: aload #21
/*     */     //   461: goto -> 466
/*     */     //   464: aload #18
/*     */     //   466: nop
/*     */     //   467: nop
/*     */     //   468: nop
/*     */     //   469: checkcast androidx/compose/runtime/MutableState
/*     */     //   472: astore #14
/*     */     //   474: aload #10
/*     */     //   476: invokeinterface endReplaceGroup : ()V
/*     */     //   481: aload #14
/*     */     //   483: astore #13
/*     */     //   485: aload #10
/*     */     //   487: ldc_w 1750762431
/*     */     //   490: invokeinterface startReplaceGroup : (I)V
/*     */     //   495: aload #10
/*     */     //   497: astore #14
/*     */     //   499: iload #12
/*     */     //   501: bipush #14
/*     */     //   503: iand
/*     */     //   504: iconst_4
/*     */     //   505: if_icmpne -> 512
/*     */     //   508: iconst_1
/*     */     //   509: goto -> 513
/*     */     //   512: iconst_0
/*     */     //   513: iload #12
/*     */     //   515: sipush #7168
/*     */     //   518: iand
/*     */     //   519: sipush #2048
/*     */     //   522: if_icmpne -> 529
/*     */     //   525: iconst_1
/*     */     //   526: goto -> 530
/*     */     //   529: iconst_0
/*     */     //   530: ior
/*     */     //   531: istore #15
/*     */     //   533: nop
/*     */     //   534: iconst_0
/*     */     //   535: istore #16
/*     */     //   537: aload #14
/*     */     //   539: invokeinterface rememberedValue : ()Ljava/lang/Object;
/*     */     //   544: astore #17
/*     */     //   546: iconst_0
/*     */     //   547: istore #18
/*     */     //   549: iload #15
/*     */     //   551: ifne -> 565
/*     */     //   554: aload #17
/*     */     //   556: getstatic androidx/compose/runtime/Composer.Companion : Landroidx/compose/runtime/Composer$Companion;
/*     */     //   559: invokevirtual getEmpty : ()Ljava/lang/Object;
/*     */     //   562: if_acmpne -> 609
/*     */     //   565: iconst_0
/*     */     //   566: istore #19
/*     */     //   568: aload #13
/*     */     //   570: aload #13
/*     */     //   572: invokestatic RadioButtonImpl$lambda$7 : (Landroidx/compose/runtime/MutableState;)J
/*     */     //   575: iload_0
/*     */     //   576: iload_3
/*     */     //   577: iconst_0
/*     */     //   578: iconst_0
/*     */     //   579: iconst_0
/*     */     //   580: iconst_0
/*     */     //   581: bipush #60
/*     */     //   583: aconst_null
/*     */     //   584: invokestatic copy-fp8g3n8$default : (JZZZZZZILjava/lang/Object;)J
/*     */     //   587: invokestatic RadioButtonImpl$lambda$8 : (Landroidx/compose/runtime/MutableState;J)V
/*     */     //   590: getstatic kotlin/Unit.INSTANCE : Lkotlin/Unit;
/*     */     //   593: astore #20
/*     */     //   595: aload #14
/*     */     //   597: aload #20
/*     */     //   599: invokeinterface updateRememberedValue : (Ljava/lang/Object;)V
/*     */     //   604: aload #20
/*     */     //   606: goto -> 611
/*     */     //   609: aload #17
/*     */     //   611: nop
/*     */     //   612: nop
/*     */     //   613: nop
/*     */     //   614: pop
/*     */     //   615: aload #10
/*     */     //   617: invokeinterface endReplaceGroup : ()V
/*     */     //   622: getstatic org/jetbrains/jewel/foundation/theme/JewelTheme.Companion : Lorg/jetbrains/jewel/foundation/theme/JewelTheme$Companion;
/*     */     //   625: aload #10
/*     */     //   627: bipush #6
/*     */     //   629: invokevirtual isSwingCompatMode : (Landroidx/compose/runtime/Composer;I)Z
/*     */     //   632: istore #14
/*     */     //   634: aload #5
/*     */     //   636: iload #14
/*     */     //   638: invokestatic valueOf : (Z)Ljava/lang/Boolean;
/*     */     //   641: aload #10
/*     */     //   643: ldc_w 1750770304
/*     */     //   646: invokeinterface startReplaceGroup : (I)V
/*     */     //   651: aload #10
/*     */     //   653: astore #16
/*     */     //   655: iload #12
/*     */     //   657: ldc 458752
/*     */     //   659: iand
/*     */     //   660: ldc 131072
/*     */     //   662: if_icmpne -> 669
/*     */     //   665: iconst_1
/*     */     //   666: goto -> 670
/*     */     //   669: iconst_0
/*     */     //   670: aload #10
/*     */     //   672: iload #14
/*     */     //   674: invokeinterface changed : (Z)Z
/*     */     //   679: ior
/*     */     //   680: istore #17
/*     */     //   682: iconst_0
/*     */     //   683: istore #18
/*     */     //   685: aload #16
/*     */     //   687: invokeinterface rememberedValue : ()Ljava/lang/Object;
/*     */     //   692: astore #19
/*     */     //   694: iconst_0
/*     */     //   695: istore #20
/*     */     //   697: iload #17
/*     */     //   699: ifne -> 713
/*     */     //   702: aload #19
/*     */     //   704: getstatic androidx/compose/runtime/Composer.Companion : Landroidx/compose/runtime/Composer$Companion;
/*     */     //   707: invokevirtual getEmpty : ()Ljava/lang/Object;
/*     */     //   710: if_acmpne -> 761
/*     */     //   713: astore #92
/*     */     //   715: astore #91
/*     */     //   717: iconst_0
/*     */     //   718: istore #21
/*     */     //   720: new org/jetbrains/jewel/ui/component/RadioButtonKt$RadioButtonImpl$2$1
/*     */     //   723: dup
/*     */     //   724: aload #5
/*     */     //   726: iload #14
/*     */     //   728: aload #13
/*     */     //   730: aconst_null
/*     */     //   731: invokespecial <init> : (Landroidx/compose/foundation/interaction/MutableInteractionSource;ZLandroidx/compose/runtime/MutableState;Lkotlin/coroutines/Continuation;)V
/*     */     //   734: checkcast kotlin/jvm/functions/Function2
/*     */     //   737: astore #93
/*     */     //   739: aload #91
/*     */     //   741: aload #92
/*     */     //   743: aload #93
/*     */     //   745: astore #22
/*     */     //   747: aload #16
/*     */     //   749: aload #22
/*     */     //   751: invokeinterface updateRememberedValue : (Ljava/lang/Object;)V
/*     */     //   756: aload #22
/*     */     //   758: goto -> 763
/*     */     //   761: aload #19
/*     */     //   763: nop
/*     */     //   764: nop
/*     */     //   765: nop
/*     */     //   766: checkcast kotlin/jvm/functions/Function2
/*     */     //   769: astore #15
/*     */     //   771: aload #10
/*     */     //   773: invokeinterface endReplaceGroup : ()V
/*     */     //   778: aload #15
/*     */     //   780: aload #10
/*     */     //   782: bipush #14
/*     */     //   784: iload #12
/*     */     //   786: bipush #15
/*     */     //   788: ishr
/*     */     //   789: iand
/*     */     //   790: invokestatic LaunchedEffect : (Ljava/lang/Object;Ljava/lang/Object;Lkotlin/jvm/functions/Function2;Landroidx/compose/runtime/Composer;I)V
/*     */     //   793: getstatic androidx/compose/ui/semantics/Role.Companion : Landroidx/compose/ui/semantics/Role$Companion;
/*     */     //   796: invokevirtual getRadioButton-o7Vup1c : ()I
/*     */     //   799: istore #16
/*     */     //   801: aload_2
/*     */     //   802: iload_0
/*     */     //   803: aload #5
/*     */     //   805: aconst_null
/*     */     //   806: iload_3
/*     */     //   807: iload #16
/*     */     //   809: invokestatic box-impl : (I)Landroidx/compose/ui/semantics/Role;
/*     */     //   812: aload_1
/*     */     //   813: invokestatic selectable-O2vRcR0 : (Landroidx/compose/ui/Modifier;ZLandroidx/compose/foundation/interaction/MutableInteractionSource;Landroidx/compose/foundation/Indication;ZLandroidx/compose/ui/semantics/Role;Lkotlin/jvm/functions/Function0;)Landroidx/compose/ui/Modifier;
/*     */     //   816: astore #15
/*     */     //   818: aload #6
/*     */     //   820: invokevirtual getColors : ()Lorg/jetbrains/jewel/ui/component/styling/RadioButtonColors;
/*     */     //   823: astore #16
/*     */     //   825: aload #6
/*     */     //   827: invokevirtual getMetrics : ()Lorg/jetbrains/jewel/ui/component/styling/RadioButtonMetrics;
/*     */     //   830: astore #17
/*     */     //   832: getstatic androidx/compose/ui/Modifier.Companion : Landroidx/compose/ui/Modifier$Companion;
/*     */     //   835: checkcast androidx/compose/ui/Modifier
/*     */     //   838: aload #17
/*     */     //   840: aload #13
/*     */     //   842: invokestatic RadioButtonImpl$lambda$7 : (Landroidx/compose/runtime/MutableState;)J
/*     */     //   845: aload #10
/*     */     //   847: iconst_0
/*     */     //   848: invokevirtual outlineSizeFor-ehnS_G0 : (JLandroidx/compose/runtime/Composer;I)Landroidx/compose/runtime/State;
/*     */     //   851: invokeinterface getValue : ()Ljava/lang/Object;
/*     */     //   856: checkcast androidx/compose/ui/unit/DpSize
/*     */     //   859: invokevirtual unbox-impl : ()J
/*     */     //   862: invokestatic size-6HolHcs : (Landroidx/compose/ui/Modifier;J)Landroidx/compose/ui/Modifier;
/*     */     //   865: aload #13
/*     */     //   867: invokestatic RadioButtonImpl$lambda$7 : (Landroidx/compose/runtime/MutableState;)J
/*     */     //   870: invokestatic box-impl : (J)Lorg/jetbrains/jewel/ui/component/RadioButtonState;
/*     */     //   873: aload #4
/*     */     //   875: invokestatic getCircleShape : ()Landroidx/compose/foundation/shape/RoundedCornerShape;
/*     */     //   878: checkcast androidx/compose/ui/graphics/Shape
/*     */     //   881: getstatic org/jetbrains/jewel/foundation/Stroke$Alignment.Center : Lorg/jetbrains/jewel/foundation/Stroke$Alignment;
/*     */     //   884: fconst_0
/*     */     //   885: aload #10
/*     */     //   887: sipush #24576
/*     */     //   890: sipush #896
/*     */     //   893: iload #12
/*     */     //   895: bipush #6
/*     */     //   897: ishr
/*     */     //   898: iand
/*     */     //   899: ior
/*     */     //   900: bipush #16
/*     */     //   902: invokestatic outline-HYR8e34 : (Landroidx/compose/ui/Modifier;Lorg/jetbrains/jewel/foundation/state/FocusableComponentState;Lorg/jetbrains/jewel/ui/Outline;Landroidx/compose/ui/graphics/Shape;Lorg/jetbrains/jewel/foundation/Stroke$Alignment;FLandroidx/compose/runtime/Composer;II)Landroidx/compose/ui/Modifier;
/*     */     //   905: astore #18
/*     */     //   907: aload #6
/*     */     //   909: invokevirtual getIcons : ()Lorg/jetbrains/jewel/ui/component/styling/RadioButtonIcons;
/*     */     //   912: invokevirtual getRadioButton : ()Lorg/jetbrains/jewel/ui/icon/IconKey;
/*     */     //   915: aconst_null
/*     */     //   916: aload #10
/*     */     //   918: iconst_0
/*     */     //   919: iconst_2
/*     */     //   920: invokestatic rememberResourcePainterProvider : (Lorg/jetbrains/jewel/ui/icon/IconKey;Ljava/lang/Class;Landroidx/compose/runtime/Composer;II)Lorg/jetbrains/jewel/ui/painter/PainterProvider;
/*     */     //   923: astore #19
/*     */     //   925: aload #19
/*     */     //   927: iconst_2
/*     */     //   928: anewarray org/jetbrains/jewel/ui/painter/PainterHint
/*     */     //   931: astore #21
/*     */     //   933: aload #21
/*     */     //   935: iconst_0
/*     */     //   936: aload #13
/*     */     //   938: invokestatic RadioButtonImpl$lambda$7 : (Landroidx/compose/runtime/MutableState;)J
/*     */     //   941: invokestatic box-impl : (J)Lorg/jetbrains/jewel/ui/component/RadioButtonState;
/*     */     //   944: invokestatic Selected : (Lorg/jetbrains/jewel/foundation/state/SelectableComponentState;)Lorg/jetbrains/jewel/ui/painter/PainterHint;
/*     */     //   947: aastore
/*     */     //   948: aload #21
/*     */     //   950: iconst_1
/*     */     //   951: aload #13
/*     */     //   953: invokestatic RadioButtonImpl$lambda$7 : (Landroidx/compose/runtime/MutableState;)J
/*     */     //   956: invokestatic box-impl : (J)Lorg/jetbrains/jewel/ui/component/RadioButtonState;
/*     */     //   959: invokestatic Stateful : (Lorg/jetbrains/jewel/foundation/state/InteractiveComponentState;)Lorg/jetbrains/jewel/ui/painter/PainterHint;
/*     */     //   962: aastore
/*     */     //   963: aload #21
/*     */     //   965: aload #10
/*     */     //   967: iconst_0
/*     */     //   968: invokeinterface getPainter : ([Lorg/jetbrains/jewel/ui/painter/PainterHint;Landroidx/compose/runtime/Composer;I)Landroidx/compose/runtime/State;
/*     */     //   973: astore #20
/*     */     //   975: getstatic androidx/compose/ui/Modifier.Companion : Landroidx/compose/ui/Modifier$Companion;
/*     */     //   978: checkcast androidx/compose/ui/Modifier
/*     */     //   981: aload #17
/*     */     //   983: invokevirtual getRadioButtonSize-MYxV2XQ : ()J
/*     */     //   986: invokestatic size-6HolHcs : (Landroidx/compose/ui/Modifier;J)Landroidx/compose/ui/Modifier;
/*     */     //   989: astore #21
/*     */     //   991: aload #9
/*     */     //   993: ifnonnull -> 1427
/*     */     //   996: aload #10
/*     */     //   998: ldc_w -1558936699
/*     */     //   1001: invokeinterface startReplaceGroup : (I)V
/*     */     //   1006: getstatic androidx/compose/ui/Alignment.Companion : Landroidx/compose/ui/Alignment$Companion;
/*     */     //   1009: invokevirtual getCenter : ()Landroidx/compose/ui/Alignment;
/*     */     //   1012: astore #22
/*     */     //   1014: bipush #48
/*     */     //   1016: istore #24
/*     */     //   1018: iconst_0
/*     */     //   1019: istore #25
/*     */     //   1021: aload #10
/*     */     //   1023: ldc_w 733328855
/*     */     //   1026: ldc_w 'CC(Box)P(2,1,3)72@3384L130:Box.kt#2w3rfo'
/*     */     //   1029: invokestatic sourceInformationMarkerStart : (Landroidx/compose/runtime/Composer;ILjava/lang/String;)V
/*     */     //   1032: iconst_0
/*     */     //   1033: istore #23
/*     */     //   1035: aload #22
/*     */     //   1037: iload #23
/*     */     //   1039: invokestatic maybeCachedBoxMeasurePolicy : (Landroidx/compose/ui/Alignment;Z)Landroidx/compose/ui/layout/MeasurePolicy;
/*     */     //   1042: astore #26
/*     */     //   1044: bipush #112
/*     */     //   1046: iload #24
/*     */     //   1048: iconst_3
/*     */     //   1049: ishl
/*     */     //   1050: iand
/*     */     //   1051: istore #27
/*     */     //   1053: nop
/*     */     //   1054: iconst_0
/*     */     //   1055: istore #28
/*     */     //   1057: aload #10
/*     */     //   1059: ldc_w -1323940314
/*     */     //   1062: ldc_w 'CC(Layout)P(!1,2)79@3208L23,82@3359L411:Layout.kt#80mrfh'
/*     */     //   1065: invokestatic sourceInformationMarkerStart : (Landroidx/compose/runtime/Composer;ILjava/lang/String;)V
/*     */     //   1068: aload #10
/*     */     //   1070: iconst_0
/*     */     //   1071: invokestatic getCurrentCompositeKeyHash : (Landroidx/compose/runtime/Composer;I)I
/*     */     //   1074: istore #29
/*     */     //   1076: aload #10
/*     */     //   1078: invokeinterface getCurrentCompositionLocalMap : ()Landroidx/compose/runtime/CompositionLocalMap;
/*     */     //   1083: astore #30
/*     */     //   1085: aload #10
/*     */     //   1087: aload #21
/*     */     //   1089: invokestatic materializeModifier : (Landroidx/compose/runtime/Composer;Landroidx/compose/ui/Modifier;)Landroidx/compose/ui/Modifier;
/*     */     //   1092: astore #31
/*     */     //   1094: getstatic androidx/compose/ui/node/ComposeUiNode.Companion : Landroidx/compose/ui/node/ComposeUiNode$Companion;
/*     */     //   1097: invokevirtual getConstructor : ()Lkotlin/jvm/functions/Function0;
/*     */     //   1100: astore #32
/*     */     //   1102: bipush #6
/*     */     //   1104: sipush #896
/*     */     //   1107: iload #27
/*     */     //   1109: bipush #6
/*     */     //   1111: ishl
/*     */     //   1112: iand
/*     */     //   1113: ior
/*     */     //   1114: istore #33
/*     */     //   1116: nop
/*     */     //   1117: iconst_0
/*     */     //   1118: istore #34
/*     */     //   1120: aload #10
/*     */     //   1122: ldc_w -692256719
/*     */     //   1125: ldc_w 'CC(ReusableComposeNode)P(1,2)376@14062L9:Composables.kt#9igjgp'
/*     */     //   1128: invokestatic sourceInformationMarkerStart : (Landroidx/compose/runtime/Composer;ILjava/lang/String;)V
/*     */     //   1131: aload #10
/*     */     //   1133: invokeinterface getApplier : ()Landroidx/compose/runtime/Applier;
/*     */     //   1138: instanceof androidx/compose/runtime/Applier
/*     */     //   1141: ifne -> 1147
/*     */     //   1144: invokestatic invalidApplier : ()V
/*     */     //   1147: aload #10
/*     */     //   1149: invokeinterface startReusableNode : ()V
/*     */     //   1154: aload #10
/*     */     //   1156: invokeinterface getInserting : ()Z
/*     */     //   1161: ifeq -> 1176
/*     */     //   1164: aload #10
/*     */     //   1166: aload #32
/*     */     //   1168: invokeinterface createNode : (Lkotlin/jvm/functions/Function0;)V
/*     */     //   1173: goto -> 1183
/*     */     //   1176: aload #10
/*     */     //   1178: invokeinterface useNode : ()V
/*     */     //   1183: aload #10
/*     */     //   1185: invokestatic constructor-impl : (Landroidx/compose/runtime/Composer;)Landroidx/compose/runtime/Composer;
/*     */     //   1188: astore #35
/*     */     //   1190: iconst_0
/*     */     //   1191: istore #36
/*     */     //   1193: aload #35
/*     */     //   1195: aload #26
/*     */     //   1197: getstatic androidx/compose/ui/node/ComposeUiNode.Companion : Landroidx/compose/ui/node/ComposeUiNode$Companion;
/*     */     //   1200: invokevirtual getSetMeasurePolicy : ()Lkotlin/jvm/functions/Function2;
/*     */     //   1203: invokestatic set-impl : (Landroidx/compose/runtime/Composer;Ljava/lang/Object;Lkotlin/jvm/functions/Function2;)V
/*     */     //   1206: aload #35
/*     */     //   1208: aload #30
/*     */     //   1210: getstatic androidx/compose/ui/node/ComposeUiNode.Companion : Landroidx/compose/ui/node/ComposeUiNode$Companion;
/*     */     //   1213: invokevirtual getSetResolvedCompositionLocals : ()Lkotlin/jvm/functions/Function2;
/*     */     //   1216: invokestatic set-impl : (Landroidx/compose/runtime/Composer;Ljava/lang/Object;Lkotlin/jvm/functions/Function2;)V
/*     */     //   1219: getstatic androidx/compose/ui/node/ComposeUiNode.Companion : Landroidx/compose/ui/node/ComposeUiNode$Companion;
/*     */     //   1222: invokevirtual getSetCompositeKeyHash : ()Lkotlin/jvm/functions/Function2;
/*     */     //   1225: astore #37
/*     */     //   1227: iconst_0
/*     */     //   1228: istore #38
/*     */     //   1230: aload #35
/*     */     //   1232: astore #39
/*     */     //   1234: iconst_0
/*     */     //   1235: istore #40
/*     */     //   1237: aload #39
/*     */     //   1239: invokeinterface getInserting : ()Z
/*     */     //   1244: ifne -> 1265
/*     */     //   1247: aload #39
/*     */     //   1249: invokeinterface rememberedValue : ()Ljava/lang/Object;
/*     */     //   1254: iload #29
/*     */     //   1256: invokestatic valueOf : (I)Ljava/lang/Integer;
/*     */     //   1259: invokestatic areEqual : (Ljava/lang/Object;Ljava/lang/Object;)Z
/*     */     //   1262: ifne -> 1291
/*     */     //   1265: aload #39
/*     */     //   1267: iload #29
/*     */     //   1269: invokestatic valueOf : (I)Ljava/lang/Integer;
/*     */     //   1272: invokeinterface updateRememberedValue : (Ljava/lang/Object;)V
/*     */     //   1277: aload #35
/*     */     //   1279: iload #29
/*     */     //   1281: invokestatic valueOf : (I)Ljava/lang/Integer;
/*     */     //   1284: aload #37
/*     */     //   1286: invokeinterface apply : (Ljava/lang/Object;Lkotlin/jvm/functions/Function2;)V
/*     */     //   1291: nop
/*     */     //   1292: nop
/*     */     //   1293: nop
/*     */     //   1294: aload #35
/*     */     //   1296: aload #31
/*     */     //   1298: getstatic androidx/compose/ui/node/ComposeUiNode.Companion : Landroidx/compose/ui/node/ComposeUiNode$Companion;
/*     */     //   1301: invokevirtual getSetModifier : ()Lkotlin/jvm/functions/Function2;
/*     */     //   1304: invokestatic set-impl : (Landroidx/compose/runtime/Composer;Ljava/lang/Object;Lkotlin/jvm/functions/Function2;)V
/*     */     //   1307: nop
/*     */     //   1308: nop
/*     */     //   1309: aload #10
/*     */     //   1311: bipush #14
/*     */     //   1313: iload #33
/*     */     //   1315: bipush #6
/*     */     //   1317: ishr
/*     */     //   1318: iand
/*     */     //   1319: istore #41
/*     */     //   1321: astore #42
/*     */     //   1323: iconst_0
/*     */     //   1324: istore #43
/*     */     //   1326: aload #42
/*     */     //   1328: ldc_w -2146769399
/*     */     //   1331: ldc_w 'C73@3429L9:Box.kt#2w3rfo'
/*     */     //   1334: invokestatic sourceInformationMarkerStart : (Landroidx/compose/runtime/Composer;ILjava/lang/String;)V
/*     */     //   1337: getstatic androidx/compose/foundation/layout/BoxScopeInstance.INSTANCE : Landroidx/compose/foundation/layout/BoxScopeInstance;
/*     */     //   1340: aload #42
/*     */     //   1342: bipush #6
/*     */     //   1344: bipush #112
/*     */     //   1346: iload #24
/*     */     //   1348: bipush #6
/*     */     //   1350: ishr
/*     */     //   1351: iand
/*     */     //   1352: ior
/*     */     //   1353: istore #44
/*     */     //   1355: astore #45
/*     */     //   1357: checkcast androidx/compose/foundation/layout/BoxScope
/*     */     //   1360: astore #46
/*     */     //   1362: iconst_0
/*     */     //   1363: istore #47
/*     */     //   1365: aload #20
/*     */     //   1367: invokestatic RadioButtonImpl$lambda$11 : (Landroidx/compose/runtime/State;)Landroidx/compose/ui/graphics/painter/Painter;
/*     */     //   1370: aconst_null
/*     */     //   1371: aload #45
/*     */     //   1373: iconst_0
/*     */     //   1374: iconst_2
/*     */     //   1375: invokestatic RadioButtonImage : (Landroidx/compose/ui/graphics/painter/Painter;Landroidx/compose/ui/Modifier;Landroidx/compose/runtime/Composer;II)V
/*     */     //   1378: aload #18
/*     */     //   1380: aload #45
/*     */     //   1382: iconst_0
/*     */     //   1383: invokestatic Box : (Landroidx/compose/ui/Modifier;Landroidx/compose/runtime/Composer;I)V
/*     */     //   1386: nop
/*     */     //   1387: aload #42
/*     */     //   1389: invokestatic sourceInformationMarkerEnd : (Landroidx/compose/runtime/Composer;)V
/*     */     //   1392: aload #10
/*     */     //   1394: invokeinterface endNode : ()V
/*     */     //   1399: aload #10
/*     */     //   1401: invokestatic sourceInformationMarkerEnd : (Landroidx/compose/runtime/Composer;)V
/*     */     //   1404: nop
/*     */     //   1405: aload #10
/*     */     //   1407: invokestatic sourceInformationMarkerEnd : (Landroidx/compose/runtime/Composer;)V
/*     */     //   1410: nop
/*     */     //   1411: aload #10
/*     */     //   1413: invokestatic sourceInformationMarkerEnd : (Landroidx/compose/runtime/Composer;)V
/*     */     //   1416: nop
/*     */     //   1417: aload #10
/*     */     //   1419: invokeinterface endReplaceGroup : ()V
/*     */     //   1424: goto -> 2618
/*     */     //   1427: aload #10
/*     */     //   1429: ldc_w -1558736718
/*     */     //   1432: invokeinterface startReplaceGroup : (I)V
/*     */     //   1437: getstatic androidx/compose/foundation/layout/Arrangement.INSTANCE : Landroidx/compose/foundation/layout/Arrangement;
/*     */     //   1440: aload #17
/*     */     //   1442: invokevirtual getIconContentGap-D9Ej5fM : ()F
/*     */     //   1445: invokevirtual spacedBy-0680j_4 : (F)Landroidx/compose/foundation/layout/Arrangement$HorizontalOrVertical;
/*     */     //   1448: checkcast androidx/compose/foundation/layout/Arrangement$Horizontal
/*     */     //   1451: astore #22
/*     */     //   1453: sipush #896
/*     */     //   1456: iload #12
/*     */     //   1458: bipush #18
/*     */     //   1460: ishr
/*     */     //   1461: iand
/*     */     //   1462: istore #23
/*     */     //   1464: nop
/*     */     //   1465: iconst_0
/*     */     //   1466: istore #24
/*     */     //   1468: aload #10
/*     */     //   1470: ldc_w 693286680
/*     */     //   1473: ldc_w 'CC(Row)P(2,1,3)99@5018L58,100@5081L130:Row.kt#2w3rfo'
/*     */     //   1476: invokestatic sourceInformationMarkerStart : (Landroidx/compose/runtime/Composer;ILjava/lang/String;)V
/*     */     //   1479: aload #22
/*     */     //   1481: aload #8
/*     */     //   1483: aload #10
/*     */     //   1485: bipush #14
/*     */     //   1487: iload #23
/*     */     //   1489: iconst_3
/*     */     //   1490: ishr
/*     */     //   1491: iand
/*     */     //   1492: bipush #112
/*     */     //   1494: iload #23
/*     */     //   1496: iconst_3
/*     */     //   1497: ishr
/*     */     //   1498: iand
/*     */     //   1499: ior
/*     */     //   1500: invokestatic rowMeasurePolicy : (Landroidx/compose/foundation/layout/Arrangement$Horizontal;Landroidx/compose/ui/Alignment$Vertical;Landroidx/compose/runtime/Composer;I)Landroidx/compose/ui/layout/MeasurePolicy;
/*     */     //   1503: astore #25
/*     */     //   1505: bipush #112
/*     */     //   1507: iload #23
/*     */     //   1509: iconst_3
/*     */     //   1510: ishl
/*     */     //   1511: iand
/*     */     //   1512: istore #26
/*     */     //   1514: nop
/*     */     //   1515: iconst_0
/*     */     //   1516: istore #27
/*     */     //   1518: aload #10
/*     */     //   1520: ldc_w -1323940314
/*     */     //   1523: ldc_w 'CC(Layout)P(!1,2)79@3208L23,82@3359L411:Layout.kt#80mrfh'
/*     */     //   1526: invokestatic sourceInformationMarkerStart : (Landroidx/compose/runtime/Composer;ILjava/lang/String;)V
/*     */     //   1529: aload #10
/*     */     //   1531: iconst_0
/*     */     //   1532: invokestatic getCurrentCompositeKeyHash : (Landroidx/compose/runtime/Composer;I)I
/*     */     //   1535: istore #28
/*     */     //   1537: aload #10
/*     */     //   1539: invokeinterface getCurrentCompositionLocalMap : ()Landroidx/compose/runtime/CompositionLocalMap;
/*     */     //   1544: astore #29
/*     */     //   1546: aload #10
/*     */     //   1548: aload #15
/*     */     //   1550: invokestatic materializeModifier : (Landroidx/compose/runtime/Composer;Landroidx/compose/ui/Modifier;)Landroidx/compose/ui/Modifier;
/*     */     //   1553: astore #30
/*     */     //   1555: getstatic androidx/compose/ui/node/ComposeUiNode.Companion : Landroidx/compose/ui/node/ComposeUiNode$Companion;
/*     */     //   1558: invokevirtual getConstructor : ()Lkotlin/jvm/functions/Function0;
/*     */     //   1561: astore #31
/*     */     //   1563: bipush #6
/*     */     //   1565: sipush #896
/*     */     //   1568: iload #26
/*     */     //   1570: bipush #6
/*     */     //   1572: ishl
/*     */     //   1573: iand
/*     */     //   1574: ior
/*     */     //   1575: istore #32
/*     */     //   1577: nop
/*     */     //   1578: iconst_0
/*     */     //   1579: istore #33
/*     */     //   1581: aload #10
/*     */     //   1583: ldc_w -692256719
/*     */     //   1586: ldc_w 'CC(ReusableComposeNode)P(1,2)376@14062L9:Composables.kt#9igjgp'
/*     */     //   1589: invokestatic sourceInformationMarkerStart : (Landroidx/compose/runtime/Composer;ILjava/lang/String;)V
/*     */     //   1592: aload #10
/*     */     //   1594: invokeinterface getApplier : ()Landroidx/compose/runtime/Applier;
/*     */     //   1599: instanceof androidx/compose/runtime/Applier
/*     */     //   1602: ifne -> 1608
/*     */     //   1605: invokestatic invalidApplier : ()V
/*     */     //   1608: aload #10
/*     */     //   1610: invokeinterface startReusableNode : ()V
/*     */     //   1615: aload #10
/*     */     //   1617: invokeinterface getInserting : ()Z
/*     */     //   1622: ifeq -> 1637
/*     */     //   1625: aload #10
/*     */     //   1627: aload #31
/*     */     //   1629: invokeinterface createNode : (Lkotlin/jvm/functions/Function0;)V
/*     */     //   1634: goto -> 1644
/*     */     //   1637: aload #10
/*     */     //   1639: invokeinterface useNode : ()V
/*     */     //   1644: aload #10
/*     */     //   1646: invokestatic constructor-impl : (Landroidx/compose/runtime/Composer;)Landroidx/compose/runtime/Composer;
/*     */     //   1649: astore #34
/*     */     //   1651: iconst_0
/*     */     //   1652: istore #35
/*     */     //   1654: aload #34
/*     */     //   1656: aload #25
/*     */     //   1658: getstatic androidx/compose/ui/node/ComposeUiNode.Companion : Landroidx/compose/ui/node/ComposeUiNode$Companion;
/*     */     //   1661: invokevirtual getSetMeasurePolicy : ()Lkotlin/jvm/functions/Function2;
/*     */     //   1664: invokestatic set-impl : (Landroidx/compose/runtime/Composer;Ljava/lang/Object;Lkotlin/jvm/functions/Function2;)V
/*     */     //   1667: aload #34
/*     */     //   1669: aload #29
/*     */     //   1671: getstatic androidx/compose/ui/node/ComposeUiNode.Companion : Landroidx/compose/ui/node/ComposeUiNode$Companion;
/*     */     //   1674: invokevirtual getSetResolvedCompositionLocals : ()Lkotlin/jvm/functions/Function2;
/*     */     //   1677: invokestatic set-impl : (Landroidx/compose/runtime/Composer;Ljava/lang/Object;Lkotlin/jvm/functions/Function2;)V
/*     */     //   1680: getstatic androidx/compose/ui/node/ComposeUiNode.Companion : Landroidx/compose/ui/node/ComposeUiNode$Companion;
/*     */     //   1683: invokevirtual getSetCompositeKeyHash : ()Lkotlin/jvm/functions/Function2;
/*     */     //   1686: astore #36
/*     */     //   1688: iconst_0
/*     */     //   1689: istore #37
/*     */     //   1691: aload #34
/*     */     //   1693: astore #38
/*     */     //   1695: iconst_0
/*     */     //   1696: istore #39
/*     */     //   1698: aload #38
/*     */     //   1700: invokeinterface getInserting : ()Z
/*     */     //   1705: ifne -> 1726
/*     */     //   1708: aload #38
/*     */     //   1710: invokeinterface rememberedValue : ()Ljava/lang/Object;
/*     */     //   1715: iload #28
/*     */     //   1717: invokestatic valueOf : (I)Ljava/lang/Integer;
/*     */     //   1720: invokestatic areEqual : (Ljava/lang/Object;Ljava/lang/Object;)Z
/*     */     //   1723: ifne -> 1752
/*     */     //   1726: aload #38
/*     */     //   1728: iload #28
/*     */     //   1730: invokestatic valueOf : (I)Ljava/lang/Integer;
/*     */     //   1733: invokeinterface updateRememberedValue : (Ljava/lang/Object;)V
/*     */     //   1738: aload #34
/*     */     //   1740: iload #28
/*     */     //   1742: invokestatic valueOf : (I)Ljava/lang/Integer;
/*     */     //   1745: aload #36
/*     */     //   1747: invokeinterface apply : (Ljava/lang/Object;Lkotlin/jvm/functions/Function2;)V
/*     */     //   1752: nop
/*     */     //   1753: nop
/*     */     //   1754: nop
/*     */     //   1755: aload #34
/*     */     //   1757: aload #30
/*     */     //   1759: getstatic androidx/compose/ui/node/ComposeUiNode.Companion : Landroidx/compose/ui/node/ComposeUiNode$Companion;
/*     */     //   1762: invokevirtual getSetModifier : ()Lkotlin/jvm/functions/Function2;
/*     */     //   1765: invokestatic set-impl : (Landroidx/compose/runtime/Composer;Ljava/lang/Object;Lkotlin/jvm/functions/Function2;)V
/*     */     //   1768: nop
/*     */     //   1769: nop
/*     */     //   1770: aload #10
/*     */     //   1772: bipush #14
/*     */     //   1774: iload #32
/*     */     //   1776: bipush #6
/*     */     //   1778: ishr
/*     */     //   1779: iand
/*     */     //   1780: istore #40
/*     */     //   1782: astore #41
/*     */     //   1784: iconst_0
/*     */     //   1785: istore #42
/*     */     //   1787: aload #41
/*     */     //   1789: ldc_w -407840262
/*     */     //   1792: ldc_w 'C101@5126L9:Row.kt#2w3rfo'
/*     */     //   1795: invokestatic sourceInformationMarkerStart : (Landroidx/compose/runtime/Composer;ILjava/lang/String;)V
/*     */     //   1798: getstatic androidx/compose/foundation/layout/RowScopeInstance.INSTANCE : Landroidx/compose/foundation/layout/RowScopeInstance;
/*     */     //   1801: aload #41
/*     */     //   1803: bipush #6
/*     */     //   1805: bipush #112
/*     */     //   1807: iload #23
/*     */     //   1809: bipush #6
/*     */     //   1811: ishr
/*     */     //   1812: iand
/*     */     //   1813: ior
/*     */     //   1814: istore #43
/*     */     //   1816: astore #44
/*     */     //   1818: checkcast androidx/compose/foundation/layout/RowScope
/*     */     //   1821: astore #45
/*     */     //   1823: iconst_0
/*     */     //   1824: istore #46
/*     */     //   1826: getstatic androidx/compose/ui/Alignment.Companion : Landroidx/compose/ui/Alignment$Companion;
/*     */     //   1829: invokevirtual getCenter : ()Landroidx/compose/ui/Alignment;
/*     */     //   1832: astore #47
/*     */     //   1834: bipush #48
/*     */     //   1836: istore #48
/*     */     //   1838: iconst_0
/*     */     //   1839: istore #49
/*     */     //   1841: aload #44
/*     */     //   1843: ldc_w 733328855
/*     */     //   1846: ldc_w 'CC(Box)P(2,1,3)72@3384L130:Box.kt#2w3rfo'
/*     */     //   1849: invokestatic sourceInformationMarkerStart : (Landroidx/compose/runtime/Composer;ILjava/lang/String;)V
/*     */     //   1852: iconst_0
/*     */     //   1853: istore #50
/*     */     //   1855: aload #47
/*     */     //   1857: iload #50
/*     */     //   1859: invokestatic maybeCachedBoxMeasurePolicy : (Landroidx/compose/ui/Alignment;Z)Landroidx/compose/ui/layout/MeasurePolicy;
/*     */     //   1862: astore #51
/*     */     //   1864: bipush #112
/*     */     //   1866: iload #48
/*     */     //   1868: iconst_3
/*     */     //   1869: ishl
/*     */     //   1870: iand
/*     */     //   1871: istore #52
/*     */     //   1873: nop
/*     */     //   1874: iconst_0
/*     */     //   1875: istore #53
/*     */     //   1877: aload #44
/*     */     //   1879: ldc_w -1323940314
/*     */     //   1882: ldc_w 'CC(Layout)P(!1,2)79@3208L23,82@3359L411:Layout.kt#80mrfh'
/*     */     //   1885: invokestatic sourceInformationMarkerStart : (Landroidx/compose/runtime/Composer;ILjava/lang/String;)V
/*     */     //   1888: aload #44
/*     */     //   1890: iconst_0
/*     */     //   1891: invokestatic getCurrentCompositeKeyHash : (Landroidx/compose/runtime/Composer;I)I
/*     */     //   1894: istore #54
/*     */     //   1896: aload #44
/*     */     //   1898: invokeinterface getCurrentCompositionLocalMap : ()Landroidx/compose/runtime/CompositionLocalMap;
/*     */     //   1903: astore #55
/*     */     //   1905: aload #44
/*     */     //   1907: aload #21
/*     */     //   1909: invokestatic materializeModifier : (Landroidx/compose/runtime/Composer;Landroidx/compose/ui/Modifier;)Landroidx/compose/ui/Modifier;
/*     */     //   1912: astore #56
/*     */     //   1914: getstatic androidx/compose/ui/node/ComposeUiNode.Companion : Landroidx/compose/ui/node/ComposeUiNode$Companion;
/*     */     //   1917: invokevirtual getConstructor : ()Lkotlin/jvm/functions/Function0;
/*     */     //   1920: astore #57
/*     */     //   1922: bipush #6
/*     */     //   1924: sipush #896
/*     */     //   1927: iload #52
/*     */     //   1929: bipush #6
/*     */     //   1931: ishl
/*     */     //   1932: iand
/*     */     //   1933: ior
/*     */     //   1934: istore #58
/*     */     //   1936: nop
/*     */     //   1937: iconst_0
/*     */     //   1938: istore #59
/*     */     //   1940: aload #44
/*     */     //   1942: ldc_w -692256719
/*     */     //   1945: ldc_w 'CC(ReusableComposeNode)P(1,2)376@14062L9:Composables.kt#9igjgp'
/*     */     //   1948: invokestatic sourceInformationMarkerStart : (Landroidx/compose/runtime/Composer;ILjava/lang/String;)V
/*     */     //   1951: aload #44
/*     */     //   1953: invokeinterface getApplier : ()Landroidx/compose/runtime/Applier;
/*     */     //   1958: instanceof androidx/compose/runtime/Applier
/*     */     //   1961: ifne -> 1967
/*     */     //   1964: invokestatic invalidApplier : ()V
/*     */     //   1967: aload #44
/*     */     //   1969: invokeinterface startReusableNode : ()V
/*     */     //   1974: aload #44
/*     */     //   1976: invokeinterface getInserting : ()Z
/*     */     //   1981: ifeq -> 1996
/*     */     //   1984: aload #44
/*     */     //   1986: aload #57
/*     */     //   1988: invokeinterface createNode : (Lkotlin/jvm/functions/Function0;)V
/*     */     //   1993: goto -> 2003
/*     */     //   1996: aload #44
/*     */     //   1998: invokeinterface useNode : ()V
/*     */     //   2003: aload #44
/*     */     //   2005: invokestatic constructor-impl : (Landroidx/compose/runtime/Composer;)Landroidx/compose/runtime/Composer;
/*     */     //   2008: astore #60
/*     */     //   2010: iconst_0
/*     */     //   2011: istore #61
/*     */     //   2013: aload #60
/*     */     //   2015: aload #51
/*     */     //   2017: getstatic androidx/compose/ui/node/ComposeUiNode.Companion : Landroidx/compose/ui/node/ComposeUiNode$Companion;
/*     */     //   2020: invokevirtual getSetMeasurePolicy : ()Lkotlin/jvm/functions/Function2;
/*     */     //   2023: invokestatic set-impl : (Landroidx/compose/runtime/Composer;Ljava/lang/Object;Lkotlin/jvm/functions/Function2;)V
/*     */     //   2026: aload #60
/*     */     //   2028: aload #55
/*     */     //   2030: getstatic androidx/compose/ui/node/ComposeUiNode.Companion : Landroidx/compose/ui/node/ComposeUiNode$Companion;
/*     */     //   2033: invokevirtual getSetResolvedCompositionLocals : ()Lkotlin/jvm/functions/Function2;
/*     */     //   2036: invokestatic set-impl : (Landroidx/compose/runtime/Composer;Ljava/lang/Object;Lkotlin/jvm/functions/Function2;)V
/*     */     //   2039: getstatic androidx/compose/ui/node/ComposeUiNode.Companion : Landroidx/compose/ui/node/ComposeUiNode$Companion;
/*     */     //   2042: invokevirtual getSetCompositeKeyHash : ()Lkotlin/jvm/functions/Function2;
/*     */     //   2045: astore #62
/*     */     //   2047: iconst_0
/*     */     //   2048: istore #63
/*     */     //   2050: aload #60
/*     */     //   2052: astore #64
/*     */     //   2054: iconst_0
/*     */     //   2055: istore #65
/*     */     //   2057: aload #64
/*     */     //   2059: invokeinterface getInserting : ()Z
/*     */     //   2064: ifne -> 2085
/*     */     //   2067: aload #64
/*     */     //   2069: invokeinterface rememberedValue : ()Ljava/lang/Object;
/*     */     //   2074: iload #54
/*     */     //   2076: invokestatic valueOf : (I)Ljava/lang/Integer;
/*     */     //   2079: invokestatic areEqual : (Ljava/lang/Object;Ljava/lang/Object;)Z
/*     */     //   2082: ifne -> 2111
/*     */     //   2085: aload #64
/*     */     //   2087: iload #54
/*     */     //   2089: invokestatic valueOf : (I)Ljava/lang/Integer;
/*     */     //   2092: invokeinterface updateRememberedValue : (Ljava/lang/Object;)V
/*     */     //   2097: aload #60
/*     */     //   2099: iload #54
/*     */     //   2101: invokestatic valueOf : (I)Ljava/lang/Integer;
/*     */     //   2104: aload #62
/*     */     //   2106: invokeinterface apply : (Ljava/lang/Object;Lkotlin/jvm/functions/Function2;)V
/*     */     //   2111: nop
/*     */     //   2112: nop
/*     */     //   2113: nop
/*     */     //   2114: aload #60
/*     */     //   2116: aload #56
/*     */     //   2118: getstatic androidx/compose/ui/node/ComposeUiNode.Companion : Landroidx/compose/ui/node/ComposeUiNode$Companion;
/*     */     //   2121: invokevirtual getSetModifier : ()Lkotlin/jvm/functions/Function2;
/*     */     //   2124: invokestatic set-impl : (Landroidx/compose/runtime/Composer;Ljava/lang/Object;Lkotlin/jvm/functions/Function2;)V
/*     */     //   2127: nop
/*     */     //   2128: nop
/*     */     //   2129: aload #44
/*     */     //   2131: bipush #14
/*     */     //   2133: iload #58
/*     */     //   2135: bipush #6
/*     */     //   2137: ishr
/*     */     //   2138: iand
/*     */     //   2139: istore #66
/*     */     //   2141: astore #67
/*     */     //   2143: iconst_0
/*     */     //   2144: istore #68
/*     */     //   2146: aload #67
/*     */     //   2148: ldc_w -2146769399
/*     */     //   2151: ldc_w 'C73@3429L9:Box.kt#2w3rfo'
/*     */     //   2154: invokestatic sourceInformationMarkerStart : (Landroidx/compose/runtime/Composer;ILjava/lang/String;)V
/*     */     //   2157: getstatic androidx/compose/foundation/layout/BoxScopeInstance.INSTANCE : Landroidx/compose/foundation/layout/BoxScopeInstance;
/*     */     //   2160: aload #67
/*     */     //   2162: bipush #6
/*     */     //   2164: bipush #112
/*     */     //   2166: iload #48
/*     */     //   2168: bipush #6
/*     */     //   2170: ishr
/*     */     //   2171: iand
/*     */     //   2172: ior
/*     */     //   2173: istore #69
/*     */     //   2175: astore #70
/*     */     //   2177: checkcast androidx/compose/foundation/layout/BoxScope
/*     */     //   2180: astore #71
/*     */     //   2182: iconst_0
/*     */     //   2183: istore #72
/*     */     //   2185: aload #20
/*     */     //   2187: invokestatic RadioButtonImpl$lambda$11 : (Landroidx/compose/runtime/State;)Landroidx/compose/ui/graphics/painter/Painter;
/*     */     //   2190: aconst_null
/*     */     //   2191: aload #70
/*     */     //   2193: iconst_0
/*     */     //   2194: iconst_2
/*     */     //   2195: invokestatic RadioButtonImage : (Landroidx/compose/ui/graphics/painter/Painter;Landroidx/compose/ui/Modifier;Landroidx/compose/runtime/Composer;II)V
/*     */     //   2198: aload #18
/*     */     //   2200: aload #70
/*     */     //   2202: iconst_0
/*     */     //   2203: invokestatic Box : (Landroidx/compose/ui/Modifier;Landroidx/compose/runtime/Composer;I)V
/*     */     //   2206: nop
/*     */     //   2207: aload #67
/*     */     //   2209: invokestatic sourceInformationMarkerEnd : (Landroidx/compose/runtime/Composer;)V
/*     */     //   2212: aload #44
/*     */     //   2214: invokeinterface endNode : ()V
/*     */     //   2219: aload #44
/*     */     //   2221: invokestatic sourceInformationMarkerEnd : (Landroidx/compose/runtime/Composer;)V
/*     */     //   2224: nop
/*     */     //   2225: aload #44
/*     */     //   2227: invokestatic sourceInformationMarkerEnd : (Landroidx/compose/runtime/Composer;)V
/*     */     //   2230: nop
/*     */     //   2231: aload #44
/*     */     //   2233: invokestatic sourceInformationMarkerEnd : (Landroidx/compose/runtime/Composer;)V
/*     */     //   2236: nop
/*     */     //   2237: aload #16
/*     */     //   2239: aload #13
/*     */     //   2241: invokestatic RadioButtonImpl$lambda$7 : (Landroidx/compose/runtime/MutableState;)J
/*     */     //   2244: aload #44
/*     */     //   2246: iconst_0
/*     */     //   2247: invokevirtual contentFor-ehnS_G0 : (JLandroidx/compose/runtime/Composer;I)Landroidx/compose/runtime/State;
/*     */     //   2250: astore #47
/*     */     //   2252: aload #44
/*     */     //   2254: ldc_w -763445994
/*     */     //   2257: invokeinterface startReplaceGroup : (I)V
/*     */     //   2262: aload #47
/*     */     //   2264: invokestatic RadioButtonImpl$lambda$18$lambda$14 : (Landroidx/compose/runtime/State;)J
/*     */     //   2267: lstore #73
/*     */     //   2269: iconst_0
/*     */     //   2270: istore #54
/*     */     //   2272: lload #73
/*     */     //   2274: lstore #75
/*     */     //   2276: iconst_0
/*     */     //   2277: istore #57
/*     */     //   2279: lload #75
/*     */     //   2281: ldc2_w 16
/*     */     //   2284: lcmp
/*     */     //   2285: ifeq -> 2292
/*     */     //   2288: iconst_1
/*     */     //   2289: goto -> 2293
/*     */     //   2292: iconst_0
/*     */     //   2293: ifeq -> 2301
/*     */     //   2296: lload #73
/*     */     //   2298: goto -> 2310
/*     */     //   2301: iconst_0
/*     */     //   2302: istore #58
/*     */     //   2304: aload #7
/*     */     //   2306: invokevirtual getColor-0d7_KjU : ()J
/*     */     //   2309: nop
/*     */     //   2310: lstore #73
/*     */     //   2312: nop
/*     */     //   2313: iconst_0
/*     */     //   2314: istore #54
/*     */     //   2316: lload #73
/*     */     //   2318: lstore #75
/*     */     //   2320: iconst_0
/*     */     //   2321: istore #57
/*     */     //   2323: lload #75
/*     */     //   2325: ldc2_w 16
/*     */     //   2328: lcmp
/*     */     //   2329: ifeq -> 2336
/*     */     //   2332: iconst_1
/*     */     //   2333: goto -> 2337
/*     */     //   2336: iconst_0
/*     */     //   2337: ifeq -> 2345
/*     */     //   2340: lload #73
/*     */     //   2342: goto -> 2398
/*     */     //   2345: iconst_0
/*     */     //   2346: istore #58
/*     */     //   2348: invokestatic getLocalContentColor : ()Landroidx/compose/runtime/ProvidableCompositionLocal;
/*     */     //   2351: checkcast androidx/compose/runtime/CompositionLocal
/*     */     //   2354: astore #59
/*     */     //   2356: iconst_0
/*     */     //   2357: istore #60
/*     */     //   2359: iconst_0
/*     */     //   2360: istore #61
/*     */     //   2362: aload #44
/*     */     //   2364: ldc_w 2023513938
/*     */     //   2367: ldc_w 'CC:CompositionLocal.kt#9igjgp'
/*     */     //   2370: invokestatic sourceInformationMarkerStart : (Landroidx/compose/runtime/Composer;ILjava/lang/String;)V
/*     */     //   2373: aload #44
/*     */     //   2375: aload #59
/*     */     //   2377: invokeinterface consume : (Landroidx/compose/runtime/CompositionLocal;)Ljava/lang/Object;
/*     */     //   2382: astore #62
/*     */     //   2384: aload #44
/*     */     //   2386: invokestatic sourceInformationMarkerEnd : (Landroidx/compose/runtime/Composer;)V
/*     */     //   2389: aload #62
/*     */     //   2391: checkcast androidx/compose/ui/graphics/Color
/*     */     //   2394: invokevirtual unbox-impl : ()J
/*     */     //   2397: nop
/*     */     //   2398: lstore #77
/*     */     //   2400: aload #44
/*     */     //   2402: invokeinterface endReplaceGroup : ()V
/*     */     //   2407: lload #77
/*     */     //   2409: lstore #79
/*     */     //   2411: iconst_2
/*     */     //   2412: anewarray androidx/compose/runtime/ProvidedValue
/*     */     //   2415: astore #49
/*     */     //   2417: aload #49
/*     */     //   2419: iconst_0
/*     */     //   2420: invokestatic getLocalTextStyle : ()Landroidx/compose/runtime/ProvidableCompositionLocal;
/*     */     //   2423: aload #7
/*     */     //   2425: aload #47
/*     */     //   2427: invokestatic RadioButtonImpl$lambda$18$lambda$14 : (Landroidx/compose/runtime/State;)J
/*     */     //   2430: lstore #81
/*     */     //   2432: iconst_0
/*     */     //   2433: istore #53
/*     */     //   2435: lload #81
/*     */     //   2437: lstore #83
/*     */     //   2439: iconst_0
/*     */     //   2440: istore #56
/*     */     //   2442: lload #83
/*     */     //   2444: ldc2_w 16
/*     */     //   2447: lcmp
/*     */     //   2448: ifeq -> 2455
/*     */     //   2451: iconst_1
/*     */     //   2452: goto -> 2456
/*     */     //   2455: iconst_0
/*     */     //   2456: ifeq -> 2464
/*     */     //   2459: lload #81
/*     */     //   2461: goto -> 2493
/*     */     //   2464: astore #85
/*     */     //   2466: astore #86
/*     */     //   2468: istore #87
/*     */     //   2470: astore #88
/*     */     //   2472: iconst_0
/*     */     //   2473: istore #57
/*     */     //   2475: aload #7
/*     */     //   2477: invokevirtual getColor-0d7_KjU : ()J
/*     */     //   2480: lstore #89
/*     */     //   2482: aload #88
/*     */     //   2484: iload #87
/*     */     //   2486: aload #86
/*     */     //   2488: aload #85
/*     */     //   2490: lload #89
/*     */     //   2492: nop
/*     */     //   2493: lconst_0
/*     */     //   2494: aconst_null
/*     */     //   2495: aconst_null
/*     */     //   2496: aconst_null
/*     */     //   2497: aconst_null
/*     */     //   2498: aconst_null
/*     */     //   2499: lconst_0
/*     */     //   2500: aconst_null
/*     */     //   2501: aconst_null
/*     */     //   2502: aconst_null
/*     */     //   2503: lconst_0
/*     */     //   2504: aconst_null
/*     */     //   2505: aconst_null
/*     */     //   2506: aconst_null
/*     */     //   2507: iconst_0
/*     */     //   2508: iconst_0
/*     */     //   2509: lconst_0
/*     */     //   2510: aconst_null
/*     */     //   2511: aconst_null
/*     */     //   2512: aconst_null
/*     */     //   2513: iconst_0
/*     */     //   2514: iconst_0
/*     */     //   2515: aconst_null
/*     */     //   2516: ldc_w 16777214
/*     */     //   2519: aconst_null
/*     */     //   2520: invokestatic copy-p1EtxEg$default : (Landroidx/compose/ui/text/TextStyle;JJLandroidx/compose/ui/text/font/FontWeight;Landroidx/compose/ui/text/font/FontStyle;Landroidx/compose/ui/text/font/FontSynthesis;Landroidx/compose/ui/text/font/FontFamily;Ljava/lang/String;JLandroidx/compose/ui/text/style/BaselineShift;Landroidx/compose/ui/text/style/TextGeometricTransform;Landroidx/compose/ui/text/intl/LocaleList;JLandroidx/compose/ui/text/style/TextDecoration;Landroidx/compose/ui/graphics/Shadow;Landroidx/compose/ui/graphics/drawscope/DrawStyle;IIJLandroidx/compose/ui/text/style/TextIndent;Landroidx/compose/ui/text/PlatformTextStyle;Landroidx/compose/ui/text/style/LineHeightStyle;IILandroidx/compose/ui/text/style/TextMotion;ILjava/lang/Object;)Landroidx/compose/ui/text/TextStyle;
/*     */     //   2523: invokevirtual provides : (Ljava/lang/Object;)Landroidx/compose/runtime/ProvidedValue;
/*     */     //   2526: aastore
/*     */     //   2527: aload #49
/*     */     //   2529: iconst_1
/*     */     //   2530: invokestatic getLocalContentColor : ()Landroidx/compose/runtime/ProvidableCompositionLocal;
/*     */     //   2533: lload #79
/*     */     //   2535: invokestatic box-impl : (J)Landroidx/compose/ui/graphics/Color;
/*     */     //   2538: invokevirtual provides : (Ljava/lang/Object;)Landroidx/compose/runtime/ProvidedValue;
/*     */     //   2541: aastore
/*     */     //   2542: aload #49
/*     */     //   2544: ldc_w -1987373942
/*     */     //   2547: iconst_1
/*     */     //   2548: new org/jetbrains/jewel/ui/component/RadioButtonKt$RadioButtonImpl$4$3
/*     */     //   2551: dup
/*     */     //   2552: aload #9
/*     */     //   2554: aload #45
/*     */     //   2556: invokespecial <init> : (Lkotlin/jvm/functions/Function3;Landroidx/compose/foundation/layout/RowScope;)V
/*     */     //   2559: aload #44
/*     */     //   2561: bipush #54
/*     */     //   2563: invokestatic rememberComposableLambda : (IZLjava/lang/Object;Landroidx/compose/runtime/Composer;I)Landroidx/compose/runtime/internal/ComposableLambda;
/*     */     //   2566: checkcast kotlin/jvm/functions/Function2
/*     */     //   2569: aload #44
/*     */     //   2571: bipush #48
/*     */     //   2573: getstatic androidx/compose/runtime/ProvidedValue.$stable : I
/*     */     //   2576: ior
/*     */     //   2577: invokestatic CompositionLocalProvider : ([Landroidx/compose/runtime/ProvidedValue;Lkotlin/jvm/functions/Function2;Landroidx/compose/runtime/Composer;I)V
/*     */     //   2580: nop
/*     */     //   2581: aload #41
/*     */     //   2583: invokestatic sourceInformationMarkerEnd : (Landroidx/compose/runtime/Composer;)V
/*     */     //   2586: aload #10
/*     */     //   2588: invokeinterface endNode : ()V
/*     */     //   2593: aload #10
/*     */     //   2595: invokestatic sourceInformationMarkerEnd : (Landroidx/compose/runtime/Composer;)V
/*     */     //   2598: nop
/*     */     //   2599: aload #10
/*     */     //   2601: invokestatic sourceInformationMarkerEnd : (Landroidx/compose/runtime/Composer;)V
/*     */     //   2604: nop
/*     */     //   2605: aload #10
/*     */     //   2607: invokestatic sourceInformationMarkerEnd : (Landroidx/compose/runtime/Composer;)V
/*     */     //   2610: nop
/*     */     //   2611: aload #10
/*     */     //   2613: invokeinterface endReplaceGroup : ()V
/*     */     //   2618: invokestatic isTraceInProgress : ()Z
/*     */     //   2621: ifeq -> 2637
/*     */     //   2624: invokestatic traceEventEnd : ()V
/*     */     //   2627: goto -> 2637
/*     */     //   2630: aload #10
/*     */     //   2632: invokeinterface skipToGroupEnd : ()V
/*     */     //   2637: aload #10
/*     */     //   2639: invokeinterface endRestartGroup : ()Landroidx/compose/runtime/ScopeUpdateScope;
/*     */     //   2644: dup
/*     */     //   2645: ifnull -> 2679
/*     */     //   2648: iload_0
/*     */     //   2649: aload_1
/*     */     //   2650: aload_2
/*     */     //   2651: iload_3
/*     */     //   2652: aload #4
/*     */     //   2654: aload #5
/*     */     //   2656: aload #6
/*     */     //   2658: aload #7
/*     */     //   2660: aload #8
/*     */     //   2662: aload #9
/*     */     //   2664: iload #11
/*     */     //   2666: <illegal opcode> invoke : (ZLkotlin/jvm/functions/Function0;Landroidx/compose/ui/Modifier;ZLorg/jetbrains/jewel/ui/Outline;Landroidx/compose/foundation/interaction/MutableInteractionSource;Lorg/jetbrains/jewel/ui/component/styling/RadioButtonStyle;Landroidx/compose/ui/text/TextStyle;Landroidx/compose/ui/Alignment$Vertical;Lkotlin/jvm/functions/Function3;I)Lkotlin/jvm/functions/Function2;
/*     */     //   2671: invokeinterface updateScope : (Lkotlin/jvm/functions/Function2;)V
/*     */     //   2676: goto -> 2680
/*     */     //   2679: pop
/*     */     //   2680: return
/*     */     // Line number table:
/*     */     //   Java source line number -> byte code offset
/*     */     //   #142	-> 0
/*     */     //   #143	-> 394
/*     */     //   #307	-> 398
/*     */     //   #308	-> 410
/*     */     //   #309	-> 421
/*     */     //   #143	-> 424
/*     */     //   #309	-> 448
/*     */     //   #310	-> 450
/*     */     //   #311	-> 459
/*     */     //   #312	-> 464
/*     */     //   #308	-> 466
/*     */     //   #307	-> 467
/*     */     //   #307	-> 468
/*     */     //   #143	-> 469
/*     */     //   #145	-> 533
/*     */     //   #313	-> 537
/*     */     //   #314	-> 549
/*     */     //   #315	-> 565
/*     */     //   #145	-> 568
/*     */     //   #315	-> 593
/*     */     //   #316	-> 595
/*     */     //   #317	-> 604
/*     */     //   #318	-> 609
/*     */     //   #314	-> 611
/*     */     //   #313	-> 612
/*     */     //   #313	-> 613
/*     */     //   #147	-> 622
/*     */     //   #148	-> 634
/*     */     //   #319	-> 685
/*     */     //   #320	-> 697
/*     */     //   #321	-> 713
/*     */     //   #148	-> 720
/*     */     //   #321	-> 745
/*     */     //   #322	-> 747
/*     */     //   #323	-> 756
/*     */     //   #324	-> 761
/*     */     //   #320	-> 763
/*     */     //   #319	-> 764
/*     */     //   #319	-> 765
/*     */     //   #148	-> 766
/*     */     //   #170	-> 793
/*     */     //   #166	-> 801
/*     */     //   #167	-> 802
/*     */     //   #171	-> 803
/*     */     //   #172	-> 805
/*     */     //   #169	-> 806
/*     */     //   #170	-> 807
/*     */     //   #168	-> 812
/*     */     //   #166	-> 813
/*     */     //   #165	-> 816
/*     */     //   #175	-> 818
/*     */     //   #176	-> 825
/*     */     //   #178	-> 832
/*     */     //   #180	-> 865
/*     */     //   #181	-> 873
/*     */     //   #182	-> 875
/*     */     //   #183	-> 881
/*     */     //   #179	-> 902
/*     */     //   #177	-> 905
/*     */     //   #186	-> 907
/*     */     //   #188	-> 925
/*     */     //   #187	-> 973
/*     */     //   #190	-> 975
/*     */     //   #192	-> 991
/*     */     //   #193	-> 1006
/*     */     //   #325	-> 1029
/*     */     //   #326	-> 1032
/*     */     //   #329	-> 1035
/*     */     //   #330	-> 1053
/*     */     //   #331	-> 1065
/*     */     //   #332	-> 1071
/*     */     //   #333	-> 1078
/*     */     //   #334	-> 1087
/*     */     //   #336	-> 1094
/*     */     //   #335	-> 1116
/*     */     //   #337	-> 1128
/*     */     //   #338	-> 1131
/*     */     //   #339	-> 1149
/*     */     //   #340	-> 1154
/*     */     //   #341	-> 1166
/*     */     //   #343	-> 1178
/*     */     //   #345	-> 1183
/*     */     //   #346	-> 1193
/*     */     //   #347	-> 1206
/*     */     //   #349	-> 1219
/*     */     //   #350	-> 1230
/*     */     //   #351	-> 1237
/*     */     //   #352	-> 1265
/*     */     //   #353	-> 1277
/*     */     //   #355	-> 1291
/*     */     //   #350	-> 1292
/*     */     //   #355	-> 1293
/*     */     //   #356	-> 1294
/*     */     //   #357	-> 1307
/*     */     //   #345	-> 1308
/*     */     //   #358	-> 1309
/*     */     //   #359	-> 1334
/*     */     //   #194	-> 1365
/*     */     //   #195	-> 1378
/*     */     //   #196	-> 1386
/*     */     //   #359	-> 1387
/*     */     //   #358	-> 1392
/*     */     //   #360	-> 1394
/*     */     //   #337	-> 1401
/*     */     //   #361	-> 1404
/*     */     //   #331	-> 1407
/*     */     //   #362	-> 1410
/*     */     //   #325	-> 1413
/*     */     //   #363	-> 1416
/*     */     //   #192	-> 1417
/*     */     //   #197	-> 1427
/*     */     //   #200	-> 1437
/*     */     //   #198	-> 1464
/*     */     //   #364	-> 1476
/*     */     //   #365	-> 1479
/*     */     //   #366	-> 1514
/*     */     //   #367	-> 1526
/*     */     //   #368	-> 1532
/*     */     //   #369	-> 1539
/*     */     //   #370	-> 1548
/*     */     //   #372	-> 1555
/*     */     //   #371	-> 1577
/*     */     //   #373	-> 1589
/*     */     //   #374	-> 1592
/*     */     //   #375	-> 1610
/*     */     //   #376	-> 1615
/*     */     //   #377	-> 1627
/*     */     //   #379	-> 1639
/*     */     //   #381	-> 1644
/*     */     //   #382	-> 1654
/*     */     //   #383	-> 1667
/*     */     //   #385	-> 1680
/*     */     //   #386	-> 1691
/*     */     //   #387	-> 1698
/*     */     //   #388	-> 1726
/*     */     //   #389	-> 1738
/*     */     //   #391	-> 1752
/*     */     //   #386	-> 1753
/*     */     //   #391	-> 1754
/*     */     //   #392	-> 1755
/*     */     //   #393	-> 1768
/*     */     //   #381	-> 1769
/*     */     //   #394	-> 1770
/*     */     //   #395	-> 1795
/*     */     //   #203	-> 1826
/*     */     //   #396	-> 1849
/*     */     //   #397	-> 1852
/*     */     //   #400	-> 1855
/*     */     //   #401	-> 1873
/*     */     //   #402	-> 1885
/*     */     //   #403	-> 1891
/*     */     //   #404	-> 1898
/*     */     //   #405	-> 1907
/*     */     //   #407	-> 1914
/*     */     //   #406	-> 1936
/*     */     //   #408	-> 1948
/*     */     //   #409	-> 1951
/*     */     //   #410	-> 1969
/*     */     //   #411	-> 1974
/*     */     //   #412	-> 1986
/*     */     //   #414	-> 1998
/*     */     //   #416	-> 2003
/*     */     //   #417	-> 2013
/*     */     //   #418	-> 2026
/*     */     //   #420	-> 2039
/*     */     //   #421	-> 2050
/*     */     //   #422	-> 2057
/*     */     //   #423	-> 2085
/*     */     //   #424	-> 2097
/*     */     //   #426	-> 2111
/*     */     //   #421	-> 2112
/*     */     //   #426	-> 2113
/*     */     //   #427	-> 2114
/*     */     //   #428	-> 2127
/*     */     //   #416	-> 2128
/*     */     //   #429	-> 2129
/*     */     //   #430	-> 2154
/*     */     //   #204	-> 2185
/*     */     //   #205	-> 2198
/*     */     //   #206	-> 2206
/*     */     //   #430	-> 2207
/*     */     //   #429	-> 2212
/*     */     //   #431	-> 2214
/*     */     //   #408	-> 2221
/*     */     //   #432	-> 2224
/*     */     //   #402	-> 2227
/*     */     //   #433	-> 2230
/*     */     //   #396	-> 2233
/*     */     //   #434	-> 2236
/*     */     //   #208	-> 2237
/*     */     //   #210	-> 2262
/*     */     //   #435	-> 2272
/*     */     //   #436	-> 2279
/*     */     //   #435	-> 2293
/*     */     //   #210	-> 2304
/*     */     //   #435	-> 2309
/*     */     //   #210	-> 2312
/*     */     //   #435	-> 2316
/*     */     //   #436	-> 2323
/*     */     //   #435	-> 2337
/*     */     //   #210	-> 2348
/*     */     //   #437	-> 2370
/*     */     //   #210	-> 2391
/*     */     //   #435	-> 2397
/*     */     //   #210	-> 2398
/*     */     //   #209	-> 2409
/*     */     //   #213	-> 2411
/*     */     //   #438	-> 2435
/*     */     //   #439	-> 2442
/*     */     //   #438	-> 2456
/*     */     //   #213	-> 2475
/*     */     //   #438	-> 2492
/*     */     //   #213	-> 2493
/*     */     //   #214	-> 2530
/*     */     //   #213	-> 2542
/*     */     //   #215	-> 2544
/*     */     //   #212	-> 2577
/*     */     //   #218	-> 2580
/*     */     //   #395	-> 2581
/*     */     //   #394	-> 2586
/*     */     //   #440	-> 2588
/*     */     //   #373	-> 2595
/*     */     //   #441	-> 2598
/*     */     //   #367	-> 2601
/*     */     //   #442	-> 2604
/*     */     //   #364	-> 2607
/*     */     //   #443	-> 2610
/*     */     //   #197	-> 2611
/*     */     //   #220	-> 2630
/*     */     // Local variable table:
/*     */     //   start	length	slot	name	descriptor
/*     */     //   424	24	20	$i$a$-cache-RadioButtonKt$RadioButtonImpl$radioButtonState$2	I
/*     */     //   450	11	21	value$iv	Ljava/lang/Object;
/*     */     //   410	57	19	$i$a$-let-ComposerKt$cache$1$iv	I
/*     */     //   407	60	18	it$iv	Ljava/lang/Object;
/*     */     //   398	71	17	$i$f$cache	I
/*     */     //   395	74	15	$this$cache$iv	Landroidx/compose/runtime/Composer;
/*     */     //   395	74	16	invalid$iv	Z
/*     */     //   568	22	19	$i$a$-cache-RadioButtonKt$RadioButtonImpl$1	I
/*     */     //   595	11	20	value$iv	Ljava/lang/Object;
/*     */     //   549	63	18	$i$a$-let-ComposerKt$cache$1$iv	I
/*     */     //   546	66	17	it$iv	Ljava/lang/Object;
/*     */     //   537	77	16	$i$f$cache	I
/*     */     //   534	80	14	$this$cache$iv	Landroidx/compose/runtime/Composer;
/*     */     //   534	80	15	invalid$iv	Z
/*     */     //   720	17	21	$i$a$-cache-RadioButtonKt$RadioButtonImpl$2	I
/*     */     //   747	11	22	value$iv	Ljava/lang/Object;
/*     */     //   697	67	20	$i$a$-let-ComposerKt$cache$1$iv	I
/*     */     //   694	70	19	it$iv	Ljava/lang/Object;
/*     */     //   685	81	18	$i$f$cache	I
/*     */     //   682	84	16	$this$cache$iv	Landroidx/compose/runtime/Composer;
/*     */     //   682	84	17	invalid$iv	Z
/*     */     //   1365	22	47	$i$a$-Box-RadioButtonKt$RadioButtonImpl$3	I
/*     */     //   1362	25	46	$this$RadioButtonImpl_u24lambda_u2412	Landroidx/compose/foundation/layout/BoxScope;
/*     */     //   1362	25	45	$composer	Landroidx/compose/runtime/Composer;
/*     */     //   1362	25	44	$changed	I
/*     */     //   1326	66	43	$i$a$-Layout-BoxKt$Box$1$iv	I
/*     */     //   1323	69	42	$composer$iv	Landroidx/compose/runtime/Composer;
/*     */     //   1323	69	41	$changed$iv	I
/*     */     //   1237	55	40	$i$a$-with-Updater$set$1$iv$iv$iv	I
/*     */     //   1234	58	39	$this$set_impl_u24lambda_u240$iv$iv$iv	Landroidx/compose/runtime/Composer;
/*     */     //   1230	64	38	$i$f$set-impl	I
/*     */     //   1227	67	37	block$iv$iv$iv	Lkotlin/jvm/functions/Function2;
/*     */     //   1193	115	36	$i$a$-ReusableComposeNode-LayoutKt$Layout$1$iv$iv	I
/*     */     //   1190	118	35	$this$Layout_u24lambda_u240$iv$iv	Landroidx/compose/runtime/Composer;
/*     */     //   1120	285	34	$i$f$ReusableComposeNode	I
/*     */     //   1117	288	32	factory$iv$iv$iv	Lkotlin/jvm/functions/Function0;
/*     */     //   1117	288	33	$changed$iv$iv$iv	I
/*     */     //   1057	354	28	$i$f$Layout	I
/*     */     //   1076	335	29	compositeKeyHash$iv$iv	I
/*     */     //   1085	326	30	localMap$iv$iv	Landroidx/compose/runtime/CompositionLocalMap;
/*     */     //   1094	317	31	materialized$iv$iv	Landroidx/compose/ui/Modifier;
/*     */     //   1054	357	27	$changed$iv$iv	I
/*     */     //   1021	396	25	$i$f$Box	I
/*     */     //   1044	373	26	measurePolicy$iv	Landroidx/compose/ui/layout/MeasurePolicy;
/*     */     //   1018	399	22	contentAlignment$iv	Landroidx/compose/ui/Alignment;
/*     */     //   1035	382	23	propagateMinConstraints$iv	Z
/*     */     //   1018	399	24	$changed$iv	I
/*     */     //   2185	22	72	$i$a$-Box-RadioButtonKt$RadioButtonImpl$4$1	I
/*     */     //   2182	25	71	$this$RadioButtonImpl_u24lambda_u2418_u24lambda_u2413	Landroidx/compose/foundation/layout/BoxScope;
/*     */     //   2182	25	70	$composer	Landroidx/compose/runtime/Composer;
/*     */     //   2182	25	69	$changed	I
/*     */     //   2146	66	68	$i$a$-Layout-BoxKt$Box$1$iv	I
/*     */     //   2143	69	67	$composer$iv	Landroidx/compose/runtime/Composer;
/*     */     //   2143	69	66	$changed$iv	I
/*     */     //   2057	55	65	$i$a$-with-Updater$set$1$iv$iv$iv	I
/*     */     //   2054	58	64	$this$set_impl_u24lambda_u240$iv$iv$iv	Landroidx/compose/runtime/Composer;
/*     */     //   2050	64	63	$i$f$set-impl	I
/*     */     //   2047	67	62	block$iv$iv$iv	Lkotlin/jvm/functions/Function2;
/*     */     //   2013	115	61	$i$a$-ReusableComposeNode-LayoutKt$Layout$1$iv$iv	I
/*     */     //   2010	118	60	$this$Layout_u24lambda_u240$iv$iv	Landroidx/compose/runtime/Composer;
/*     */     //   1940	285	59	$i$f$ReusableComposeNode	I
/*     */     //   1937	288	57	factory$iv$iv$iv	Lkotlin/jvm/functions/Function0;
/*     */     //   1937	288	58	$changed$iv$iv$iv	I
/*     */     //   1877	354	53	$i$f$Layout	I
/*     */     //   1896	335	54	compositeKeyHash$iv$iv	I
/*     */     //   1905	326	55	localMap$iv$iv	Landroidx/compose/runtime/CompositionLocalMap;
/*     */     //   1914	317	56	materialized$iv$iv	Landroidx/compose/ui/Modifier;
/*     */     //   1874	357	52	$changed$iv$iv	I
/*     */     //   1841	396	49	$i$f$Box	I
/*     */     //   1864	373	51	measurePolicy$iv	Landroidx/compose/ui/layout/MeasurePolicy;
/*     */     //   1838	399	47	contentAlignment$iv	Landroidx/compose/ui/Alignment;
/*     */     //   1855	382	50	propagateMinConstraints$iv	Z
/*     */     //   1838	399	48	$changed$iv	I
/*     */     //   2304	5	58	$i$a$-takeOrElse-DxMtmZc-RadioButtonKt$RadioButtonImpl$4$resolvedContentColor$1	I
/*     */     //   2279	14	57	$i$f$isSpecified-8_81llA	I
/*     */     //   2276	17	75	$this$isSpecified$iv$iv	J
/*     */     //   2272	38	54	$i$f$takeOrElse-DxMtmZc	I
/*     */     //   2269	41	73	$this$takeOrElse_u2dDxMtmZc$iv	J
/*     */     //   2362	29	61	$i$f$getCurrent	I
/*     */     //   2359	32	59	this_$iv	Landroidx/compose/runtime/CompositionLocal;
/*     */     //   2359	32	60	$changed$iv	I
/*     */     //   2348	49	58	$i$a$-takeOrElse-DxMtmZc-RadioButtonKt$RadioButtonImpl$4$resolvedContentColor$2	I
/*     */     //   2323	14	57	$i$f$isSpecified-8_81llA	I
/*     */     //   2320	17	75	$this$isSpecified$iv$iv	J
/*     */     //   2316	82	54	$i$f$takeOrElse-DxMtmZc	I
/*     */     //   2313	85	73	$this$takeOrElse_u2dDxMtmZc$iv	J
/*     */     //   2475	5	57	$i$a$-takeOrElse-DxMtmZc-RadioButtonKt$RadioButtonImpl$4$2	I
/*     */     //   2442	14	56	$i$f$isSpecified-8_81llA	I
/*     */     //   2439	17	83	$this$isSpecified$iv$iv	J
/*     */     //   2435	58	53	$i$f$takeOrElse-DxMtmZc	I
/*     */     //   2432	61	81	$this$takeOrElse_u2dDxMtmZc$iv	J
/*     */     //   1826	755	46	$i$a$-Row-RadioButtonKt$RadioButtonImpl$4	I
/*     */     //   2252	329	47	contentColor$delegate	Landroidx/compose/runtime/State;
/*     */     //   2411	170	79	resolvedContentColor	J
/*     */     //   1823	758	45	$this$RadioButtonImpl_u24lambda_u2418	Landroidx/compose/foundation/layout/RowScope;
/*     */     //   1823	758	44	$composer	Landroidx/compose/runtime/Composer;
/*     */     //   1823	758	43	$changed	I
/*     */     //   1787	799	42	$i$a$-Layout-RowKt$Row$1$iv	I
/*     */     //   1784	802	41	$composer$iv	Landroidx/compose/runtime/Composer;
/*     */     //   1784	802	40	$changed$iv	I
/*     */     //   1698	55	39	$i$a$-with-Updater$set$1$iv$iv$iv	I
/*     */     //   1695	58	38	$this$set_impl_u24lambda_u240$iv$iv$iv	Landroidx/compose/runtime/Composer;
/*     */     //   1691	64	37	$i$f$set-impl	I
/*     */     //   1688	67	36	block$iv$iv$iv	Lkotlin/jvm/functions/Function2;
/*     */     //   1654	115	35	$i$a$-ReusableComposeNode-LayoutKt$Layout$1$iv$iv	I
/*     */     //   1651	118	34	$this$Layout_u24lambda_u240$iv$iv	Landroidx/compose/runtime/Composer;
/*     */     //   1581	1018	33	$i$f$ReusableComposeNode	I
/*     */     //   1578	1021	31	factory$iv$iv$iv	Lkotlin/jvm/functions/Function0;
/*     */     //   1578	1021	32	$changed$iv$iv$iv	I
/*     */     //   1518	1087	27	$i$f$Layout	I
/*     */     //   1537	1068	28	compositeKeyHash$iv$iv	I
/*     */     //   1546	1059	29	localMap$iv$iv	Landroidx/compose/runtime/CompositionLocalMap;
/*     */     //   1555	1050	30	materialized$iv$iv	Landroidx/compose/ui/Modifier;
/*     */     //   1515	1090	26	$changed$iv$iv	I
/*     */     //   1468	1143	24	$i$f$Row	I
/*     */     //   1505	1106	25	measurePolicy$iv	Landroidx/compose/ui/layout/MeasurePolicy;
/*     */     //   1465	1146	22	horizontalArrangement$iv	Landroidx/compose/foundation/layout/Arrangement$Horizontal;
/*     */     //   1465	1146	23	$changed$iv	I
/*     */     //   485	2142	13	radioButtonState$delegate	Landroidx/compose/runtime/MutableState;
/*     */     //   634	1993	14	swingCompatMode	Z
/*     */     //   818	1809	15	wrapperModifier	Landroidx/compose/ui/Modifier;
/*     */     //   825	1802	16	colors	Lorg/jetbrains/jewel/ui/component/styling/RadioButtonColors;
/*     */     //   832	1795	17	metrics	Lorg/jetbrains/jewel/ui/component/styling/RadioButtonMetrics;
/*     */     //   907	1720	18	outlineModifier	Landroidx/compose/ui/Modifier;
/*     */     //   925	1702	19	radioButtonPainterProvider	Lorg/jetbrains/jewel/ui/painter/PainterProvider;
/*     */     //   975	1652	20	radioButtonPainter$delegate	Landroidx/compose/runtime/State;
/*     */     //   991	1636	21	radioButtonBoxModifier	Landroidx/compose/ui/Modifier;
/*     */     //   16	2665	12	$dirty	I
/*     */     //   0	2681	0	selected	Z
/*     */     //   0	2681	1	onClick	Lkotlin/jvm/functions/Function0;
/*     */     //   0	2681	2	modifier	Landroidx/compose/ui/Modifier;
/*     */     //   0	2681	3	enabled	Z
/*     */     //   0	2681	4	outline	Lorg/jetbrains/jewel/ui/Outline;
/*     */     //   0	2681	5	interactionSource	Landroidx/compose/foundation/interaction/MutableInteractionSource;
/*     */     //   0	2681	6	style	Lorg/jetbrains/jewel/ui/component/styling/RadioButtonStyle;
/*     */     //   0	2681	7	textStyle	Landroidx/compose/ui/text/TextStyle;
/*     */     //   0	2681	8	verticalAlignment	Landroidx/compose/ui/Alignment$Vertical;
/*     */     //   0	2681	9	content	Lkotlin/jvm/functions/Function3;
/*     */     //   0	2681	10	$composer	Landroidx/compose/runtime/Composer;
/*     */     //   0	2681	11	$changed	I
/*     */   }
/*     */ 
/*     */ 
/*     */ 
/*     */ 
/*     */ 
/*     */   
/*     */   private static final long RadioButtonImpl$lambda$7(MutableState $radioButtonState$delegate)
/*     */   {
/* 143 */     State state = (State)$radioButtonState$delegate; Object object = null; KProperty property$iv = null; int $i$f$getValue = 0; return (
/*     */ 
/*     */ 
/*     */ 
/*     */ 
/*     */ 
/*     */ 
/*     */ 
/*     */ 
/*     */ 
/*     */ 
/*     */ 
/*     */ 
/*     */ 
/*     */ 
/*     */ 
/*     */ 
/*     */ 
/*     */ 
/*     */ 
/*     */ 
/*     */ 
/*     */ 
/*     */ 
/*     */ 
/*     */ 
/*     */ 
/*     */ 
/*     */ 
/*     */ 
/*     */ 
/*     */ 
/*     */ 
/*     */ 
/*     */ 
/*     */ 
/*     */ 
/*     */ 
/*     */ 
/*     */ 
/*     */ 
/*     */ 
/*     */ 
/*     */ 
/*     */ 
/*     */ 
/*     */ 
/*     */ 
/*     */ 
/*     */ 
/*     */ 
/*     */ 
/*     */ 
/*     */ 
/*     */ 
/*     */ 
/*     */ 
/*     */ 
/*     */ 
/*     */ 
/*     */ 
/*     */ 
/*     */ 
/*     */ 
/*     */ 
/*     */ 
/*     */ 
/*     */ 
/*     */ 
/*     */ 
/*     */ 
/*     */ 
/*     */ 
/*     */ 
/*     */ 
/*     */ 
/*     */ 
/*     */ 
/*     */ 
/*     */ 
/*     */ 
/*     */ 
/*     */ 
/*     */ 
/*     */ 
/*     */ 
/*     */ 
/*     */ 
/*     */ 
/*     */ 
/*     */ 
/*     */ 
/*     */ 
/*     */ 
/*     */ 
/*     */ 
/*     */ 
/*     */ 
/*     */ 
/*     */ 
/*     */ 
/*     */ 
/*     */ 
/*     */ 
/*     */ 
/*     */ 
/*     */ 
/*     */ 
/*     */ 
/*     */ 
/*     */ 
/*     */ 
/*     */ 
/*     */ 
/*     */ 
/*     */ 
/*     */ 
/*     */ 
/*     */ 
/*     */ 
/*     */ 
/*     */ 
/*     */ 
/*     */ 
/*     */ 
/*     */ 
/*     */ 
/*     */ 
/*     */ 
/*     */ 
/*     */ 
/*     */ 
/*     */ 
/*     */ 
/*     */ 
/*     */ 
/*     */ 
/*     */ 
/*     */ 
/*     */ 
/*     */ 
/*     */ 
/*     */ 
/*     */ 
/*     */ 
/*     */ 
/*     */ 
/*     */ 
/*     */ 
/*     */ 
/*     */ 
/*     */ 
/*     */ 
/*     */ 
/*     */ 
/*     */ 
/*     */ 
/*     */ 
/*     */ 
/*     */ 
/*     */ 
/*     */ 
/*     */ 
/*     */ 
/*     */ 
/*     */ 
/*     */ 
/*     */ 
/*     */ 
/*     */ 
/*     */ 
/*     */ 
/*     */ 
/*     */ 
/*     */ 
/*     */ 
/*     */ 
/*     */ 
/*     */ 
/*     */ 
/*     */ 
/*     */ 
/*     */ 
/*     */ 
/*     */ 
/*     */ 
/*     */ 
/*     */ 
/*     */ 
/*     */ 
/*     */ 
/*     */ 
/*     */ 
/*     */ 
/*     */ 
/*     */ 
/*     */ 
/*     */ 
/*     */ 
/*     */ 
/*     */ 
/*     */ 
/*     */ 
/*     */ 
/*     */ 
/*     */ 
/*     */ 
/*     */ 
/*     */ 
/*     */ 
/*     */ 
/*     */ 
/*     */ 
/*     */ 
/*     */ 
/*     */ 
/*     */ 
/*     */ 
/*     */ 
/*     */ 
/*     */ 
/*     */ 
/*     */ 
/*     */ 
/*     */ 
/*     */ 
/*     */ 
/*     */ 
/*     */ 
/*     */ 
/*     */ 
/*     */ 
/*     */ 
/*     */ 
/*     */ 
/*     */ 
/*     */ 
/*     */ 
/*     */ 
/*     */ 
/*     */ 
/*     */ 
/*     */ 
/*     */ 
/*     */ 
/*     */ 
/*     */ 
/*     */ 
/*     */ 
/*     */ 
/*     */ 
/*     */ 
/*     */ 
/*     */ 
/*     */ 
/*     */ 
/*     */ 
/*     */ 
/*     */ 
/*     */ 
/*     */ 
/*     */ 
/*     */ 
/*     */ 
/*     */ 
/*     */ 
/*     */ 
/*     */ 
/*     */ 
/*     */ 
/*     */ 
/*     */ 
/*     */ 
/*     */ 
/*     */ 
/*     */ 
/*     */ 
/*     */ 
/*     */ 
/*     */ 
/*     */ 
/*     */ 
/*     */ 
/*     */ 
/*     */ 
/*     */ 
/*     */ 
/*     */ 
/*     */ 
/*     */ 
/*     */ 
/*     */ 
/*     */ 
/*     */ 
/*     */ 
/*     */ 
/*     */ 
/*     */ 
/*     */ 
/*     */ 
/*     */       
/* 444 */       (RadioButtonState)state.getValue()).unbox-impl(); } private static final void RadioButtonImpl$lambda$8(MutableState $radioButtonState$delegate, long <set-?>) { MutableState mutableState = $radioButtonState$delegate; Object object1 = null, object2 = null; Object value$iv = RadioButtonState.box-impl(<set-?>); int $i$f$setValue = 0;
/* 445 */     mutableState.setValue(value$iv); } private static final Painter RadioButtonImpl$lambda$11(State $radioButtonPainter$delegate) { State state = $radioButtonPainter$delegate; Object object = null; KProperty property$iv = null;
/*     */     int $i$f$getValue = 0;
/* 447 */     return (Painter)state.getValue(); } @DebugMetadata(f = "RadioButton.kt", l = {149}, i = {}, s = {}, n = {}, m = "invokeSuspend", c = "org.jetbrains.jewel.ui.component.RadioButtonKt$RadioButtonImpl$2$1") @Metadata(mv = {2, 0, 0}, k = 3, xi = 48, d1 = {"\000\n\n\000\n\002\020\002\n\002\030\002\020\000\032\0020\001*\0020\002H\n"}, d2 = {"<anonymous>", "", "Lkotlinx/coroutines/CoroutineScope;"}) static final class RadioButtonKt$RadioButtonImpl$2$1 extends SuspendLambda implements Function2<CoroutineScope, Continuation<? super Unit>, Object> {
/* 448 */     int label; RadioButtonKt$RadioButtonImpl$2$1(MutableInteractionSource $interactionSource, boolean $swingCompatMode, MutableState<RadioButtonState> $radioButtonState$delegate, Continuation $completion) { super(2, $completion); } public final Object invokeSuspend(Object $result) { Object object = IntrinsicsKt.getCOROUTINE_SUSPENDED(); switch (this.label) { case 0: ResultKt.throwOnFailure(SYNTHETIC_LOCAL_VARIABLE_1); this.label = 1; if (this.$interactionSource.getInteractions().collect(new FlowCollector(this.$swingCompatMode, this.$radioButtonState$delegate) { public final Object emit(Interaction interaction, Continuation $completion) { Interaction interaction1 = interaction; if (interaction1 instanceof androidx.compose.foundation.interaction.PressInteraction.Press) { RadioButtonKt.RadioButtonImpl$lambda$8(this.$radioButtonState$delegate, RadioButtonState.copy-fp8g3n8$default(RadioButtonKt.RadioButtonImpl$lambda$7(this.$radioButtonState$delegate), false, false, false, !this.$swingCompatMode, false, false, 55, null)); } else if (interaction1 instanceof androidx.compose.foundation.interaction.PressInteraction.Cancel || interaction1 instanceof androidx.compose.foundation.interaction.PressInteraction.Release) { RadioButtonKt.RadioButtonImpl$lambda$8(this.$radioButtonState$delegate, RadioButtonState.copy-fp8g3n8$default(RadioButtonKt.RadioButtonImpl$lambda$7(this.$radioButtonState$delegate), false, false, false, false, false, false, 55, null)); } else if (interaction1 instanceof androidx.compose.foundation.interaction.HoverInteraction.Enter) { RadioButtonKt.RadioButtonImpl$lambda$8(this.$radioButtonState$delegate, RadioButtonState.copy-fp8g3n8$default(RadioButtonKt.RadioButtonImpl$lambda$7(this.$radioButtonState$delegate), false, false, false, false, !this.$swingCompatMode, false, 47, null)); } else if (interaction1 instanceof androidx.compose.foundation.interaction.HoverInteraction.Exit) { RadioButtonKt.RadioButtonImpl$lambda$8(this.$radioButtonState$delegate, RadioButtonState.copy-fp8g3n8$default(RadioButtonKt.RadioButtonImpl$lambda$7(this.$radioButtonState$delegate), false, false, false, false, false, false, 47, null)); } else if (interaction1 instanceof androidx.compose.foundation.interaction.FocusInteraction.Focus) { RadioButtonKt.RadioButtonImpl$lambda$8(this.$radioButtonState$delegate, RadioButtonState.copy-fp8g3n8$default(RadioButtonKt.RadioButtonImpl$lambda$7(this.$radioButtonState$delegate), false, false, true, false, false, false, 59, null)); } else if (interaction1 instanceof androidx.compose.foundation.interaction.FocusInteraction.Unfocus) { RadioButtonKt.RadioButtonImpl$lambda$8(this.$radioButtonState$delegate, RadioButtonState.copy-fp8g3n8$default(RadioButtonKt.RadioButtonImpl$lambda$7(this.$radioButtonState$delegate), false, false, false, false, false, false, 59, null)); }  return Unit.INSTANCE; } }(Continuation)this) == object) return object;  this.$interactionSource.getInteractions().collect(new FlowCollector(this.$swingCompatMode, this.$radioButtonState$delegate) { public final Object emit(Interaction interaction, Continuation $completion) { Interaction interaction1 = interaction; if (interaction1 instanceof androidx.compose.foundation.interaction.PressInteraction.Press) { RadioButtonKt.RadioButtonImpl$lambda$8(this.$radioButtonState$delegate, RadioButtonState.copy-fp8g3n8$default(RadioButtonKt.RadioButtonImpl$lambda$7(this.$radioButtonState$delegate), false, false, false, !this.$swingCompatMode, false, false, 55, null)); } else if (interaction1 instanceof androidx.compose.foundation.interaction.PressInteraction.Cancel || interaction1 instanceof androidx.compose.foundation.interaction.PressInteraction.Release) { RadioButtonKt.RadioButtonImpl$lambda$8(this.$radioButtonState$delegate, RadioButtonState.copy-fp8g3n8$default(RadioButtonKt.RadioButtonImpl$lambda$7(this.$radioButtonState$delegate), false, false, false, false, false, false, 55, null)); } else if (interaction1 instanceof androidx.compose.foundation.interaction.HoverInteraction.Enter) { RadioButtonKt.RadioButtonImpl$lambda$8(this.$radioButtonState$delegate, RadioButtonState.copy-fp8g3n8$default(RadioButtonKt.RadioButtonImpl$lambda$7(this.$radioButtonState$delegate), false, false, false, false, !this.$swingCompatMode, false, 47, null)); } else if (interaction1 instanceof androidx.compose.foundation.interaction.HoverInteraction.Exit) { RadioButtonKt.RadioButtonImpl$lambda$8(this.$radioButtonState$delegate, RadioButtonState.copy-fp8g3n8$default(RadioButtonKt.RadioButtonImpl$lambda$7(this.$radioButtonState$delegate), false, false, false, false, false, false, 47, null)); } else if (interaction1 instanceof androidx.compose.foundation.interaction.FocusInteraction.Focus) { RadioButtonKt.RadioButtonImpl$lambda$8(this.$radioButtonState$delegate, RadioButtonState.copy-fp8g3n8$default(RadioButtonKt.RadioButtonImpl$lambda$7(this.$radioButtonState$delegate), false, false, true, false, false, false, 59, null)); } else if (interaction1 instanceof androidx.compose.foundation.interaction.FocusInteraction.Unfocus) { RadioButtonKt.RadioButtonImpl$lambda$8(this.$radioButtonState$delegate, RadioButtonState.copy-fp8g3n8$default(RadioButtonKt.RadioButtonImpl$lambda$7(this.$radioButtonState$delegate), false, false, false, false, false, false, 59, null)); }  return Unit.INSTANCE; } }(Continuation)this); return Unit.INSTANCE;case 1: ResultKt.throwOnFailure(SYNTHETIC_LOCAL_VARIABLE_1); return Unit.INSTANCE; }  throw new IllegalStateException("call to 'resume' before 'invoke' with coroutine"); } public final Continuation<Unit> create(Object value, Continuation<? super RadioButtonKt$RadioButtonImpl$2$1> $completion) { return (Continuation<Unit>)new RadioButtonKt$RadioButtonImpl$2$1(this.$interactionSource, this.$swingCompatMode, this.$radioButtonState$delegate, $completion); } public final Object invoke(CoroutineScope p1, Continuation<?> p2) { return ((RadioButtonKt$RadioButtonImpl$2$1)create(p1, p2)).invokeSuspend(Unit.INSTANCE); } } private static final long RadioButtonImpl$lambda$18$lambda$14(State $contentColor$delegate) { State state = $contentColor$delegate; Object object = null; KProperty property$iv = null; int $i$f$getValue = 0; return ((Color)state.getValue()).unbox-impl(); }
/*     */ 
/*     */   
/*     */   @Metadata(mv = {2, 0, 0}, k = 3, xi = 48)
/*     */   static final class RadioButtonKt$RadioButtonImpl$4$3 implements Function2<Composer, Integer, Unit> {
/*     */     @Composable
/*     */     @ComposableTarget(applier = "androidx.compose.ui.UiComposable")
/*     */     public final void invoke(Composer $composer, int $changed) {
/*     */       if (($changed & 0x3) != 2 || !$composer.getSkipping()) {
/*     */         if (ComposerKt.isTraceInProgress())
/*     */           ComposerKt.traceEventStart(-1987373942, $changed, -1, "org.jetbrains.jewel.ui.component.RadioButtonImpl.<anonymous>.<anonymous> (RadioButton.kt:215)"); 
/*     */         this.$content.invoke(this.$this_Row, $composer, Integer.valueOf(0));
/*     */         if (ComposerKt.isTraceInProgress())
/*     */           ComposerKt.traceEventEnd(); 
/*     */       } else {
/*     */         $composer.skipToGroupEnd();
/*     */       } 
/*     */     }
/*     */     
/*     */     RadioButtonKt$RadioButtonImpl$4$3(Function3<RowScope, Composer, Integer, Unit> $content, RowScope $receiver) {}
/*     */   }
/*     */   
/*     */   @Composable
/*     */   @ComposableTarget(applier = "androidx.compose.ui.UiComposable")
/*     */   private static final void RadioButtonImage(Painter radioButtonPainter, Modifier modifier, Composer $composer, int $changed, int paramInt1) {
/*     */     // Byte code:
/*     */     //   0: aload_2
/*     */     //   1: ldc_w 270878499
/*     */     //   4: invokeinterface startRestartGroup : (I)Landroidx/compose/runtime/Composer;
/*     */     //   9: astore_2
/*     */     //   10: iload_3
/*     */     //   11: istore #5
/*     */     //   13: iload #4
/*     */     //   15: iconst_1
/*     */     //   16: iand
/*     */     //   17: ifeq -> 30
/*     */     //   20: iload #5
/*     */     //   22: bipush #6
/*     */     //   24: ior
/*     */     //   25: istore #5
/*     */     //   27: goto -> 57
/*     */     //   30: iload_3
/*     */     //   31: bipush #6
/*     */     //   33: iand
/*     */     //   34: ifne -> 57
/*     */     //   37: iload #5
/*     */     //   39: aload_2
/*     */     //   40: aload_0
/*     */     //   41: invokeinterface changedInstance : (Ljava/lang/Object;)Z
/*     */     //   46: ifeq -> 53
/*     */     //   49: iconst_4
/*     */     //   50: goto -> 54
/*     */     //   53: iconst_2
/*     */     //   54: ior
/*     */     //   55: istore #5
/*     */     //   57: iload #4
/*     */     //   59: iconst_2
/*     */     //   60: iand
/*     */     //   61: ifeq -> 74
/*     */     //   64: iload #5
/*     */     //   66: bipush #48
/*     */     //   68: ior
/*     */     //   69: istore #5
/*     */     //   71: goto -> 103
/*     */     //   74: iload_3
/*     */     //   75: bipush #48
/*     */     //   77: iand
/*     */     //   78: ifne -> 103
/*     */     //   81: iload #5
/*     */     //   83: aload_2
/*     */     //   84: aload_1
/*     */     //   85: invokeinterface changed : (Ljava/lang/Object;)Z
/*     */     //   90: ifeq -> 98
/*     */     //   93: bipush #32
/*     */     //   95: goto -> 100
/*     */     //   98: bipush #16
/*     */     //   100: ior
/*     */     //   101: istore #5
/*     */     //   103: iload #5
/*     */     //   105: bipush #19
/*     */     //   107: iand
/*     */     //   108: bipush #18
/*     */     //   110: if_icmpne -> 122
/*     */     //   113: aload_2
/*     */     //   114: invokeinterface getSkipping : ()Z
/*     */     //   119: ifne -> 189
/*     */     //   122: iload #4
/*     */     //   124: iconst_2
/*     */     //   125: iand
/*     */     //   126: ifeq -> 136
/*     */     //   129: getstatic androidx/compose/ui/Modifier.Companion : Landroidx/compose/ui/Modifier$Companion;
/*     */     //   132: checkcast androidx/compose/ui/Modifier
/*     */     //   135: astore_1
/*     */     //   136: invokestatic isTraceInProgress : ()Z
/*     */     //   139: ifeq -> 154
/*     */     //   142: ldc_w 270878499
/*     */     //   145: iload #5
/*     */     //   147: iconst_m1
/*     */     //   148: ldc_w 'org.jetbrains.jewel.ui.component.RadioButtonImage (RadioButton.kt:222)'
/*     */     //   151: invokestatic traceEventStart : (IIILjava/lang/String;)V
/*     */     //   154: aload_1
/*     */     //   155: aload_0
/*     */     //   156: iconst_0
/*     */     //   157: getstatic androidx/compose/ui/Alignment.Companion : Landroidx/compose/ui/Alignment$Companion;
/*     */     //   160: invokevirtual getTopStart : ()Landroidx/compose/ui/Alignment;
/*     */     //   163: aconst_null
/*     */     //   164: fconst_0
/*     */     //   165: aconst_null
/*     */     //   166: bipush #58
/*     */     //   168: aconst_null
/*     */     //   169: invokestatic paint$default : (Landroidx/compose/ui/Modifier;Landroidx/compose/ui/graphics/painter/Painter;ZLandroidx/compose/ui/Alignment;Landroidx/compose/ui/layout/ContentScale;FLandroidx/compose/ui/graphics/ColorFilter;ILjava/lang/Object;)Landroidx/compose/ui/Modifier;
/*     */     //   172: aload_2
/*     */     //   173: iconst_0
/*     */     //   174: invokestatic Box : (Landroidx/compose/ui/Modifier;Landroidx/compose/runtime/Composer;I)V
/*     */     //   177: invokestatic isTraceInProgress : ()Z
/*     */     //   180: ifeq -> 195
/*     */     //   183: invokestatic traceEventEnd : ()V
/*     */     //   186: goto -> 195
/*     */     //   189: aload_2
/*     */     //   190: invokeinterface skipToGroupEnd : ()V
/*     */     //   195: aload_2
/*     */     //   196: invokeinterface endRestartGroup : ()Landroidx/compose/runtime/ScopeUpdateScope;
/*     */     //   201: dup
/*     */     //   202: ifnull -> 223
/*     */     //   205: aload_0
/*     */     //   206: aload_1
/*     */     //   207: iload_3
/*     */     //   208: iload #4
/*     */     //   210: <illegal opcode> invoke : (Landroidx/compose/ui/graphics/painter/Painter;Landroidx/compose/ui/Modifier;II)Lkotlin/jvm/functions/Function2;
/*     */     //   215: invokeinterface updateScope : (Lkotlin/jvm/functions/Function2;)V
/*     */     //   220: goto -> 224
/*     */     //   223: pop
/*     */     //   224: return
/*     */     // Line number table:
/*     */     //   Java source line number -> byte code offset
/*     */     //   #223	-> 0
/*     */     //   #224	-> 154
/*     */     //   #225	-> 189
/*     */     // Local variable table:
/*     */     //   start	length	slot	name	descriptor
/*     */     //   13	212	5	$dirty	I
/*     */     //   0	225	0	radioButtonPainter	Landroidx/compose/ui/graphics/painter/Painter;
/*     */     //   0	225	1	modifier	Landroidx/compose/ui/Modifier;
/*     */     //   0	225	2	$composer	Landroidx/compose/runtime/Composer;
/*     */     //   0	225	3	$changed	I
/*     */   }
/*     */   
/*     */   private static final Unit RadioButton$lambda$1(boolean $selected, Function0<Unit> $onClick, Modifier $modifier, boolean $enabled, Outline $outline, MutableInteractionSource $interactionSource, RadioButtonStyle $style, TextStyle $textStyle, Alignment.Vertical $verticalAlignment, int $$changed, int $$default, Composer $composer, int $force) {
/*     */     RadioButton($selected, $onClick, $modifier, $enabled, $outline, $interactionSource, $style, $textStyle, $verticalAlignment, $composer, RecomposeScopeImplKt.updateChangedFlags($$changed | 0x1), $$default);
/*     */     return Unit.INSTANCE;
/*     */   }
/*     */   
/*     */   private static final Unit RadioButtonRow$lambda$3(String $text, boolean $selected, Function0<Unit> $onClick, Modifier $modifier, boolean $enabled, Outline $outline, MutableInteractionSource $interactionSource, RadioButtonStyle $style, TextStyle $textStyle, Alignment.Vertical $verticalAlignment, int $$changed, int $$default, Composer $composer, int $force) {
/*     */     RadioButtonRow($text, $selected, $onClick, $modifier, $enabled, $outline, $interactionSource, $style, $textStyle, $verticalAlignment, $composer, RecomposeScopeImplKt.updateChangedFlags($$changed | 0x1), $$default);
/*     */     return Unit.INSTANCE;
/*     */   }
/*     */   
/*     */   private static final Unit RadioButtonRow$lambda$5(boolean $selected, Function0<Unit> $onClick, Modifier $modifier, boolean $enabled, Outline $outline, MutableInteractionSource $interactionSource, RadioButtonStyle $style, TextStyle $textStyle, Alignment.Vertical $verticalAlignment, Function3<? super RowScope, ? super Composer, ? super Integer, Unit> $content, int $$changed, int $$default, Composer $composer, int $force) {
/*     */     RadioButtonRow($selected, $onClick, $modifier, $enabled, $outline, $interactionSource, $style, $textStyle, $verticalAlignment, $content, $composer, RecomposeScopeImplKt.updateChangedFlags($$changed | 0x1), $$default);
/*     */     return Unit.INSTANCE;
/*     */   }
/*     */   
/*     */   private static final Unit RadioButtonImpl$lambda$19(boolean $selected, Function0<Unit> $onClick, Modifier $modifier, boolean $enabled, Outline $outline, MutableInteractionSource $interactionSource, RadioButtonStyle $style, TextStyle $textStyle, Alignment.Vertical $verticalAlignment, Function3<? super RowScope, ? super Composer, ? super Integer, Unit> $content, int $$changed, Composer $composer, int $force) {
/*     */     RadioButtonImpl($selected, $onClick, $modifier, $enabled, $outline, $interactionSource, $style, $textStyle, $verticalAlignment, $content, $composer, RecomposeScopeImplKt.updateChangedFlags($$changed | 0x1));
/*     */     return Unit.INSTANCE;
/*     */   }
/*     */   
/*     */   private static final Unit RadioButtonImage$lambda$20(Painter $radioButtonPainter, Modifier $modifier, int $$changed, int $$default, Composer $composer, int $force) {
/*     */     RadioButtonImage($radioButtonPainter, $modifier, $composer, RecomposeScopeImplKt.updateChangedFlags($$changed | 0x1), $$default);
/*     */     return Unit.INSTANCE;
/*     */   }
/*     */ }


/* Location:              C:\Users\yuzum\Downloads\ej-release-243.132.63.zip!\ej\lib\jewel-ui-243-0.27.0.jar!\org\jetbrains\jewe\\ui\component\RadioButtonKt.class
 * Java compiler version: 17 (61.0)
 * JD-Core Version:       1.1.3
 */