/*     */ package com.intellij.ml.llm.matterhorn.activation.state.junie;
/*     */ import com.intellij.ml.llm.matterhorn.activation.state.model.AipLicenseJourney;
/*     */ import com.intellij.openapi.diagnostic.Logger;
/*     */ import kotlin.Metadata;
/*     */ import kotlin.Unit;
/*     */ import kotlin.coroutines.Continuation;
/*     */ import kotlin.coroutines.jvm.internal.SuspendFunction;
/*     */ import kotlin.jvm.functions.Function0;
/*     */ import kotlin.jvm.functions.Function1;
/*     */ import kotlin.jvm.internal.FunctionReferenceImpl;
/*     */ import kotlin.jvm.internal.Intrinsics;
/*     */ import kotlin.jvm.internal.SourceDebugExtension;
/*     */ import org.jetbrains.annotations.NotNull;
/*     */ 
/*     */ @Metadata(mv = {2, 1, 0}, k = 2, xi = 48, d1 = {"\000\020\n\000\n\002\030\002\n\002\b\002\n\002\030\002\n\000\032\r\020\000\032\0020\001H\007¢\006\002\020\002\"\016\020\003\032\0020\004X\004¢\006\002\n\000¨\006\005"}, d2 = {"aiProJbaActivation", "Lcom/intellij/ml/llm/matterhorn/activation/state/model/AiaActivation;", "(Landroidx/compose/runtime/Composer;I)Lcom/intellij/ml/llm/matterhorn/activation/state/model/AiaActivation;", "LOG", "Lcom/intellij/openapi/diagnostic/Logger;", "state.junie.impl"})
/*     */ @SourceDebugExtension({"SMAP\naiProJbaActivation.kt\nKotlin\n*S Kotlin\n*F\n+ 1 aiProJbaActivation.kt\ncom/intellij/ml/llm/matterhorn/activation/state/junie/AiProJbaActivationKt\n+ 2 Composer.kt\nandroidx/compose/runtime/ComposerKt\n+ 3 outcome.kt\ncom/intellij/ml/llm/matterhorn/activation/state/junie/util/OutcomeKt\n+ 4 Outcome.kt\ncom/intellij/ml/llm/matterhorn/activation/state/model/Outcome\n+ 5 logger.kt\ncom/intellij/openapi/diagnostic/LoggerKt\n*L\n1#1,104:1\n1225#2,6:105\n1225#2,6:135\n1225#2,6:147\n1225#2,6:153\n1225#2,6:159\n30#3:111\n21#3:112\n22#3:116\n30#3:117\n21#3:118\n22#3:122\n30#3:123\n21#3:124\n22#3:128\n30#3:129\n21#3:130\n22#3:134\n30#3:141\n21#3:142\n22#3:146\n30#3:165\n21#3:166\n22#3:170\n16#4,3:113\n16#4,3:119\n16#4,3:125\n16#4,3:131\n16#4,3:143\n16#4,3:167\n58#5:171\n36#5,2:172\n*S KotlinDebug\n*F\n+ 1 aiProJbaActivation.kt\ncom/intellij/ml/llm/matterhorn/activation/state/junie/AiProJbaActivationKt\n*L\n19#1:105,6\n50#1:135,6\n69#1:147,6\n70#1:153,6\n71#1:159,6\n29#1:111\n29#1:112\n29#1:116\n33#1:117\n33#1:118\n33#1:122\n37#1:123\n37#1:124\n37#1:128\n44#1:129\n44#1:130\n44#1:134\n53#1:141\n53#1:142\n53#1:146\n75#1:165\n75#1:166\n75#1:170\n29#1:113,3\n33#1:119,3\n37#1:125,3\n44#1:131,3\n53#1:143,3\n75#1:167,3\n103#1:171\n103#1:172,2\n*E\n"})
/*     */ public final class AiProJbaActivationKt {
/*     */   private static final String aiProJbaActivation$lambda$1$lambda$0() {
/*  19 */     return "AI Pro activation through JBA";
/*     */   }
/*     */ 
/*     */ 
/*     */ 
/*     */ 
/*     */ 
/*     */ 
/*     */   
/*     */   @NotNull
/*     */   private static final Logger LOG;
/*     */ 
/*     */ 
/*     */ 
/*     */ 
/*     */ 
/*     */ 
/*     */   
/*     */   @Composable
/*     */   @NotNull
/*     */   public static final AiaActivation aiProJbaActivation(@Nullable Composer $composer, int $changed) {
/*     */     // Byte code:
/*     */     //   0: aload_0
/*     */     //   1: ldc -1542651721
/*     */     //   3: invokeinterface startReplaceGroup : (I)V
/*     */     //   8: invokestatic isTraceInProgress : ()Z
/*     */     //   11: ifeq -> 23
/*     */     //   14: ldc -1542651721
/*     */     //   16: iload_1
/*     */     //   17: iconst_m1
/*     */     //   18: ldc 'com.intellij.ml.llm.matterhorn.activation.state.junie.aiProJbaActivation (aiProJbaActivation.kt:17)'
/*     */     //   20: invokestatic traceEventStart : (IIILjava/lang/String;)V
/*     */     //   23: getstatic com/intellij/ml/llm/matterhorn/activation/state/junie/AiProJbaActivationKt.LOG : Lcom/intellij/openapi/diagnostic/Logger;
/*     */     //   26: aload_0
/*     */     //   27: ldc -317067875
/*     */     //   29: invokeinterface startReplaceGroup : (I)V
/*     */     //   34: aload_0
/*     */     //   35: astore_3
/*     */     //   36: iconst_0
/*     */     //   37: istore #4
/*     */     //   39: iconst_0
/*     */     //   40: istore #5
/*     */     //   42: aload_3
/*     */     //   43: invokeinterface rememberedValue : ()Ljava/lang/Object;
/*     */     //   48: astore #6
/*     */     //   50: iconst_0
/*     */     //   51: istore #7
/*     */     //   53: aload #6
/*     */     //   55: getstatic androidx/compose/runtime/Composer.Companion : Landroidx/compose/runtime/Composer$Companion;
/*     */     //   58: invokevirtual getEmpty : ()Ljava/lang/Object;
/*     */     //   61: if_acmpne -> 92
/*     */     //   64: astore #23
/*     */     //   66: iconst_0
/*     */     //   67: istore #8
/*     */     //   69: <illegal opcode> invoke : ()Lkotlin/jvm/functions/Function0;
/*     */     //   74: aload #23
/*     */     //   76: swap
/*     */     //   77: astore #8
/*     */     //   79: aload_3
/*     */     //   80: aload #8
/*     */     //   82: invokeinterface updateRememberedValue : (Ljava/lang/Object;)V
/*     */     //   87: aload #8
/*     */     //   89: goto -> 94
/*     */     //   92: aload #6
/*     */     //   94: nop
/*     */     //   95: nop
/*     */     //   96: nop
/*     */     //   97: checkcast kotlin/jvm/functions/Function0
/*     */     //   100: astore_2
/*     */     //   101: aload_0
/*     */     //   102: invokeinterface endReplaceGroup : ()V
/*     */     //   107: aload_2
/*     */     //   108: aload_0
/*     */     //   109: bipush #48
/*     */     //   111: invokestatic TraceComposition : (Lcom/intellij/openapi/diagnostic/Logger;Lkotlin/jvm/functions/Function0;Landroidx/compose/runtime/Composer;I)V
/*     */     //   114: aload_0
/*     */     //   115: iconst_0
/*     */     //   116: invokestatic regionCheckerStep : (Landroidx/compose/runtime/Composer;I)Lcom/intellij/ml/llm/matterhorn/activation/state/model/RegionCheckStep;
/*     */     //   119: astore_2
/*     */     //   120: aconst_null
/*     */     //   121: aload_0
/*     */     //   122: iconst_0
/*     */     //   123: iconst_1
/*     */     //   124: invokestatic ideLicenseAiAllowanceStep : (Lcom/intellij/ml/llm/matterhorn/activation/state/junie/data/IdeLicenseStore;Landroidx/compose/runtime/Composer;II)Lcom/intellij/ml/llm/matterhorn/activation/state/model/IdeLicenseAiAllowanceStep;
/*     */     //   127: astore_3
/*     */     //   128: aconst_null
/*     */     //   129: aload_0
/*     */     //   130: iconst_0
/*     */     //   131: iconst_1
/*     */     //   132: invokestatic jbaAuthStep : (Lcom/intellij/ml/llm/matterhorn/activation/state/junie/data/JbaUserStore;Landroidx/compose/runtime/Composer;II)Lcom/intellij/ml/llm/matterhorn/activation/state/model/JbaAuthStep;
/*     */     //   135: astore #4
/*     */     //   137: aload_2
/*     */     //   138: checkcast com/intellij/ml/llm/matterhorn/activation/state/model/Journey
/*     */     //   141: astore #5
/*     */     //   143: iconst_0
/*     */     //   144: istore #6
/*     */     //   146: aload #5
/*     */     //   148: invokeinterface getOutcome-07x5Wys : ()Ljava/lang/Object;
/*     */     //   153: astore #7
/*     */     //   155: iconst_0
/*     */     //   156: istore #8
/*     */     //   158: iconst_0
/*     */     //   159: istore #9
/*     */     //   161: aload #7
/*     */     //   163: invokestatic isIncomplete-impl : (Ljava/lang/Object;)Z
/*     */     //   166: istore #10
/*     */     //   168: iload #10
/*     */     //   170: iconst_1
/*     */     //   171: if_icmpne -> 235
/*     */     //   174: aload #7
/*     */     //   176: invokestatic incompleteOrNull-impl : (Ljava/lang/Object;)Ljava/lang/Object;
/*     */     //   179: checkcast com/intellij/ml/llm/matterhorn/activation/state/model/JunieRegionCheckProhibited
/*     */     //   182: astore #11
/*     */     //   184: iconst_0
/*     */     //   185: istore #12
/*     */     //   187: new com/intellij/ml/llm/matterhorn/activation/state/model/AiProJbaActivation
/*     */     //   190: dup
/*     */     //   191: aload_2
/*     */     //   192: aload_3
/*     */     //   193: aload #4
/*     */     //   195: aconst_null
/*     */     //   196: aconst_null
/*     */     //   197: aconst_null
/*     */     //   198: getstatic com/intellij/ml/llm/matterhorn/activation/state/model/Outcome.Companion : Lcom/intellij/ml/llm/matterhorn/activation/state/model/Outcome$Companion;
/*     */     //   201: aload #11
/*     */     //   203: invokevirtual ofIncomplete-l12Rbqo : (Ljava/lang/Object;)Ljava/lang/Object;
/*     */     //   206: bipush #56
/*     */     //   208: aconst_null
/*     */     //   209: invokespecial <init> : (Lcom/intellij/ml/llm/matterhorn/activation/state/model/RegionCheckStep;Lcom/intellij/ml/llm/matterhorn/activation/state/model/IdeLicenseAiAllowanceStep;Lcom/intellij/ml/llm/matterhorn/activation/state/model/JbaAuthStep;Lcom/intellij/ml/llm/matterhorn/activation/state/model/GrazieCloudUrlStep;Lcom/intellij/ml/llm/matterhorn/activation/state/model/AipLicenseJourney;Lcom/intellij/ml/llm/matterhorn/activation/state/model/GrazieJbaAuthStep;Ljava/lang/Object;ILkotlin/jvm/internal/DefaultConstructorMarker;)V
/*     */     //   212: astore #13
/*     */     //   214: invokestatic isTraceInProgress : ()Z
/*     */     //   217: ifeq -> 223
/*     */     //   220: invokestatic traceEventEnd : ()V
/*     */     //   223: aload_0
/*     */     //   224: invokeinterface endReplaceGroup : ()V
/*     */     //   229: aload #13
/*     */     //   231: checkcast com/intellij/ml/llm/matterhorn/activation/state/model/AiaActivation
/*     */     //   234: areturn
/*     */     //   235: iload #10
/*     */     //   237: ifne -> 254
/*     */     //   240: aload #7
/*     */     //   242: invokestatic getOrNull-impl : (Ljava/lang/Object;)Ljava/lang/Object;
/*     */     //   245: astore #14
/*     */     //   247: iconst_0
/*     */     //   248: istore #15
/*     */     //   250: nop
/*     */     //   251: goto -> 262
/*     */     //   254: new kotlin/NoWhenBranchMatchedException
/*     */     //   257: dup
/*     */     //   258: invokespecial <init> : ()V
/*     */     //   261: athrow
/*     */     //   262: nop
/*     */     //   263: nop
/*     */     //   264: aload #4
/*     */     //   266: checkcast com/intellij/ml/llm/matterhorn/activation/state/model/Journey
/*     */     //   269: astore #6
/*     */     //   271: iconst_0
/*     */     //   272: istore #7
/*     */     //   274: aload #6
/*     */     //   276: invokeinterface getOutcome-07x5Wys : ()Ljava/lang/Object;
/*     */     //   281: astore #8
/*     */     //   283: iconst_0
/*     */     //   284: istore #9
/*     */     //   286: iconst_0
/*     */     //   287: istore #10
/*     */     //   289: aload #8
/*     */     //   291: invokestatic isIncomplete-impl : (Ljava/lang/Object;)Z
/*     */     //   294: istore #11
/*     */     //   296: iload #11
/*     */     //   298: iconst_1
/*     */     //   299: if_icmpne -> 363
/*     */     //   302: aload #8
/*     */     //   304: invokestatic incompleteOrNull-impl : (Ljava/lang/Object;)Ljava/lang/Object;
/*     */     //   307: checkcast com/intellij/ml/llm/matterhorn/activation/state/model/JbaAuthPending
/*     */     //   310: astore #12
/*     */     //   312: iconst_0
/*     */     //   313: istore #13
/*     */     //   315: new com/intellij/ml/llm/matterhorn/activation/state/model/AiProJbaActivation
/*     */     //   318: dup
/*     */     //   319: aload_2
/*     */     //   320: aload_3
/*     */     //   321: aload #4
/*     */     //   323: aconst_null
/*     */     //   324: aconst_null
/*     */     //   325: aconst_null
/*     */     //   326: getstatic com/intellij/ml/llm/matterhorn/activation/state/model/Outcome.Companion : Lcom/intellij/ml/llm/matterhorn/activation/state/model/Outcome$Companion;
/*     */     //   329: aload #12
/*     */     //   331: invokevirtual ofIncomplete-l12Rbqo : (Ljava/lang/Object;)Ljava/lang/Object;
/*     */     //   334: bipush #56
/*     */     //   336: aconst_null
/*     */     //   337: invokespecial <init> : (Lcom/intellij/ml/llm/matterhorn/activation/state/model/RegionCheckStep;Lcom/intellij/ml/llm/matterhorn/activation/state/model/IdeLicenseAiAllowanceStep;Lcom/intellij/ml/llm/matterhorn/activation/state/model/JbaAuthStep;Lcom/intellij/ml/llm/matterhorn/activation/state/model/GrazieCloudUrlStep;Lcom/intellij/ml/llm/matterhorn/activation/state/model/AipLicenseJourney;Lcom/intellij/ml/llm/matterhorn/activation/state/model/GrazieJbaAuthStep;Ljava/lang/Object;ILkotlin/jvm/internal/DefaultConstructorMarker;)V
/*     */     //   340: astore #14
/*     */     //   342: invokestatic isTraceInProgress : ()Z
/*     */     //   345: ifeq -> 351
/*     */     //   348: invokestatic traceEventEnd : ()V
/*     */     //   351: aload_0
/*     */     //   352: invokeinterface endReplaceGroup : ()V
/*     */     //   357: aload #14
/*     */     //   359: checkcast com/intellij/ml/llm/matterhorn/activation/state/model/AiaActivation
/*     */     //   362: areturn
/*     */     //   363: iload #11
/*     */     //   365: ifne -> 383
/*     */     //   368: aload #8
/*     */     //   370: invokestatic getOrNull-impl : (Ljava/lang/Object;)Ljava/lang/Object;
/*     */     //   373: astore #15
/*     */     //   375: iconst_0
/*     */     //   376: istore #16
/*     */     //   378: aload #15
/*     */     //   380: goto -> 391
/*     */     //   383: new kotlin/NoWhenBranchMatchedException
/*     */     //   386: dup
/*     */     //   387: invokespecial <init> : ()V
/*     */     //   390: athrow
/*     */     //   391: nop
/*     */     //   392: nop
/*     */     //   393: checkcast com/intellij/ml/llm/matterhorn/activation/data/model/JbaAuthData
/*     */     //   396: astore #5
/*     */     //   398: aload_3
/*     */     //   399: checkcast com/intellij/ml/llm/matterhorn/activation/state/model/Journey
/*     */     //   402: astore #6
/*     */     //   404: iconst_0
/*     */     //   405: istore #7
/*     */     //   407: aload #6
/*     */     //   409: invokeinterface getOutcome-07x5Wys : ()Ljava/lang/Object;
/*     */     //   414: astore #8
/*     */     //   416: iconst_0
/*     */     //   417: istore #9
/*     */     //   419: iconst_0
/*     */     //   420: istore #10
/*     */     //   422: aload #8
/*     */     //   424: invokestatic isIncomplete-impl : (Ljava/lang/Object;)Z
/*     */     //   427: istore #11
/*     */     //   429: iload #11
/*     */     //   431: iconst_1
/*     */     //   432: if_icmpne -> 496
/*     */     //   435: aload #8
/*     */     //   437: invokestatic incompleteOrNull-impl : (Ljava/lang/Object;)Ljava/lang/Object;
/*     */     //   440: checkcast com/intellij/ml/llm/matterhorn/activation/state/model/IdeLicenseAiAllowancePending
/*     */     //   443: astore #12
/*     */     //   445: iconst_0
/*     */     //   446: istore #13
/*     */     //   448: new com/intellij/ml/llm/matterhorn/activation/state/model/AiProJbaActivation
/*     */     //   451: dup
/*     */     //   452: aload_2
/*     */     //   453: aload_3
/*     */     //   454: aload #4
/*     */     //   456: aconst_null
/*     */     //   457: aconst_null
/*     */     //   458: aconst_null
/*     */     //   459: getstatic com/intellij/ml/llm/matterhorn/activation/state/model/Outcome.Companion : Lcom/intellij/ml/llm/matterhorn/activation/state/model/Outcome$Companion;
/*     */     //   462: aload #12
/*     */     //   464: invokevirtual ofIncomplete-l12Rbqo : (Ljava/lang/Object;)Ljava/lang/Object;
/*     */     //   467: bipush #56
/*     */     //   469: aconst_null
/*     */     //   470: invokespecial <init> : (Lcom/intellij/ml/llm/matterhorn/activation/state/model/RegionCheckStep;Lcom/intellij/ml/llm/matterhorn/activation/state/model/IdeLicenseAiAllowanceStep;Lcom/intellij/ml/llm/matterhorn/activation/state/model/JbaAuthStep;Lcom/intellij/ml/llm/matterhorn/activation/state/model/GrazieCloudUrlStep;Lcom/intellij/ml/llm/matterhorn/activation/state/model/AipLicenseJourney;Lcom/intellij/ml/llm/matterhorn/activation/state/model/GrazieJbaAuthStep;Ljava/lang/Object;ILkotlin/jvm/internal/DefaultConstructorMarker;)V
/*     */     //   473: astore #14
/*     */     //   475: invokestatic isTraceInProgress : ()Z
/*     */     //   478: ifeq -> 484
/*     */     //   481: invokestatic traceEventEnd : ()V
/*     */     //   484: aload_0
/*     */     //   485: invokeinterface endReplaceGroup : ()V
/*     */     //   490: aload #14
/*     */     //   492: checkcast com/intellij/ml/llm/matterhorn/activation/state/model/AiaActivation
/*     */     //   495: areturn
/*     */     //   496: iload #11
/*     */     //   498: ifne -> 515
/*     */     //   501: aload #8
/*     */     //   503: invokestatic getOrNull-impl : (Ljava/lang/Object;)Ljava/lang/Object;
/*     */     //   506: astore #15
/*     */     //   508: iconst_0
/*     */     //   509: istore #16
/*     */     //   511: nop
/*     */     //   512: goto -> 523
/*     */     //   515: new kotlin/NoWhenBranchMatchedException
/*     */     //   518: dup
/*     */     //   519: invokespecial <init> : ()V
/*     */     //   522: athrow
/*     */     //   523: nop
/*     */     //   524: nop
/*     */     //   525: aconst_null
/*     */     //   526: aload_0
/*     */     //   527: iconst_0
/*     */     //   528: iconst_1
/*     */     //   529: invokestatic grazieCloudUrlStep : (Lcom/intellij/ml/llm/matterhorn/activation/config/AiaConfig;Landroidx/compose/runtime/Composer;II)Lcom/intellij/ml/llm/matterhorn/activation/state/model/GrazieCloudUrlStep;
/*     */     //   532: astore #6
/*     */     //   534: aload #6
/*     */     //   536: checkcast com/intellij/ml/llm/matterhorn/activation/state/model/Journey
/*     */     //   539: astore #8
/*     */     //   541: iconst_0
/*     */     //   542: istore #9
/*     */     //   544: aload #8
/*     */     //   546: invokeinterface getOutcome-07x5Wys : ()Ljava/lang/Object;
/*     */     //   551: astore #10
/*     */     //   553: iconst_0
/*     */     //   554: istore #11
/*     */     //   556: iconst_0
/*     */     //   557: istore #12
/*     */     //   559: aload #10
/*     */     //   561: invokestatic isIncomplete-impl : (Ljava/lang/Object;)Z
/*     */     //   564: istore #13
/*     */     //   566: iload #13
/*     */     //   568: iconst_1
/*     */     //   569: if_icmpne -> 634
/*     */     //   572: aload #10
/*     */     //   574: invokestatic incompleteOrNull-impl : (Ljava/lang/Object;)Ljava/lang/Object;
/*     */     //   577: checkcast com/intellij/ml/llm/matterhorn/activation/state/model/GrazieCloudUrlPending
/*     */     //   580: astore #14
/*     */     //   582: iconst_0
/*     */     //   583: istore #15
/*     */     //   585: new com/intellij/ml/llm/matterhorn/activation/state/model/AiProJbaActivation
/*     */     //   588: dup
/*     */     //   589: aload_2
/*     */     //   590: aload_3
/*     */     //   591: aload #4
/*     */     //   593: aload #6
/*     */     //   595: aconst_null
/*     */     //   596: aconst_null
/*     */     //   597: getstatic com/intellij/ml/llm/matterhorn/activation/state/model/Outcome.Companion : Lcom/intellij/ml/llm/matterhorn/activation/state/model/Outcome$Companion;
/*     */     //   600: aload #14
/*     */     //   602: invokevirtual ofIncomplete-l12Rbqo : (Ljava/lang/Object;)Ljava/lang/Object;
/*     */     //   605: bipush #48
/*     */     //   607: aconst_null
/*     */     //   608: invokespecial <init> : (Lcom/intellij/ml/llm/matterhorn/activation/state/model/RegionCheckStep;Lcom/intellij/ml/llm/matterhorn/activation/state/model/IdeLicenseAiAllowanceStep;Lcom/intellij/ml/llm/matterhorn/activation/state/model/JbaAuthStep;Lcom/intellij/ml/llm/matterhorn/activation/state/model/GrazieCloudUrlStep;Lcom/intellij/ml/llm/matterhorn/activation/state/model/AipLicenseJourney;Lcom/intellij/ml/llm/matterhorn/activation/state/model/GrazieJbaAuthStep;Ljava/lang/Object;ILkotlin/jvm/internal/DefaultConstructorMarker;)V
/*     */     //   611: astore #16
/*     */     //   613: invokestatic isTraceInProgress : ()Z
/*     */     //   616: ifeq -> 622
/*     */     //   619: invokestatic traceEventEnd : ()V
/*     */     //   622: aload_0
/*     */     //   623: invokeinterface endReplaceGroup : ()V
/*     */     //   628: aload #16
/*     */     //   630: checkcast com/intellij/ml/llm/matterhorn/activation/state/model/AiaActivation
/*     */     //   633: areturn
/*     */     //   634: iload #13
/*     */     //   636: ifne -> 654
/*     */     //   639: aload #10
/*     */     //   641: invokestatic getOrNull-impl : (Ljava/lang/Object;)Ljava/lang/Object;
/*     */     //   644: astore #17
/*     */     //   646: iconst_0
/*     */     //   647: istore #18
/*     */     //   649: aload #17
/*     */     //   651: goto -> 662
/*     */     //   654: new kotlin/NoWhenBranchMatchedException
/*     */     //   657: dup
/*     */     //   658: invokespecial <init> : ()V
/*     */     //   661: athrow
/*     */     //   662: nop
/*     */     //   663: nop
/*     */     //   664: checkcast com/intellij/ml/llm/matterhorn/activation/data/model/GrazieApiUrl
/*     */     //   667: invokevirtual unbox-impl : ()Ljava/lang/String;
/*     */     //   670: astore #7
/*     */     //   672: aload #5
/*     */     //   674: aload #4
/*     */     //   676: invokevirtual getOnAuthRejected : ()Lkotlin/jvm/functions/Function0;
/*     */     //   679: astore #10
/*     */     //   681: aload_0
/*     */     //   682: ldc -317023462
/*     */     //   684: invokeinterface startReplaceGroup : (I)V
/*     */     //   689: aload #10
/*     */     //   691: dup
/*     */     //   692: ifnonnull -> 783
/*     */     //   695: pop
/*     */     //   696: aload_0
/*     */     //   697: ldc -317022532
/*     */     //   699: invokeinterface startReplaceGroup : (I)V
/*     */     //   704: aload_0
/*     */     //   705: astore #13
/*     */     //   707: iconst_0
/*     */     //   708: istore #14
/*     */     //   710: iconst_0
/*     */     //   711: istore #15
/*     */     //   713: aload #13
/*     */     //   715: invokeinterface rememberedValue : ()Ljava/lang/Object;
/*     */     //   720: astore #16
/*     */     //   722: iconst_0
/*     */     //   723: istore #17
/*     */     //   725: aload #16
/*     */     //   727: getstatic androidx/compose/runtime/Composer.Companion : Landroidx/compose/runtime/Composer$Companion;
/*     */     //   730: invokevirtual getEmpty : ()Ljava/lang/Object;
/*     */     //   733: if_acmpne -> 765
/*     */     //   736: astore #23
/*     */     //   738: iconst_0
/*     */     //   739: istore #18
/*     */     //   741: <illegal opcode> invoke : ()Lkotlin/jvm/functions/Function0;
/*     */     //   746: aload #23
/*     */     //   748: swap
/*     */     //   749: astore #18
/*     */     //   751: aload #13
/*     */     //   753: aload #18
/*     */     //   755: invokeinterface updateRememberedValue : (Ljava/lang/Object;)V
/*     */     //   760: aload #18
/*     */     //   762: goto -> 767
/*     */     //   765: aload #16
/*     */     //   767: nop
/*     */     //   768: nop
/*     */     //   769: nop
/*     */     //   770: checkcast kotlin/jvm/functions/Function0
/*     */     //   773: astore #12
/*     */     //   775: aload_0
/*     */     //   776: invokeinterface endReplaceGroup : ()V
/*     */     //   781: aload #12
/*     */     //   783: astore #11
/*     */     //   785: aload_0
/*     */     //   786: invokeinterface endReplaceGroup : ()V
/*     */     //   791: aload #11
/*     */     //   793: astore #9
/*     */     //   795: aload_0
/*     */     //   796: ldc -317023462
/*     */     //   798: invokeinterface startReplaceGroup : (I)V
/*     */     //   803: aload_0
/*     */     //   804: astore #11
/*     */     //   806: aload_0
/*     */     //   807: aload #9
/*     */     //   809: invokeinterface changed : (Ljava/lang/Object;)Z
/*     */     //   814: istore #12
/*     */     //   816: iconst_0
/*     */     //   817: istore #13
/*     */     //   819: aload #11
/*     */     //   821: invokeinterface rememberedValue : ()Ljava/lang/Object;
/*     */     //   826: astore #14
/*     */     //   828: iconst_0
/*     */     //   829: istore #15
/*     */     //   831: iload #12
/*     */     //   833: ifne -> 847
/*     */     //   836: aload #14
/*     */     //   838: getstatic androidx/compose/runtime/Composer.Companion : Landroidx/compose/runtime/Composer$Companion;
/*     */     //   841: invokevirtual getEmpty : ()Ljava/lang/Object;
/*     */     //   844: if_acmpne -> 883
/*     */     //   847: astore #23
/*     */     //   849: iconst_0
/*     */     //   850: istore #16
/*     */     //   852: new com/intellij/ml/llm/matterhorn/activation/state/junie/AiProJbaActivationKt$aiProJbaActivation$licenseJourney$2$1
/*     */     //   855: dup
/*     */     //   856: aload #9
/*     */     //   858: invokespecial <init> : (Ljava/lang/Object;)V
/*     */     //   861: checkcast kotlin/jvm/functions/Function1
/*     */     //   864: aload #23
/*     */     //   866: swap
/*     */     //   867: astore #17
/*     */     //   869: aload #11
/*     */     //   871: aload #17
/*     */     //   873: invokeinterface updateRememberedValue : (Ljava/lang/Object;)V
/*     */     //   878: aload #17
/*     */     //   880: goto -> 885
/*     */     //   883: aload #14
/*     */     //   885: nop
/*     */     //   886: nop
/*     */     //   887: nop
/*     */     //   888: checkcast kotlin/jvm/functions/Function1
/*     */     //   891: astore #10
/*     */     //   893: aload_0
/*     */     //   894: invokeinterface endReplaceGroup : ()V
/*     */     //   899: aload #10
/*     */     //   901: aload_0
/*     */     //   902: iconst_0
/*     */     //   903: invokestatic aipLicenseJourney : (Lcom/intellij/ml/llm/matterhorn/activation/data/model/JbaAuthData;Lkotlin/jvm/functions/Function1;Landroidx/compose/runtime/Composer;I)Lcom/intellij/ml/llm/matterhorn/activation/state/model/AipLicenseJourney;
/*     */     //   906: astore #8
/*     */     //   908: aload #8
/*     */     //   910: checkcast com/intellij/ml/llm/matterhorn/activation/state/model/Journey
/*     */     //   913: astore #10
/*     */     //   915: iconst_0
/*     */     //   916: istore #11
/*     */     //   918: aload #10
/*     */     //   920: invokeinterface getOutcome-07x5Wys : ()Ljava/lang/Object;
/*     */     //   925: astore #12
/*     */     //   927: iconst_0
/*     */     //   928: istore #13
/*     */     //   930: iconst_0
/*     */     //   931: istore #14
/*     */     //   933: aload #12
/*     */     //   935: invokestatic isIncomplete-impl : (Ljava/lang/Object;)Z
/*     */     //   938: istore #15
/*     */     //   940: iload #15
/*     */     //   942: iconst_1
/*     */     //   943: if_icmpne -> 1009
/*     */     //   946: aload #12
/*     */     //   948: invokestatic incompleteOrNull-impl : (Ljava/lang/Object;)Ljava/lang/Object;
/*     */     //   951: checkcast com/intellij/ml/llm/matterhorn/activation/state/model/AipLicensePending
/*     */     //   954: astore #16
/*     */     //   956: iconst_0
/*     */     //   957: istore #17
/*     */     //   959: new com/intellij/ml/llm/matterhorn/activation/state/model/AiProJbaActivation
/*     */     //   962: dup
/*     */     //   963: aload_2
/*     */     //   964: aload_3
/*     */     //   965: aload #4
/*     */     //   967: aload #6
/*     */     //   969: aload #8
/*     */     //   971: aconst_null
/*     */     //   972: getstatic com/intellij/ml/llm/matterhorn/activation/state/model/Outcome.Companion : Lcom/intellij/ml/llm/matterhorn/activation/state/model/Outcome$Companion;
/*     */     //   975: aload #16
/*     */     //   977: invokevirtual ofIncomplete-l12Rbqo : (Ljava/lang/Object;)Ljava/lang/Object;
/*     */     //   980: bipush #32
/*     */     //   982: aconst_null
/*     */     //   983: invokespecial <init> : (Lcom/intellij/ml/llm/matterhorn/activation/state/model/RegionCheckStep;Lcom/intellij/ml/llm/matterhorn/activation/state/model/IdeLicenseAiAllowanceStep;Lcom/intellij/ml/llm/matterhorn/activation/state/model/JbaAuthStep;Lcom/intellij/ml/llm/matterhorn/activation/state/model/GrazieCloudUrlStep;Lcom/intellij/ml/llm/matterhorn/activation/state/model/AipLicenseJourney;Lcom/intellij/ml/llm/matterhorn/activation/state/model/GrazieJbaAuthStep;Ljava/lang/Object;ILkotlin/jvm/internal/DefaultConstructorMarker;)V
/*     */     //   986: astore #18
/*     */     //   988: invokestatic isTraceInProgress : ()Z
/*     */     //   991: ifeq -> 997
/*     */     //   994: invokestatic traceEventEnd : ()V
/*     */     //   997: aload_0
/*     */     //   998: invokeinterface endReplaceGroup : ()V
/*     */     //   1003: aload #18
/*     */     //   1005: checkcast com/intellij/ml/llm/matterhorn/activation/state/model/AiaActivation
/*     */     //   1008: areturn
/*     */     //   1009: iload #15
/*     */     //   1011: ifne -> 1029
/*     */     //   1014: aload #12
/*     */     //   1016: invokestatic getOrNull-impl : (Ljava/lang/Object;)Ljava/lang/Object;
/*     */     //   1019: astore #19
/*     */     //   1021: iconst_0
/*     */     //   1022: istore #20
/*     */     //   1024: aload #19
/*     */     //   1026: goto -> 1037
/*     */     //   1029: new kotlin/NoWhenBranchMatchedException
/*     */     //   1032: dup
/*     */     //   1033: invokespecial <init> : ()V
/*     */     //   1036: athrow
/*     */     //   1037: nop
/*     */     //   1038: nop
/*     */     //   1039: checkcast com/intellij/ml/llm/matterhorn/activation/data/model/AipLicense
/*     */     //   1042: astore #9
/*     */     //   1044: aload_0
/*     */     //   1045: ldc -317012375
/*     */     //   1047: aload_0
/*     */     //   1048: aload_0
/*     */     //   1049: aload #9
/*     */     //   1051: invokevirtual getLicenseId-EIc-D0M : ()Ljava/lang/String;
/*     */     //   1054: invokestatic box-impl : (Ljava/lang/String;)Lcom/intellij/ml/llm/matterhorn/activation/data/model/AipLicenseId;
/*     */     //   1057: aload #5
/*     */     //   1059: invokevirtual getIdToken-9HrtA_0 : ()Ljava/lang/String;
/*     */     //   1062: dup
/*     */     //   1063: ifnull -> 1072
/*     */     //   1066: invokestatic box-impl : (Ljava/lang/String;)Lcom/intellij/ml/llm/matterhorn/activation/data/model/JbaIdToken;
/*     */     //   1069: goto -> 1074
/*     */     //   1072: pop
/*     */     //   1073: aconst_null
/*     */     //   1074: invokeinterface joinKey : (Ljava/lang/Object;Ljava/lang/Object;)Ljava/lang/Object;
/*     */     //   1079: aload #7
/*     */     //   1081: invokestatic box-impl : (Ljava/lang/String;)Lcom/intellij/ml/llm/matterhorn/activation/data/model/GrazieApiUrl;
/*     */     //   1084: invokeinterface joinKey : (Ljava/lang/Object;Ljava/lang/Object;)Ljava/lang/Object;
/*     */     //   1089: invokeinterface startMovableGroup : (ILjava/lang/Object;)V
/*     */     //   1094: aload #7
/*     */     //   1096: aload #5
/*     */     //   1098: invokevirtual getIdToken-9HrtA_0 : ()Ljava/lang/String;
/*     */     //   1101: aload #9
/*     */     //   1103: invokevirtual getLicenseId-EIc-D0M : ()Ljava/lang/String;
/*     */     //   1106: aload #4
/*     */     //   1108: invokevirtual getOnAuthRejected : ()Lkotlin/jvm/functions/Function0;
/*     */     //   1111: dup
/*     */     //   1112: ifnonnull -> 1214
/*     */     //   1115: pop
/*     */     //   1116: aload_0
/*     */     //   1117: ldc -317004644
/*     */     //   1119: invokeinterface startReplaceGroup : (I)V
/*     */     //   1124: aload_0
/*     */     //   1125: astore #16
/*     */     //   1127: iconst_0
/*     */     //   1128: istore #17
/*     */     //   1130: iconst_0
/*     */     //   1131: istore #18
/*     */     //   1133: aload #16
/*     */     //   1135: invokeinterface rememberedValue : ()Ljava/lang/Object;
/*     */     //   1140: astore #19
/*     */     //   1142: iconst_0
/*     */     //   1143: istore #20
/*     */     //   1145: aload #19
/*     */     //   1147: getstatic androidx/compose/runtime/Composer.Companion : Landroidx/compose/runtime/Composer$Companion;
/*     */     //   1150: invokevirtual getEmpty : ()Ljava/lang/Object;
/*     */     //   1153: if_acmpne -> 1196
/*     */     //   1156: astore #25
/*     */     //   1158: astore #24
/*     */     //   1160: astore #23
/*     */     //   1162: iconst_0
/*     */     //   1163: istore #21
/*     */     //   1165: <illegal opcode> invoke : ()Lkotlin/jvm/functions/Function0;
/*     */     //   1170: astore #26
/*     */     //   1172: aload #23
/*     */     //   1174: aload #24
/*     */     //   1176: aload #25
/*     */     //   1178: aload #26
/*     */     //   1180: astore #21
/*     */     //   1182: aload #16
/*     */     //   1184: aload #21
/*     */     //   1186: invokeinterface updateRememberedValue : (Ljava/lang/Object;)V
/*     */     //   1191: aload #21
/*     */     //   1193: goto -> 1198
/*     */     //   1196: aload #19
/*     */     //   1198: nop
/*     */     //   1199: nop
/*     */     //   1200: nop
/*     */     //   1201: checkcast kotlin/jvm/functions/Function0
/*     */     //   1204: astore #15
/*     */     //   1206: aload_0
/*     */     //   1207: invokeinterface endReplaceGroup : ()V
/*     */     //   1212: aload #15
/*     */     //   1214: astore #12
/*     */     //   1216: aload_0
/*     */     //   1217: ldc -317005574
/*     */     //   1219: invokeinterface startReplaceGroup : (I)V
/*     */     //   1224: aload_0
/*     */     //   1225: astore #14
/*     */     //   1227: aload_0
/*     */     //   1228: aload #12
/*     */     //   1230: invokeinterface changed : (Ljava/lang/Object;)Z
/*     */     //   1235: istore #15
/*     */     //   1237: iconst_0
/*     */     //   1238: istore #16
/*     */     //   1240: aload #14
/*     */     //   1242: invokeinterface rememberedValue : ()Ljava/lang/Object;
/*     */     //   1247: astore #17
/*     */     //   1249: iconst_0
/*     */     //   1250: istore #18
/*     */     //   1252: iload #15
/*     */     //   1254: ifne -> 1268
/*     */     //   1257: aload #17
/*     */     //   1259: getstatic androidx/compose/runtime/Composer.Companion : Landroidx/compose/runtime/Composer$Companion;
/*     */     //   1262: invokevirtual getEmpty : ()Ljava/lang/Object;
/*     */     //   1265: if_acmpne -> 1315
/*     */     //   1268: astore #25
/*     */     //   1270: astore #24
/*     */     //   1272: astore #23
/*     */     //   1274: iconst_0
/*     */     //   1275: istore #19
/*     */     //   1277: new com/intellij/ml/llm/matterhorn/activation/state/junie/AiProJbaActivationKt$aiProJbaActivation$grazieJbaAuthStep$2$1
/*     */     //   1280: dup
/*     */     //   1281: aload #12
/*     */     //   1283: invokespecial <init> : (Ljava/lang/Object;)V
/*     */     //   1286: checkcast kotlin/jvm/functions/Function1
/*     */     //   1289: astore #26
/*     */     //   1291: aload #23
/*     */     //   1293: aload #24
/*     */     //   1295: aload #25
/*     */     //   1297: aload #26
/*     */     //   1299: astore #20
/*     */     //   1301: aload #14
/*     */     //   1303: aload #20
/*     */     //   1305: invokeinterface updateRememberedValue : (Ljava/lang/Object;)V
/*     */     //   1310: aload #20
/*     */     //   1312: goto -> 1317
/*     */     //   1315: aload #17
/*     */     //   1317: nop
/*     */     //   1318: nop
/*     */     //   1319: nop
/*     */     //   1320: checkcast kotlin/jvm/functions/Function1
/*     */     //   1323: astore #13
/*     */     //   1325: aload_0
/*     */     //   1326: invokeinterface endReplaceGroup : ()V
/*     */     //   1331: aload #13
/*     */     //   1333: aload_0
/*     */     //   1334: ldc -317003632
/*     */     //   1336: invokeinterface startReplaceGroup : (I)V
/*     */     //   1341: aload_0
/*     */     //   1342: astore #13
/*     */     //   1344: aload_0
/*     */     //   1345: aload #8
/*     */     //   1347: invokeinterface changedInstance : (Ljava/lang/Object;)Z
/*     */     //   1352: istore #14
/*     */     //   1354: nop
/*     */     //   1355: iconst_0
/*     */     //   1356: istore #15
/*     */     //   1358: aload #13
/*     */     //   1360: invokeinterface rememberedValue : ()Ljava/lang/Object;
/*     */     //   1365: astore #16
/*     */     //   1367: iconst_0
/*     */     //   1368: istore #17
/*     */     //   1370: iload #14
/*     */     //   1372: ifne -> 1386
/*     */     //   1375: aload #16
/*     */     //   1377: getstatic androidx/compose/runtime/Composer.Companion : Landroidx/compose/runtime/Composer$Companion;
/*     */     //   1380: invokevirtual getEmpty : ()Ljava/lang/Object;
/*     */     //   1383: if_acmpne -> 1438
/*     */     //   1386: astore #26
/*     */     //   1388: astore #25
/*     */     //   1390: astore #24
/*     */     //   1392: astore #23
/*     */     //   1394: iconst_0
/*     */     //   1395: istore #18
/*     */     //   1397: new com/intellij/ml/llm/matterhorn/activation/state/junie/AiProJbaActivationKt$aiProJbaActivation$grazieJbaAuthStep$3$1
/*     */     //   1400: dup
/*     */     //   1401: aload #8
/*     */     //   1403: aconst_null
/*     */     //   1404: invokespecial <init> : (Lcom/intellij/ml/llm/matterhorn/activation/state/model/AipLicenseJourney;Lkotlin/coroutines/Continuation;)V
/*     */     //   1407: checkcast kotlin/jvm/functions/Function1
/*     */     //   1410: astore #27
/*     */     //   1412: aload #23
/*     */     //   1414: aload #24
/*     */     //   1416: aload #25
/*     */     //   1418: aload #26
/*     */     //   1420: aload #27
/*     */     //   1422: astore #19
/*     */     //   1424: aload #13
/*     */     //   1426: aload #19
/*     */     //   1428: invokeinterface updateRememberedValue : (Ljava/lang/Object;)V
/*     */     //   1433: aload #19
/*     */     //   1435: goto -> 1440
/*     */     //   1438: aload #16
/*     */     //   1440: nop
/*     */     //   1441: nop
/*     */     //   1442: nop
/*     */     //   1443: checkcast kotlin/jvm/functions/Function1
/*     */     //   1446: astore #12
/*     */     //   1448: aload_0
/*     */     //   1449: invokeinterface endReplaceGroup : ()V
/*     */     //   1454: aload #12
/*     */     //   1456: aload #8
/*     */     //   1458: invokevirtual getAgreementAcceptStep : ()Lcom/intellij/ml/llm/matterhorn/activation/state/model/AipLicenseAgreementAcceptStep;
/*     */     //   1461: dup
/*     */     //   1462: ifnull -> 1471
/*     */     //   1465: invokevirtual getOnAgreementRequired : ()Lkotlin/jvm/functions/Function0;
/*     */     //   1468: goto -> 1473
/*     */     //   1471: pop
/*     */     //   1472: aconst_null
/*     */     //   1473: dup
/*     */     //   1474: ifnonnull -> 1584
/*     */     //   1477: pop
/*     */     //   1478: aload_0
/*     */     //   1479: ldc -316997444
/*     */     //   1481: invokeinterface startReplaceGroup : (I)V
/*     */     //   1486: aload_0
/*     */     //   1487: astore #16
/*     */     //   1489: iconst_0
/*     */     //   1490: istore #17
/*     */     //   1492: iconst_0
/*     */     //   1493: istore #18
/*     */     //   1495: aload #16
/*     */     //   1497: invokeinterface rememberedValue : ()Ljava/lang/Object;
/*     */     //   1502: astore #19
/*     */     //   1504: iconst_0
/*     */     //   1505: istore #20
/*     */     //   1507: aload #19
/*     */     //   1509: getstatic androidx/compose/runtime/Composer.Companion : Landroidx/compose/runtime/Composer$Companion;
/*     */     //   1512: invokevirtual getEmpty : ()Ljava/lang/Object;
/*     */     //   1515: if_acmpne -> 1566
/*     */     //   1518: astore #27
/*     */     //   1520: astore #26
/*     */     //   1522: astore #25
/*     */     //   1524: astore #24
/*     */     //   1526: astore #23
/*     */     //   1528: iconst_0
/*     */     //   1529: istore #21
/*     */     //   1531: <illegal opcode> invoke : ()Lkotlin/jvm/functions/Function0;
/*     */     //   1536: astore #28
/*     */     //   1538: aload #23
/*     */     //   1540: aload #24
/*     */     //   1542: aload #25
/*     */     //   1544: aload #26
/*     */     //   1546: aload #27
/*     */     //   1548: aload #28
/*     */     //   1550: astore #21
/*     */     //   1552: aload #16
/*     */     //   1554: aload #21
/*     */     //   1556: invokeinterface updateRememberedValue : (Ljava/lang/Object;)V
/*     */     //   1561: aload #21
/*     */     //   1563: goto -> 1568
/*     */     //   1566: aload #19
/*     */     //   1568: nop
/*     */     //   1569: nop
/*     */     //   1570: nop
/*     */     //   1571: checkcast kotlin/jvm/functions/Function0
/*     */     //   1574: astore #15
/*     */     //   1576: aload_0
/*     */     //   1577: invokeinterface endReplaceGroup : ()V
/*     */     //   1582: aload #15
/*     */     //   1584: astore #12
/*     */     //   1586: aload_0
/*     */     //   1587: ldc_w -316999273
/*     */     //   1590: invokeinterface startReplaceGroup : (I)V
/*     */     //   1595: aload_0
/*     */     //   1596: astore #14
/*     */     //   1598: aload_0
/*     */     //   1599: aload #12
/*     */     //   1601: invokeinterface changed : (Ljava/lang/Object;)Z
/*     */     //   1606: istore #15
/*     */     //   1608: iconst_0
/*     */     //   1609: istore #16
/*     */     //   1611: aload #14
/*     */     //   1613: invokeinterface rememberedValue : ()Ljava/lang/Object;
/*     */     //   1618: astore #17
/*     */     //   1620: iconst_0
/*     */     //   1621: istore #18
/*     */     //   1623: iload #15
/*     */     //   1625: ifne -> 1639
/*     */     //   1628: aload #17
/*     */     //   1630: getstatic androidx/compose/runtime/Composer.Companion : Landroidx/compose/runtime/Composer$Companion;
/*     */     //   1633: invokevirtual getEmpty : ()Ljava/lang/Object;
/*     */     //   1636: if_acmpne -> 1694
/*     */     //   1639: astore #27
/*     */     //   1641: astore #26
/*     */     //   1643: astore #25
/*     */     //   1645: astore #24
/*     */     //   1647: astore #23
/*     */     //   1649: iconst_0
/*     */     //   1650: istore #19
/*     */     //   1652: new com/intellij/ml/llm/matterhorn/activation/state/junie/AiProJbaActivationKt$aiProJbaActivation$grazieJbaAuthStep$5$1
/*     */     //   1655: dup
/*     */     //   1656: aload #12
/*     */     //   1658: invokespecial <init> : (Ljava/lang/Object;)V
/*     */     //   1661: checkcast kotlin/jvm/functions/Function1
/*     */     //   1664: astore #28
/*     */     //   1666: aload #23
/*     */     //   1668: aload #24
/*     */     //   1670: aload #25
/*     */     //   1672: aload #26
/*     */     //   1674: aload #27
/*     */     //   1676: aload #28
/*     */     //   1678: astore #20
/*     */     //   1680: aload #14
/*     */     //   1682: aload #20
/*     */     //   1684: invokeinterface updateRememberedValue : (Ljava/lang/Object;)V
/*     */     //   1689: aload #20
/*     */     //   1691: goto -> 1696
/*     */     //   1694: aload #17
/*     */     //   1696: nop
/*     */     //   1697: nop
/*     */     //   1698: nop
/*     */     //   1699: checkcast kotlin/jvm/functions/Function1
/*     */     //   1702: astore #13
/*     */     //   1704: aload_0
/*     */     //   1705: invokeinterface endReplaceGroup : ()V
/*     */     //   1710: aload #13
/*     */     //   1712: aload_0
/*     */     //   1713: iconst_0
/*     */     //   1714: invokestatic grazieJbaAuthStep-toclVnw : (Ljava/lang/String;Ljava/lang/String;Ljava/lang/String;Lkotlin/jvm/functions/Function1;Lkotlin/jvm/functions/Function1;Lkotlin/jvm/functions/Function1;Landroidx/compose/runtime/Composer;I)Lcom/intellij/ml/llm/matterhorn/activation/state/model/GrazieJbaAuthStep;
/*     */     //   1717: astore #11
/*     */     //   1719: aload_0
/*     */     //   1720: invokeinterface endMovableGroup : ()V
/*     */     //   1725: aload #11
/*     */     //   1727: astore #10
/*     */     //   1729: aload #10
/*     */     //   1731: checkcast com/intellij/ml/llm/matterhorn/activation/state/model/Journey
/*     */     //   1734: astore #12
/*     */     //   1736: iconst_0
/*     */     //   1737: istore #13
/*     */     //   1739: aload #12
/*     */     //   1741: invokeinterface getOutcome-07x5Wys : ()Ljava/lang/Object;
/*     */     //   1746: astore #14
/*     */     //   1748: iconst_0
/*     */     //   1749: istore #15
/*     */     //   1751: iconst_0
/*     */     //   1752: istore #16
/*     */     //   1754: aload #14
/*     */     //   1756: invokestatic isIncomplete-impl : (Ljava/lang/Object;)Z
/*     */     //   1759: istore #17
/*     */     //   1761: iload #17
/*     */     //   1763: iconst_1
/*     */     //   1764: if_icmpne -> 1829
/*     */     //   1767: aload #14
/*     */     //   1769: invokestatic incompleteOrNull-impl : (Ljava/lang/Object;)Ljava/lang/Object;
/*     */     //   1772: checkcast com/intellij/ml/llm/matterhorn/activation/state/model/GrazieJbaAuthPending
/*     */     //   1775: astore #18
/*     */     //   1777: iconst_0
/*     */     //   1778: istore #19
/*     */     //   1780: new com/intellij/ml/llm/matterhorn/activation/state/model/AiProJbaActivation
/*     */     //   1783: dup
/*     */     //   1784: aload_2
/*     */     //   1785: aload_3
/*     */     //   1786: aload #4
/*     */     //   1788: aload #6
/*     */     //   1790: aload #8
/*     */     //   1792: aload #10
/*     */     //   1794: getstatic com/intellij/ml/llm/matterhorn/activation/state/model/Outcome.Companion : Lcom/intellij/ml/llm/matterhorn/activation/state/model/Outcome$Companion;
/*     */     //   1797: aload #18
/*     */     //   1799: invokevirtual ofIncomplete-l12Rbqo : (Ljava/lang/Object;)Ljava/lang/Object;
/*     */     //   1802: aconst_null
/*     */     //   1803: invokespecial <init> : (Lcom/intellij/ml/llm/matterhorn/activation/state/model/RegionCheckStep;Lcom/intellij/ml/llm/matterhorn/activation/state/model/IdeLicenseAiAllowanceStep;Lcom/intellij/ml/llm/matterhorn/activation/state/model/JbaAuthStep;Lcom/intellij/ml/llm/matterhorn/activation/state/model/GrazieCloudUrlStep;Lcom/intellij/ml/llm/matterhorn/activation/state/model/AipLicenseJourney;Lcom/intellij/ml/llm/matterhorn/activation/state/model/GrazieJbaAuthStep;Ljava/lang/Object;Lkotlin/jvm/internal/DefaultConstructorMarker;)V
/*     */     //   1806: astore #20
/*     */     //   1808: invokestatic isTraceInProgress : ()Z
/*     */     //   1811: ifeq -> 1817
/*     */     //   1814: invokestatic traceEventEnd : ()V
/*     */     //   1817: aload_0
/*     */     //   1818: invokeinterface endReplaceGroup : ()V
/*     */     //   1823: aload #20
/*     */     //   1825: checkcast com/intellij/ml/llm/matterhorn/activation/state/model/AiaActivation
/*     */     //   1828: areturn
/*     */     //   1829: iload #17
/*     */     //   1831: ifne -> 1849
/*     */     //   1834: aload #14
/*     */     //   1836: invokestatic getOrNull-impl : (Ljava/lang/Object;)Ljava/lang/Object;
/*     */     //   1839: astore #21
/*     */     //   1841: iconst_0
/*     */     //   1842: istore #22
/*     */     //   1844: aload #21
/*     */     //   1846: goto -> 1857
/*     */     //   1849: new kotlin/NoWhenBranchMatchedException
/*     */     //   1852: dup
/*     */     //   1853: invokespecial <init> : ()V
/*     */     //   1856: athrow
/*     */     //   1857: nop
/*     */     //   1858: nop
/*     */     //   1859: checkcast com/intellij/ml/llm/matterhorn/activation/data/model/GrazieAuthData
/*     */     //   1862: astore #11
/*     */     //   1864: new com/intellij/ml/llm/matterhorn/activation/state/model/GrazieAuthContext
/*     */     //   1867: dup
/*     */     //   1868: aload #7
/*     */     //   1870: aload #11
/*     */     //   1872: aload #9
/*     */     //   1874: invokevirtual getProductType : ()Lcom/intellij/ml/llm/matterhorn/activation/data/model/AipLicenseProductType;
/*     */     //   1877: iconst_0
/*     */     //   1878: aconst_null
/*     */     //   1879: invokespecial <init> : (Ljava/lang/String;Lcom/intellij/ml/llm/matterhorn/activation/data/model/GrazieAuthData;Lcom/intellij/ml/llm/matterhorn/activation/data/model/AipLicenseProductType;ZLkotlin/jvm/internal/DefaultConstructorMarker;)V
/*     */     //   1882: astore #12
/*     */     //   1884: new com/intellij/ml/llm/matterhorn/activation/state/model/AiProJbaActivation
/*     */     //   1887: dup
/*     */     //   1888: aload_2
/*     */     //   1889: aload_3
/*     */     //   1890: aload #4
/*     */     //   1892: aload #6
/*     */     //   1894: aload #8
/*     */     //   1896: aload #10
/*     */     //   1898: aload #12
/*     */     //   1900: invokestatic done : (Ljava/lang/Object;)Ljava/lang/Object;
/*     */     //   1903: aconst_null
/*     */     //   1904: invokespecial <init> : (Lcom/intellij/ml/llm/matterhorn/activation/state/model/RegionCheckStep;Lcom/intellij/ml/llm/matterhorn/activation/state/model/IdeLicenseAiAllowanceStep;Lcom/intellij/ml/llm/matterhorn/activation/state/model/JbaAuthStep;Lcom/intellij/ml/llm/matterhorn/activation/state/model/GrazieCloudUrlStep;Lcom/intellij/ml/llm/matterhorn/activation/state/model/AipLicenseJourney;Lcom/intellij/ml/llm/matterhorn/activation/state/model/GrazieJbaAuthStep;Ljava/lang/Object;Lkotlin/jvm/internal/DefaultConstructorMarker;)V
/*     */     //   1907: astore #13
/*     */     //   1909: invokestatic isTraceInProgress : ()Z
/*     */     //   1912: ifeq -> 1918
/*     */     //   1915: invokestatic traceEventEnd : ()V
/*     */     //   1918: aload_0
/*     */     //   1919: invokeinterface endReplaceGroup : ()V
/*     */     //   1924: aload #13
/*     */     //   1926: checkcast com/intellij/ml/llm/matterhorn/activation/state/model/AiaActivation
/*     */     //   1929: areturn
/*     */     // Line number table:
/*     */     //   Java source line number -> byte code offset
/*     */     //   #18	-> 20
/*     */     //   #19	-> 23
/*     */     //   #105	-> 42
/*     */     //   #106	-> 53
/*     */     //   #107	-> 64
/*     */     //   #107	-> 77
/*     */     //   #108	-> 79
/*     */     //   #109	-> 87
/*     */     //   #110	-> 92
/*     */     //   #106	-> 94
/*     */     //   #105	-> 95
/*     */     //   #105	-> 96
/*     */     //   #19	-> 97
/*     */     //   #21	-> 116
/*     */     //   #25	-> 124
/*     */     //   #27	-> 132
/*     */     //   #29	-> 137
/*     */     //   #111	-> 146
/*     */     //   #112	-> 158
/*     */     //   #113	-> 161
/*     */     //   #114	-> 168
/*     */     //   #30	-> 187
/*     */     //   #115	-> 235
/*     */     //   #116	-> 250
/*     */     //   #115	-> 251
/*     */     //   #113	-> 254
/*     */     //   #112	-> 262
/*     */     //   #111	-> 263
/*     */     //   #33	-> 264
/*     */     //   #117	-> 274
/*     */     //   #118	-> 286
/*     */     //   #119	-> 289
/*     */     //   #120	-> 296
/*     */     //   #34	-> 315
/*     */     //   #121	-> 363
/*     */     //   #122	-> 378
/*     */     //   #121	-> 380
/*     */     //   #119	-> 383
/*     */     //   #118	-> 391
/*     */     //   #117	-> 392
/*     */     //   #33	-> 393
/*     */     //   #37	-> 398
/*     */     //   #123	-> 407
/*     */     //   #124	-> 419
/*     */     //   #125	-> 422
/*     */     //   #126	-> 429
/*     */     //   #38	-> 448
/*     */     //   #127	-> 496
/*     */     //   #128	-> 511
/*     */     //   #127	-> 512
/*     */     //   #125	-> 515
/*     */     //   #124	-> 523
/*     */     //   #123	-> 524
/*     */     //   #43	-> 529
/*     */     //   #44	-> 534
/*     */     //   #129	-> 544
/*     */     //   #130	-> 556
/*     */     //   #131	-> 559
/*     */     //   #132	-> 566
/*     */     //   #45	-> 585
/*     */     //   #133	-> 634
/*     */     //   #134	-> 649
/*     */     //   #133	-> 651
/*     */     //   #131	-> 654
/*     */     //   #130	-> 662
/*     */     //   #129	-> 663
/*     */     //   #44	-> 664
/*     */     //   #49	-> 672
/*     */     //   #50	-> 674
/*     */     //   #135	-> 713
/*     */     //   #136	-> 725
/*     */     //   #137	-> 736
/*     */     //   #137	-> 749
/*     */     //   #138	-> 751
/*     */     //   #139	-> 760
/*     */     //   #140	-> 765
/*     */     //   #136	-> 767
/*     */     //   #135	-> 768
/*     */     //   #135	-> 769
/*     */     //   #50	-> 770
/*     */     //   #135	-> 819
/*     */     //   #136	-> 831
/*     */     //   #137	-> 847
/*     */     //   #50	-> 852
/*     */     //   #137	-> 867
/*     */     //   #138	-> 869
/*     */     //   #139	-> 878
/*     */     //   #140	-> 883
/*     */     //   #136	-> 885
/*     */     //   #135	-> 886
/*     */     //   #135	-> 887
/*     */     //   #50	-> 888
/*     */     //   #48	-> 903
/*     */     //   #53	-> 908
/*     */     //   #141	-> 918
/*     */     //   #142	-> 930
/*     */     //   #143	-> 933
/*     */     //   #144	-> 940
/*     */     //   #54	-> 959
/*     */     //   #55	-> 963
/*     */     //   #56	-> 964
/*     */     //   #57	-> 965
/*     */     //   #58	-> 967
/*     */     //   #59	-> 969
/*     */     //   #54	-> 971
/*     */     //   #60	-> 972
/*     */     //   #54	-> 980
/*     */     //   #145	-> 1009
/*     */     //   #146	-> 1024
/*     */     //   #145	-> 1026
/*     */     //   #143	-> 1029
/*     */     //   #142	-> 1037
/*     */     //   #141	-> 1038
/*     */     //   #53	-> 1039
/*     */     //   #64	-> 1049
/*     */     //   #66	-> 1094
/*     */     //   #67	-> 1096
/*     */     //   #68	-> 1101
/*     */     //   #69	-> 1106
/*     */     //   #147	-> 1133
/*     */     //   #148	-> 1145
/*     */     //   #149	-> 1156
/*     */     //   #149	-> 1180
/*     */     //   #150	-> 1182
/*     */     //   #151	-> 1191
/*     */     //   #152	-> 1196
/*     */     //   #148	-> 1198
/*     */     //   #147	-> 1199
/*     */     //   #147	-> 1200
/*     */     //   #69	-> 1201
/*     */     //   #147	-> 1240
/*     */     //   #148	-> 1252
/*     */     //   #149	-> 1268
/*     */     //   #69	-> 1277
/*     */     //   #149	-> 1299
/*     */     //   #150	-> 1301
/*     */     //   #151	-> 1310
/*     */     //   #152	-> 1315
/*     */     //   #148	-> 1317
/*     */     //   #147	-> 1318
/*     */     //   #147	-> 1319
/*     */     //   #69	-> 1320
/*     */     //   #70	-> 1354
/*     */     //   #153	-> 1358
/*     */     //   #154	-> 1370
/*     */     //   #155	-> 1386
/*     */     //   #70	-> 1397
/*     */     //   #155	-> 1422
/*     */     //   #156	-> 1424
/*     */     //   #157	-> 1433
/*     */     //   #158	-> 1438
/*     */     //   #154	-> 1440
/*     */     //   #153	-> 1441
/*     */     //   #153	-> 1442
/*     */     //   #70	-> 1443
/*     */     //   #71	-> 1456
/*     */     //   #159	-> 1495
/*     */     //   #160	-> 1507
/*     */     //   #161	-> 1518
/*     */     //   #161	-> 1550
/*     */     //   #162	-> 1552
/*     */     //   #163	-> 1561
/*     */     //   #164	-> 1566
/*     */     //   #160	-> 1568
/*     */     //   #159	-> 1569
/*     */     //   #159	-> 1570
/*     */     //   #71	-> 1571
/*     */     //   #159	-> 1611
/*     */     //   #160	-> 1623
/*     */     //   #161	-> 1639
/*     */     //   #71	-> 1652
/*     */     //   #161	-> 1678
/*     */     //   #162	-> 1680
/*     */     //   #163	-> 1689
/*     */     //   #164	-> 1694
/*     */     //   #160	-> 1696
/*     */     //   #159	-> 1697
/*     */     //   #159	-> 1698
/*     */     //   #71	-> 1699
/*     */     //   #65	-> 1714
/*     */     //   #64	-> 1727
/*     */     //   #75	-> 1729
/*     */     //   #165	-> 1739
/*     */     //   #166	-> 1751
/*     */     //   #167	-> 1754
/*     */     //   #168	-> 1761
/*     */     //   #76	-> 1780
/*     */     //   #77	-> 1784
/*     */     //   #78	-> 1785
/*     */     //   #79	-> 1786
/*     */     //   #80	-> 1788
/*     */     //   #81	-> 1790
/*     */     //   #82	-> 1792
/*     */     //   #83	-> 1794
/*     */     //   #76	-> 1803
/*     */     //   #169	-> 1829
/*     */     //   #170	-> 1844
/*     */     //   #169	-> 1846
/*     */     //   #167	-> 1849
/*     */     //   #166	-> 1857
/*     */     //   #165	-> 1858
/*     */     //   #75	-> 1859
/*     */     //   #86	-> 1864
/*     */     //   #87	-> 1868
/*     */     //   #88	-> 1870
/*     */     //   #89	-> 1872
/*     */     //   #90	-> 1877
/*     */     //   #86	-> 1879
/*     */     //   #92	-> 1884
/*     */     //   #93	-> 1888
/*     */     //   #94	-> 1889
/*     */     //   #95	-> 1890
/*     */     //   #96	-> 1892
/*     */     //   #97	-> 1894
/*     */     //   #98	-> 1896
/*     */     //   #99	-> 1898
/*     */     //   #92	-> 1904
/*     */     // Local variable table:
/*     */     //   start	length	slot	name	descriptor
/*     */     //   69	5	8	$i$a$-cache-AiProJbaActivationKt$aiProJbaActivation$1	I
/*     */     //   79	10	8	value$iv	Ljava/lang/Object;
/*     */     //   53	42	7	$i$a$-let-ComposerKt$cache$1$iv	I
/*     */     //   50	45	6	it$iv	Ljava/lang/Object;
/*     */     //   42	55	5	$i$f$cache	I
/*     */     //   39	58	3	$this$cache$iv	Landroidx/compose/runtime/Composer;
/*     */     //   39	58	4	invalid$iv	Z
/*     */     //   187	48	12	$i$a$-completeOrElse-AiProJbaActivationKt$aiProJbaActivation$2	I
/*     */     //   184	51	11	regionPending	Lcom/intellij/ml/llm/matterhorn/activation/state/model/JunieRegionCheckProhibited;
/*     */     //   250	1	15	$i$a$-fold-impl-OutcomeKt$getOrElse$1$iv$iv	I
/*     */     //   247	4	14	it$iv$iv	Ljava/lang/Object;
/*     */     //   161	101	9	$i$f$fold-impl	I
/*     */     //   158	105	8	$i$f$getOrElse-G1CwGJM	I
/*     */     //   155	108	7	$this$getOrElse_u2dG1CwGJM$iv$iv	Ljava/lang/Object;
/*     */     //   146	118	6	$i$f$completeOrElse	I
/*     */     //   143	121	5	$this$completeOrElse$iv	Lcom/intellij/ml/llm/matterhorn/activation/state/model/Journey;
/*     */     //   315	48	13	$i$a$-completeOrElse-AiProJbaActivationKt$aiProJbaActivation$jbaAuthData$1	I
/*     */     //   312	51	12	authPending	Lcom/intellij/ml/llm/matterhorn/activation/state/model/JbaAuthPending;
/*     */     //   378	2	16	$i$a$-fold-impl-OutcomeKt$getOrElse$1$iv$iv	I
/*     */     //   375	5	15	it$iv$iv	Ljava/lang/Object;
/*     */     //   289	102	10	$i$f$fold-impl	I
/*     */     //   286	106	9	$i$f$getOrElse-G1CwGJM	I
/*     */     //   283	109	8	$this$getOrElse_u2dG1CwGJM$iv$iv	Ljava/lang/Object;
/*     */     //   274	119	7	$i$f$completeOrElse	I
/*     */     //   271	122	6	$this$completeOrElse$iv	Lcom/intellij/ml/llm/matterhorn/activation/state/model/Journey;
/*     */     //   448	48	13	$i$a$-completeOrElse-AiProJbaActivationKt$aiProJbaActivation$3	I
/*     */     //   445	51	12	allowancePending	Lcom/intellij/ml/llm/matterhorn/activation/state/model/IdeLicenseAiAllowancePending;
/*     */     //   511	1	16	$i$a$-fold-impl-OutcomeKt$getOrElse$1$iv$iv	I
/*     */     //   508	4	15	it$iv$iv	Ljava/lang/Object;
/*     */     //   422	101	10	$i$f$fold-impl	I
/*     */     //   419	105	9	$i$f$getOrElse-G1CwGJM	I
/*     */     //   416	108	8	$this$getOrElse_u2dG1CwGJM$iv$iv	Ljava/lang/Object;
/*     */     //   407	118	7	$i$f$completeOrElse	I
/*     */     //   404	121	6	$this$completeOrElse$iv	Lcom/intellij/ml/llm/matterhorn/activation/state/model/Journey;
/*     */     //   585	49	15	$i$a$-completeOrElse-AiProJbaActivationKt$aiProJbaActivation$grazieApiUrl$1	I
/*     */     //   582	52	14	urlPending	Lcom/intellij/ml/llm/matterhorn/activation/state/model/GrazieCloudUrlPending;
/*     */     //   649	2	18	$i$a$-fold-impl-OutcomeKt$getOrElse$1$iv$iv	I
/*     */     //   646	5	17	it$iv$iv	Ljava/lang/Object;
/*     */     //   559	103	12	$i$f$fold-impl	I
/*     */     //   556	107	11	$i$f$getOrElse-G1CwGJM	I
/*     */     //   553	110	10	$this$getOrElse_u2dG1CwGJM$iv$iv	Ljava/lang/Object;
/*     */     //   544	120	9	$i$f$completeOrElse	I
/*     */     //   541	123	8	$this$completeOrElse$iv	Lcom/intellij/ml/llm/matterhorn/activation/state/model/Journey;
/*     */     //   741	5	18	$i$a$-cache-AiProJbaActivationKt$aiProJbaActivation$licenseJourney$1	I
/*     */     //   751	11	18	value$iv	Ljava/lang/Object;
/*     */     //   725	43	17	$i$a$-let-ComposerKt$cache$1$iv	I
/*     */     //   722	46	16	it$iv	Ljava/lang/Object;
/*     */     //   713	57	15	$i$f$cache	I
/*     */     //   710	60	13	$this$cache$iv	Landroidx/compose/runtime/Composer;
/*     */     //   710	60	14	invalid$iv	Z
/*     */     //   852	12	16	$i$a$-cache-AiProJbaActivationKt$aiProJbaActivation$licenseJourney$2	I
/*     */     //   869	11	17	value$iv	Ljava/lang/Object;
/*     */     //   831	55	15	$i$a$-let-ComposerKt$cache$1$iv	I
/*     */     //   828	58	14	it$iv	Ljava/lang/Object;
/*     */     //   819	69	13	$i$f$cache	I
/*     */     //   816	72	11	$this$cache$iv	Landroidx/compose/runtime/Composer;
/*     */     //   816	72	12	invalid$iv	Z
/*     */     //   959	50	17	$i$a$-completeOrElse-AiProJbaActivationKt$aiProJbaActivation$activeLicense$1	I
/*     */     //   956	53	16	licensePending	Lcom/intellij/ml/llm/matterhorn/activation/state/model/AipLicensePending;
/*     */     //   1024	2	20	$i$a$-fold-impl-OutcomeKt$getOrElse$1$iv$iv	I
/*     */     //   1021	5	19	it$iv$iv	Ljava/lang/Object;
/*     */     //   933	104	14	$i$f$fold-impl	I
/*     */     //   930	108	13	$i$f$getOrElse-G1CwGJM	I
/*     */     //   927	111	12	$this$getOrElse_u2dG1CwGJM$iv$iv	Ljava/lang/Object;
/*     */     //   918	121	11	$i$f$completeOrElse	I
/*     */     //   915	124	10	$this$completeOrElse$iv	Lcom/intellij/ml/llm/matterhorn/activation/state/model/Journey;
/*     */     //   1165	5	21	$i$a$-cache-AiProJbaActivationKt$aiProJbaActivation$grazieJbaAuthStep$1	I
/*     */     //   1182	11	21	value$iv	Ljava/lang/Object;
/*     */     //   1145	54	20	$i$a$-let-ComposerKt$cache$1$iv	I
/*     */     //   1142	57	19	it$iv	Ljava/lang/Object;
/*     */     //   1133	68	18	$i$f$cache	I
/*     */     //   1130	71	16	$this$cache$iv	Landroidx/compose/runtime/Composer;
/*     */     //   1130	71	17	invalid$iv	Z
/*     */     //   1277	12	19	$i$a$-cache-AiProJbaActivationKt$aiProJbaActivation$grazieJbaAuthStep$2	I
/*     */     //   1301	11	20	value$iv	Ljava/lang/Object;
/*     */     //   1252	66	18	$i$a$-let-ComposerKt$cache$1$iv	I
/*     */     //   1249	69	17	it$iv	Ljava/lang/Object;
/*     */     //   1240	80	16	$i$f$cache	I
/*     */     //   1237	83	14	$this$cache$iv	Landroidx/compose/runtime/Composer;
/*     */     //   1237	83	15	invalid$iv	Z
/*     */     //   1397	13	18	$i$a$-cache-AiProJbaActivationKt$aiProJbaActivation$grazieJbaAuthStep$3	I
/*     */     //   1424	11	19	value$iv	Ljava/lang/Object;
/*     */     //   1370	71	17	$i$a$-let-ComposerKt$cache$1$iv	I
/*     */     //   1367	74	16	it$iv	Ljava/lang/Object;
/*     */     //   1358	85	15	$i$f$cache	I
/*     */     //   1355	88	13	$this$cache$iv	Landroidx/compose/runtime/Composer;
/*     */     //   1355	88	14	invalid$iv	Z
/*     */     //   1531	5	21	$i$a$-cache-AiProJbaActivationKt$aiProJbaActivation$grazieJbaAuthStep$4	I
/*     */     //   1552	11	21	value$iv	Ljava/lang/Object;
/*     */     //   1507	62	20	$i$a$-let-ComposerKt$cache$1$iv	I
/*     */     //   1504	65	19	it$iv	Ljava/lang/Object;
/*     */     //   1495	76	18	$i$f$cache	I
/*     */     //   1492	79	16	$this$cache$iv	Landroidx/compose/runtime/Composer;
/*     */     //   1492	79	17	invalid$iv	Z
/*     */     //   1652	12	19	$i$a$-cache-AiProJbaActivationKt$aiProJbaActivation$grazieJbaAuthStep$5	I
/*     */     //   1680	11	20	value$iv	Ljava/lang/Object;
/*     */     //   1623	74	18	$i$a$-let-ComposerKt$cache$1$iv	I
/*     */     //   1620	77	17	it$iv	Ljava/lang/Object;
/*     */     //   1611	88	16	$i$f$cache	I
/*     */     //   1608	91	14	$this$cache$iv	Landroidx/compose/runtime/Composer;
/*     */     //   1608	91	15	invalid$iv	Z
/*     */     //   1780	49	19	$i$a$-completeOrElse-AiProJbaActivationKt$aiProJbaActivation$grazieAuthData$1	I
/*     */     //   1777	52	18	accessPending	Lcom/intellij/ml/llm/matterhorn/activation/state/model/GrazieJbaAuthPending;
/*     */     //   1844	2	22	$i$a$-fold-impl-OutcomeKt$getOrElse$1$iv$iv	I
/*     */     //   1841	5	21	it$iv$iv	Ljava/lang/Object;
/*     */     //   1754	103	16	$i$f$fold-impl	I
/*     */     //   1751	107	15	$i$f$getOrElse-G1CwGJM	I
/*     */     //   1748	110	14	$this$getOrElse_u2dG1CwGJM$iv$iv	Ljava/lang/Object;
/*     */     //   1739	120	13	$i$f$completeOrElse	I
/*     */     //   1736	123	12	$this$completeOrElse$iv	Lcom/intellij/ml/llm/matterhorn/activation/state/model/Journey;
/*     */     //   120	1810	2	regionStep	Lcom/intellij/ml/llm/matterhorn/activation/state/model/RegionCheckStep;
/*     */     //   128	1802	3	aiAllowanceStep	Lcom/intellij/ml/llm/matterhorn/activation/state/model/IdeLicenseAiAllowanceStep;
/*     */     //   137	1793	4	jbaAuthStep	Lcom/intellij/ml/llm/matterhorn/activation/state/model/JbaAuthStep;
/*     */     //   398	1532	5	jbaAuthData	Lcom/intellij/ml/llm/matterhorn/activation/data/model/JbaAuthData;
/*     */     //   534	1396	6	grazieCloudUrlStep	Lcom/intellij/ml/llm/matterhorn/activation/state/model/GrazieCloudUrlStep;
/*     */     //   672	1258	7	grazieApiUrl	Ljava/lang/String;
/*     */     //   908	1022	8	licenseJourney	Lcom/intellij/ml/llm/matterhorn/activation/state/model/AipLicenseJourney;
/*     */     //   1044	886	9	activeLicense	Lcom/intellij/ml/llm/matterhorn/activation/data/model/AipLicense;
/*     */     //   1729	201	10	grazieJbaAuthStep	Lcom/intellij/ml/llm/matterhorn/activation/state/model/GrazieJbaAuthStep;
/*     */     //   1864	66	11	grazieAuthData	Lcom/intellij/ml/llm/matterhorn/activation/data/model/GrazieAuthData;
/*     */     //   1884	46	12	grazieAuthContext	Lcom/intellij/ml/llm/matterhorn/activation/state/model/GrazieAuthContext;
/*     */     //   0	1930	0	$composer	Landroidx/compose/runtime/Composer;
/*     */     //   0	1930	1	$changed	I
/*     */   }
/*     */ 
/*     */ 
/*     */ 
/*     */ 
/*     */ 
/*     */ 
/*     */   
/*     */   private static final Unit aiProJbaActivation$lambda$7$lambda$6() {
/*  50 */     return Unit.INSTANCE;
/*     */   }
/*     */ 
/*     */ 
/*     */ 
/*     */ 
/*     */ 
/*     */ 
/*     */ 
/*     */ 
/*     */ 
/*     */ 
/*     */ 
/*     */ 
/*     */ 
/*     */ 
/*     */ 
/*     */   
/*     */   private static final Unit aiProJbaActivation$lambda$12$lambda$11() {
/*  69 */     return Unit.INSTANCE; } @DebugMetadata(f = "aiProJbaActivation.kt", l = {}, i = {}, s = {}, n = {}, m = "invokeSuspend", c = "com.intellij.ml.llm.matterhorn.activation.state.junie.AiProJbaActivationKt$aiProJbaActivation$grazieJbaAuthStep$3$1") @Metadata(mv = {2, 1, 0}, k = 3, xi = 48, d1 = {"\000\006\n\000\n\002\020\002\020\000\032\0020\001H\n"}, d2 = {"<anonymous>", ""})
/*  70 */   static final class AiProJbaActivationKt$aiProJbaActivation$grazieJbaAuthStep$3$1 extends SuspendLambda implements Function1<Continuation<? super Unit>, Object> { int label; public final Object invokeSuspend(Object $result) { IntrinsicsKt.getCOROUTINE_SUSPENDED(); switch (this.label) { case 0: ResultKt.throwOnFailure(SYNTHETIC_LOCAL_VARIABLE_1); this.$licenseJourney.getLicenseFetchStep().getOnFetchRequested().invoke(); return Unit.INSTANCE; }  throw new IllegalStateException("call to 'resume' before 'invoke' with coroutine"); } AiProJbaActivationKt$aiProJbaActivation$grazieJbaAuthStep$3$1(AipLicenseJourney $licenseJourney, Continuation $completion) { super(1, $completion); } public final Continuation<Unit> create(Continuation<? super AiProJbaActivationKt$aiProJbaActivation$grazieJbaAuthStep$3$1> $completion) { return (Continuation<Unit>)new AiProJbaActivationKt$aiProJbaActivation$grazieJbaAuthStep$3$1(this.$licenseJourney, $completion); } public final Object invoke(Continuation<?> p1) { return ((AiProJbaActivationKt$aiProJbaActivation$grazieJbaAuthStep$3$1)create(p1)).invokeSuspend(Unit.INSTANCE); } }
/*  71 */    private static final Unit aiProJbaActivation$lambda$16$lambda$15() { return Unit.INSTANCE; }
/*     */ 
/*     */ 
/*     */ 
/*     */ 
/*     */ 
/*     */ 
/*     */ 
/*     */ 
/*     */ 
/*     */ 
/*     */ 
/*     */ 
/*     */ 
/*     */ 
/*     */ 
/*     */ 
/*     */ 
/*     */ 
/*     */ 
/*     */ 
/*     */ 
/*     */ 
/*     */ 
/*     */ 
/*     */ 
/*     */ 
/*     */ 
/*     */ 
/*     */ 
/*     */   
/*     */   static {
/* 103 */     int $i$f$fileLogger = 0;
/*     */ 
/*     */ 
/*     */ 
/*     */ 
/*     */ 
/*     */ 
/*     */ 
/*     */ 
/*     */ 
/*     */ 
/*     */ 
/*     */ 
/*     */ 
/*     */ 
/*     */ 
/*     */ 
/*     */ 
/*     */ 
/*     */ 
/*     */ 
/*     */ 
/*     */ 
/*     */ 
/*     */ 
/*     */ 
/*     */ 
/*     */ 
/*     */ 
/*     */ 
/*     */ 
/*     */ 
/*     */ 
/*     */ 
/*     */ 
/*     */ 
/*     */ 
/*     */ 
/*     */ 
/*     */ 
/*     */ 
/*     */ 
/*     */ 
/*     */ 
/*     */ 
/*     */ 
/*     */ 
/*     */ 
/*     */ 
/*     */ 
/*     */ 
/*     */ 
/*     */ 
/*     */ 
/*     */ 
/*     */ 
/*     */ 
/*     */ 
/*     */ 
/*     */ 
/*     */ 
/*     */ 
/*     */ 
/*     */ 
/*     */ 
/*     */ 
/*     */ 
/*     */     
/* 171 */     int $i$f$currentClassLogger = 0;
/* 172 */     Class<?> clazz$iv$iv = MethodHandles.lookup().lookupClass();
/* 173 */     Intrinsics.checkNotNullExpressionValue(Logger.getInstance(clazz$iv$iv), "getInstance(...)"); LOG = Logger.getInstance(clazz$iv$iv);
/*     */   }
/*     */ }


/* Location:              C:\Users\yuzum\Downloads\ej-release-243.132.63.zip!\ej\lib\ej-243.132.63.jar!\com\intellij\ml\llm\matterhorn\activation\state\junie\AiProJbaActivationKt.class
 * Java compiler version: 17 (61.0)
 * JD-Core Version:       1.1.3
 */