/*     */ package com.intellij.ml.llm.matterhorn.activation.state.junie;
/*     */ import com.intellij.ml.llm.matterhorn.activation.data.model.GrazieApiUrl;
/*     */ import com.intellij.ml.llm.matterhorn.activation.data.model.result.GrazieResult;
/*     */ import com.intellij.ml.llm.matterhorn.activation.state.junie.activity.ActivityCallable;
/*     */ import com.intellij.openapi.diagnostic.Logger;
/*     */ import kotlin.Metadata;
/*     */ import kotlin.ResultKt;
/*     */ import kotlin.Unit;
/*     */ import kotlin.coroutines.Continuation;
/*     */ import kotlin.coroutines.intrinsics.IntrinsicsKt;
/*     */ import kotlin.coroutines.jvm.internal.ContinuationImpl;
/*     */ import kotlin.coroutines.jvm.internal.DebugMetadata;
/*     */ import kotlin.coroutines.jvm.internal.SuspendLambda;
/*     */ import kotlin.jvm.functions.Function2;
/*     */ import kotlin.time.DurationKt;
/*     */ import kotlin.time.DurationUnit;
/*     */ import kotlinx.coroutines.CoroutineScope;
/*     */ import kotlinx.coroutines.TimeoutKt;
/*     */ import org.jetbrains.annotations.NotNull;
/*     */ import org.jetbrains.annotations.Nullable;
/*     */ 
/*     */ @Metadata(mv = {2, 1, 0}, k = 2, xi = 48, d1 = {"\000(\n\000\n\002\030\002\n\000\n\002\030\002\n\002\b\002\n\002\030\002\n\002\030\002\n\000\n\002\020\016\n\002\b\002\n\002\030\002\n\000\032\027\020\000\032\0020\0012\b\b\002\020\002\032\0020\003H\001¢\006\002\020\004\032\034\020\005\032\b\022\004\022\0020\0070\0062\006\020\b\032\0020\tH@¢\006\002\020\n\"\016\020\013\032\0020\fX\004¢\006\002\n\000¨\006\r"}, d2 = {"grazieCloudUrlStep", "Lcom/intellij/ml/llm/matterhorn/activation/state/model/GrazieCloudUrlStep;", "aiaConfig", "Lcom/intellij/ml/llm/matterhorn/activation/config/AiaConfig;", "(Lcom/intellij/ml/llm/matterhorn/activation/config/AiaConfig;Landroidx/compose/runtime/Composer;II)Lcom/intellij/ml/llm/matterhorn/activation/state/model/GrazieCloudUrlStep;", "resolveApiUrl", "Lcom/intellij/ml/llm/matterhorn/activation/data/model/result/GrazieResult;", "Lcom/intellij/ml/llm/matterhorn/activation/data/model/GrazieApiUrl;", "configJsonRawUrl", "", "(Ljava/lang/String;Lkotlin/coroutines/Continuation;)Ljava/lang/Object;", "LOG", "Lcom/intellij/openapi/diagnostic/Logger;", "state.junie.impl"})
/*     */ @SourceDebugExtension({"SMAP\ngrazieCloudUrlStep.kt\nKotlin\n*S Kotlin\n*F\n+ 1 grazieCloudUrlStep.kt\ncom/intellij/ml/llm/matterhorn/activation/state/junie/GrazieCloudUrlStepKt\n+ 2 service.kt\ncom/intellij/openapi/components/ServiceKt\n+ 3 Composer.kt\nandroidx/compose/runtime/ComposerKt\n+ 4 logger.kt\ncom/intellij/openapi/diagnostic/LoggerKt\n*L\n1#1,82:1\n40#2,3:83\n1225#3,6:86\n1225#3,6:92\n1225#3,6:98\n58#4:104\n36#4,2:105\n*S KotlinDebug\n*F\n+ 1 grazieCloudUrlStep.kt\ncom/intellij/ml/llm/matterhorn/activation/state/junie/GrazieCloudUrlStepKt\n*L\n34#1:83,3\n35#1:86,6\n45#1:92,6\n50#1:98,6\n81#1:104\n81#1:105,2\n*E\n"})
/*     */ public final class GrazieCloudUrlStepKt {
/*     */   @NotNull
/*     */   private static final Logger LOG;
/*     */   
/*     */   @Composable
/*     */   @NotNull
/*     */   public static final GrazieCloudUrlStep grazieCloudUrlStep(@Nullable AiaConfig aiaConfig, @Nullable Composer $composer, int $changed, int paramInt1) {
/*     */     // Byte code:
/*     */     //   0: aload_1
/*     */     //   1: ldc -2140782967
/*     */     //   3: invokeinterface startReplaceGroup : (I)V
/*     */     //   8: iload_3
/*     */     //   9: iconst_1
/*     */     //   10: iand
/*     */     //   11: ifeq -> 104
/*     */     //   14: iconst_0
/*     */     //   15: istore #4
/*     */     //   17: ldc com/intellij/ml/llm/matterhorn/activation/config/AiaConfig
/*     */     //   19: astore #5
/*     */     //   21: invokestatic getApplication : ()Lcom/intellij/openapi/application/Application;
/*     */     //   24: aload #5
/*     */     //   26: invokeinterface getService : (Ljava/lang/Class;)Ljava/lang/Object;
/*     */     //   31: dup
/*     */     //   32: ifnonnull -> 99
/*     */     //   35: pop
/*     */     //   36: new java/lang/RuntimeException
/*     */     //   39: dup
/*     */     //   40: new java/lang/StringBuilder
/*     */     //   43: dup
/*     */     //   44: invokespecial <init> : ()V
/*     */     //   47: ldc 'Cannot find service '
/*     */     //   49: invokevirtual append : (Ljava/lang/String;)Ljava/lang/StringBuilder;
/*     */     //   52: aload #5
/*     */     //   54: invokevirtual getName : ()Ljava/lang/String;
/*     */     //   57: invokevirtual append : (Ljava/lang/String;)Ljava/lang/StringBuilder;
/*     */     //   60: ldc ' (classloader='
/*     */     //   62: invokevirtual append : (Ljava/lang/String;)Ljava/lang/StringBuilder;
/*     */     //   65: aload #5
/*     */     //   67: invokevirtual getClassLoader : ()Ljava/lang/ClassLoader;
/*     */     //   70: invokevirtual append : (Ljava/lang/Object;)Ljava/lang/StringBuilder;
/*     */     //   73: ldc ', client='
/*     */     //   75: invokevirtual append : (Ljava/lang/String;)Ljava/lang/StringBuilder;
/*     */     //   78: getstatic com/intellij/codeWithMe/ClientId.Companion : Lcom/intellij/codeWithMe/ClientId$Companion;
/*     */     //   81: invokevirtual getCurrentOrNull : ()Lcom/intellij/codeWithMe/ClientId;
/*     */     //   84: invokevirtual append : (Ljava/lang/Object;)Ljava/lang/StringBuilder;
/*     */     //   87: bipush #41
/*     */     //   89: invokevirtual append : (C)Ljava/lang/StringBuilder;
/*     */     //   92: invokevirtual toString : ()Ljava/lang/String;
/*     */     //   95: invokespecial <init> : (Ljava/lang/String;)V
/*     */     //   98: athrow
/*     */     //   99: nop
/*     */     //   100: checkcast com/intellij/ml/llm/matterhorn/activation/config/AiaConfig
/*     */     //   103: astore_0
/*     */     //   104: invokestatic isTraceInProgress : ()Z
/*     */     //   107: ifeq -> 119
/*     */     //   110: ldc -2140782967
/*     */     //   112: iload_2
/*     */     //   113: iconst_m1
/*     */     //   114: ldc 'com.intellij.ml.llm.matterhorn.activation.state.junie.grazieCloudUrlStep (grazieCloudUrlStep.kt:33)'
/*     */     //   116: invokestatic traceEventStart : (IIILjava/lang/String;)V
/*     */     //   119: getstatic com/intellij/ml/llm/matterhorn/activation/state/junie/GrazieCloudUrlStepKt.LOG : Lcom/intellij/openapi/diagnostic/Logger;
/*     */     //   122: aload_1
/*     */     //   123: ldc -1374177979
/*     */     //   125: invokeinterface startReplaceGroup : (I)V
/*     */     //   130: aload_1
/*     */     //   131: astore #5
/*     */     //   133: iconst_0
/*     */     //   134: istore #6
/*     */     //   136: iconst_0
/*     */     //   137: istore #7
/*     */     //   139: aload #5
/*     */     //   141: invokeinterface rememberedValue : ()Ljava/lang/Object;
/*     */     //   146: astore #8
/*     */     //   148: iconst_0
/*     */     //   149: istore #9
/*     */     //   151: aload #8
/*     */     //   153: getstatic androidx/compose/runtime/Composer.Companion : Landroidx/compose/runtime/Composer$Companion;
/*     */     //   156: invokevirtual getEmpty : ()Ljava/lang/Object;
/*     */     //   159: if_acmpne -> 191
/*     */     //   162: astore #16
/*     */     //   164: iconst_0
/*     */     //   165: istore #10
/*     */     //   167: <illegal opcode> invoke : ()Lkotlin/jvm/functions/Function0;
/*     */     //   172: aload #16
/*     */     //   174: swap
/*     */     //   175: astore #10
/*     */     //   177: aload #5
/*     */     //   179: aload #10
/*     */     //   181: invokeinterface updateRememberedValue : (Ljava/lang/Object;)V
/*     */     //   186: aload #10
/*     */     //   188: goto -> 193
/*     */     //   191: aload #8
/*     */     //   193: nop
/*     */     //   194: nop
/*     */     //   195: nop
/*     */     //   196: checkcast kotlin/jvm/functions/Function0
/*     */     //   199: astore #4
/*     */     //   201: aload_1
/*     */     //   202: invokeinterface endReplaceGroup : ()V
/*     */     //   207: aload #4
/*     */     //   209: aload_1
/*     */     //   210: bipush #48
/*     */     //   212: invokestatic TraceComposition : (Lcom/intellij/openapi/diagnostic/Logger;Lkotlin/jvm/functions/Function0;Landroidx/compose/runtime/Composer;I)V
/*     */     //   215: aload_0
/*     */     //   216: invokevirtual getGrazieStagingUrl-0_pFto0 : ()Ljava/lang/String;
/*     */     //   219: astore #4
/*     */     //   221: aload #4
/*     */     //   223: ifnull -> 263
/*     */     //   226: new com/intellij/ml/llm/matterhorn/activation/state/model/GrazieCloudUrlStep
/*     */     //   229: dup
/*     */     //   230: aconst_null
/*     */     //   231: aload #4
/*     */     //   233: invokestatic box-impl : (Ljava/lang/String;)Lcom/intellij/ml/llm/matterhorn/activation/data/model/GrazieApiUrl;
/*     */     //   236: invokestatic done : (Ljava/lang/Object;)Ljava/lang/Object;
/*     */     //   239: aconst_null
/*     */     //   240: invokespecial <init> : (Lkotlin/jvm/functions/Function0;Ljava/lang/Object;Lkotlin/jvm/internal/DefaultConstructorMarker;)V
/*     */     //   243: astore #5
/*     */     //   245: invokestatic isTraceInProgress : ()Z
/*     */     //   248: ifeq -> 254
/*     */     //   251: invokestatic traceEventEnd : ()V
/*     */     //   254: aload_1
/*     */     //   255: invokeinterface endReplaceGroup : ()V
/*     */     //   260: aload #5
/*     */     //   262: areturn
/*     */     //   263: aload_0
/*     */     //   264: invokevirtual getGrazieConfigJsonRawUrl : ()Ljava/lang/String;
/*     */     //   267: astore #5
/*     */     //   269: getstatic com/intellij/ml/llm/matterhorn/activation/state/junie/GrazieResultMapper.Companion : Lcom/intellij/ml/llm/matterhorn/activation/state/junie/GrazieResultMapper$Companion;
/*     */     //   272: invokevirtual invoke : ()Lcom/intellij/ml/llm/matterhorn/activation/state/junie/GrazieResultMapper;
/*     */     //   275: checkcast com/intellij/ml/llm/matterhorn/activation/state/junie/activity/OpResultMapper
/*     */     //   278: aload_1
/*     */     //   279: iconst_0
/*     */     //   280: invokestatic rememberActivityLauncher : (Lcom/intellij/ml/llm/matterhorn/activation/state/junie/activity/OpResultMapper;Landroidx/compose/runtime/Composer;I)Lcom/intellij/ml/llm/matterhorn/activation/state/junie/activity/ActivityLauncher;
/*     */     //   283: astore #6
/*     */     //   285: aload #6
/*     */     //   287: aload_1
/*     */     //   288: ldc -1374165259
/*     */     //   290: invokeinterface startReplaceGroup : (I)V
/*     */     //   295: aload_1
/*     */     //   296: astore #9
/*     */     //   298: aload_1
/*     */     //   299: aload #5
/*     */     //   301: invokeinterface changed : (Ljava/lang/Object;)Z
/*     */     //   306: istore #10
/*     */     //   308: iconst_0
/*     */     //   309: istore #11
/*     */     //   311: aload #9
/*     */     //   313: invokeinterface rememberedValue : ()Ljava/lang/Object;
/*     */     //   318: astore #12
/*     */     //   320: iconst_0
/*     */     //   321: istore #13
/*     */     //   323: iload #10
/*     */     //   325: ifne -> 339
/*     */     //   328: aload #12
/*     */     //   330: getstatic androidx/compose/runtime/Composer.Companion : Landroidx/compose/runtime/Composer$Companion;
/*     */     //   333: invokevirtual getEmpty : ()Ljava/lang/Object;
/*     */     //   336: if_acmpne -> 376
/*     */     //   339: astore #16
/*     */     //   341: iconst_0
/*     */     //   342: istore #14
/*     */     //   344: new com/intellij/ml/llm/matterhorn/activation/state/junie/GrazieCloudUrlStepKt$grazieCloudUrlStep$resolveUrlCallable$1$1
/*     */     //   347: dup
/*     */     //   348: aload #5
/*     */     //   350: aconst_null
/*     */     //   351: invokespecial <init> : (Ljava/lang/String;Lkotlin/coroutines/Continuation;)V
/*     */     //   354: checkcast kotlin/jvm/functions/Function1
/*     */     //   357: aload #16
/*     */     //   359: swap
/*     */     //   360: astore #15
/*     */     //   362: aload #9
/*     */     //   364: aload #15
/*     */     //   366: invokeinterface updateRememberedValue : (Ljava/lang/Object;)V
/*     */     //   371: aload #15
/*     */     //   373: goto -> 378
/*     */     //   376: aload #12
/*     */     //   378: nop
/*     */     //   379: nop
/*     */     //   380: nop
/*     */     //   381: checkcast kotlin/jvm/functions/Function1
/*     */     //   384: astore #8
/*     */     //   386: aload_1
/*     */     //   387: invokeinterface endReplaceGroup : ()V
/*     */     //   392: aload #8
/*     */     //   394: invokestatic bind : (Lcom/intellij/ml/llm/matterhorn/activation/state/junie/activity/ActivityLauncher;Lkotlin/jvm/functions/Function1;)Lcom/intellij/ml/llm/matterhorn/activation/state/junie/activity/ActivityCallable;
/*     */     //   397: astore #7
/*     */     //   399: aload #5
/*     */     //   401: aload_1
/*     */     //   402: ldc -1374161427
/*     */     //   404: invokeinterface startReplaceGroup : (I)V
/*     */     //   409: aload_1
/*     */     //   410: astore #9
/*     */     //   412: aload_1
/*     */     //   413: aload #7
/*     */     //   415: invokeinterface changedInstance : (Ljava/lang/Object;)Z
/*     */     //   420: istore #10
/*     */     //   422: iconst_0
/*     */     //   423: istore #11
/*     */     //   425: aload #9
/*     */     //   427: invokeinterface rememberedValue : ()Ljava/lang/Object;
/*     */     //   432: astore #12
/*     */     //   434: iconst_0
/*     */     //   435: istore #13
/*     */     //   437: iload #10
/*     */     //   439: ifne -> 453
/*     */     //   442: aload #12
/*     */     //   444: getstatic androidx/compose/runtime/Composer.Companion : Landroidx/compose/runtime/Composer$Companion;
/*     */     //   447: invokevirtual getEmpty : ()Ljava/lang/Object;
/*     */     //   450: if_acmpne -> 490
/*     */     //   453: astore #16
/*     */     //   455: iconst_0
/*     */     //   456: istore #14
/*     */     //   458: new com/intellij/ml/llm/matterhorn/activation/state/junie/GrazieCloudUrlStepKt$grazieCloudUrlStep$2$1
/*     */     //   461: dup
/*     */     //   462: aload #7
/*     */     //   464: aconst_null
/*     */     //   465: invokespecial <init> : (Lcom/intellij/ml/llm/matterhorn/activation/state/junie/activity/ActivityCallable;Lkotlin/coroutines/Continuation;)V
/*     */     //   468: checkcast kotlin/jvm/functions/Function2
/*     */     //   471: aload #16
/*     */     //   473: swap
/*     */     //   474: astore #15
/*     */     //   476: aload #9
/*     */     //   478: aload #15
/*     */     //   480: invokeinterface updateRememberedValue : (Ljava/lang/Object;)V
/*     */     //   485: aload #15
/*     */     //   487: goto -> 492
/*     */     //   490: aload #12
/*     */     //   492: nop
/*     */     //   493: nop
/*     */     //   494: nop
/*     */     //   495: checkcast kotlin/jvm/functions/Function2
/*     */     //   498: astore #8
/*     */     //   500: aload_1
/*     */     //   501: invokeinterface endReplaceGroup : ()V
/*     */     //   506: aload #8
/*     */     //   508: aload_1
/*     */     //   509: iconst_0
/*     */     //   510: invokestatic LaunchedEffect : (Ljava/lang/Object;Lkotlin/jvm/functions/Function2;Landroidx/compose/runtime/Composer;I)V
/*     */     //   513: aload #6
/*     */     //   515: invokeinterface getLatestOpResult : ()Lcom/intellij/ml/llm/matterhorn/activation/state/model/OpResult;
/*     */     //   520: astore #9
/*     */     //   522: aload #9
/*     */     //   524: ifnonnull -> 539
/*     */     //   527: getstatic com/intellij/ml/llm/matterhorn/activation/state/model/GrazieCloudUrlPending$GrazieUrlResolveInProgress.INSTANCE : Lcom/intellij/ml/llm/matterhorn/activation/state/model/GrazieCloudUrlPending$GrazieUrlResolveInProgress;
/*     */     //   530: checkcast com/intellij/ml/llm/matterhorn/activation/state/model/AiaActivationProgressing
/*     */     //   533: invokestatic activationProgressing : (Lcom/intellij/ml/llm/matterhorn/activation/state/model/AiaActivationProgressing;)Ljava/lang/Object;
/*     */     //   536: goto -> 570
/*     */     //   539: aload #9
/*     */     //   541: instanceof com/intellij/ml/llm/matterhorn/activation/state/model/OpResult$OpCompleted$OpSucceeded
/*     */     //   544: ifne -> 559
/*     */     //   547: getstatic com/intellij/ml/llm/matterhorn/activation/state/model/GrazieCloudUrlPending$GrazieUrlResolveFailure.INSTANCE : Lcom/intellij/ml/llm/matterhorn/activation/state/model/GrazieCloudUrlPending$GrazieUrlResolveFailure;
/*     */     //   550: checkcast com/intellij/ml/llm/matterhorn/activation/state/model/AiaActivationStalled
/*     */     //   553: invokestatic activationStalled : (Lcom/intellij/ml/llm/matterhorn/activation/state/model/AiaActivationStalled;)Ljava/lang/Object;
/*     */     //   556: goto -> 570
/*     */     //   559: aload #9
/*     */     //   561: checkcast com/intellij/ml/llm/matterhorn/activation/state/model/OpResult$OpCompleted$OpSucceeded
/*     */     //   564: invokevirtual getValue : ()Ljava/lang/Object;
/*     */     //   567: invokestatic done : (Ljava/lang/Object;)Ljava/lang/Object;
/*     */     //   570: astore #8
/*     */     //   572: new com/intellij/ml/llm/matterhorn/activation/state/model/GrazieCloudUrlStep
/*     */     //   575: dup
/*     */     //   576: aload #7
/*     */     //   578: checkcast kotlin/jvm/functions/Function0
/*     */     //   581: aload #8
/*     */     //   583: aconst_null
/*     */     //   584: invokespecial <init> : (Lkotlin/jvm/functions/Function0;Ljava/lang/Object;Lkotlin/jvm/internal/DefaultConstructorMarker;)V
/*     */     //   587: astore #9
/*     */     //   589: invokestatic isTraceInProgress : ()Z
/*     */     //   592: ifeq -> 598
/*     */     //   595: invokestatic traceEventEnd : ()V
/*     */     //   598: aload_1
/*     */     //   599: invokeinterface endReplaceGroup : ()V
/*     */     //   604: aload #9
/*     */     //   606: areturn
/*     */     // Line number table:
/*     */     //   Java source line number -> byte code offset
/*     */     //   #34	-> 14
/*     */     //   #83	-> 17
/*     */     //   #84	-> 21
/*     */     //   #85	-> 36
/*     */     //   #84	-> 99
/*     */     //   #34	-> 116
/*     */     //   #35	-> 119
/*     */     //   #86	-> 139
/*     */     //   #87	-> 151
/*     */     //   #88	-> 162
/*     */     //   #88	-> 175
/*     */     //   #89	-> 177
/*     */     //   #90	-> 186
/*     */     //   #91	-> 191
/*     */     //   #87	-> 193
/*     */     //   #86	-> 194
/*     */     //   #86	-> 195
/*     */     //   #35	-> 196
/*     */     //   #37	-> 215
/*     */     //   #38	-> 221
/*     */     //   #39	-> 226
/*     */     //   #42	-> 263
/*     */     //   #44	-> 269
/*     */     //   #45	-> 285
/*     */     //   #92	-> 311
/*     */     //   #93	-> 323
/*     */     //   #94	-> 339
/*     */     //   #45	-> 344
/*     */     //   #94	-> 360
/*     */     //   #95	-> 362
/*     */     //   #96	-> 371
/*     */     //   #97	-> 376
/*     */     //   #93	-> 378
/*     */     //   #92	-> 379
/*     */     //   #92	-> 380
/*     */     //   #45	-> 381
/*     */     //   #50	-> 399
/*     */     //   #98	-> 425
/*     */     //   #99	-> 437
/*     */     //   #100	-> 453
/*     */     //   #50	-> 458
/*     */     //   #100	-> 474
/*     */     //   #101	-> 476
/*     */     //   #102	-> 485
/*     */     //   #103	-> 490
/*     */     //   #99	-> 492
/*     */     //   #98	-> 493
/*     */     //   #98	-> 494
/*     */     //   #50	-> 495
/*     */     //   #62	-> 513
/*     */     //   #63	-> 522
/*     */     //   #64	-> 539
/*     */     //   #65	-> 559
/*     */     //   #62	-> 570
/*     */     //   #68	-> 572
/*     */     // Local variable table:
/*     */     //   start	length	slot	name	descriptor
/*     */     //   17	83	4	$i$f$service	I
/*     */     //   21	79	5	serviceClass$iv	Ljava/lang/Class;
/*     */     //   167	5	10	$i$a$-cache-GrazieCloudUrlStepKt$grazieCloudUrlStep$1	I
/*     */     //   177	11	10	value$iv	Ljava/lang/Object;
/*     */     //   151	43	9	$i$a$-let-ComposerKt$cache$1$iv	I
/*     */     //   148	46	8	it$iv	Ljava/lang/Object;
/*     */     //   139	57	7	$i$f$cache	I
/*     */     //   136	60	5	$this$cache$iv	Landroidx/compose/runtime/Composer;
/*     */     //   136	60	6	invalid$iv	Z
/*     */     //   344	13	14	$i$a$-cache-GrazieCloudUrlStepKt$grazieCloudUrlStep$resolveUrlCallable$1	I
/*     */     //   362	11	15	value$iv	Ljava/lang/Object;
/*     */     //   323	56	13	$i$a$-let-ComposerKt$cache$1$iv	I
/*     */     //   320	59	12	it$iv	Ljava/lang/Object;
/*     */     //   311	70	11	$i$f$cache	I
/*     */     //   308	73	9	$this$cache$iv	Landroidx/compose/runtime/Composer;
/*     */     //   308	73	10	invalid$iv	Z
/*     */     //   458	13	14	$i$a$-cache-GrazieCloudUrlStepKt$grazieCloudUrlStep$2	I
/*     */     //   476	11	15	value$iv	Ljava/lang/Object;
/*     */     //   437	56	13	$i$a$-let-ComposerKt$cache$1$iv	I
/*     */     //   434	59	12	it$iv	Ljava/lang/Object;
/*     */     //   425	70	11	$i$f$cache	I
/*     */     //   422	73	9	$this$cache$iv	Landroidx/compose/runtime/Composer;
/*     */     //   422	73	10	invalid$iv	Z
/*     */     //   522	48	9	result	Lcom/intellij/ml/llm/matterhorn/activation/state/model/OpResult;
/*     */     //   221	386	4	stagingUrl	Ljava/lang/String;
/*     */     //   269	338	5	configJsonRawUrl	Ljava/lang/String;
/*     */     //   285	322	6	resolveUrlActivity	Lcom/intellij/ml/llm/matterhorn/activation/state/junie/activity/ActivityLauncher;
/*     */     //   399	208	7	resolveUrlCallable	Lcom/intellij/ml/llm/matterhorn/activation/state/junie/activity/ActivityCallable;
/*     */     //   572	35	8	outcome	Ljava/lang/Object;
/*     */     //   0	607	0	aiaConfig	Lcom/intellij/ml/llm/matterhorn/activation/config/AiaConfig;
/*     */     //   0	607	1	$composer	Landroidx/compose/runtime/Composer;
/*     */     //   0	607	2	$changed	I
/*     */   }
/*     */   
/*     */   private static final String grazieCloudUrlStep$lambda$1$lambda$0() {
/*  35 */     return "Grazie cloud URL resolver";
/*     */   }
/*     */   @DebugMetadata(f = "grazieCloudUrlStep.kt", l = {46}, i = {}, s = {}, n = {}, m = "invokeSuspend", c = "com.intellij.ml.llm.matterhorn.activation.state.junie.GrazieCloudUrlStepKt$grazieCloudUrlStep$resolveUrlCallable$1$1")
/*     */   @Metadata(mv = {2, 1, 0}, k = 3, xi = 48, d1 = {"\000\n\n\000\n\002\030\002\n\002\030\002\020\000\032\b\022\004\022\0020\0020\001H\n"}, d2 = {"<anonymous>", "Lcom/intellij/ml/llm/matterhorn/activation/data/model/result/GrazieResult;", "Lcom/intellij/ml/llm/matterhorn/activation/data/model/GrazieApiUrl;"})
/*     */   static final class GrazieCloudUrlStepKt$grazieCloudUrlStep$resolveUrlCallable$1$1 extends SuspendLambda implements Function1<Continuation<? super GrazieResult<? extends GrazieApiUrl>>, Object> { int label;
/*     */     GrazieCloudUrlStepKt$grazieCloudUrlStep$resolveUrlCallable$1$1(String $configJsonRawUrl, Continuation $completion) {
/*     */       super(1, $completion);
/*     */     }
/*     */     
/*     */     public final Object invokeSuspend(Object $result) {
/*  45 */       Object object = IntrinsicsKt.getCOROUTINE_SUSPENDED(); switch (this.label) { case 0: ResultKt.throwOnFailure(SYNTHETIC_LOCAL_VARIABLE_1);
/*  46 */           this.label = 1; if (TimeoutKt.withTimeout-KLykuaI(DurationKt.toDuration(20, DurationUnit.SECONDS), new Function2<CoroutineScope, Continuation<? super GrazieResult<? extends GrazieApiUrl>>, Object>(this.$configJsonRawUrl, null) { int label; public final Continuation<Unit> create(Object value, Continuation<? super null> $completion) { return (Continuation)new Function2<>(this.$configJsonRawUrl, $completion); } public final Object invoke(CoroutineScope p1, Continuation<?> p2) { return ((null)create(p1, p2)).invokeSuspend(Unit.INSTANCE); } public final Object invokeSuspend(Object $result) { Object object = IntrinsicsKt.getCOROUTINE_SUSPENDED(); switch (this.label) { case 0: ResultKt.throwOnFailure(SYNTHETIC_LOCAL_VARIABLE_1);
/*  47 */                       this.label = 1; if (GrazieCloudUrlStepKt.resolveApiUrl(this.$configJsonRawUrl, (Continuation)this) == object) return object;  return GrazieCloudUrlStepKt.resolveApiUrl(this.$configJsonRawUrl, (Continuation)this);case 1: ResultKt.throwOnFailure(SYNTHETIC_LOCAL_VARIABLE_1); return SYNTHETIC_LOCAL_VARIABLE_1; }  throw new IllegalStateException("call to 'resume' before 'invoke' with coroutine"); } }(Continuation)this) == object) return object;  return TimeoutKt.withTimeout-KLykuaI(DurationKt.toDuration(20, DurationUnit.SECONDS), new Function2<CoroutineScope, Continuation<? super GrazieResult<? extends GrazieApiUrl>>, Object>(this.$configJsonRawUrl, null) { int label; public final Object invokeSuspend(Object $result) { Object object = IntrinsicsKt.getCOROUTINE_SUSPENDED(); switch (this.label) { case 0: ResultKt.throwOnFailure(SYNTHETIC_LOCAL_VARIABLE_1); this.label = 1; if (GrazieCloudUrlStepKt.resolveApiUrl(this.$configJsonRawUrl, (Continuation)this) == object) return object;  return GrazieCloudUrlStepKt.resolveApiUrl(this.$configJsonRawUrl, (Continuation)this);
/*     */                     case 1:
/*     */                       ResultKt.throwOnFailure(SYNTHETIC_LOCAL_VARIABLE_1);
/*     */                       return SYNTHETIC_LOCAL_VARIABLE_1; }
/*     */                   
/*     */                   throw new IllegalStateException("call to 'resume' before 'invoke' with coroutine"); } public final Continuation<Unit> create(Object value, Continuation<? super null> $completion) {
/*     */                   return (Continuation)new Function2<>(this.$configJsonRawUrl, $completion);
/*     */                 } public final Object invoke(CoroutineScope p1, Continuation<?> p2) {
/*     */                   return ((null)create(p1, p2)).invokeSuspend(Unit.INSTANCE);
/*     */                 } }
/*     */               (Continuation)this);
/*     */         case 1:
/*     */           ResultKt.throwOnFailure(SYNTHETIC_LOCAL_VARIABLE_1);
/*     */           return SYNTHETIC_LOCAL_VARIABLE_1; }
/*     */       
/*     */       throw new IllegalStateException("call to 'resume' before 'invoke' with coroutine");
/*     */     } public final Continuation<Unit> create(Continuation<? super GrazieCloudUrlStepKt$grazieCloudUrlStep$resolveUrlCallable$1$1> $completion) {
/*     */       return (Continuation<Unit>)new GrazieCloudUrlStepKt$grazieCloudUrlStep$resolveUrlCallable$1$1(this.$configJsonRawUrl, $completion);
/*     */     } public final Object invoke(Continuation<?> p1) {
/*     */       return ((GrazieCloudUrlStepKt$grazieCloudUrlStep$resolveUrlCallable$1$1)create(p1)).invokeSuspend(Unit.INSTANCE);
/*     */     } } @DebugMetadata(f = "grazieCloudUrlStep.kt", l = {52, 58}, i = {}, s = {}, n = {}, m = "invokeSuspend", c = "com.intellij.ml.llm.matterhorn.activation.state.junie.GrazieCloudUrlStepKt$grazieCloudUrlStep$2$1")
/*     */   @Metadata(mv = {2, 1, 0}, k = 3, xi = 48, d1 = {"\000\n\n\000\n\002\020\002\n\002\030\002\020\000\032\0020\001*\0020\002H\n"}, d2 = {"<anonymous>", "", "Lkotlinx/coroutines/CoroutineScope;"})
/*     */   static final class GrazieCloudUrlStepKt$grazieCloudUrlStep$2$1 extends SuspendLambda implements Function2<CoroutineScope, Continuation<? super Unit>, Object> { int label; GrazieCloudUrlStepKt$grazieCloudUrlStep$2$1(ActivityCallable<GrazieResult<GrazieApiUrl>, GrazieResult.GrazieFailure, GrazieApiUrl> $resolveUrlCallable, Continuation $completion) {
/*     */       super(2, $completion);
/*     */     } public final Object invokeSuspend(Object $result) {
/*     */       // Byte code:
/*     */       //   0: invokestatic getCOROUTINE_SUSPENDED : ()Ljava/lang/Object;
/*     */       //   3: astore #5
/*     */       //   5: aload_0
/*     */       //   6: getfield label : I
/*     */       //   9: tableswitch default -> 145, 0 -> 36, 1 -> 71, 2 -> 136
/*     */       //   36: aload_1
/*     */       //   37: invokestatic throwOnFailure : (Ljava/lang/Object;)V
/*     */       //   40: nop
/*     */       //   41: aload_0
/*     */       //   42: getfield $resolveUrlCallable : Lcom/intellij/ml/llm/matterhorn/activation/state/junie/activity/ActivityCallable;
/*     */       //   45: invokeinterface invoke : ()Lcom/intellij/ml/llm/matterhorn/activation/state/junie/activity/ActivityHandle;
/*     */       //   50: aload_0
/*     */       //   51: checkcast kotlin/coroutines/Continuation
/*     */       //   54: aload_0
/*     */       //   55: iconst_1
/*     */       //   56: putfield label : I
/*     */       //   59: invokevirtual awaitOpResult : (Lkotlin/coroutines/Continuation;)Ljava/lang/Object;
/*     */       //   62: dup
/*     */       //   63: aload #5
/*     */       //   65: if_acmpne -> 76
/*     */       //   68: aload #5
/*     */       //   70: areturn
/*     */       //   71: aload_1
/*     */       //   72: invokestatic throwOnFailure : (Ljava/lang/Object;)V
/*     */       //   75: aload_1
/*     */       //   76: checkcast com/intellij/ml/llm/matterhorn/activation/state/model/OpResult
/*     */       //   79: astore_2
/*     */       //   80: aload_2
/*     */       //   81: instanceof com/intellij/ml/llm/matterhorn/activation/state/model/OpResult$OpCompleted$OpSucceeded
/*     */       //   84: ifeq -> 101
/*     */       //   87: getstatic kotlin/time/Duration.Companion : Lkotlin/time/Duration$Companion;
/*     */       //   90: pop
/*     */       //   91: iconst_2
/*     */       //   92: getstatic kotlin/time/DurationUnit.HOURS : Lkotlin/time/DurationUnit;
/*     */       //   95: invokestatic toDuration : (ILkotlin/time/DurationUnit;)J
/*     */       //   98: goto -> 113
/*     */       //   101: getstatic kotlin/time/Duration.Companion : Lkotlin/time/Duration$Companion;
/*     */       //   104: pop
/*     */       //   105: bipush #10
/*     */       //   107: getstatic kotlin/time/DurationUnit.SECONDS : Lkotlin/time/DurationUnit;
/*     */       //   110: invokestatic toDuration : (ILkotlin/time/DurationUnit;)J
/*     */       //   113: lstore_3
/*     */       //   114: lload_3
/*     */       //   115: aload_0
/*     */       //   116: checkcast kotlin/coroutines/Continuation
/*     */       //   119: aload_0
/*     */       //   120: iconst_2
/*     */       //   121: putfield label : I
/*     */       //   124: invokestatic delay-VtjQ1oo : (JLkotlin/coroutines/Continuation;)Ljava/lang/Object;
/*     */       //   127: dup
/*     */       //   128: aload #5
/*     */       //   130: if_acmpne -> 141
/*     */       //   133: aload #5
/*     */       //   135: areturn
/*     */       //   136: aload_1
/*     */       //   137: invokestatic throwOnFailure : (Ljava/lang/Object;)V
/*     */       //   140: aload_1
/*     */       //   141: pop
/*     */       //   142: goto -> 40
/*     */       //   145: new java/lang/IllegalStateException
/*     */       //   148: dup
/*     */       //   149: ldc 'call to 'resume' before 'invoke' with coroutine'
/*     */       //   151: invokespecial <init> : (Ljava/lang/String;)V
/*     */       //   154: athrow
/*     */       // Line number table:
/*     */       //   Java source line number -> byte code offset
/*     */       //   #50	-> 3
/*     */       //   #51	-> 40
/*     */       //   #52	-> 41
/*     */       //   #50	-> 68
/*     */       //   #54	-> 80
/*     */       //   #55	-> 81
/*     */       //   #56	-> 101
/*     */       //   #54	-> 113
/*     */       //   #58	-> 114
/*     */       //   #50	-> 133
/*     */       //   #58	-> 141
/*     */       //   #50	-> 145
/*     */       // Local variable table:
/*     */       //   start	length	slot	name	descriptor
/*     */       //   80	1	2	result	Lcom/intellij/ml/llm/matterhorn/activation/state/model/OpResult;
/*     */       //   114	13	3	delayUntilUpdate	J
/*     */       //   0	155	0	this	Lcom/intellij/ml/llm/matterhorn/activation/state/junie/GrazieCloudUrlStepKt$grazieCloudUrlStep$2$1;
/*     */       //   40	105	1	$result	Ljava/lang/Object;
/*     */     } public final Continuation<Unit> create(Object value, Continuation<? super GrazieCloudUrlStepKt$grazieCloudUrlStep$2$1> $completion) {
/*     */       return (Continuation<Unit>)new GrazieCloudUrlStepKt$grazieCloudUrlStep$2$1(this.$resolveUrlCallable, $completion);
/*     */     } public final Object invoke(CoroutineScope p1, Continuation<?> p2) {
/*     */       return ((GrazieCloudUrlStepKt$grazieCloudUrlStep$2$1)create(p1, p2)).invokeSuspend(Unit.INSTANCE);
/*     */     } } private static final Object resolveApiUrl(String configJsonRawUrl, Continuation $completion) {
/*     */     // Byte code:
/*     */     //   0: aload_1
/*     */     //   1: instanceof com/intellij/ml/llm/matterhorn/activation/state/junie/GrazieCloudUrlStepKt$resolveApiUrl$1
/*     */     //   4: ifeq -> 41
/*     */     //   7: aload_1
/*     */     //   8: checkcast com/intellij/ml/llm/matterhorn/activation/state/junie/GrazieCloudUrlStepKt$resolveApiUrl$1
/*     */     //   11: astore #7
/*     */     //   13: aload #7
/*     */     //   15: getfield label : I
/*     */     //   18: ldc_w -2147483648
/*     */     //   21: iand
/*     */     //   22: ifeq -> 41
/*     */     //   25: aload #7
/*     */     //   27: dup
/*     */     //   28: getfield label : I
/*     */     //   31: ldc_w -2147483648
/*     */     //   34: isub
/*     */     //   35: putfield label : I
/*     */     //   38: goto -> 51
/*     */     //   41: new com/intellij/ml/llm/matterhorn/activation/state/junie/GrazieCloudUrlStepKt$resolveApiUrl$1
/*     */     //   44: dup
/*     */     //   45: aload_1
/*     */     //   46: invokespecial <init> : (Lkotlin/coroutines/Continuation;)V
/*     */     //   49: astore #7
/*     */     //   51: aload #7
/*     */     //   53: getfield result : Ljava/lang/Object;
/*     */     //   56: astore #6
/*     */     //   58: invokestatic getCOROUTINE_SUSPENDED : ()Ljava/lang/Object;
/*     */     //   61: astore #8
/*     */     //   63: aload #7
/*     */     //   65: getfield label : I
/*     */     //   68: tableswitch default -> 331, 0 -> 104, 1 -> 138, 2 -> 193, 3 -> 258, 4 -> 323
/*     */     //   104: aload #6
/*     */     //   106: invokestatic throwOnFailure : (Ljava/lang/Object;)V
/*     */     //   109: getstatic com/intellij/ml/llm/matterhorn/activation/data/repos/JunieRegionUrlRepository.Companion : Lcom/intellij/ml/llm/matterhorn/activation/data/repos/JunieRegionUrlRepository$Companion;
/*     */     //   112: aload #7
/*     */     //   114: aload #7
/*     */     //   116: aload_0
/*     */     //   117: putfield L$0 : Ljava/lang/Object;
/*     */     //   120: aload #7
/*     */     //   122: iconst_1
/*     */     //   123: putfield label : I
/*     */     //   126: invokevirtual instance : (Lkotlin/coroutines/Continuation;)Ljava/lang/Object;
/*     */     //   129: dup
/*     */     //   130: aload #8
/*     */     //   132: if_acmpne -> 154
/*     */     //   135: aload #8
/*     */     //   137: areturn
/*     */     //   138: aload #7
/*     */     //   140: getfield L$0 : Ljava/lang/Object;
/*     */     //   143: checkcast java/lang/String
/*     */     //   146: astore_0
/*     */     //   147: aload #6
/*     */     //   149: invokestatic throwOnFailure : (Ljava/lang/Object;)V
/*     */     //   152: aload #6
/*     */     //   154: checkcast com/intellij/ml/llm/matterhorn/activation/data/repos/JunieRegionUrlRepository
/*     */     //   157: astore_2
/*     */     //   158: getstatic com/intellij/ml/llm/matterhorn/activation/data/repos/JunieGrazieRepository.Companion : Lcom/intellij/ml/llm/matterhorn/activation/data/repos/JunieGrazieRepository$Companion;
/*     */     //   161: aload #7
/*     */     //   163: aload #7
/*     */     //   165: aload_0
/*     */     //   166: putfield L$0 : Ljava/lang/Object;
/*     */     //   169: aload #7
/*     */     //   171: aload_2
/*     */     //   172: putfield L$1 : Ljava/lang/Object;
/*     */     //   175: aload #7
/*     */     //   177: iconst_2
/*     */     //   178: putfield label : I
/*     */     //   181: invokevirtual instance : (Lkotlin/coroutines/Continuation;)Ljava/lang/Object;
/*     */     //   184: dup
/*     */     //   185: aload #8
/*     */     //   187: if_acmpne -> 218
/*     */     //   190: aload #8
/*     */     //   192: areturn
/*     */     //   193: aload #7
/*     */     //   195: getfield L$1 : Ljava/lang/Object;
/*     */     //   198: checkcast com/intellij/ml/llm/matterhorn/activation/data/repos/JunieRegionUrlRepository
/*     */     //   201: astore_2
/*     */     //   202: aload #7
/*     */     //   204: getfield L$0 : Ljava/lang/Object;
/*     */     //   207: checkcast java/lang/String
/*     */     //   210: astore_0
/*     */     //   211: aload #6
/*     */     //   213: invokestatic throwOnFailure : (Ljava/lang/Object;)V
/*     */     //   216: aload #6
/*     */     //   218: checkcast com/intellij/ml/llm/matterhorn/activation/data/repos/JunieGrazieRepository
/*     */     //   221: astore_3
/*     */     //   222: aload_2
/*     */     //   223: aload_0
/*     */     //   224: aload #7
/*     */     //   226: aload #7
/*     */     //   228: aload_3
/*     */     //   229: putfield L$0 : Ljava/lang/Object;
/*     */     //   232: aload #7
/*     */     //   234: aconst_null
/*     */     //   235: putfield L$1 : Ljava/lang/Object;
/*     */     //   238: aload #7
/*     */     //   240: iconst_3
/*     */     //   241: putfield label : I
/*     */     //   244: invokeinterface mapRegionUrl-dorYjGE : (Ljava/lang/String;Lkotlin/coroutines/Continuation;)Ljava/lang/Object;
/*     */     //   249: dup
/*     */     //   250: aload #8
/*     */     //   252: if_acmpne -> 280
/*     */     //   255: aload #8
/*     */     //   257: areturn
/*     */     //   258: aload #7
/*     */     //   260: getfield L$0 : Ljava/lang/Object;
/*     */     //   263: checkcast com/intellij/ml/llm/matterhorn/activation/data/repos/JunieGrazieRepository
/*     */     //   266: astore_3
/*     */     //   267: aload #6
/*     */     //   269: invokestatic throwOnFailure : (Ljava/lang/Object;)V
/*     */     //   272: aload #6
/*     */     //   274: checkcast com/intellij/ml/llm/matterhorn/activation/data/model/RegionUrl
/*     */     //   277: invokevirtual unbox-impl : ()Ljava/lang/String;
/*     */     //   280: checkcast java/lang/String
/*     */     //   283: astore #4
/*     */     //   285: aload #4
/*     */     //   287: invokestatic constructor-impl : (Ljava/lang/String;)Ljava/lang/String;
/*     */     //   290: astore #5
/*     */     //   292: aload_3
/*     */     //   293: aload #5
/*     */     //   295: aload #7
/*     */     //   297: aload #7
/*     */     //   299: aconst_null
/*     */     //   300: putfield L$0 : Ljava/lang/Object;
/*     */     //   303: aload #7
/*     */     //   305: iconst_4
/*     */     //   306: putfield label : I
/*     */     //   309: invokeinterface resolveApiUrl-7oKCuCM : (Ljava/lang/String;Lkotlin/coroutines/Continuation;)Ljava/lang/Object;
/*     */     //   314: dup
/*     */     //   315: aload #8
/*     */     //   317: if_acmpne -> 330
/*     */     //   320: aload #8
/*     */     //   322: areturn
/*     */     //   323: aload #6
/*     */     //   325: invokestatic throwOnFailure : (Ljava/lang/Object;)V
/*     */     //   328: aload #6
/*     */     //   330: areturn
/*     */     //   331: new java/lang/IllegalStateException
/*     */     //   334: dup
/*     */     //   335: ldc_w 'call to 'resume' before 'invoke' with coroutine'
/*     */     //   338: invokespecial <init> : (Ljava/lang/String;)V
/*     */     //   341: athrow
/*     */     // Line number table:
/*     */     //   Java source line number -> byte code offset
/*     */     //   #71	-> 61
/*     */     //   #72	-> 109
/*     */     //   #71	-> 135
/*     */     //   #73	-> 158
/*     */     //   #71	-> 190
/*     */     //   #75	-> 222
/*     */     //   #71	-> 255
/*     */     //   #75	-> 280
/*     */     //   #76	-> 285
/*     */     //   #78	-> 292
/*     */     //   #71	-> 320
/*     */     //   #78	-> 330
/*     */     //   #71	-> 331
/*     */     // Local variable table:
/*     */     //   start	length	slot	name	descriptor
/*     */     //   109	29	0	configJsonRawUrl	Ljava/lang/String;
/*     */     //   147	46	0	configJsonRawUrl	Ljava/lang/String;
/*     */     //   211	38	0	configJsonRawUrl	Ljava/lang/String;
/*     */     //   158	35	2	regionUrlRepository	Lcom/intellij/ml/llm/matterhorn/activation/data/repos/JunieRegionUrlRepository;
/*     */     //   202	47	2	regionUrlRepository	Lcom/intellij/ml/llm/matterhorn/activation/data/repos/JunieRegionUrlRepository;
/*     */     //   222	36	3	grazieRepository	Lcom/intellij/ml/llm/matterhorn/activation/data/repos/JunieGrazieRepository;
/*     */     //   267	47	3	grazieRepository	Lcom/intellij/ml/llm/matterhorn/activation/data/repos/JunieGrazieRepository;
/*     */     //   285	7	4	mappedUrl	Ljava/lang/String;
/*     */     //   292	22	5	configJsonUrl	Ljava/lang/String;
/*     */     //   0	342	1	$completion	Lkotlin/coroutines/Continuation;
/*     */     //   51	280	7	$continuation	Lkotlin/coroutines/Continuation;
/*     */     //   58	273	6	$result	Ljava/lang/Object;
/*     */   }
/*     */   static {
/*  81 */     int $i$f$fileLogger = 0;
/*     */ 
/*     */ 
/*     */ 
/*     */ 
/*     */ 
/*     */ 
/*     */ 
/*     */ 
/*     */ 
/*     */ 
/*     */ 
/*     */ 
/*     */ 
/*     */ 
/*     */ 
/*     */ 
/*     */ 
/*     */ 
/*     */ 
/*     */ 
/*     */ 
/*     */     
/* 104 */     int $i$f$currentClassLogger = 0;
/* 105 */     Class<?> clazz$iv$iv = MethodHandles.lookup().lookupClass();
/* 106 */     Intrinsics.checkNotNullExpressionValue(Logger.getInstance(clazz$iv$iv), "getInstance(...)"); LOG = Logger.getInstance(clazz$iv$iv);
/*     */   }
/*     */   
/*     */   @DebugMetadata(f = "grazieCloudUrlStep.kt", l = {72, 73, 75, 78}, i = {0, 1, 1, 2}, s = {"L$0", "L$0", "L$1", "L$0"}, n = {"configJsonRawUrl", "configJsonRawUrl", "regionUrlRepository", "grazieRepository"}, m = "resolveApiUrl", c = "com.intellij.ml.llm.matterhorn.activation.state.junie.GrazieCloudUrlStepKt")
/*     */   @Metadata(mv = {2, 1, 0}, k = 3, xi = 48)
/*     */   static final class GrazieCloudUrlStepKt$resolveApiUrl$1 extends ContinuationImpl {
/*     */     Object L$0;
/*     */     Object L$1;
/*     */     int label;
/*     */     
/*     */     GrazieCloudUrlStepKt$resolveApiUrl$1(Continuation $completion) {
/*     */       super($completion);
/*     */     }
/*     */     
/*     */     @Nullable
/*     */     public final Object invokeSuspend(@NotNull Object $result) {
/*     */       this.result = $result;
/*     */       this.label |= Integer.MIN_VALUE;
/*     */       return GrazieCloudUrlStepKt.resolveApiUrl(null, (Continuation)this);
/*     */     }
/*     */   }
/*     */ }


/* Location:              C:\Users\yuzum\Downloads\ej-release-243.132.63.zip!\ej\lib\ej-243.132.63.jar!\com\intellij\ml\llm\matterhorn\activation\state\junie\GrazieCloudUrlStepKt.class
 * Java compiler version: 17 (61.0)
 * JD-Core Version:       1.1.3
 */