/*    */ package ai.grazie.utils.mpp.geo;
/*    */ 
/*    */ import kotlin.jvm.internal.SourceDebugExtension;
/*    */ import org.jetbrains.annotations.NotNull;
/*    */ import org.jetbrains.annotations.Nullable;
/*    */ 
/*    */ @Metadata(mv = {1, 7, 0}, k = 1, xi = 48, d1 = {"\000\032\n\002\030\002\n\002\020\000\n\002\b\002\n\002\030\002\n\002\b\030\n\002\020\016\n\000\b\003\030\0002\0020\001B\007\b\002¢\006\002\020\002J\020\020\033\032\004\030\0010\0042\006\020\034\032\0020\035R\021\020\003\032\0020\004¢\006\b\n\000\032\004\b\005\020\006R\021\020\007\032\0020\004¢\006\b\n\000\032\004\b\b\020\006R\021\020\t\032\0020\004¢\006\b\n\000\032\004\b\n\020\006R\021\020\013\032\0020\004¢\006\b\n\000\032\004\b\f\020\006R\021\020\r\032\0020\004¢\006\b\n\000\032\004\b\016\020\006R\021\020\017\032\0020\004¢\006\b\n\000\032\004\b\020\020\006R\021\020\021\032\0020\004¢\006\b\n\000\032\004\b\022\020\006R\021\020\023\032\0020\004¢\006\b\n\000\032\004\b\024\020\006R\021\020\025\032\0020\004¢\006\b\n\000\032\004\b\026\020\006R\021\020\027\032\0020\004¢\006\b\n\000\032\004\b\030\020\006R\021\020\031\032\0020\004¢\006\b\n\000\032\004\b\032\020\006¨\006\036"}, d2 = {"Lai/grazie/utils/mpp/geo/Country$Companion;", "", "()V", "Australia", "Lai/grazie/utils/mpp/geo/Country;", "getAustralia", "()Lai/grazie/utils/mpp/geo/Country;", "Brazil", "getBrazil", "Brunei", "getBrunei", "Canada", "getCanada", "China", "getChina", "Congo", "getCongo", "Germany", "getGermany", "India", "getIndia", "Russia", "getRussia", "USA", "getUSA", "Vietnam", "getVietnam", "findByAlpha2", "alpha2", "", "utils-common"})
/*    */ @SourceDebugExtension({"SMAP\nCountry.kt\nKotlin\n*S Kotlin\n*F\n+ 1 Country.kt\nai/grazie/utils/mpp/geo/Country$Companion\n+ 2 fake.kt\nkotlin/jvm/internal/FakeKt\n*L\n1#1,31:1\n1#2:32\n*E\n"})
/*    */ public final class Companion {
/*    */   private Companion() {}
/*    */   
/*    */   @Nullable
/*    */   public final Country findByAlpha2(@NotNull String alpha2) {
/*    */     // Byte code:
/*    */     //   0: aload_1
/*    */     //   1: ldc 'alpha2'
/*    */     //   3: invokestatic checkNotNullParameter : (Ljava/lang/Object;Ljava/lang/String;)V
/*    */     //   6: invokestatic values : ()[Lai/grazie/utils/mpp/geo/CountryISO;
/*    */     //   9: astore_3
/*    */     //   10: iconst_0
/*    */     //   11: istore #4
/*    */     //   13: aload_3
/*    */     //   14: arraylength
/*    */     //   15: istore #5
/*    */     //   17: iload #4
/*    */     //   19: iload #5
/*    */     //   21: if_icmpge -> 61
/*    */     //   24: aload_3
/*    */     //   25: iload #4
/*    */     //   27: aaload
/*    */     //   28: astore #6
/*    */     //   30: aload #6
/*    */     //   32: astore #7
/*    */     //   34: iconst_0
/*    */     //   35: istore #8
/*    */     //   37: aload #7
/*    */     //   39: invokevirtual getAlpha2 : ()Ljava/lang/String;
/*    */     //   42: aload_1
/*    */     //   43: iconst_1
/*    */     //   44: invokestatic equals : (Ljava/lang/String;Ljava/lang/String;Z)Z
/*    */     //   47: ifeq -> 55
/*    */     //   50: aload #6
/*    */     //   52: goto -> 62
/*    */     //   55: iinc #4, 1
/*    */     //   58: goto -> 17
/*    */     //   61: aconst_null
/*    */     //   62: dup
/*    */     //   63: ifnonnull -> 69
/*    */     //   66: pop
/*    */     //   67: aconst_null
/*    */     //   68: areturn
/*    */     //   69: astore_2
/*    */     //   70: new ai/grazie/utils/mpp/geo/Country
/*    */     //   73: dup
/*    */     //   74: aload_2
/*    */     //   75: invokespecial <init> : (Lai/grazie/utils/mpp/geo/CountryISO;)V
/*    */     //   78: areturn
/*    */     // Line number table:
/*    */     //   Java source line number -> byte code offset
/*    */     //   #14	-> 6
/*    */     //   #32	-> 34
/*    */     //   #14	-> 37
/*    */     //   #14	-> 47
/*    */     //   #14	-> 62
/*    */     //   #15	-> 70
/*    */     // Local variable table:
/*    */     //   start	length	slot	name	descriptor
/*    */     //   37	10	8	$i$a$-find-Country$Companion$findByAlpha2$iso$1	I
/*    */     //   34	13	7	it	Lai/grazie/utils/mpp/geo/CountryISO;
/*    */     //   70	9	2	iso	Lai/grazie/utils/mpp/geo/CountryISO;
/*    */     //   0	79	0	this	Lai/grazie/utils/mpp/geo/Country$Companion;
/*    */     //   0	79	1	alpha2	Ljava/lang/String;
/*    */   }
/*    */   
/*    */   @NotNull
/* 18 */   public final Country getRussia() { return Country.access$getRussia$cp(); } @NotNull
/* 19 */   public final Country getChina() { return Country.access$getChina$cp(); } @NotNull
/* 20 */   public final Country getUSA() { return Country.access$getUSA$cp(); } @NotNull
/* 21 */   public final Country getGermany() { return Country.access$getGermany$cp(); } @NotNull
/* 22 */   public final Country getBrunei() { return Country.access$getBrunei$cp(); } @NotNull
/* 23 */   public final Country getVietnam() { return Country.access$getVietnam$cp(); } @NotNull
/* 24 */   public final Country getAustralia() { return Country.access$getAustralia$cp(); } @NotNull
/* 25 */   public final Country getCanada() { return Country.access$getCanada$cp(); } @NotNull
/* 26 */   public final Country getBrazil() { return Country.access$getBrazil$cp(); } @NotNull
/* 27 */   public final Country getIndia() { return Country.access$getIndia$cp(); } @NotNull
/* 28 */   public final Country getCongo() { return Country.access$getCongo$cp(); }
/*    */ 
/*    */ }


/* Location:              C:\Users\yuzum\Downloads\ej-release-243.132.63.zip!\ej\li\\utils-common-jvm-0.4.32.jar!\ai\grazi\\utils\mpp\geo\Country$Companion.class
 * Java compiler version: 17 (61.0)
 * JD-Core Version:       1.1.3
 */